{
  "type": "Feature",
  "properties": {
    "gn:admin1_code":"08",
    "gn:asciiname":"Madrono",
    "gn:country_code":"PA",
    "gn:dem":197,
    "gn:feature_class":"P",
    "gn:feature_code":"PPL",
    "gn:name":"Madro\u00f1o",
    "gn:population":0,
    "gn:timezone":"America/Panama",
    "iso:country":"PA",
    "wof:name":"Madrono",
    "wof:placetype":"locality"
},
  "geometry": {"coordinates":[-79.13333,9.28333],"type":"Point"}
}