{
  "type": "Feature",
  "properties": {
    "gn:admin1_code":"03",
    "gn:asciiname":"Los Molejones",
    "gn:country_code":"PA",
    "gn:dem":157,
    "gn:feature_class":"P",
    "gn:feature_code":"PPL",
    "gn:name":"Los Molejones",
    "gn:population":42,
    "gn:timezone":"America/Panama",
    "iso:country":"PA",
    "wof:name":"Los Molejones",
    "wof:placetype":"locality",
    "wof:population":42
},
  "geometry": {"coordinates":[-80.17369000000002,8.87706],"type":"Point"}
}