{
  "type": "Feature",
  "properties": {
    "gn:admin1_code":"13",
    "gn:asciiname":"Loma del Guayabo",
    "gn:country_code":"PA",
    "gn:dem":277,
    "gn:feature_class":"P",
    "gn:feature_code":"PPL",
    "gn:name":"Loma del Guayabo",
    "gn:population":0,
    "gn:timezone":"America/Panama",
    "iso:country":"PA",
    "wof:name":"Loma del Guayabo",
    "wof:placetype":"locality"
},
  "geometry": {"coordinates":[-79.98333000000002,8.58333],"type":"Point"}
}