{
  "type": "Feature",
  "properties": {
    "gn:admin1_code":"07",
    "gn:asciiname":"Agua Buena",
    "gn:country_code":"PA",
    "gn:dem":36,
    "gn:feature_class":"P",
    "gn:feature_code":"PPL",
    "gn:name":"Agua Buena",
    "gn:population":0,
    "gn:timezone":"America/Panama",
    "iso:country":"PA",
    "name:und_x_variant":[
        "Aguas Buenas",
        "Agua Buena"
    ],
    "wof:name":"Agua Buena",
    "wof:placetype":"locality"
},
  "geometry": {"coordinates":[-80.34305000000001,7.45276],"type":"Point"}
}