{
  "type": "Feature",
  "properties": {
    "gn:admin1_code":"06",
    "gn:asciiname":"Cantarrana",
    "gn:country_code":"PA",
    "gn:dem":21,
    "gn:feature_class":"P",
    "gn:feature_code":"PPL",
    "gn:name":"Cantarrana",
    "gn:population":0,
    "gn:timezone":"America/Panama",
    "iso:country":"PA",
    "name:spa_x_preferred":[
        "Cantarrana"
    ],
    "wof:name":"Cantarrana",
    "wof:placetype":"locality"
},
  "geometry": {"coordinates":[-80.44365999999999,7.95262],"type":"Point"}
}