{
  "type": "Feature",
  "properties": {
    "gn:admin1_code":"10",
    "gn:asciiname":"Tebario",
    "gn:country_code":"PA",
    "gn:dem":13,
    "gn:feature_class":"P",
    "gn:feature_code":"PPLA3",
    "gn:name":"Tebario",
    "gn:population":190,
    "gn:timezone":"America/Panama",
    "iso:country":"PA",
    "name:ita_x_preferred":[
        "Mariato"
    ],
    "name:spa_x_preferred":[
        "Mariato"
    ],
    "name:und_x_variant":[
        "Mariato",
        "Tebario"
    ],
    "name:zho_x_preferred":[
        "\u99ac\u91cc\u4e9e\u6258"
    ],
    "wof:name":"Tebario",
    "wof:placetype":"locality",
    "wof:population":190
},
  "geometry": {"coordinates":[-80.97825,7.71369],"type":"Point"}
}