{
  "type": "Feature",
  "properties": {
    "gn:admin1_code":"04",
    "gn:asciiname":"Mata de Guineo",
    "gn:cc2":"PA",
    "gn:country_code":"PA",
    "gn:dem":52,
    "gn:feature_class":"P",
    "gn:feature_code":"PPL",
    "gn:name":"Mata de Guineo",
    "gn:population":0,
    "gn:timezone":"America/Panama",
    "iso:country":"PA",
    "name:und_x_variant":[
        "Mata Guineo",
        "Mata de Guineo"
    ],
    "wof:name":"Mata de Guineo",
    "wof:placetype":"locality"
},
  "geometry": {"coordinates":[-80.09999999999999,9.18333],"type":"Point"}
}