{
  "type": "Feature",
  "properties": {
    "iso:country":"PA",
    "name:ceb_x_preferred":[
        "Calobre"
    ],
    "name:eng_x_preferred":[
        "Calobre"
    ],
    "name:fra_x_preferred":[
        "Calobre"
    ],
    "name:ita_x_preferred":[
        "Calobre"
    ],
    "name:nld_x_preferred":[
        "Calobre"
    ],
    "name:spa_x_preferred":[
        "Calobre"
    ],
    "name:und_x_variant":[
        "Colobre"
    ],
    "name:zho_x_preferred":[
        "\u5361\u6d1b\u5f17\u96f7"
    ],
    "qs:gn_country":"PA",
    "qs:gn_fcode":"PPL",
    "qs:gn_pop":937,
    "qs:name":"Calobre",
    "qs:name_adm0":"Panam\u00e1",
    "qs:name_adm1":"Veraguas",
    "qs:photos":9,
    "qs:photos_1k":2,
    "qs:photos_9k":1,
    "qs:photos_9r":1,
    "qs:photos_all":9,
    "qs:photos_sr":1,
    "qs:placetype":"LocalAdmin",
    "qs:pop_sr":"2",
    "qs:woe_adm0":23424924,
    "wd:wordcount":286,
    "wof:name":"Calobre",
    "wof:placetype":"localadmin",
    "wof:population":937
},
  "geometry": {"coordinates":[-80.84999999999999,8.31667],"type":"Point"}
}