{
  "type": "Feature",
  "properties": {
    "gn:admin1_code":"13",
    "gn:asciiname":"Los Hatillos",
    "gn:country_code":"PA",
    "gn:dem":27,
    "gn:feature_class":"P",
    "gn:feature_code":"PPL",
    "gn:name":"Los Hatillos",
    "gn:population":38,
    "gn:timezone":"America/Panama",
    "iso:country":"PA",
    "name:und_x_variant":[
        "Los Hatillo",
        "Los Hatillos"
    ],
    "wof:name":"Los Hatillos",
    "wof:placetype":"locality",
    "wof:population":38
},
  "geometry": {"coordinates":[-79.77185,8.80501],"type":"Point"}
}