{
  "type": "Feature",
  "properties": {
    "gn:admin1_code":"02",
    "gn:asciiname":"Paso Canoas",
    "gn:country_code":"PA",
    "gn:dem":96,
    "gn:feature_class":"P",
    "gn:feature_code":"PPL",
    "gn:name":"Paso Canoas",
    "gn:population":0,
    "gn:timezone":"America/Panama",
    "iso:country":"PA",
    "name:kat_x_preferred":[
        "\u10de\u10d0\u10e1\u10dd-\u10d9\u10d0\u10dc\u10dd\u10d0\u10e1\u10d8"
    ],
    "name:nor_x_preferred":[
        "Paso Canoas"
    ],
    "name:spa_x_preferred":[
        "Paso Canoas"
    ],
    "name:und_x_variant":[
        "Paso de Canoa",
        "Canoa Arriba"
    ],
    "wof:name":"Paso Canoas",
    "wof:placetype":"locality"
},
  "geometry": {"coordinates":[-82.83466,8.5318],"type":"Point"}
}