{
  "type": "Feature",
  "properties": {
    "gn:admin1_code":"13",
    "gn:asciiname":"El Mangote",
    "gn:country_code":"PA",
    "gn:dem":19,
    "gn:feature_class":"P",
    "gn:feature_code":"PPL",
    "gn:name":"El Mangote",
    "gn:population":0,
    "gn:timezone":"America/Panama",
    "iso:country":"PA",
    "name:spa_x_preferred":[
        "El Mangote"
    ],
    "wof:name":"El Mangote",
    "wof:placetype":"locality"
},
  "geometry": {"coordinates":[-79.86742,8.61011],"type":"Point"}
}