{
  "type": "Feature",
  "properties": {
    "gn:admin1_code":"13",
    "gn:asciiname":"Florida Abajo",
    "gn:country_code":"PA",
    "gn:dem":153,
    "gn:feature_class":"P",
    "gn:feature_code":"PPL",
    "gn:name":"Florida Abajo",
    "gn:population":0,
    "gn:timezone":"America/Panama",
    "iso:country":"PA",
    "name:und_x_variant":[
        "La Florida",
        "La Florida Abajo",
        "Florida Abajo"
    ],
    "wof:name":"Florida Abajo",
    "wof:placetype":"locality"
},
  "geometry": {"coordinates":[-80.01167,8.84694],"type":"Point"}
}