{
  "type": "Feature",
  "properties": {
    "gn:admin1_code":"06",
    "gn:asciiname":"Portobelillo",
    "gn:country_code":"PA",
    "gn:dem":59,
    "gn:feature_class":"P",
    "gn:feature_code":"PPLA3",
    "gn:name":"Portobelillo",
    "gn:population":497,
    "gn:timezone":"America/Panama",
    "iso:country":"PA",
    "name:und_x_variant":[
        "Porto Bello",
        "Portobelillo"
    ],
    "wof:name":"Portobelillo",
    "wof:placetype":"locality",
    "wof:population":497
},
  "geometry": {"coordinates":[-80.59538000000001,8.01738],"type":"Point"}
}