{
  "type": "Feature",
  "properties": {
    "gn:admin1_code":"10",
    "gn:asciiname":"Los Quinteros",
    "gn:country_code":"PA",
    "gn:dem":102,
    "gn:feature_class":"P",
    "gn:feature_code":"PPL",
    "gn:name":"Los Quinteros",
    "gn:population":42,
    "gn:timezone":"America/Panama",
    "iso:country":"PA",
    "wof:name":"Los Quinteros",
    "wof:placetype":"locality",
    "wof:population":42
},
  "geometry": {"coordinates":[-81.34999999999999,8.16667],"type":"Point"}
}