{
  "type": "Feature",
  "properties": {
    "gn:admin1_code":"13",
    "gn:asciiname":"Corocital",
    "gn:country_code":"PA",
    "gn:dem":125,
    "gn:feature_class":"P",
    "gn:feature_code":"PPL",
    "gn:name":"Corocital",
    "gn:population":35,
    "gn:timezone":"America/Panama",
    "iso:country":"PA",
    "name:und_x_variant":[
        "Corozital",
        "Corocital"
    ],
    "wof:name":"Corocital",
    "wof:placetype":"locality",
    "wof:population":35
},
  "geometry": {"coordinates":[-79.91547,8.75473],"type":"Point"}
}