{
  "type": "Feature",
  "properties": {
    "gn:admin1_code":"03",
    "gn:asciiname":"El Cope",
    "gn:country_code":"PA",
    "gn:dem":338,
    "gn:feature_class":"P",
    "gn:feature_code":"PPLA3",
    "gn:name":"El Cop\u00e9",
    "gn:population":190,
    "gn:timezone":"America/Panama",
    "iso:country":"PA",
    "name:spa_x_preferred":[
        "El Cop\u00e9"
    ],
    "wof:name":"El Cope",
    "wof:placetype":"locality",
    "wof:population":190
},
  "geometry": {"coordinates":[-80.67929000000002,8.43773],"type":"Point"}
}