{
  "type": "Feature",
  "properties": {
    "gn:admin1_code":"02",
    "gn:asciiname":"Alto del Quira",
    "gn:cc2":"PA",
    "gn:country_code":"PA",
    "gn:dem":447,
    "gn:feature_class":"P",
    "gn:feature_code":"PPL",
    "gn:name":"Alto del Quira",
    "gn:population":0,
    "gn:timezone":"America/Panama",
    "iso:country":"PA",
    "name:und_x_variant":[
        "Alto de Quira",
        "Alto del Quira"
    ],
    "wof:name":"Alto del Quira",
    "wof:placetype":"locality"
},
  "geometry": {"coordinates":[-82.33333,8.66667],"type":"Point"}
}