{
  "type": "Feature",
  "properties": {
    "gn:admin1_code":"13",
    "gn:asciiname":"Barriada Royo",
    "gn:country_code":"PA",
    "gn:dem":110,
    "gn:feature_class":"P",
    "gn:feature_code":"PPL",
    "gn:name":"Barriada Royo",
    "gn:population":0,
    "gn:timezone":"America/Panama",
    "iso:country":"PA",
    "name:spa_x_preferred":[
        "Barriada Royo"
    ],
    "wof:name":"Barriada Royo",
    "wof:placetype":"locality"
},
  "geometry": {"coordinates":[-79.86986,8.75636],"type":"Point"}
}