{
  "type": "Feature",
  "properties": {
    "gn:admin1_code":"10",
    "gn:asciiname":"Tinajita",
    "gn:country_code":"PA",
    "gn:dem":112,
    "gn:feature_class":"P",
    "gn:feature_code":"PPL",
    "gn:name":"Tinajita",
    "gn:population":30,
    "gn:timezone":"America/Panama",
    "iso:country":"PA",
    "wof:name":"Tinajita",
    "wof:placetype":"locality",
    "wof:population":30
},
  "geometry": {"coordinates":[-80.94674999999999,8.02158],"type":"Point"}
}