{
  "type": "Feature",
  "properties": {
    "gn:admin1_code":"02",
    "gn:asciiname":"Peje",
    "gn:country_code":"PA",
    "gn:dem":241,
    "gn:feature_class":"P",
    "gn:feature_code":"PPL",
    "gn:name":"Peje",
    "gn:population":0,
    "gn:timezone":"America/Panama",
    "iso:country":"PA",
    "wof:name":"Peje",
    "wof:placetype":"locality"
},
  "geometry": {"coordinates":[-82.26666999999998,8.58333],"type":"Point"}
}