{
  "type": "Feature",
  "properties": {
    "gn:admin1_code":"05",
    "gn:asciiname":"Isleta",
    "gn:country_code":"PA",
    "gn:dem":21,
    "gn:feature_class":"P",
    "gn:feature_code":"PPL",
    "gn:name":"Isleta",
    "gn:population":0,
    "gn:timezone":"America/Panama",
    "iso:country":"PA",
    "name:und_x_variant":[
        "La Isleta"
    ],
    "wof:name":"Isleta",
    "wof:placetype":"locality"
},
  "geometry": {"coordinates":[-78.15491999999998,8.63397],"type":"Point"}
}