{
  "type": "Feature",
  "properties": {
    "gn:admin1_code":"08",
    "gn:asciiname":"Monte Oscuro",
    "gn:country_code":"PA",
    "gn:dem":28,
    "gn:feature_class":"P",
    "gn:feature_code":"PPL",
    "gn:name":"Monte Oscuro",
    "gn:population":0,
    "gn:timezone":"America/Panama",
    "iso:country":"PA",
    "wof:name":"Monte Oscuro",
    "wof:placetype":"locality"
},
  "geometry": {"coordinates":[-79.51666999999998,9.03333],"type":"Point"}
}