{
  "type": "Feature",
  "properties": {
    "gn:admin1_code":"10",
    "gn:asciiname":"Los Hernandez Numero Dos",
    "gn:country_code":"PA",
    "gn:dem":257,
    "gn:feature_class":"P",
    "gn:feature_code":"PPL",
    "gn:name":"Los Hern\u00e1ndez N\u00famero Dos",
    "gn:population":0,
    "gn:timezone":"America/Panama",
    "iso:country":"PA",
    "name:spa_x_preferred":[
        "Los Hern\u00e1ndez N\u00famero Dos"
    ],
    "wof:name":"Los Hernandez Numero Dos",
    "wof:placetype":"locality"
},
  "geometry": {"coordinates":[-81.05694,8.36851],"type":"Point"}
}