{
  "type": "Feature",
  "properties": {
    "gn:admin1_code":"02",
    "gn:asciiname":"Escobal",
    "gn:country_code":"PA",
    "gn:dem":11,
    "gn:feature_class":"P",
    "gn:feature_code":"PPL",
    "gn:name":"Escobal",
    "gn:population":0,
    "gn:timezone":"America/Panama",
    "iso:country":"PA",
    "name:ceb_x_preferred":[
        "Escobal"
    ],
    "name:ita_x_preferred":[
        "Escobal"
    ],
    "name:nld_x_preferred":[
        "Escobal"
    ],
    "name:spa_x_preferred":[
        "Escobal"
    ],
    "name:zho_x_preferred":[
        "\u57c3\u65af\u79d1\u74e6\u5c14"
    ],
    "wof:name":"Escobal",
    "wof:placetype":"locality"
},
  "geometry": {"coordinates":[-82.40441,8.4203],"type":"Point"}
}