{
  "type": "Feature",
  "properties": {
    "gn:admin1_code":"04",
    "gn:asciiname":"El Escobal",
    "gn:country_code":"PA",
    "gn:dem":108,
    "gn:feature_class":"P",
    "gn:feature_code":"PPL",
    "gn:name":"El Escobal",
    "gn:population":0,
    "gn:timezone":"America/Panama",
    "iso:country":"PA",
    "wof:name":"El Escobal",
    "wof:placetype":"locality"
},
  "geometry": {"coordinates":[-80.31667,8.91667],"type":"Point"}
}