{
  "type": "Feature",
  "properties": {
    "gn:admin1_code":"09",
    "gn:asciiname":"Nusadup",
    "gn:country_code":"PA",
    "gn:dem":-9999,
    "gn:feature_class":"P",
    "gn:feature_code":"PPL",
    "gn:name":"Nusadup",
    "gn:population":0,
    "gn:timezone":"America/Panama",
    "iso:country":"PA",
    "name:spa_x_preferred":[
        "Nusadup"
    ],
    "name:und_x_variant":[
        "Isla Rat\u00f3n",
        "Nusatupo"
    ],
    "wof:name":"Nusadup",
    "wof:placetype":"locality"
},
  "geometry": {"coordinates":[-78.83651999999999,9.44208],"type":"Point"}
}