{
  "type": "Feature",
  "properties": {
    "gn:admin1_code":"13",
    "gn:asciiname":"Altos de Campana",
    "gn:country_code":"PA",
    "gn:dem":36,
    "gn:feature_class":"P",
    "gn:feature_code":"PPL",
    "gn:name":"Altos de Campana",
    "gn:population":0,
    "gn:timezone":"America/Panama",
    "iso:country":"PA",
    "wof:name":"Altos de Campana",
    "wof:placetype":"locality"
},
  "geometry": {"coordinates":[-79.86667,8.71667],"type":"Point"}
}