{
  "type": "Feature",
  "properties": {
    "gn:admin1_code":"12",
    "gn:asciiname":"Centro Daira",
    "gn:country_code":"PA",
    "gn:dem":4,
    "gn:feature_class":"P",
    "gn:feature_code":"PPL",
    "gn:name":"Centro Daira",
    "gn:population":302,
    "gn:timezone":"America/Panama",
    "iso:country":"PA",
    "name:spa_x_preferred":[
        "Centro Daira"
    ],
    "wof:name":"Centro Daira",
    "wof:placetype":"locality",
    "wof:population":302
},
  "geometry": {"coordinates":[-82.02226999999998,8.8973],"type":"Point"}
}