{
  "type": "Feature",
  "properties": {
    "gn:admin1_code":"01",
    "gn:asciiname":"Istmito",
    "gn:country_code":"PA",
    "gn:dem":1,
    "gn:feature_class":"P",
    "gn:feature_code":"PPL",
    "gn:name":"Istmito",
    "gn:population":0,
    "gn:timezone":"America/Panama",
    "iso:country":"PA",
    "wof:name":"Istmito",
    "wof:placetype":"locality"
},
  "geometry": {"coordinates":[-82.25,9.35],"type":"Point"}
}