{
  "type": "Feature",
  "properties": {
    "gn:admin1_code":"03",
    "gn:asciiname":"Ciruelito",
    "gn:country_code":"PA",
    "gn:dem":29,
    "gn:feature_class":"P",
    "gn:feature_code":"PPL",
    "gn:name":"Ciruelito",
    "gn:population":526,
    "gn:timezone":"America/Panama",
    "iso:country":"PA",
    "name:spa_x_preferred":[
        "Ciruelito"
    ],
    "wof:name":"Ciruelito",
    "wof:placetype":"locality",
    "wof:population":526
},
  "geometry": {"coordinates":[-80.45,8.45317],"type":"Point"}
}