{
  "type": "Feature",
  "properties": {
    "gn:admin1_code":"07",
    "gn:asciiname":"El Canafistulo",
    "gn:cc2":"PA",
    "gn:country_code":"PA",
    "gn:dem":279,
    "gn:feature_class":"P",
    "gn:feature_code":"PPL",
    "gn:name":"El Ca\u00f1af\u00edstulo",
    "gn:population":0,
    "gn:timezone":"America/Panama",
    "iso:country":"PA",
    "name:und_x_variant":[
        "El Ca\u00f1afisto",
        "El Ca\u00f1af\u00edstulo"
    ],
    "wof:name":"El Canafistulo",
    "wof:placetype":"locality"
},
  "geometry": {"coordinates":[-80.53333000000001,7.63333],"type":"Point"}
}