{
  "type": "Feature",
  "properties": {
    "gn:admin1_code":"12",
    "gn:asciiname":"Jengibrales",
    "gn:country_code":"PA",
    "gn:dem":306,
    "gn:feature_class":"P",
    "gn:feature_code":"PPL",
    "gn:name":"Jengibrales",
    "gn:population":0,
    "gn:timezone":"America/Panama",
    "iso:country":"PA",
    "wof:name":"Jengibrales",
    "wof:placetype":"locality"
},
  "geometry": {"coordinates":[-81.68333,8.35],"type":"Point"}
}