{
  "type": "Feature",
  "properties": {
    "gn:admin1_code":"04",
    "gn:asciiname":"La Encantada",
    "gn:country_code":"PA",
    "gn:dem":6,
    "gn:feature_class":"P",
    "gn:feature_code":"PPLA3",
    "gn:name":"La Encantada",
    "gn:population":0,
    "gn:timezone":"America/Panama",
    "iso:country":"PA",
    "name:ita_x_preferred":[
        "La Encantada"
    ],
    "name:spa_x_preferred":[
        "La Encantada"
    ],
    "name:und_x_variant":[
        "Alcarreto",
        "La Encantada"
    ],
    "name:zho_x_preferred":[
        "\u62c9\u6069\u574e\u5854\u9054"
    ],
    "wof:name":"La Encantada",
    "wof:placetype":"locality"
},
  "geometry": {"coordinates":[-80.19158,9.08703],"type":"Point"}
}