{
  "type": "Feature",
  "properties": {
    "gn:admin1_code":"02",
    "gn:asciiname":"Cabrera",
    "gn:country_code":"PA",
    "gn:dem":3,
    "gn:feature_class":"P",
    "gn:feature_code":"PPL",
    "gn:name":"Cabrera",
    "gn:population":0,
    "gn:timezone":"America/Panama",
    "iso:country":"PA",
    "wof:name":"Cabrera",
    "wof:placetype":"locality"
},
  "geometry": {"coordinates":[-81.83333,8.16667],"type":"Point"}
}