{
  "type": "Feature",
  "properties": {
    "gn:admin1_code":"10",
    "gn:asciiname":"El Mangal",
    "gn:country_code":"PA",
    "gn:dem":290,
    "gn:feature_class":"P",
    "gn:feature_code":"PPL",
    "gn:name":"El Mangal",
    "gn:population":0,
    "gn:timezone":"America/Panama",
    "iso:country":"PA",
    "wof:name":"El Mangal",
    "wof:placetype":"locality"
},
  "geometry": {"coordinates":[-81.26666999999998,8.38333],"type":"Point"}
}