{
  "type": "Feature",
  "properties": {
    "gn:admin1_code":"10",
    "gn:asciiname":"El Yaya",
    "gn:country_code":"PA",
    "gn:dem":380,
    "gn:feature_class":"P",
    "gn:feature_code":"PPL",
    "gn:name":"El Yaya",
    "gn:population":0,
    "gn:timezone":"America/Panama",
    "iso:country":"PA",
    "wof:name":"El Yaya",
    "wof:placetype":"locality"
},
  "geometry": {"coordinates":[-81.35389000000001,7.85722],"type":"Point"}
}