{
  "type": "Feature",
  "properties": {
    "iso:country":"PA",
    "name:ast_x_preferred":[
        "Pacora"
    ],
    "name:bel_x_variant":[
        "\u041f\u0430\u043a\u043e\u0440\u0430"
    ],
    "name:ceb_x_preferred":[
        "Pacora"
    ],
    "name:eng_x_preferred":[
        "Pacora"
    ],
    "name:fra_x_preferred":[
        "Pacora"
    ],
    "name:ita_x_preferred":[
        "Pacora"
    ],
    "name:jpn_x_preferred":[
        "\u30d1\u30b3\u30e9"
    ],
    "name:kat_x_preferred":[
        "\u10de\u10d0\u10d9\u10dd\u10e0\u10d0"
    ],
    "name:nld_x_preferred":[
        "Pacora"
    ],
    "name:pol_x_preferred":[
        "Pacora"
    ],
    "name:sco_x_preferred":[
        "Pacora"
    ],
    "name:spa_x_preferred":[
        "Pacora"
    ],
    "name:zho_x_preferred":[
        "\u5e15\u79d1\u62c9"
    ],
    "qs:gn_country":"PA",
    "qs:gn_fcode":"PPL",
    "qs:gn_pop":55530,
    "qs:name":"Pacora",
    "qs:name_adm0":"Panam\u00e1",
    "qs:name_adm1":"Panam\u00e1",
    "qs:photos":5,
    "qs:photos_1k":1,
    "qs:photos_9k":1,
    "qs:photos_9r":1,
    "qs:photos_all":5,
    "qs:photos_sr":1,
    "qs:placetype":"LocalAdmin",
    "qs:pop_sr":"8",
    "qs:woe_adm0":23424924,
    "wd:wordcount":83,
    "wof:name":"Pacora",
    "wof:placetype":"localadmin",
    "wof:population":55530
},
  "geometry": {"coordinates":[-79.28333000000001,9.08333],"type":"Point"}
}