{
  "type": "Feature",
  "properties": {
    "gn:admin1_code":"10",
    "gn:asciiname":"Cerro Armado",
    "gn:country_code":"PA",
    "gn:dem":323,
    "gn:feature_class":"P",
    "gn:feature_code":"PPL",
    "gn:name":"Cerro Armado",
    "gn:population":0,
    "gn:timezone":"America/Panama",
    "iso:country":"PA",
    "wof:name":"Cerro Armado",
    "wof:placetype":"locality"
},
  "geometry": {"coordinates":[-81.56667,8.16667],"type":"Point"}
}