{
  "type": "Feature",
  "properties": {
    "gn:admin1_code":"12",
    "gn:asciiname":"Bisira Arriba",
    "gn:country_code":"PA",
    "gn:dem":711,
    "gn:feature_class":"P",
    "gn:feature_code":"PPL",
    "gn:name":"Bisira Arriba",
    "gn:population":0,
    "gn:timezone":"America/Panama",
    "iso:country":"PA",
    "name:spa_x_preferred":[
        "Bisira Arriba"
    ],
    "wof:name":"Bisira Arriba",
    "wof:placetype":"locality"
},
  "geometry": {"coordinates":[-81.75577,8.63322],"type":"Point"}
}