{
  "type": "Feature",
  "properties": {
    "gn:admin1_code":"03",
    "gn:asciiname":"El Mono",
    "gn:country_code":"PA",
    "gn:dem":100,
    "gn:feature_class":"P",
    "gn:feature_code":"PPL",
    "gn:name":"El Mono",
    "gn:population":28,
    "gn:timezone":"America/Panama",
    "iso:country":"PA",
    "wof:name":"El Mono",
    "wof:placetype":"locality",
    "wof:population":28
},
  "geometry": {"coordinates":[-80.69524,8.3016],"type":"Point"}
}