{
  "type": "Feature",
  "properties": {
    "gn:admin1_code":"02",
    "gn:asciiname":"Quebrada Cacao",
    "gn:country_code":"PA",
    "gn:dem":49,
    "gn:feature_class":"P",
    "gn:feature_code":"PPL",
    "gn:name":"Quebrada Cacao",
    "gn:population":0,
    "gn:timezone":"America/Panama",
    "iso:country":"PA",
    "wof:name":"Quebrada Cacao",
    "wof:placetype":"locality"
},
  "geometry": {"coordinates":[-82.76666999999998,8.46667],"type":"Point"}
}