{
  "type": "Feature",
  "properties": {
    "gn:admin1_code":"12",
    "gn:asciiname":"Bahia Grande",
    "gn:country_code":"PA",
    "gn:dem":-9999,
    "gn:feature_class":"P",
    "gn:feature_code":"PPL",
    "gn:name":"Bah\u00eda Grande",
    "gn:population":252,
    "gn:timezone":"America/Panama",
    "iso:country":"PA",
    "name:spa_x_preferred":[
        "Bah\u00eda Grande"
    ],
    "wof:name":"Bahia Grande",
    "wof:placetype":"locality",
    "wof:population":252
},
  "geometry": {"coordinates":[-81.82148000000002,9.02209],"type":"Point"}
}