{
  "type": "Feature",
  "properties": {
    "gn:admin1_code":"11",
    "gn:asciiname":"Lajas Blancas",
    "gn:country_code":"PA",
    "gn:dem":20,
    "gn:feature_class":"P",
    "gn:feature_code":"PPLA3",
    "gn:name":"Lajas Blancas",
    "gn:population":0,
    "gn:timezone":"America/Panama",
    "iso:country":"PA",
    "name:ita_x_preferred":[
        "Lajas Blancas"
    ],
    "name:spa_x_preferred":[
        "Lajas Blancas"
    ],
    "name:zho_x_preferred":[
        "\u62c9\u54c8\u65af\u5e03\u862d\u5361\u65af"
    ],
    "wof:name":"Lajas Blancas",
    "wof:placetype":"locality"
},
  "geometry": {"coordinates":[-77.81161,8.41482],"type":"Point"}
}