{
  "type": "Feature",
  "properties": {
    "gn:admin1_code":"05",
    "gn:asciiname":"Reserva",
    "gn:country_code":"PA",
    "gn:dem":46,
    "gn:feature_class":"P",
    "gn:feature_code":"PPL",
    "gn:name":"Reserva",
    "gn:population":0,
    "gn:timezone":"America/Panama",
    "iso:country":"PA",
    "name:spa_x_preferred":[
        "Reserva"
    ],
    "wof:name":"Reserva",
    "wof:placetype":"locality"
},
  "geometry": {"coordinates":[-78.3954,8.62395],"type":"Point"}
}