{
  "type": "Feature",
  "properties": {
    "gn:admin1_code":"06",
    "gn:asciiname":"Los Panamaes",
    "gn:country_code":"PA",
    "gn:dem":23,
    "gn:feature_class":"P",
    "gn:feature_code":"PPL",
    "gn:name":"Los Panamaes",
    "gn:population":1,
    "gn:timezone":"America/Panama",
    "iso:country":"PA",
    "wof:name":"Los Panamaes",
    "wof:placetype":"locality",
    "wof:population":1
},
  "geometry": {"coordinates":[-80.55459999999999,7.98769],"type":"Point"}
}