{
  "type": "Feature",
  "properties": {
    "gn:admin1_code":"03",
    "gn:asciiname":"Perecabe",
    "gn:country_code":"PA",
    "gn:dem":253,
    "gn:feature_class":"P",
    "gn:feature_code":"PPL",
    "gn:name":"Perecab\u00e9",
    "gn:population":195,
    "gn:timezone":"America/Panama",
    "iso:country":"PA",
    "name:spa_x_preferred":[
        "Perecab\u00e9"
    ],
    "wof:name":"Perecabe",
    "wof:placetype":"locality",
    "wof:population":195
},
  "geometry": {"coordinates":[-80.38464999999999,8.65421],"type":"Point"}
}