{
  "type": "Feature",
  "properties": {
    "gn:admin1_code":"03",
    "gn:asciiname":"Hato de San Juan de Dios",
    "gn:country_code":"PA",
    "gn:dem":96,
    "gn:feature_class":"P",
    "gn:feature_code":"PPL",
    "gn:name":"Hato de San Juan de Dios",
    "gn:population":458,
    "gn:timezone":"America/Panama",
    "iso:country":"PA",
    "name:spa_x_preferred":[
        "Hato de San Juan de Dios"
    ],
    "name:und_x_variant":[
        "El Hato de San Juan de Dios"
    ],
    "wof:name":"Hato de San Juan de Dios",
    "wof:placetype":"locality",
    "wof:population":458
},
  "geometry": {"coordinates":[-80.66886,8.27802],"type":"Point"}
}