{
  "type": "Feature",
  "properties": {
    "gn:admin1_code":"03",
    "gn:asciiname":"El Hatillo",
    "gn:cc2":"PA",
    "gn:country_code":"PA",
    "gn:dem":178,
    "gn:feature_class":"P",
    "gn:feature_code":"PPL",
    "gn:name":"El Hatillo",
    "gn:population":38,
    "gn:timezone":"America/Panama",
    "iso:country":"PA",
    "name:und_x_variant":[
        "Hatillo",
        "El Artillo",
        "El Hatillo"
    ],
    "wof:name":"El Hatillo",
    "wof:placetype":"locality",
    "wof:population":38
},
  "geometry": {"coordinates":[-80.38333,8.58333],"type":"Point"}
}