{
  "type": "Feature",
  "properties": {
    "gn:admin1_code":"02",
    "gn:asciiname":"Canafistulo",
    "gn:cc2":"PA",
    "gn:country_code":"PA",
    "gn:dem":57,
    "gn:feature_class":"P",
    "gn:feature_code":"PPL",
    "gn:name":"Ca\u00f1af\u00edstulo",
    "gn:population":49,
    "gn:timezone":"America/Panama",
    "iso:country":"PA",
    "name:und_x_variant":[
        "Canafistula",
        "Ca\u00f1af\u00edstulo"
    ],
    "wof:name":"Canafistulo",
    "wof:placetype":"locality",
    "wof:population":49
},
  "geometry": {"coordinates":[-82.11508000000001,8.34476],"type":"Point"}
}