{
  "type": "Feature",
  "properties": {
    "gn:admin1_code":"08",
    "gn:asciiname":"Limonada",
    "gn:country_code":"PA",
    "gn:dem":150,
    "gn:feature_class":"P",
    "gn:feature_code":"PPL",
    "gn:name":"Limonada",
    "gn:population":0,
    "gn:timezone":"America/Panama",
    "iso:country":"PA",
    "name:spa_x_preferred":[
        "Limonada"
    ],
    "wof:name":"Limonada",
    "wof:placetype":"locality"
},
  "geometry": {"coordinates":[-78.97103,9.08028],"type":"Point"}
}