{
  "type": "Feature",
  "properties": {
    "gn:admin1_code":"01",
    "gn:asciiname":"Juan Cuero",
    "gn:country_code":"PA",
    "gn:dem":2,
    "gn:feature_class":"P",
    "gn:feature_code":"PPL",
    "gn:name":"Juan Cuero",
    "gn:population":0,
    "gn:timezone":"America/Panama",
    "iso:country":"PA",
    "wof:name":"Juan Cuero",
    "wof:placetype":"locality"
},
  "geometry": {"coordinates":[-82.09999999999999,8.93333],"type":"Point"}
}