{
  "type": "Feature",
  "properties": {
    "gn:admin1_code":"04",
    "gn:asciiname":"Alto de la Cruz",
    "gn:country_code":"PA",
    "gn:dem":28,
    "gn:feature_class":"P",
    "gn:feature_code":"PPL",
    "gn:name":"Alto de la Cruz",
    "gn:population":0,
    "gn:timezone":"America/Panama",
    "iso:country":"PA",
    "name:spa_x_preferred":[
        "Alto de la Cruz"
    ],
    "wof:name":"Alto de la Cruz",
    "wof:placetype":"locality"
},
  "geometry": {"coordinates":[-79.72123000000001,9.47482],"type":"Point"}
}