{
  "type": "Feature",
  "properties": {
    "gn:admin1_code":"02",
    "gn:asciiname":"Alto Quiel",
    "gn:country_code":"PA",
    "gn:dem":1105,
    "gn:feature_class":"P",
    "gn:feature_code":"PPL",
    "gn:name":"Alto Quiel",
    "gn:population":576,
    "gn:timezone":"America/Panama",
    "iso:country":"PA",
    "name:spa_x_preferred":[
        "Alto Quiel"
    ],
    "wof:name":"Alto Quiel",
    "wof:placetype":"locality",
    "wof:population":576
},
  "geometry": {"coordinates":[-82.89905999999998,8.72978],"type":"Point"}
}