{
  "type": "Feature",
  "properties": {
    "gn:admin1_code":"12",
    "gn:asciiname":"El Penon",
    "gn:country_code":"PA",
    "gn:dem":379,
    "gn:feature_class":"P",
    "gn:feature_code":"PPL",
    "gn:name":"El Pe\u00f1\u00f3n",
    "gn:population":176,
    "gn:timezone":"America/Panama",
    "iso:country":"PA",
    "name:spa_x_preferred":[
        "El Pe\u00f1\u00f3n"
    ],
    "wof:name":"El Penon",
    "wof:placetype":"locality",
    "wof:population":176
},
  "geometry": {"coordinates":[-81.41956,8.4531],"type":"Point"}
}