{
  "type": "Feature",
  "properties": {
    "gn:admin1_code":"04",
    "gn:asciiname":"Petaquilla",
    "gn:cc2":"PA",
    "gn:country_code":"PA",
    "gn:dem":64,
    "gn:feature_class":"P",
    "gn:feature_code":"PPL",
    "gn:name":"Petaquilla",
    "gn:population":0,
    "gn:timezone":"America/Panama",
    "iso:country":"PA",
    "name:spa_x_preferred":[
        "Petaquilla"
    ],
    "name:und_x_variant":[
        "Petaquilla N\u00famero Dos",
        "Petaquilla"
    ],
    "wof:name":"Petaquilla",
    "wof:placetype":"locality"
},
  "geometry": {"coordinates":[-80.75,8.98333],"type":"Point"}
}