{
  "type": "Feature",
  "properties": {
    "gn:admin1_code":"03",
    "gn:asciiname":"Hato de San Antonio",
    "gn:country_code":"PA",
    "gn:dem":14,
    "gn:feature_class":"P",
    "gn:feature_code":"PPL",
    "gn:name":"Hato de San Antonio",
    "gn:population":392,
    "gn:timezone":"America/Panama",
    "iso:country":"PA",
    "name:und_x_variant":[
        "Hato San Antonio"
    ],
    "wof:name":"Hato de San Antonio",
    "wof:placetype":"locality",
    "wof:population":392
},
  "geometry": {"coordinates":[-80.6837,8.1489],"type":"Point"}
}