{
  "type": "Feature",
  "properties": {
    "gn:admin1_code":"03",
    "gn:asciiname":"Banazo Abajo",
    "gn:country_code":"PA",
    "gn:dem":150,
    "gn:feature_class":"P",
    "gn:feature_code":"PPL",
    "gn:name":"Banazo Abajo",
    "gn:population":0,
    "gn:timezone":"America/Panama",
    "iso:country":"PA",
    "wof:name":"Banazo Abajo",
    "wof:placetype":"locality"
},
  "geometry": {"coordinates":[-80.31667,8.81667],"type":"Point"}
}