{
  "type": "Feature",
  "properties": {
    "gn:admin1_code":"03",
    "gn:asciiname":"Las Tablas",
    "gn:country_code":"PA",
    "gn:dem":146,
    "gn:feature_class":"P",
    "gn:feature_code":"PPL",
    "gn:name":"Las Tablas",
    "gn:population":0,
    "gn:timezone":"America/Panama",
    "iso:country":"PA",
    "name:ceb_x_preferred":[
        "Las Tablas"
    ],
    "name:ita_x_preferred":[
        "Las Tablas"
    ],
    "name:spa_x_preferred":[
        "Las Tablas"
    ],
    "name:srp_x_preferred":[
        "\u041b\u0430\u0441 \u0422\u0430\u0431\u043b\u0430\u0441"
    ],
    "name:swe_x_preferred":[
        "Las Tablas"
    ],
    "wof:name":"Las Tablas",
    "wof:placetype":"locality"
},
  "geometry": {"coordinates":[-80.54304,8.59292],"type":"Point"}
}