{
  "type": "Feature",
  "properties": {
    "gn:admin1_code":"10",
    "gn:asciiname":"El Caimito",
    "gn:country_code":"PA",
    "gn:dem":47,
    "gn:feature_class":"P",
    "gn:feature_code":"PPL",
    "gn:name":"El Caimito",
    "gn:population":11,
    "gn:timezone":"America/Panama",
    "iso:country":"PA",
    "wof:name":"El Caimito",
    "wof:placetype":"locality",
    "wof:population":11
},
  "geometry": {"coordinates":[-81.12976999999999,8.04014],"type":"Point"}
}