{
  "type": "Feature",
  "properties": {
    "gn:admin1_code":"10",
    "gn:asciiname":"Bubi",
    "gn:country_code":"PA",
    "gn:dem":10,
    "gn:feature_class":"P",
    "gn:feature_code":"PPL",
    "gn:name":"Bubi",
    "gn:population":16,
    "gn:timezone":"America/Panama",
    "iso:country":"PA",
    "name:ceb_x_preferred":[
        "Bubi"
    ],
    "name:deu_x_preferred":[
        "Bubi"
    ],
    "name:fin_x_preferred":[
        "Bubi"
    ],
    "name:fra_x_preferred":[
        "Bubi"
    ],
    "name:hun_x_preferred":[
        "Bubi"
    ],
    "name:ita_x_preferred":[
        "Bubi"
    ],
    "name:nld_x_preferred":[
        "Bubi"
    ],
    "name:rus_x_preferred":[
        "\u0411\u0443\u0431\u0438"
    ],
    "name:swe_x_preferred":[
        "Bubi"
    ],
    "name:tat_x_preferred":[
        "\u0411\u0443\u0431\u0438"
    ],
    "wof:name":"Bubi",
    "wof:placetype":"locality",
    "wof:population":16
},
  "geometry": {"coordinates":[-81.54553,8.01046],"type":"Point"}
}