{
  "type": "Feature",
  "properties": {
    "gn:admin1_code":"01",
    "gn:asciiname":"Isla Tigre",
    "gn:country_code":"PA",
    "gn:dem":5,
    "gn:feature_class":"P",
    "gn:feature_code":"PPL",
    "gn:name":"Isla Tigre",
    "gn:population":540,
    "gn:timezone":"America/Panama",
    "iso:country":"PA",
    "name:spa_x_preferred":[
        "Isla Tigre"
    ],
    "wof:name":"Isla Tigre",
    "wof:placetype":"locality",
    "wof:population":540
},
  "geometry": {"coordinates":[-82.08041,9.17471],"type":"Point"}
}