{
  "type": "Feature",
  "properties": {
    "gn:admin1_code":"10",
    "gn:asciiname":"Pedregoso",
    "gn:country_code":"PA",
    "gn:dem":46,
    "gn:feature_class":"P",
    "gn:feature_code":"PPL",
    "gn:name":"Pedregoso",
    "gn:population":0,
    "gn:timezone":"America/Panama",
    "iso:country":"PA",
    "wof:name":"Pedregoso",
    "wof:placetype":"locality"
},
  "geometry": {"coordinates":[-80.96666999999999,8.01667],"type":"Point"}
}