{
  "type": "Feature",
  "properties": {
    "gn:admin1_code":"02",
    "gn:asciiname":"Quebrada de Lajas",
    "gn:country_code":"PA",
    "gn:dem":484,
    "gn:feature_class":"P",
    "gn:feature_code":"PPL",
    "gn:name":"Quebrada de Lajas",
    "gn:population":0,
    "gn:timezone":"America/Panama",
    "iso:country":"PA",
    "wof:name":"Quebrada de Lajas",
    "wof:placetype":"locality"
},
  "geometry": {"coordinates":[-81.65000000000001,8.15],"type":"Point"}
}