{
  "type": "Feature",
  "properties": {
    "gn:admin1_code":"01",
    "gn:asciiname":"Milla Tres",
    "gn:country_code":"PA",
    "gn:dem":10,
    "gn:feature_class":"P",
    "gn:feature_code":"PPL",
    "gn:name":"Milla Tres",
    "gn:population":0,
    "gn:timezone":"America/Panama",
    "iso:country":"PA",
    "name:spa_x_preferred":[
        "Milla Tres"
    ],
    "wof:name":"Milla Tres",
    "wof:placetype":"locality"
},
  "geometry": {"coordinates":[-82.41679000000001,9.31033],"type":"Point"}
}