{
  "type": "Feature",
  "properties": {
    "gn:admin1_code":"02",
    "gn:asciiname":"Finca Balsa",
    "gn:country_code":"PA",
    "gn:dem":21,
    "gn:feature_class":"P",
    "gn:feature_code":"PPL",
    "gn:name":"Finca Balsa",
    "gn:population":502,
    "gn:timezone":"America/Panama",
    "iso:country":"PA",
    "name:spa_x_preferred":[
        "Finca Balsa"
    ],
    "wof:name":"Finca Balsa",
    "wof:placetype":"locality",
    "wof:population":502
},
  "geometry": {"coordinates":[-82.89726,8.42891],"type":"Point"}
}