{
  "type": "Feature",
  "properties": {
    "gn:admin1_code":"06",
    "gn:asciiname":"Las Cuestas",
    "gn:country_code":"PA",
    "gn:dem":138,
    "gn:feature_class":"P",
    "gn:feature_code":"PPL",
    "gn:name":"Las Cuestas",
    "gn:population":74,
    "gn:timezone":"America/Panama",
    "iso:country":"PA",
    "wof:name":"Las Cuestas",
    "wof:placetype":"locality",
    "wof:population":74
},
  "geometry": {"coordinates":[-80.67399,7.82806],"type":"Point"}
}