{
  "type": "Feature",
  "properties": {
    "gn:admin1_code":"12",
    "gn:asciiname":"Alto Caballero",
    "gn:country_code":"PA",
    "gn:dem":446,
    "gn:feature_class":"P",
    "gn:feature_code":"PPLA3",
    "gn:name":"Alto Caballero",
    "gn:population":0,
    "gn:timezone":"America/Panama",
    "iso:country":"PA",
    "name:spa_x_preferred":[
        "Alto Caballero"
    ],
    "wof:name":"Alto Caballero",
    "wof:placetype":"locality"
},
  "geometry": {"coordinates":[-81.67349,8.28989],"type":"Point"}
}