{
  "type": "Feature",
  "properties": {
    "gn:admin1_code":"05",
    "gn:asciiname":"Calle Larga",
    "gn:country_code":"PA",
    "gn:dem":217,
    "gn:feature_class":"P",
    "gn:feature_code":"PPL",
    "gn:name":"Calle Larga",
    "gn:population":0,
    "gn:timezone":"America/Panama",
    "iso:country":"PA",
    "name:ara_x_preferred":[
        "\u0643\u0627\u0644\u064a \u0627\u0631\u063a\u0627"
    ],
    "name:ceb_x_preferred":[
        "Calle Larga"
    ],
    "name:eus_x_preferred":[
        "Calle Larga"
    ],
    "name:fas_x_preferred":[
        "\u06a9\u0627\u06cc\u0647 \u0644\u0627\u0631\u06af\u0627"
    ],
    "name:fra_x_preferred":[
        "Calle Larga"
    ],
    "name:ita_x_preferred":[
        "Calle Larga"
    ],
    "name:kor_x_preferred":[
        "\uce74\uc608\ub77c\ub974\uac00"
    ],
    "name:nld_x_preferred":[
        "Calle Larga"
    ],
    "name:por_x_preferred":[
        "Calle Larga"
    ],
    "name:ron_x_preferred":[
        "Calle Larga"
    ],
    "name:rus_x_preferred":[
        "\u041a\u0430\u043b\u044c\u0435-\u041b\u0430\u0440\u0433\u0430"
    ],
    "name:spa_x_preferred":[
        "Calle Larga"
    ],
    "name:zho_x_preferred":[
        "\u5361\u840a\u62c9\u723e\u52a0"
    ],
    "wof:name":"Calle Larga",
    "wof:placetype":"locality"
},
  "geometry": {"coordinates":[-78.06917,7.6125],"type":"Point"}
}