{
  "type": "Feature",
  "properties": {
    "gn:admin1_code":"05",
    "gn:asciiname":"Calle Larga",
    "gn:country_code":"PA",
    "gn:dem":217,
    "gn:feature_class":"P",
    "gn:feature_code":"PPL",
    "gn:name":"Calle Larga",
    "gn:population":0,
    "gn:timezone":"America/Panama",
    "iso:country":"PA",
    "wof:name":"Calle Larga",
    "wof:placetype":"locality"
},
  "geometry": {"coordinates":[-78.06917,7.6125],"type":"Point"}
}