{
  "type": "Feature",
  "properties": {
    "iso:country":"PA",
    "name:eng_x_preferred":[
        "Dolega"
    ],
    "name:fra_x_preferred":[
        "Dolega"
    ],
    "name:ita_x_preferred":[
        "Dolega"
    ],
    "name:kat_x_preferred":[
        "\u10d3\u10dd\u10da\u10d4\u10d2\u10d0"
    ],
    "name:nld_x_preferred":[
        "Dolega"
    ],
    "name:spa_x_preferred":[
        "Dolega"
    ],
    "name:zho_x_preferred":[
        "\u591a\u840a\u52a0"
    ],
    "qs:gn_country":"PA",
    "qs:gn_fcode":"PPL",
    "qs:gn_pop":1653,
    "qs:name":"Dolega",
    "qs:name_adm0":"Panam\u00e1",
    "qs:name_adm1":"Chiriqu\u00ed",
    "qs:photos":2,
    "qs:photos_1k":1,
    "qs:photos_9k":1,
    "qs:photos_9r":1,
    "qs:photos_all":2,
    "qs:photos_sr":1,
    "qs:placetype":"LocalAdmin",
    "qs:pop_sr":"3",
    "qs:woe_adm0":23424924,
    "wd:wordcount":112,
    "wof:name":"Dolega",
    "wof:placetype":"localadmin",
    "wof:population":1653
},
  "geometry": {"coordinates":[-82.41667,8.56667],"type":"Point"}
}