{
  "type": "Feature",
  "properties": {
    "gn:admin1_code":"07",
    "gn:asciiname":"El Tabanito",
    "gn:cc2":"PA",
    "gn:country_code":"PA",
    "gn:dem":97,
    "gn:feature_class":"P",
    "gn:feature_code":"PPL",
    "gn:name":"El Tabanito",
    "gn:population":0,
    "gn:timezone":"America/Panama",
    "iso:country":"PA",
    "name:und_x_variant":[
        "Tabanito",
        "El Tabanito"
    ],
    "wof:name":"El Tabanito",
    "wof:placetype":"locality"
},
  "geometry": {"coordinates":[-80.16667,7.58333],"type":"Point"}
}