{
  "type": "Feature",
  "properties": {
    "gn:admin1_code":"13",
    "gn:asciiname":"La Uva",
    "gn:country_code":"PA",
    "gn:dem":204,
    "gn:feature_class":"P",
    "gn:feature_code":"PPL",
    "gn:name":"La Uva",
    "gn:population":78,
    "gn:timezone":"America/Panama",
    "iso:country":"PA",
    "name:und_x_variant":[
        "La Uba",
        "La Uva"
    ],
    "wof:name":"La Uva",
    "wof:placetype":"locality",
    "wof:population":78
},
  "geometry": {"coordinates":[-80.01666999999998,8.53333],"type":"Point"}
}