{
  "type": "Feature",
  "properties": {
    "gn:admin1_code":"04",
    "gn:asciiname":"Lima",
    "gn:country_code":"PA",
    "gn:dem":13,
    "gn:feature_class":"P",
    "gn:feature_code":"PPL",
    "gn:name":"Lima",
    "gn:population":0,
    "gn:timezone":"America/Panama",
    "iso:country":"PA",
    "wof:name":"Lima",
    "wof:placetype":"locality"
},
  "geometry": {"coordinates":[-79.56667,9.61667],"type":"Point"}
}