{
  "type": "Feature",
  "properties": {
    "gn:admin1_code":"06",
    "gn:asciiname":"Llano de Los Reyes",
    "gn:country_code":"PA",
    "gn:dem":96,
    "gn:feature_class":"P",
    "gn:feature_code":"PPL",
    "gn:name":"Llano de Los Reyes",
    "gn:population":0,
    "gn:timezone":"America/Panama",
    "iso:country":"PA",
    "name:spa_x_preferred":[
        "Llano de Los Reyes"
    ],
    "wof:name":"Llano de Los Reyes",
    "wof:placetype":"locality"
},
  "geometry": {"coordinates":[-80.67229,7.89493],"type":"Point"}
}