{
  "type": "Feature",
  "properties": {
    "gn:admin1_code":"07",
    "gn:asciiname":"La Queseria",
    "gn:country_code":"PA",
    "gn:dem":117,
    "gn:feature_class":"P",
    "gn:feature_code":"PPL",
    "gn:name":"La Queser\u00eda",
    "gn:population":0,
    "gn:timezone":"America/Panama",
    "iso:country":"PA",
    "wof:name":"La Queseria",
    "wof:placetype":"locality"
},
  "geometry": {"coordinates":[-80.09999999999999,7.48333],"type":"Point"}
}