{
  "type": "Feature",
  "properties": {
    "gn:admin1_code":"10",
    "gn:asciiname":"Pan de Azucar",
    "gn:cc2":"PA",
    "gn:country_code":"PA",
    "gn:dem":67,
    "gn:feature_class":"P",
    "gn:feature_code":"PPL",
    "gn:name":"Pan de Az\u00facar",
    "gn:population":0,
    "gn:timezone":"America/Panama",
    "iso:country":"PA",
    "name:und_x_variant":[
        "Pan de Az\u00facar N\u00famero Dos",
        "Pan de Az\u00facar"
    ],
    "wof:name":"Pan de Azucar",
    "wof:placetype":"locality"
},
  "geometry": {"coordinates":[-80.98333000000002,8.21667],"type":"Point"}
}