{
  "type": "Feature",
  "properties": {
    "gn:admin1_code":"02",
    "gn:asciiname":"Palmito Numero Uno",
    "gn:country_code":"PA",
    "gn:dem":18,
    "gn:feature_class":"P",
    "gn:feature_code":"PPL",
    "gn:name":"Palmito N\u00famero Uno",
    "gn:population":0,
    "gn:timezone":"America/Panama",
    "iso:country":"PA",
    "name:spa_x_preferred":[
        "Palmito N\u00famero Uno"
    ],
    "wof:name":"Palmito Numero Uno",
    "wof:placetype":"locality"
},
  "geometry": {"coordinates":[-82.86133000000002,8.4006],"type":"Point"}
}