{
  "type": "Feature",
  "properties": {
    "gn:admin1_code":"06",
    "gn:asciiname":"Los Ceibos",
    "gn:country_code":"PA",
    "gn:dem":454,
    "gn:feature_class":"P",
    "gn:feature_code":"PPL",
    "gn:name":"Los Ceibos",
    "gn:population":0,
    "gn:timezone":"America/Panama",
    "iso:country":"PA",
    "wof:name":"Los Ceibos",
    "wof:placetype":"locality"
},
  "geometry": {"coordinates":[-80.81667,7.75],"type":"Point"}
}