{
  "type": "Feature",
  "properties": {
    "iso:country":"PA",
    "name:ceb_x_preferred":[
        "Santa F\u00e9"
    ],
    "name:deu_x_preferred":[
        "Santa F\u00e9"
    ],
    "name:eng_x_preferred":[
        "Santa Fe"
    ],
    "name:hun_x_preferred":[
        "Santa Fe"
    ],
    "name:ita_x_preferred":[
        "Santa F\u00e9"
    ],
    "name:jpn_x_preferred":[
        "\u30b5\u30f3\u30bf\u30d5\u30a7"
    ],
    "name:lit_x_preferred":[
        "Santa F\u0117"
    ],
    "name:nld_x_preferred":[
        "Santa Fe"
    ],
    "name:spa_x_preferred":[
        "Santa Fe"
    ],
    "name:spa_x_variant":[
        "Santa F\u00e9"
    ],
    "name:urd_x_preferred":[
        "\u0633\u0627\u0646\u062a\u0627 \u0641\u06d2\u060c \u0648\u06cc\u0631\u0627\u06af\u0648\u0627\u0633"
    ],
    "name:urd_x_variant":[
        "\u0633\u0627\u0646\u062a\u0627 \u0641\u06d2"
    ],
    "name:zho_x_preferred":[
        "\u8056\u9054\u83f2"
    ],
    "qs:gn_country":"PA",
    "qs:gn_fcode":"PPL",
    "qs:gn_pop":950,
    "qs:name":"Santa Fe",
    "qs:name_adm0":"Panam\u00e1",
    "qs:name_adm1":"Veraguas",
    "qs:photos":110,
    "qs:photos_1k":22,
    "qs:photos_9k":1,
    "qs:photos_9r":3,
    "qs:photos_all":110,
    "qs:photos_sr":3,
    "qs:placetype":"Town",
    "qs:pop_sr":"2",
    "qs:woe_adm0":23424924,
    "wd:wordcount":602,
    "wof:name":"Santa Fe",
    "wof:placetype":"locality",
    "wof:population":950
},
  "geometry": {"coordinates":[-81.08333,8.51667],"type":"Point"}
}