{
  "type": "Feature",
  "properties": {
    "gn:admin1_code":"06",
    "gn:asciiname":"El Higuito",
    "gn:country_code":"PA",
    "gn:dem":58,
    "gn:feature_class":"P",
    "gn:feature_code":"PPL",
    "gn:name":"El Higuito",
    "gn:population":0,
    "gn:timezone":"America/Panama",
    "iso:country":"PA",
    "wof:name":"El Higuito",
    "wof:placetype":"locality"
},
  "geometry": {"coordinates":[-80.78333000000001,8.06667],"type":"Point"}
}