{
  "type": "Feature",
  "properties": {
    "gn:admin1_code":"13",
    "gn:asciiname":"San Sebastian",
    "gn:country_code":"PA",
    "gn:dem":259,
    "gn:feature_class":"P",
    "gn:feature_code":"PPL",
    "gn:name":"San Sebastian",
    "gn:population":81,
    "gn:timezone":"America/Panama",
    "iso:country":"PA",
    "wof:name":"San Sebastian",
    "wof:placetype":"locality",
    "wof:population":81
},
  "geometry": {"coordinates":[-79.97139,8.87583],"type":"Point"}
}