{
  "type": "Feature",
  "properties": {
    "gn:admin1_code":"10",
    "gn:asciiname":"Marea Arriba",
    "gn:country_code":"PA",
    "gn:dem":72,
    "gn:feature_class":"P",
    "gn:feature_code":"PPL",
    "gn:name":"Marea Arriba",
    "gn:population":15,
    "gn:timezone":"America/Panama",
    "iso:country":"PA",
    "wof:name":"Marea Arriba",
    "wof:placetype":"locality",
    "wof:population":15
},
  "geometry": {"coordinates":[-80.99633,7.90514],"type":"Point"}
}