{
  "type": "Feature",
  "properties": {
    "gn:admin1_code":"10",
    "gn:asciiname":"Pueblo Viejo",
    "gn:cc2":"PA",
    "gn:country_code":"PA",
    "gn:dem":31,
    "gn:feature_class":"P",
    "gn:feature_code":"PPL",
    "gn:name":"Pueblo Viejo",
    "gn:population":30,
    "gn:timezone":"America/Panama",
    "iso:country":"PA",
    "name:ceb_x_preferred":[
        "Pueblo Viejo"
    ],
    "name:deu_x_preferred":[
        "Pueblo Viejo"
    ],
    "name:fra_x_preferred":[
        "Pueblo Viejo"
    ],
    "name:nds_x_preferred":[
        "Pueblo Viejo"
    ],
    "name:sco_x_preferred":[
        "Pueblo Viejo"
    ],
    "name:spa_x_preferred":[
        "Pueblo Viejo"
    ],
    "name:swe_x_preferred":[
        "Pueblo Viejo"
    ],
    "name:und_x_variant":[
        "Pueblo Viego"
    ],
    "name:vie_x_preferred":[
        "Pueblo Viejo"
    ],
    "wof:name":"Pueblo Viejo",
    "wof:placetype":"locality",
    "wof:population":30
},
  "geometry": {"coordinates":[-81.05512,8.01279],"type":"Point"}
}