{
  "type": "Feature",
  "properties": {
    "gn:admin1_code":"03",
    "gn:asciiname":"Juan Julio",
    "gn:country_code":"PA",
    "gn:dem":163,
    "gn:feature_class":"P",
    "gn:feature_code":"PPL",
    "gn:name":"Juan Julio",
    "gn:population":0,
    "gn:timezone":"America/Panama",
    "iso:country":"PA",
    "wof:name":"Juan Julio",
    "wof:placetype":"locality"
},
  "geometry": {"coordinates":[-80.56667,8.75],"type":"Point"}
}