{
  "type": "Feature",
  "properties": {
    "gn:admin1_code":"10",
    "gn:asciiname":"Los Planes",
    "gn:cc2":"PA",
    "gn:country_code":"PA",
    "gn:dem":132,
    "gn:feature_class":"P",
    "gn:feature_code":"PPL",
    "gn:name":"Los Planes",
    "gn:population":0,
    "gn:timezone":"America/Panama",
    "iso:country":"PA",
    "name:und_x_variant":[
        "Planetas",
        "Los Planetas",
        "Los Planes"
    ],
    "wof:name":"Los Planes",
    "wof:placetype":"locality"
},
  "geometry": {"coordinates":[-81.03361,7.79806],"type":"Point"}
}