{
  "type": "Feature",
  "properties": {
    "gn:admin1_code":"01",
    "gn:asciiname":"Carenero",
    "gn:country_code":"PA",
    "gn:dem":2,
    "gn:feature_class":"P",
    "gn:feature_code":"PPL",
    "gn:name":"Carenero",
    "gn:population":0,
    "gn:timezone":"America/Panama",
    "iso:country":"PA",
    "name:spa_x_preferred":[
        "Carenero"
    ],
    "wof:name":"Carenero",
    "wof:placetype":"locality"
},
  "geometry": {"coordinates":[-82.23563,9.33997],"type":"Point"}
}