{
  "type": "Feature",
  "properties": {
    "gn:admin1_code":"04",
    "gn:asciiname":"La Encantada Numero Uno",
    "gn:country_code":"PA",
    "gn:dem":85,
    "gn:feature_class":"P",
    "gn:feature_code":"PPL",
    "gn:name":"La Encantada N\u00famero Uno",
    "gn:population":0,
    "gn:timezone":"America/Panama",
    "iso:country":"PA",
    "wof:name":"La Encantada Numero Uno",
    "wof:placetype":"locality"
},
  "geometry": {"coordinates":[-80.13333,8.98333],"type":"Point"}
}