{
  "type": "Feature",
  "properties": {
    "gn:admin1_code":"10",
    "gn:asciiname":"Angulo",
    "gn:country_code":"PA",
    "gn:dem":24,
    "gn:feature_class":"P",
    "gn:feature_code":"PPL",
    "gn:name":"\u00c1ngulo",
    "gn:population":0,
    "gn:timezone":"America/Panama",
    "iso:country":"PA",
    "wof:name":"Angulo",
    "wof:placetype":"locality"
},
  "geometry": {"coordinates":[-80.96666999999999,7.68333],"type":"Point"}
}