{
  "type": "Feature",
  "properties": {
    "gn:admin1_code":"10",
    "gn:asciiname":"Los Algarrobos",
    "gn:country_code":"PA",
    "gn:dem":25,
    "gn:feature_class":"P",
    "gn:feature_code":"PPL",
    "gn:name":"Los Algarrobos",
    "gn:population":221,
    "gn:timezone":"America/Panama",
    "iso:country":"PA",
    "name:und_x_variant":[
        "Los Algarrobas",
        "Los Algarrobos"
    ],
    "wof:name":"Los Algarrobos",
    "wof:placetype":"locality",
    "wof:population":221
},
  "geometry": {"coordinates":[-81.33335,8.02006],"type":"Point"}
}