{
  "type": "Feature",
  "properties": {
    "gn:admin1_code":"10",
    "gn:asciiname":"Los Panamaes",
    "gn:country_code":"PA",
    "gn:dem":41,
    "gn:feature_class":"P",
    "gn:feature_code":"PPL",
    "gn:name":"Los Panamaes",
    "gn:population":0,
    "gn:timezone":"America/Panama",
    "iso:country":"PA",
    "name:ita_x_preferred":[
        "Corral Falso"
    ],
    "name:spa_x_preferred":[
        "Corral Falso"
    ],
    "name:und_x_variant":[
        "Corral Falso",
        "Los Panamaes"
    ],
    "name:zho_x_preferred":[
        "\u79d1\u62c9\u723e\u6cd5\u723e\u7d22"
    ],
    "wof:name":"Los Panamaes",
    "wof:placetype":"locality"
},
  "geometry": {"coordinates":[-80.84396,8.1914],"type":"Point"}
}