{
  "type": "Feature",
  "properties": {
    "gn:admin1_code":"03",
    "gn:asciiname":"La Albina",
    "gn:country_code":"PA",
    "gn:dem":7,
    "gn:feature_class":"P",
    "gn:feature_code":"PPL",
    "gn:name":"La Albina",
    "gn:population":0,
    "gn:timezone":"America/Panama",
    "iso:country":"PA",
    "wof:name":"La Albina",
    "wof:placetype":"locality"
},
  "geometry": {"coordinates":[-80.18333,8.33333],"type":"Point"}
}