{
  "type": "Feature",
  "properties": {
    "gn:admin1_code":"06",
    "gn:asciiname":"Quebrada Risacua",
    "gn:country_code":"PA",
    "gn:dem":303,
    "gn:feature_class":"P",
    "gn:feature_code":"PPL",
    "gn:name":"Quebrada Risacua",
    "gn:population":81,
    "gn:timezone":"America/Panama",
    "iso:country":"PA",
    "name:spa_x_preferred":[
        "Quebrada Risacua"
    ],
    "wof:name":"Quebrada Risacua",
    "wof:placetype":"locality",
    "wof:population":81
},
  "geometry": {"coordinates":[-80.79567,7.83657],"type":"Point"}
}