{
  "type": "Feature",
  "properties": {
    "gn:admin1_code":"07",
    "gn:asciiname":"El Guayabo",
    "gn:country_code":"PA",
    "gn:dem":54,
    "gn:feature_class":"P",
    "gn:feature_code":"PPL",
    "gn:name":"El Guayabo",
    "gn:population":31,
    "gn:timezone":"America/Panama",
    "iso:country":"PA",
    "wof:name":"El Guayabo",
    "wof:placetype":"locality",
    "wof:population":31
},
  "geometry": {"coordinates":[-80.55029999999999,7.44306],"type":"Point"}
}