{
  "type": "Feature",
  "properties": {
    "gn:admin1_code":"08",
    "gn:asciiname":"Pingandicito",
    "gn:country_code":"PA",
    "gn:dem":118,
    "gn:feature_class":"P",
    "gn:feature_code":"PPL",
    "gn:name":"Pingandicito",
    "gn:population":0,
    "gn:timezone":"America/Panama",
    "iso:country":"PA",
    "name:spa_x_preferred":[
        "Pingandicito"
    ],
    "wof:name":"Pingandicito",
    "wof:placetype":"locality"
},
  "geometry": {"coordinates":[-78.14050999999998,8.95356],"type":"Point"}
}