{
  "type": "Feature",
  "properties": {
    "gn:admin1_code":"07",
    "gn:asciiname":"La Palma",
    "gn:country_code":"PA",
    "gn:dem":73,
    "gn:feature_class":"P",
    "gn:feature_code":"PPL",
    "gn:name":"La Palma",
    "gn:population":5,
    "gn:timezone":"America/Panama",
    "iso:country":"PA",
    "wof:name":"La Palma",
    "wof:placetype":"locality",
    "wof:population":5
},
  "geometry": {"coordinates":[-80.48042,7.31831],"type":"Point"}
}