{
  "type": "Feature",
  "properties": {
    "iso:country":"PA",
    "qs:gn_pop":0,
    "qs:name":"Rio Grande",
    "qs:name_adm0":"Panam\u00e1",
    "qs:name_adm1":"Veraguas",
    "qs:photos":97,
    "qs:photos_1k":20,
    "qs:photos_9k":2,
    "qs:photos_9r":5,
    "qs:photos_all":561,
    "qs:photos_sr":3,
    "qs:placetype":"LocalAdmin",
    "qs:pop_sr":"0",
    "qs:woe_adm0":23424924,
    "wof:name":"Rio Grande",
    "wof:placetype":"localadmin"
},
  "geometry": {"coordinates":[-81.25102,7.628735],"type":"Point"}
}