{
  "type": "Feature",
  "properties": {
    "gn:admin1_code":"02",
    "gn:asciiname":"El Guabo Arriba",
    "gn:cc2":"PA",
    "gn:country_code":"PA",
    "gn:dem":163,
    "gn:feature_class":"P",
    "gn:feature_code":"PPL",
    "gn:name":"El Guabo Arriba",
    "gn:population":0,
    "gn:timezone":"America/Panama",
    "iso:country":"PA",
    "name:und_x_variant":[
        "El Guabo",
        "El Guabo Arriba"
    ],
    "wof:name":"El Guabo Arriba",
    "wof:placetype":"locality"
},
  "geometry": {"coordinates":[-82.26666999999998,8.55],"type":"Point"}
}