{
  "type": "Feature",
  "properties": {
    "gn:admin1_code":"10",
    "gn:asciiname":"La Pina",
    "gn:cc2":"PA",
    "gn:country_code":"PA",
    "gn:dem":124,
    "gn:feature_class":"P",
    "gn:feature_code":"PPL",
    "gn:name":"La Pi\u00f1a",
    "gn:population":0,
    "gn:timezone":"America/Panama",
    "iso:country":"PA",
    "name:und_x_variant":[
        "La Pe\u00f1a",
        "La Pi\u00f1a"
    ],
    "wof:name":"La Pina",
    "wof:placetype":"locality"
},
  "geometry": {"coordinates":[-81.33360999999999,7.92444],"type":"Point"}
}