{
  "type": "Feature",
  "properties": {
    "gn:admin1_code":"10",
    "gn:asciiname":"Salmonete",
    "gn:country_code":"PA",
    "gn:dem":9,
    "gn:feature_class":"P",
    "gn:feature_code":"PPL",
    "gn:name":"Salmonete",
    "gn:population":210,
    "gn:timezone":"America/Panama",
    "iso:country":"PA",
    "name:spa_x_preferred":[
        "Salmonete"
    ],
    "wof:name":"Salmonete",
    "wof:placetype":"locality",
    "wof:population":210
},
  "geometry": {"coordinates":[-81.50655,7.77766],"type":"Point"}
}