{
  "type": "Feature",
  "properties": {
    "gn:admin1_code":"03",
    "gn:asciiname":"Santa Elena",
    "gn:cc2":"PA",
    "gn:country_code":"PA",
    "gn:dem":168,
    "gn:feature_class":"P",
    "gn:feature_code":"PPL",
    "gn:name":"Santa Elena",
    "gn:population":0,
    "gn:timezone":"America/Panama",
    "iso:country":"PA",
    "name:cat_x_preferred":[
        "Santa Elena"
    ],
    "name:ceb_x_preferred":[
        "Santa Elena"
    ],
    "name:deu_x_preferred":[
        "Santa Elena"
    ],
    "name:eus_x_preferred":[
        "Santa Elena"
    ],
    "name:fra_x_preferred":[
        "Santa Elena"
    ],
    "name:hye_x_preferred":[
        "\u054d\u0561\u0576\u057f\u0561 \u0537\u056c\u0565\u0576\u0561"
    ],
    "name:ita_x_preferred":[
        "Santa Elena"
    ],
    "name:lit_x_preferred":[
        "Santa Elena"
    ],
    "name:nds_x_preferred":[
        "Santa Elena"
    ],
    "name:nld_x_preferred":[
        "Santa Elena"
    ],
    "name:por_x_preferred":[
        "Santa Elena"
    ],
    "name:ron_x_preferred":[
        "Santa Elena"
    ],
    "name:rus_x_preferred":[
        "\u0421\u0430\u043d\u0442\u0430-\u042d\u043b\u0435\u043d\u0430"
    ],
    "name:sco_x_preferred":[
        "Santa Elena"
    ],
    "name:slk_x_preferred":[
        "Santa Elena"
    ],
    "name:spa_x_preferred":[
        "Santa Elena"
    ],
    "name:srp_x_preferred":[
        "\u0421\u0430\u043d\u0442\u0430 \u0415\u043b\u0435\u043d\u0430"
    ],
    "name:swe_x_preferred":[
        "Santa Elena"
    ],
    "name:tgl_x_preferred":[
        "Santa Elena"
    ],
    "name:und_x_variant":[
        "Las Cabuyas"
    ],
    "name:vie_x_preferred":[
        "Santa Elena"
    ],
    "name:war_x_preferred":[
        "Santa Elena"
    ],
    "wof:name":"Santa Elena",
    "wof:placetype":"locality"
},
  "geometry": {"coordinates":[-80.26666999999998,8.55],"type":"Point"}
}