{
  "type": "Feature",
  "properties": {
    "gn:admin1_code":"03",
    "gn:asciiname":"El Nancito",
    "gn:country_code":"PA",
    "gn:dem":556,
    "gn:feature_class":"P",
    "gn:feature_code":"PPL",
    "gn:name":"El Nancito",
    "gn:population":0,
    "gn:timezone":"America/Panama",
    "iso:country":"PA",
    "name:ita_x_preferred":[
        "El Nancito"
    ],
    "name:spa_x_preferred":[
        "El Nancito"
    ],
    "name:zho_x_preferred":[
        "\u57c3\u723e\u5357\u897f\u6258"
    ],
    "wof:name":"El Nancito",
    "wof:placetype":"locality"
},
  "geometry": {"coordinates":[-80.15000000000001,8.56667],"type":"Point"}
}