{
  "type": "Feature",
  "properties": {
    "gn:admin1_code":"03",
    "gn:asciiname":"Las Brujas",
    "gn:country_code":"PA",
    "gn:dem":25,
    "gn:feature_class":"P",
    "gn:feature_code":"PPL",
    "gn:name":"Las Brujas",
    "gn:population":4,
    "gn:timezone":"America/Panama",
    "iso:country":"PA",
    "wof:name":"Las Brujas",
    "wof:placetype":"locality",
    "wof:population":4
},
  "geometry": {"coordinates":[-80.15000000000001,8.38333],"type":"Point"}
}