{
  "type": "Feature",
  "properties": {
    "gn:admin1_code":"12",
    "gn:asciiname":"Gasparillo",
    "gn:country_code":"PA",
    "gn:dem":403,
    "gn:feature_class":"P",
    "gn:feature_code":"PPL",
    "gn:name":"Gasparillo",
    "gn:population":0,
    "gn:timezone":"America/Panama",
    "iso:country":"PA",
    "name:spa_x_preferred":[
        "Gasparillo"
    ],
    "wof:name":"Gasparillo",
    "wof:placetype":"locality"
},
  "geometry": {"coordinates":[-81.99469000000001,8.49216],"type":"Point"}
}