{
  "type": "Feature",
  "properties": {
    "iso:country":"PA",
    "name:eng_x_preferred":[
        "Juan D\u00edaz"
    ],
    "name:ita_x_preferred":[
        "Juan D\u00edaz"
    ],
    "name:nld_x_preferred":[
        "Juan D\u00edaz"
    ],
    "name:spa_x_preferred":[
        "Juan D\u00edaz"
    ],
    "name:zho_x_preferred":[
        "\u80e1\u5b89\u8fea\u4e9e\u65af"
    ],
    "qs:gn_country":"PA",
    "qs:gn_fcode":"PPL",
    "qs:gn_pop":0,
    "qs:name":"Juan D\u00edaz",
    "qs:name_adm0":"Panam\u00e1",
    "qs:name_adm1":"Panam\u00e1",
    "qs:photos":28,
    "qs:photos_1k":6,
    "qs:photos_9k":1,
    "qs:photos_9r":2,
    "qs:photos_all":28,
    "qs:photos_sr":2,
    "qs:placetype":"Town",
    "qs:pop_sr":"0",
    "qs:woe_adm0":23424924,
    "wd:wordcount":118,
    "wof:name":"Juan D\u00edaz",
    "wof:placetype":"locality"
},
  "geometry": {"coordinates":[-79.45,9.05],"type":"Point"}
}