{
  "type": "Feature",
  "properties": {
    "gn:admin1_code":"10",
    "gn:asciiname":"Chorrillo",
    "gn:country_code":"PA",
    "gn:dem":471,
    "gn:feature_class":"P",
    "gn:feature_code":"PPL",
    "gn:name":"Chorrillo",
    "gn:population":107,
    "gn:timezone":"America/Panama",
    "iso:country":"PA",
    "name:spa_x_preferred":[
        "Chorrillo"
    ],
    "wof:name":"Chorrillo",
    "wof:placetype":"locality",
    "wof:population":107
},
  "geometry": {"coordinates":[-80.95899,8.3903],"type":"Point"}
}