{
  "type": "Feature",
  "properties": {
    "gn:admin1_code":"07",
    "gn:asciiname":"Los Dominguez",
    "gn:country_code":"PA",
    "gn:dem":241,
    "gn:feature_class":"P",
    "gn:feature_code":"PPL",
    "gn:name":"Los Dom\u00ednguez",
    "gn:population":0,
    "gn:timezone":"America/Panama",
    "iso:country":"PA",
    "wof:name":"Los Dominguez",
    "wof:placetype":"locality"
},
  "geometry": {"coordinates":[-80.63333,7.58333],"type":"Point"}
}