{
  "type": "Feature",
  "properties": {
    "gn:admin1_code":"07",
    "gn:asciiname":"Platanal",
    "gn:country_code":"PA",
    "gn:dem":327,
    "gn:feature_class":"P",
    "gn:feature_code":"PPL",
    "gn:name":"Platanal",
    "gn:population":0,
    "gn:timezone":"America/Panama",
    "iso:country":"PA",
    "wof:name":"Platanal",
    "wof:placetype":"locality"
},
  "geometry": {"coordinates":[-80.51666999999998,7.58333],"type":"Point"}
}