{
  "type": "Feature",
  "properties": {
    "gn:admin1_code":"02",
    "gn:asciiname":"Bajo Hondo",
    "gn:country_code":"PA",
    "gn:dem":626,
    "gn:feature_class":"P",
    "gn:feature_code":"PPL",
    "gn:name":"Bajo Hondo",
    "gn:population":0,
    "gn:timezone":"America/Panama",
    "iso:country":"PA",
    "name:nld_x_preferred":[
        "Bajo Hondo"
    ],
    "name:spa_x_preferred":[
        "Bajo Hondo"
    ],
    "wof:name":"Bajo Hondo",
    "wof:placetype":"locality"
},
  "geometry": {"coordinates":[-82.38333,8.68333],"type":"Point"}
}