{
  "type": "Feature",
  "properties": {
    "gn:admin1_code":"06",
    "gn:asciiname":"El Calvario",
    "gn:country_code":"PA",
    "gn:dem":447,
    "gn:feature_class":"P",
    "gn:feature_code":"PPL",
    "gn:name":"El Calvario",
    "gn:population":0,
    "gn:timezone":"America/Panama",
    "iso:country":"PA",
    "wof:name":"El Calvario",
    "wof:placetype":"locality"
},
  "geometry": {"coordinates":[-80.90000000000001,7.85],"type":"Point"}
}