{
  "type": "Feature",
  "properties": {
    "gn:admin1_code":"02",
    "gn:asciiname":"San Martin Numero Dos",
    "gn:cc2":"PA",
    "gn:country_code":"PA",
    "gn:dem":106,
    "gn:feature_class":"P",
    "gn:feature_code":"PPL",
    "gn:name":"San Mart\u00edn N\u00famero Dos",
    "gn:population":0,
    "gn:timezone":"America/Panama",
    "iso:country":"PA",
    "name:und_x_variant":[
        "San Mart\u00edn Abajo N\u00famero Dos",
        "San Mart\u00edn N\u00famero Dos"
    ],
    "wof:name":"San Martin Numero Dos",
    "wof:placetype":"locality"
},
  "geometry": {"coordinates":[-82.66667,8.45],"type":"Point"}
}