{
  "type": "Feature",
  "properties": {
    "gn:admin1_code":"03",
    "gn:asciiname":"Palo Verde",
    "gn:country_code":"PA",
    "gn:dem":17,
    "gn:feature_class":"P",
    "gn:feature_code":"PPL",
    "gn:name":"Palo Verde",
    "gn:population":0,
    "gn:timezone":"America/Panama",
    "iso:country":"PA",
    "wof:name":"Palo Verde",
    "wof:placetype":"locality"
},
  "geometry": {"coordinates":[-80.45,8.41667],"type":"Point"}
}