{
  "type": "Feature",
  "properties": {
    "gn:admin1_code":"03",
    "gn:asciiname":"Palo Verde",
    "gn:country_code":"PA",
    "gn:dem":17,
    "gn:feature_class":"P",
    "gn:feature_code":"PPL",
    "gn:name":"Palo Verde",
    "gn:population":0,
    "gn:timezone":"America/Panama",
    "iso:country":"PA",
    "name:ceb_x_preferred":[
        "Palo Verde"
    ],
    "name:deu_x_preferred":[
        "Palo Verde"
    ],
    "name:fra_x_preferred":[
        "Palo Verde"
    ],
    "name:spa_x_preferred":[
        "Palo Verde"
    ],
    "name:srp_x_preferred":[
        "\u041f\u0430\u043b\u043e \u0412\u0435\u0440\u0434\u0435"
    ],
    "name:swe_x_preferred":[
        "Palo Verde"
    ],
    "wof:name":"Palo Verde",
    "wof:placetype":"locality"
},
  "geometry": {"coordinates":[-80.45,8.41667],"type":"Point"}
}