{
  "type": "Feature",
  "properties": {
    "gn:admin1_code":"10",
    "gn:asciiname":"Diferente",
    "gn:country_code":"PA",
    "gn:dem":95,
    "gn:feature_class":"P",
    "gn:feature_code":"PPL",
    "gn:name":"Diferente",
    "gn:population":0,
    "gn:timezone":"America/Panama",
    "iso:country":"PA",
    "wof:name":"Diferente",
    "wof:placetype":"locality"
},
  "geometry": {"coordinates":[-81.21666999999999,8.18333],"type":"Point"}
}