{
  "type": "Feature",
  "properties": {
    "gn:admin1_code":"10",
    "gn:asciiname":"El Jagua",
    "gn:country_code":"PA",
    "gn:dem":172,
    "gn:feature_class":"P",
    "gn:feature_code":"PPL",
    "gn:name":"El Jagua",
    "gn:population":0,
    "gn:timezone":"America/Panama",
    "iso:country":"PA",
    "wof:name":"El Jagua",
    "wof:placetype":"locality"
},
  "geometry": {"coordinates":[-81.38333,8.28333],"type":"Point"}
}