{
  "type": "Feature",
  "properties": {
    "gn:admin1_code":"07",
    "gn:asciiname":"Zape Chiquito",
    "gn:cc2":"PA",
    "gn:country_code":"PA",
    "gn:dem":121,
    "gn:feature_class":"P",
    "gn:feature_code":"PPL",
    "gn:name":"Zape Chiquito",
    "gn:population":0,
    "gn:timezone":"America/Panama",
    "iso:country":"PA",
    "name:und_x_variant":[
        "Zape Abajo",
        "Zape Chiquito"
    ],
    "wof:name":"Zape Chiquito",
    "wof:placetype":"locality"
},
  "geometry": {"coordinates":[-80.41667,7.76667],"type":"Point"}
}