{
  "type": "Feature",
  "properties": {
    "gn:admin1_code":"05",
    "gn:asciiname":"Camoganti",
    "gn:country_code":"PA",
    "gn:dem":9,
    "gn:feature_class":"P",
    "gn:feature_code":"PPLA3",
    "gn:name":"Camogant\u00ed",
    "gn:population":179,
    "gn:timezone":"America/Panama",
    "iso:country":"PA",
    "name:spa_x_preferred":[
        "Camogant\u00ed"
    ],
    "wof:name":"Camoganti",
    "wof:placetype":"locality",
    "wof:population":179
},
  "geometry": {"coordinates":[-77.88682,8.04171],"type":"Point"}
}