{
  "type": "Feature",
  "properties": {
    "gn:admin1_code":"12",
    "gn:asciiname":"Las Lagunas",
    "gn:country_code":"PA",
    "gn:dem":697,
    "gn:feature_class":"P",
    "gn:feature_code":"PPL",
    "gn:name":"Las Lagunas",
    "gn:population":0,
    "gn:timezone":"America/Panama",
    "iso:country":"PA",
    "name:ceb_x_preferred":[
        "Las Lagunas"
    ],
    "name:spa_x_preferred":[
        "Las Lagunas"
    ],
    "name:srp_x_preferred":[
        "\u041b\u0430\u0441 \u041b\u0430\u0433\u0443\u043d\u0430\u0441"
    ],
    "name:swe_x_preferred":[
        "Las Lagunas"
    ],
    "wof:name":"Las Lagunas",
    "wof:placetype":"locality"
},
  "geometry": {"coordinates":[-81.75,8.43333],"type":"Point"}
}