{
  "type": "Feature",
  "properties": {
    "gn:admin1_code":"12",
    "gn:asciiname":"Las Lagunas",
    "gn:country_code":"PA",
    "gn:dem":697,
    "gn:feature_class":"P",
    "gn:feature_code":"PPL",
    "gn:name":"Las Lagunas",
    "gn:population":0,
    "gn:timezone":"America/Panama",
    "iso:country":"PA",
    "wof:name":"Las Lagunas",
    "wof:placetype":"locality"
},
  "geometry": {"coordinates":[-81.75,8.43333],"type":"Point"}
}