{
  "type": "Feature",
  "properties": {
    "gn:admin1_code":"05",
    "gn:asciiname":"Joselito",
    "gn:country_code":"PA",
    "gn:dem":15,
    "gn:feature_class":"P",
    "gn:feature_code":"PPL",
    "gn:name":"Joselito",
    "gn:population":0,
    "gn:timezone":"America/Panama",
    "iso:country":"PA",
    "name:deu_x_preferred":[
        "Joselito"
    ],
    "name:fra_x_preferred":[
        "Joselito"
    ],
    "name:por_x_preferred":[
        "Joselito"
    ],
    "name:rus_x_preferred":[
        "\u0425\u043e\u0441\u0435\u043b\u0438\u0442\u043e"
    ],
    "name:spa_x_preferred":[
        "Joselito"
    ],
    "wof:name":"Joselito",
    "wof:placetype":"locality"
},
  "geometry": {"coordinates":[-78.13954,8.58564],"type":"Point"}
}