{
  "type": "Feature",
  "properties": {
    "gn:admin1_code":"05",
    "gn:asciiname":"Joselito",
    "gn:country_code":"PA",
    "gn:dem":15,
    "gn:feature_class":"P",
    "gn:feature_code":"PPL",
    "gn:name":"Joselito",
    "gn:population":0,
    "gn:timezone":"America/Panama",
    "iso:country":"PA",
    "wof:name":"Joselito",
    "wof:placetype":"locality"
},
  "geometry": {"coordinates":[-78.13954,8.58564],"type":"Point"}
}