{
  "type": "Feature",
  "properties": {
    "gn:admin1_code":"07",
    "gn:asciiname":"El Limoncito",
    "gn:cc2":"PA",
    "gn:country_code":"PA",
    "gn:dem":237,
    "gn:feature_class":"P",
    "gn:feature_code":"PPL",
    "gn:name":"El Limoncito",
    "gn:population":19,
    "gn:timezone":"America/Panama",
    "iso:country":"PA",
    "name:und_x_variant":[
        "Limoncito",
        "El Limoneito",
        "El Limoncito"
    ],
    "wof:name":"El Limoncito",
    "wof:placetype":"locality",
    "wof:population":19
},
  "geometry": {"coordinates":[-80.17245,7.55324],"type":"Point"}
}