{
  "type": "Feature",
  "properties": {
    "gn:admin1_code":"10",
    "gn:asciiname":"La Pacora",
    "gn:cc2":"PA",
    "gn:country_code":"PA",
    "gn:dem":119,
    "gn:feature_class":"P",
    "gn:feature_code":"PPL",
    "gn:name":"La Pacora",
    "gn:population":9,
    "gn:timezone":"America/Panama",
    "iso:country":"PA",
    "name:und_x_variant":[
        "Cativ\u00e9",
        "La Pacora"
    ],
    "wof:name":"La Pacora",
    "wof:placetype":"locality",
    "wof:population":9
},
  "geometry": {"coordinates":[-81.37306,7.9275],"type":"Point"}
}