{
  "type": "Feature",
  "properties": {
    "gn:admin1_code":"02",
    "gn:asciiname":"Finca Corotu",
    "gn:country_code":"PA",
    "gn:dem":9,
    "gn:feature_class":"P",
    "gn:feature_code":"PPL",
    "gn:name":"Finca Corot\u00fa",
    "gn:population":0,
    "gn:timezone":"America/Panama",
    "iso:country":"PA",
    "wof:name":"Finca Corotu",
    "wof:placetype":"locality"
},
  "geometry": {"coordinates":[-82.78333000000001,8.36667],"type":"Point"}
}