{
  "type": "Feature",
  "properties": {
    "gn:admin1_code":"02",
    "gn:asciiname":"El Flor",
    "gn:country_code":"PA",
    "gn:dem":286,
    "gn:feature_class":"P",
    "gn:feature_code":"PPL",
    "gn:name":"El Flor",
    "gn:population":660,
    "gn:timezone":"America/Panama",
    "iso:country":"PA",
    "name:spa_x_preferred":[
        "El Flor"
    ],
    "wof:name":"El Flor",
    "wof:placetype":"locality",
    "wof:population":660
},
  "geometry": {"coordinates":[-82.43929,8.56802],"type":"Point"}
}