{
  "type": "Feature",
  "properties": {
    "gn:admin1_code":"07",
    "gn:asciiname":"Limoncito",
    "gn:country_code":"PA",
    "gn:dem":7,
    "gn:feature_class":"P",
    "gn:feature_code":"PPL",
    "gn:name":"Limoncito",
    "gn:population":0,
    "gn:timezone":"America/Panama",
    "iso:country":"PA",
    "name:ceb_x_preferred":[
        "Limoncito"
    ],
    "name:deu_x_preferred":[
        "Limoncito"
    ],
    "name:zho_x_preferred":[
        "\u5229\u8499\u897f\u6258"
    ],
    "wof:name":"Limoncito",
    "wof:placetype":"locality"
},
  "geometry": {"coordinates":[-80.40000000000001,7.38333],"type":"Point"}
}