{
  "type": "Feature",
  "properties": {
    "gn:admin1_code":"06",
    "gn:asciiname":"Ave Maria",
    "gn:cc2":"PA",
    "gn:country_code":"PA",
    "gn:dem":235,
    "gn:feature_class":"P",
    "gn:feature_code":"PPL",
    "gn:name":"Ave Mar\u00eda",
    "gn:population":0,
    "gn:timezone":"America/Panama",
    "iso:country":"PA",
    "name:und_x_variant":[
        "El Ave Mar\u00eda",
        "Ave Mar\u00eda"
    ],
    "wof:name":"Ave Maria",
    "wof:placetype":"locality"
},
  "geometry": {"coordinates":[-80.84999999999999,7.88333],"type":"Point"}
}