{
  "type": "Feature",
  "properties": {
    "gn:admin1_code":"06",
    "gn:asciiname":"Los Carates",
    "gn:country_code":"PA",
    "gn:dem":81,
    "gn:feature_class":"P",
    "gn:feature_code":"PPL",
    "gn:name":"Los Carates",
    "gn:population":0,
    "gn:timezone":"America/Panama",
    "iso:country":"PA",
    "name:spa_x_preferred":[
        "Los Carates"
    ],
    "wof:name":"Los Carates",
    "wof:placetype":"locality"
},
  "geometry": {"coordinates":[-80.7837,8.00916],"type":"Point"}
}