{
  "type": "Feature",
  "properties": {
    "gn:admin1_code":"10",
    "gn:asciiname":"Garnaderita",
    "gn:country_code":"PA",
    "gn:dem":79,
    "gn:feature_class":"P",
    "gn:feature_code":"PPL",
    "gn:name":"Garnaderita",
    "gn:population":202,
    "gn:timezone":"America/Panama",
    "iso:country":"PA",
    "name:spa_x_preferred":[
        "Garnaderita"
    ],
    "wof:name":"Garnaderita",
    "wof:placetype":"locality",
    "wof:population":202
},
  "geometry": {"coordinates":[-80.94486999999999,8.04341],"type":"Point"}
}