{
  "type": "Feature",
  "properties": {
    "gn:admin1_code":"10",
    "gn:asciiname":"San Juanito",
    "gn:country_code":"PA",
    "gn:dem":61,
    "gn:feature_class":"P",
    "gn:feature_code":"PPL",
    "gn:name":"San Juanito",
    "gn:population":205,
    "gn:timezone":"America/Panama",
    "iso:country":"PA",
    "name:ceb_x_preferred":[
        "San Juanito"
    ],
    "name:deu_x_preferred":[
        "San Juanito"
    ],
    "name:msa_x_preferred":[
        "San Juanito"
    ],
    "name:spa_x_preferred":[
        "San Juanito"
    ],
    "name:swe_x_preferred":[
        "San Juanito"
    ],
    "name:tgl_x_preferred":[
        "San Juanito"
    ],
    "name:vie_x_preferred":[
        "San Juanito"
    ],
    "wof:name":"San Juanito",
    "wof:placetype":"locality",
    "wof:population":205
},
  "geometry": {"coordinates":[-81.30944000000002,7.88224],"type":"Point"}
}