{
  "type": "Feature",
  "properties": {
    "gn:admin1_code":"13",
    "gn:asciiname":"Cortadera",
    "gn:country_code":"PA",
    "gn:dem":348,
    "gn:feature_class":"P",
    "gn:feature_code":"PPL",
    "gn:name":"Cortadera",
    "gn:population":0,
    "gn:timezone":"America/Panama",
    "iso:country":"PA",
    "wof:name":"Cortadera",
    "wof:placetype":"locality"
},
  "geometry": {"coordinates":[-79.96666999999999,8.66667],"type":"Point"}
}