{
  "type": "Feature",
  "properties": {
    "gn:admin1_code":"10",
    "gn:asciiname":"El Cedro",
    "gn:country_code":"PA",
    "gn:dem":263,
    "gn:feature_class":"P",
    "gn:feature_code":"PPL",
    "gn:name":"El Cedro",
    "gn:population":164,
    "gn:timezone":"America/Panama",
    "iso:country":"PA",
    "name:ceb_x_preferred":[
        "El Cedro"
    ],
    "name:fra_x_preferred":[
        "El Cedro"
    ],
    "name:ita_x_preferred":[
        "El Cedro"
    ],
    "name:spa_x_preferred":[
        "El Cedro"
    ],
    "name:swe_x_preferred":[
        "El Cedro"
    ],
    "wof:name":"El Cedro",
    "wof:placetype":"locality",
    "wof:population":164
},
  "geometry": {"coordinates":[-81.55594000000001,8.16688],"type":"Point"}
}