{
  "type": "Feature",
  "properties": {
    "gn:admin1_code":"07",
    "gn:asciiname":"Barriada Once de Octubre",
    "gn:country_code":"PA",
    "gn:dem":96,
    "gn:feature_class":"P",
    "gn:feature_code":"PPL",
    "gn:name":"Barriada Once de Octubre",
    "gn:population":0,
    "gn:timezone":"America/Panama",
    "iso:country":"PA",
    "name:spa_x_preferred":[
        "Barriada Once de Octubre"
    ],
    "wof:name":"Barriada Once de Octubre",
    "wof:placetype":"locality"
},
  "geometry": {"coordinates":[-80.55665999999999,7.71324],"type":"Point"}
}