{
  "type": "Feature",
  "properties": {
    "gn:admin1_code":"00",
    "gn:asciiname":"Norteno",
    "gn:country_code":"PA",
    "gn:dem":94,
    "gn:feature_class":"P",
    "gn:feature_code":"PPLA3",
    "gn:name":"Norte\u00f1o",
    "gn:population":0,
    "gn:timezone":"America/Panama",
    "iso:country":"PA",
    "name:spa_x_preferred":[
        "Norte\u00f1o"
    ],
    "wof:name":"Norteno",
    "wof:placetype":"locality"
},
  "geometry": {"coordinates":[-82.31475999999998,9.00308],"type":"Point"}
}