{
  "type": "Feature",
  "properties": {
    "gn:admin1_code":"13",
    "gn:asciiname":"Llanito Verde",
    "gn:country_code":"PA",
    "gn:dem":159,
    "gn:feature_class":"P",
    "gn:feature_code":"PPL",
    "gn:name":"Llanito Verde",
    "gn:population":0,
    "gn:timezone":"America/Panama",
    "iso:country":"PA",
    "wof:name":"Llanito Verde",
    "wof:placetype":"locality"
},
  "geometry": {"coordinates":[-79.895,8.90417],"type":"Point"}
}