{
  "type": "Feature",
  "properties": {
    "gn:admin1_code":"01",
    "gn:asciiname":"Paunch",
    "gn:country_code":"PA",
    "gn:dem":46,
    "gn:feature_class":"P",
    "gn:feature_code":"PPL",
    "gn:name":"Paunch",
    "gn:population":0,
    "gn:timezone":"America/Panama",
    "iso:country":"PA",
    "wof:name":"Paunch",
    "wof:placetype":"locality"
},
  "geometry": {"coordinates":[-82.25,9.38333],"type":"Point"}
}