{
  "type": "Feature",
  "properties": {
    "gn:admin1_code":"13",
    "gn:asciiname":"Tranquilla",
    "gn:country_code":"PA",
    "gn:dem":114,
    "gn:feature_class":"P",
    "gn:feature_code":"PPL",
    "gn:name":"Tranquilla",
    "gn:population":0,
    "gn:timezone":"America/Panama",
    "iso:country":"PA",
    "wof:name":"Tranquilla",
    "wof:placetype":"locality"
},
  "geometry": {"coordinates":[-79.98333000000002,8.51667],"type":"Point"}
}