{
  "type": "Feature",
  "properties": {
    "gn:admin1_code":"02",
    "gn:asciiname":"Cerro Corotu",
    "gn:cc2":"PA",
    "gn:country_code":"PA",
    "gn:dem":443,
    "gn:feature_class":"P",
    "gn:feature_code":"PPL",
    "gn:name":"Cerro Corot\u00fa",
    "gn:population":0,
    "gn:timezone":"America/Panama",
    "iso:country":"PA",
    "name:und_x_variant":[
        "Cerro Sabana",
        "Cerro Corot\u00fa"
    ],
    "wof:name":"Cerro Corotu",
    "wof:placetype":"locality"
},
  "geometry": {"coordinates":[-82.28333000000001,8.58333],"type":"Point"}
}