{
  "type": "Feature",
  "properties": {
    "gn:admin1_code":"01",
    "gn:asciiname":"Finca Cincuenta y Uno",
    "gn:country_code":"PA",
    "gn:dem":3,
    "gn:feature_class":"P",
    "gn:feature_code":"PPL",
    "gn:name":"Finca Cincuenta y Uno",
    "gn:population":0,
    "gn:timezone":"America/Panama",
    "iso:country":"PA",
    "name:und_x_variant":[
        "Finca 51",
        "Finca Cincuenta y Uno"
    ],
    "wof:name":"Finca Cincuenta y Uno",
    "wof:placetype":"locality"
},
  "geometry": {"coordinates":[-82.58326,9.49177],"type":"Point"}
}