{
  "type": "Feature",
  "properties": {
    "gn:admin1_code":"01",
    "gn:asciiname":"Lennan",
    "gn:cc2":"PA",
    "gn:country_code":"PA",
    "gn:dem":4,
    "gn:feature_class":"P",
    "gn:feature_code":"PPL",
    "gn:name":"Lennan",
    "gn:population":0,
    "gn:timezone":"America/Panama",
    "iso:country":"PA",
    "name:und_x_variant":[
        "Lennond",
        "Lennan"
    ],
    "wof:name":"Lennan",
    "wof:placetype":"locality"
},
  "geometry": {"coordinates":[-82.26491999999998,9.35651],"type":"Point"}
}