{
  "type": "Feature",
  "properties": {
    "iso:country":"PA",
    "name:eng_x_preferred":[
        "La Tiza"
    ],
    "name:ita_x_preferred":[
        "La Tiza"
    ],
    "name:kat_x_preferred":[
        "\u10da\u10d0-\u10e2\u10d8\u10e1\u10d0"
    ],
    "name:nld_x_preferred":[
        "La Tiza"
    ],
    "name:spa_x_preferred":[
        "La Tiza"
    ],
    "name:urd_x_preferred":[
        "\u0644\u0627 \u0679\u06cc\u0632\u0627"
    ],
    "qs:gn_country":"PA",
    "qs:gn_fcode":"PPL",
    "qs:gn_pop":1091,
    "qs:name":"La Tiza",
    "qs:name_adm0":"Panam\u00e1",
    "qs:name_adm1":"Los Santos",
    "qs:photos":0,
    "qs:photos_1k":0,
    "qs:photos_9k":1,
    "qs:photos_9r":1,
    "qs:photos_all":1,
    "qs:photos_sr":0,
    "qs:placetype":"Town",
    "qs:pop_sr":"3",
    "qs:woe_adm0":23424924,
    "wd:wordcount":80,
    "wof:name":"La Tiza",
    "wof:placetype":"locality",
    "wof:population":1091
},
  "geometry": {"coordinates":[-80.28333000000001,7.75],"type":"Point"}
}