{
  "type": "Feature",
  "properties": {
    "gn:admin1_code":"12",
    "gn:asciiname":"Cerro Ceniza",
    "gn:country_code":"PA",
    "gn:dem":463,
    "gn:feature_class":"P",
    "gn:feature_code":"PPL",
    "gn:name":"Cerro Ceniza",
    "gn:population":612,
    "gn:timezone":"America/Panama",
    "iso:country":"PA",
    "name:spa_x_preferred":[
        "Cerro Ceniza"
    ],
    "wof:name":"Cerro Ceniza",
    "wof:placetype":"locality",
    "wof:population":612
},
  "geometry": {"coordinates":[-81.76618000000001,8.34298],"type":"Point"}
}