{
  "type": "Feature",
  "properties": {
    "gn:admin1_code":"08",
    "gn:asciiname":"Rincon Tapia",
    "gn:country_code":"PA",
    "gn:dem":54,
    "gn:feature_class":"P",
    "gn:feature_code":"PPL",
    "gn:name":"Rinc\u00f3n Tapia",
    "gn:population":0,
    "gn:timezone":"America/Panama",
    "iso:country":"PA",
    "wof:name":"Rincon Tapia",
    "wof:placetype":"locality"
},
  "geometry": {"coordinates":[-79.41667,9.08333],"type":"Point"}
}