{
  "type": "Feature",
  "properties": {
    "gn:admin1_code":"04",
    "gn:asciiname":"El Bendito",
    "gn:cc2":"PA",
    "gn:country_code":"PA",
    "gn:dem":11,
    "gn:feature_class":"P",
    "gn:feature_code":"PPL",
    "gn:name":"El Bendito",
    "gn:population":0,
    "gn:timezone":"America/Panama",
    "iso:country":"PA",
    "name:und_x_variant":[
        "Bendito",
        "El Bendito"
    ],
    "wof:name":"El Bendito",
    "wof:placetype":"locality"
},
  "geometry": {"coordinates":[-80.13221999999998,9.18944],"type":"Point"}
}