{
  "type": "Feature",
  "properties": {
    "gn:admin1_code":"10",
    "gn:asciiname":"El Ponton",
    "gn:country_code":"PA",
    "gn:dem":22,
    "gn:feature_class":"P",
    "gn:feature_code":"PPL",
    "gn:name":"El Pont\u00f3n",
    "gn:population":0,
    "gn:timezone":"America/Panama",
    "iso:country":"PA",
    "wof:name":"El Ponton",
    "wof:placetype":"locality"
},
  "geometry": {"coordinates":[-81.18778,7.92444],"type":"Point"}
}