{
  "type": "Feature",
  "properties": {
    "gn:admin1_code":"07",
    "gn:asciiname":"La Albina Grande",
    "gn:country_code":"PA",
    "gn:dem":9,
    "gn:feature_class":"P",
    "gn:feature_code":"PPL",
    "gn:name":"La Albina Grande",
    "gn:population":168,
    "gn:timezone":"America/Panama",
    "iso:country":"PA",
    "name:und_x_variant":[
        "Puerto Guarar\u00e9",
        "La Albina Grande"
    ],
    "wof:name":"La Albina Grande",
    "wof:placetype":"locality",
    "wof:population":168
},
  "geometry": {"coordinates":[-80.30176999999998,7.86965],"type":"Point"}
}