{
  "type": "Feature",
  "properties": {
    "iso:country":"PA",
    "name:spa_x_preferred":[
        "Dolequita"
    ],
    "name:spa_x_variant":[
        "Paso de Pina"
    ],
    "qs:gn_adm0_cc":"PA",
    "qs:gn_fcode":"PPLX",
    "qs:gn_local":3711668,
    "qs:gn_namadm1":"02",
    "qs:gn_name":"Dolequita",
    "qs:local_max":169,
    "qs:local_sum":189,
    "qs:localhoods":3,
    "qs:name":"Dolequita",
    "qs:name_adm0":"Panam\u00e1",
    "qs:name_adm1":"Chiriqu\u00ed",
    "qs:name_adm2":"David",
    "qs:name_lau":"San Carlos",
    "qs:name_local":"David",
    "qs:photo_max":2,
    "qs:photo_sum":3,
    "qs:placetype":"Suburb",
    "qs:quad_count":2,
    "qs:woe_adm0":23424924,
    "qs:woe_adm1":2346552,
    "qs:woe_adm2":26793107,
    "qs:woe_lau":26793198,
    "qs:woe_local":155775,
    "qs:woe_ver":"7.10.0",
    "wof:lang":[
        "spa"
    ],
    "wof:name":"Dolequita",
    "wof:placetype":"neighbourhood"
},
  "geometry": {"coordinates":[-82.427673,8.466033],"type":"Point"}
}