{
  "type": "Feature",
  "properties": {
    "gn:admin1_code":"10",
    "gn:asciiname":"Palo Alto",
    "gn:cc2":"PA",
    "gn:country_code":"PA",
    "gn:dem":97,
    "gn:feature_class":"P",
    "gn:feature_code":"PPL",
    "gn:name":"Palo Alto",
    "gn:population":74,
    "gn:timezone":"America/Panama",
    "iso:country":"PA",
    "name:und_x_variant":[
        "Los Mu\u00f1oces",
        "Pala Alto",
        "Palo Alto"
    ],
    "wof:name":"Palo Alto",
    "wof:placetype":"locality",
    "wof:population":74
},
  "geometry": {"coordinates":[-81.1298,8.11897],"type":"Point"}
}