{
  "type": "Feature",
  "properties": {
    "gn:admin1_code":"10",
    "gn:asciiname":"La Barra Numero Dos",
    "gn:country_code":"PA",
    "gn:dem":122,
    "gn:feature_class":"P",
    "gn:feature_code":"PPL",
    "gn:name":"La Barra N\u00famero Dos",
    "gn:population":0,
    "gn:timezone":"America/Panama",
    "iso:country":"PA",
    "wof:name":"La Barra Numero Dos",
    "wof:placetype":"locality"
},
  "geometry": {"coordinates":[-80.76666999999998,7.36667],"type":"Point"}
}