{
  "type": "Feature",
  "properties": {
    "gn:admin1_code":"13",
    "gn:asciiname":"Mata de Coco",
    "gn:country_code":"PA",
    "gn:dem":79,
    "gn:feature_class":"P",
    "gn:feature_code":"PPL",
    "gn:name":"Mata de Coco",
    "gn:population":0,
    "gn:timezone":"America/Panama",
    "iso:country":"PA",
    "name:und_x_variant":[
        "La Mata del Coco",
        "Mata del Coco",
        "Mata de Coco"
    ],
    "wof:name":"Mata de Coco",
    "wof:placetype":"locality"
},
  "geometry": {"coordinates":[-79.79639,8.87583],"type":"Point"}
}