{
  "type": "Feature",
  "properties": {
    "gn:admin1_code":"07",
    "gn:asciiname":"El Naranjito",
    "gn:cc2":"PA",
    "gn:country_code":"PA",
    "gn:dem":226,
    "gn:feature_class":"P",
    "gn:feature_code":"PPL",
    "gn:name":"El Naranjito",
    "gn:population":0,
    "gn:timezone":"America/Panama",
    "iso:country":"PA",
    "name:und_x_variant":[
        "Naronjito",
        "El Naranjito"
    ],
    "wof:name":"El Naranjito",
    "wof:placetype":"locality"
},
  "geometry": {"coordinates":[-80.65000000000001,7.43333],"type":"Point"}
}