{
  "type": "Feature",
  "properties": {
    "gn:admin1_code":"06",
    "gn:asciiname":"El Barrero",
    "gn:cc2":"PA",
    "gn:country_code":"PA",
    "gn:dem":119,
    "gn:feature_class":"P",
    "gn:feature_code":"PPL",
    "gn:name":"El Barrero",
    "gn:population":0,
    "gn:timezone":"America/Panama",
    "iso:country":"PA",
    "name:ita_x_preferred":[
        "El Barrero"
    ],
    "name:spa_x_preferred":[
        "El Barrero"
    ],
    "name:und_x_variant":[
        "El Barrero N\u00famero Uno"
    ],
    "name:zho_x_preferred":[
        "\u57c3\u5c14\u5df4\u96f7\u7f57"
    ],
    "wof:name":"El Barrero",
    "wof:placetype":"locality"
},
  "geometry": {"coordinates":[-80.73333000000002,7.86667],"type":"Point"}
}