{
  "type": "Feature",
  "properties": {
    "gn:admin1_code":"07",
    "gn:asciiname":"San Jose",
    "gn:country_code":"PA",
    "gn:dem":49,
    "gn:feature_class":"P",
    "gn:feature_code":"PPLA3",
    "gn:name":"San Jos\u00e9",
    "gn:population":523,
    "gn:timezone":"America/Panama",
    "iso:country":"PA",
    "name:ita_x_preferred":[
        "San Jos\u00e9"
    ],
    "name:spa_x_preferred":[
        "San Jos\u00e9"
    ],
    "name:zho_x_preferred":[
        "\u5723\u8377\u897f"
    ],
    "wof:name":"San Jose",
    "wof:placetype":"locality",
    "wof:population":523
},
  "geometry": {"coordinates":[-80.24438000000001,7.67395],"type":"Point"}
}