{
  "type": "Feature",
  "properties": {
    "gn:admin1_code":"07",
    "gn:asciiname":"Nuario",
    "gn:country_code":"PA",
    "gn:dem":404,
    "gn:feature_class":"P",
    "gn:feature_code":"PPLA3",
    "gn:name":"Nuario",
    "gn:population":92,
    "gn:timezone":"America/Panama",
    "iso:country":"PA",
    "name:spa_x_preferred":[
        "Nuario"
    ],
    "wof:name":"Nuario",
    "wof:placetype":"locality",
    "wof:population":92
},
  "geometry": {"coordinates":[-80.32692,7.53047],"type":"Point"}
}