{
  "type": "Feature",
  "properties": {
    "gn:admin1_code":"05",
    "gn:asciiname":"Cahoba Negra",
    "gn:country_code":"PA",
    "gn:dem":37,
    "gn:feature_class":"P",
    "gn:feature_code":"PPL",
    "gn:name":"Cahoba Negra",
    "gn:population":0,
    "gn:timezone":"America/Panama",
    "iso:country":"PA",
    "wof:name":"Cahoba Negra",
    "wof:placetype":"locality"
},
  "geometry": {"coordinates":[-78.14997,8.57683],"type":"Point"}
}