{
  "type": "Feature",
  "properties": {
    "gn:admin1_code":"03",
    "gn:asciiname":"El Pasal",
    "gn:cc2":"PA",
    "gn:country_code":"PA",
    "gn:dem":185,
    "gn:feature_class":"P",
    "gn:feature_code":"PPL",
    "gn:name":"El Pasal",
    "gn:population":0,
    "gn:timezone":"America/Panama",
    "iso:country":"PA",
    "name:und_x_variant":[
        "El Pajal",
        "El Pasal"
    ],
    "wof:name":"El Pasal",
    "wof:placetype":"locality"
},
  "geometry": {"coordinates":[-80.28333000000001,8.73333],"type":"Point"}
}