{
  "type": "Feature",
  "properties": {
    "gn:admin1_code":"13",
    "gn:asciiname":"El Pastoreo",
    "gn:country_code":"PA",
    "gn:dem":97,
    "gn:feature_class":"P",
    "gn:feature_code":"PPL",
    "gn:name":"El Pastoreo",
    "gn:population":0,
    "gn:timezone":"America/Panama",
    "iso:country":"PA",
    "wof:name":"El Pastoreo",
    "wof:placetype":"locality"
},
  "geometry": {"coordinates":[-80.05,8.46667],"type":"Point"}
}