{
  "type": "Feature",
  "properties": {
    "gn:admin1_code":"04",
    "gn:asciiname":"Nuevo Chagres",
    "gn:country_code":"PA",
    "gn:dem":24,
    "gn:feature_class":"P",
    "gn:feature_code":"PPLA2",
    "gn:name":"Nuevo Chagres",
    "gn:population":410,
    "gn:timezone":"America/Panama",
    "iso:country":"PA",
    "name:ceb_x_preferred":[
        "Nuevo Chagres"
    ],
    "name:ell_x_preferred":[
        "\u039d\u03bf\u03c5\u03ad\u03b2\u03bf \u03a4\u03c3\u03ac\u03b3\u03c1\u03b5\u03c2"
    ],
    "name:ita_x_preferred":[
        "Nuevo Chagres"
    ],
    "name:pol_x_preferred":[
        "Nuevo Chagres"
    ],
    "name:por_x_preferred":[
        "Nuevo Chagres"
    ],
    "name:spa_x_preferred":[
        "Nuevo Chagres"
    ],
    "name:zho_x_preferred":[
        "\u65b0\u67e5\u683c\u96f7\u65af"
    ],
    "wof:name":"Nuevo Chagres",
    "wof:placetype":"locality",
    "wof:population":410
},
  "geometry": {"coordinates":[-80.08266999999999,9.23979],"type":"Point"}
}