{
  "type": "Feature",
  "properties": {
    "gn:admin1_code":"04",
    "gn:asciiname":"Nuevo Chagres",
    "gn:country_code":"PA",
    "gn:dem":24,
    "gn:feature_class":"P",
    "gn:feature_code":"PPLA2",
    "gn:name":"Nuevo Chagres",
    "gn:population":410,
    "gn:timezone":"America/Panama",
    "iso:country":"PA",
    "wof:name":"Nuevo Chagres",
    "wof:placetype":"locality",
    "wof:population":410
},
  "geometry": {"coordinates":[-80.08266999999999,9.23979],"type":"Point"}
}