{
  "type": "Feature",
  "properties": {
    "gn:admin1_code":"13",
    "gn:asciiname":"La Gloria",
    "gn:country_code":"PA",
    "gn:dem":135,
    "gn:feature_class":"P",
    "gn:feature_code":"PPL",
    "gn:name":"La Gloria",
    "gn:population":478,
    "gn:timezone":"America/Panama",
    "iso:country":"PA",
    "name:spa_x_preferred":[
        "La Gloria"
    ],
    "wof:name":"La Gloria",
    "wof:placetype":"locality",
    "wof:population":478
},
  "geometry": {"coordinates":[-79.73699999999999,9.01882],"type":"Point"}
}