{
  "type": "Feature",
  "properties": {
    "gn:admin1_code":"13",
    "gn:asciiname":"La Humildad",
    "gn:country_code":"PA",
    "gn:dem":127,
    "gn:feature_class":"P",
    "gn:feature_code":"PPL",
    "gn:name":"La Humildad",
    "gn:population":144,
    "gn:timezone":"America/Panama",
    "iso:country":"PA",
    "name:spa_x_preferred":[
        "La Humildad"
    ],
    "wof:name":"La Humildad",
    "wof:placetype":"locality",
    "wof:population":144
},
  "geometry": {"coordinates":[-80.02703000000002,8.95111],"type":"Point"}
}