{
  "type": "Feature",
  "properties": {
    "gn:admin1_code":"01",
    "gn:asciiname":"Dos Canos",
    "gn:country_code":"PA",
    "gn:dem":21,
    "gn:feature_class":"P",
    "gn:feature_code":"PPL",
    "gn:name":"Dos Ca\u00f1os",
    "gn:population":0,
    "gn:timezone":"America/Panama",
    "iso:country":"PA",
    "wof:name":"Dos Canos",
    "wof:placetype":"locality"
},
  "geometry": {"coordinates":[-82.75,9.56667],"type":"Point"}
}