{
  "type": "Feature",
  "properties": {
    "gn:admin1_code":"10",
    "gn:asciiname":"Cerro Viejo",
    "gn:country_code":"PA",
    "gn:dem":394,
    "gn:feature_class":"P",
    "gn:feature_code":"PPL",
    "gn:name":"Cerro Viejo",
    "gn:population":141,
    "gn:timezone":"America/Panama",
    "iso:country":"PA",
    "name:ita_x_preferred":[
        "Cerro Viejo"
    ],
    "name:spa_x_preferred":[
        "Cerro Viejo"
    ],
    "name:zho_x_preferred":[
        "\u585e\u7f85\u5225\u970d"
    ],
    "wof:name":"Cerro Viejo",
    "wof:placetype":"locality",
    "wof:population":141
},
  "geometry": {"coordinates":[-81.18289,8.33974],"type":"Point"}
}