{
  "type": "Feature",
  "properties": {
    "gn:admin1_code":"06",
    "gn:asciiname":"Los Higos",
    "gn:country_code":"PA",
    "gn:dem":65,
    "gn:feature_class":"P",
    "gn:feature_code":"PPL",
    "gn:name":"Los Higos",
    "gn:population":303,
    "gn:timezone":"America/Panama",
    "iso:country":"PA",
    "name:spa_x_preferred":[
        "Los Higos"
    ],
    "wof:name":"Los Higos",
    "wof:placetype":"locality",
    "wof:population":303
},
  "geometry": {"coordinates":[-80.65711999999998,8.00558],"type":"Point"}
}