{
  "type": "Feature",
  "properties": {
    "gn:admin1_code":"07",
    "gn:asciiname":"La Provincia",
    "gn:cc2":"PA",
    "gn:country_code":"PA",
    "gn:dem":519,
    "gn:feature_class":"P",
    "gn:feature_code":"PPL",
    "gn:name":"La Provincia",
    "gn:population":0,
    "gn:timezone":"America/Panama",
    "iso:country":"PA",
    "name:und_x_variant":[
        "Provincia",
        "La Provincia"
    ],
    "wof:name":"La Provincia",
    "wof:placetype":"locality"
},
  "geometry": {"coordinates":[-80.68333,7.43333],"type":"Point"}
}