{
  "type": "Feature",
  "properties": {
    "gn:admin1_code":"12",
    "gn:asciiname":"El Gato",
    "gn:country_code":"PA",
    "gn:dem":261,
    "gn:feature_class":"P",
    "gn:feature_code":"PPL",
    "gn:name":"El Gato",
    "gn:population":0,
    "gn:timezone":"America/Panama",
    "iso:country":"PA",
    "name:und_x_variant":[
        "Quebrada Gato",
        "El Gato"
    ],
    "wof:name":"El Gato",
    "wof:placetype":"locality"
},
  "geometry": {"coordinates":[-81.76666999999998,8.31667],"type":"Point"}
}