{
  "type": "Feature",
  "properties": {
    "gn:admin1_code":"07",
    "gn:asciiname":"Hondo de la Cutarra",
    "gn:country_code":"PA",
    "gn:dem":413,
    "gn:feature_class":"P",
    "gn:feature_code":"PPL",
    "gn:name":"Hondo de la Cutarra",
    "gn:population":0,
    "gn:timezone":"America/Panama",
    "iso:country":"PA",
    "wof:name":"Hondo de la Cutarra",
    "wof:placetype":"locality"
},
  "geometry": {"coordinates":[-80.3601,7.53408],"type":"Point"}
}