{
  "type": "Feature",
  "properties": {
    "gn:admin1_code":"13",
    "gn:asciiname":"Loma Lisa",
    "gn:country_code":"PA",
    "gn:dem":131,
    "gn:feature_class":"P",
    "gn:feature_code":"PPL",
    "gn:name":"Loma Lisa",
    "gn:population":0,
    "gn:timezone":"America/Panama",
    "iso:country":"PA",
    "name:und_x_variant":[
        "Loma Elisa",
        "Loma Lisa"
    ],
    "wof:name":"Loma Lisa",
    "wof:placetype":"locality"
},
  "geometry": {"coordinates":[-79.91083,8.85528],"type":"Point"}
}