{
  "type": "Feature",
  "properties": {
    "gn:admin1_code":"08",
    "gn:asciiname":"Ipeti Choco",
    "gn:country_code":"PA",
    "gn:dem":93,
    "gn:feature_class":"P",
    "gn:feature_code":"PPL",
    "gn:name":"Ipet\u00ed Choc\u00f3",
    "gn:population":0,
    "gn:timezone":"America/Panama",
    "iso:country":"PA",
    "name:spa_x_preferred":[
        "Ipet\u00ed Choc\u00f3"
    ],
    "wof:name":"Ipeti Choco",
    "wof:placetype":"locality"
},
  "geometry": {"coordinates":[-78.52856,8.97306],"type":"Point"}
}