{
  "type": "Feature",
  "properties": {
    "gn:admin1_code":"02",
    "gn:asciiname":"Bajo Frio",
    "gn:country_code":"PA",
    "gn:dem":721,
    "gn:feature_class":"P",
    "gn:feature_code":"PPL",
    "gn:name":"Bajo Fr\u00edo",
    "gn:population":73,
    "gn:timezone":"America/Panama",
    "iso:country":"PA",
    "wof:name":"Bajo Frio",
    "wof:placetype":"locality",
    "wof:population":73
},
  "geometry": {"coordinates":[-82.65574000000002,8.64137],"type":"Point"}
}