{
  "type": "Feature",
  "properties": {
    "gn:admin1_code":"03",
    "gn:asciiname":"El Calabazo",
    "gn:country_code":"PA",
    "gn:dem":305,
    "gn:feature_class":"P",
    "gn:feature_code":"PPL",
    "gn:name":"El Calabazo",
    "gn:population":489,
    "gn:timezone":"America/Panama",
    "iso:country":"PA",
    "name:spa_x_preferred":[
        "El Calabazo"
    ],
    "wof:name":"El Calabazo",
    "wof:placetype":"locality",
    "wof:population":489
},
  "geometry": {"coordinates":[-80.49165000000001,8.62978],"type":"Point"}
}