{
  "type": "Feature",
  "properties": {
    "gn:admin1_code":"10",
    "gn:asciiname":"Perdices",
    "gn:country_code":"PA",
    "gn:dem":30,
    "gn:feature_class":"P",
    "gn:feature_code":"PPL",
    "gn:name":"Perdices",
    "gn:population":0,
    "gn:timezone":"America/Panama",
    "iso:country":"PA",
    "wof:name":"Perdices",
    "wof:placetype":"locality"
},
  "geometry": {"coordinates":[-81.24444,7.79222],"type":"Point"}
}