{
  "type": "Feature",
  "properties": {
    "gn:admin1_code":"02",
    "gn:asciiname":"Silla de Pando",
    "gn:country_code":"PA",
    "gn:dem":1822,
    "gn:feature_class":"P",
    "gn:feature_code":"PPL",
    "gn:name":"Silla de Pando",
    "gn:population":0,
    "gn:timezone":"America/Panama",
    "iso:country":"PA",
    "wof:name":"Silla de Pando",
    "wof:placetype":"locality"
},
  "geometry": {"coordinates":[-82.68333,8.83333],"type":"Point"}
}