{
  "type": "Feature",
  "properties": {
    "gn:admin1_code":"06",
    "gn:asciiname":"Los Mitres",
    "gn:country_code":"PA",
    "gn:dem":138,
    "gn:feature_class":"P",
    "gn:feature_code":"PPL",
    "gn:name":"Los Mitres",
    "gn:population":8,
    "gn:timezone":"America/Panama",
    "iso:country":"PA",
    "wof:name":"Los Mitres",
    "wof:placetype":"locality",
    "wof:population":8
},
  "geometry": {"coordinates":[-80.76246,7.96225],"type":"Point"}
}