{
  "type": "Feature",
  "properties": {
    "gn:admin1_code":"08",
    "gn:asciiname":"Aserrio",
    "gn:cc2":"PA",
    "gn:country_code":"PA",
    "gn:dem":49,
    "gn:feature_class":"P",
    "gn:feature_code":"PPL",
    "gn:name":"Aserr\u00edo",
    "gn:population":0,
    "gn:timezone":"America/Panama",
    "iso:country":"PA",
    "name:und_x_variant":[
        "Entrada a Cerro Azul",
        "Entrada de Cerro Azul",
        "Aserr\u00edo"
    ],
    "wof:name":"Aserrio",
    "wof:placetype":"locality"
},
  "geometry": {"coordinates":[-79.36667,9.11667],"type":"Point"}
}