{
  "type": "Feature",
  "properties": {
    "gn:admin1_code":"12",
    "gn:asciiname":"Quebrada Muleto",
    "gn:country_code":"PA",
    "gn:dem":633,
    "gn:feature_class":"P",
    "gn:feature_code":"PPL",
    "gn:name":"Quebrada Muleto",
    "gn:population":0,
    "gn:timezone":"America/Panama",
    "iso:country":"PA",
    "name:spa_x_preferred":[
        "Quebrada Muleto"
    ],
    "wof:name":"Quebrada Muleto",
    "wof:placetype":"locality"
},
  "geometry": {"coordinates":[-81.97049,8.52607],"type":"Point"}
}