{
  "type": "Feature",
  "properties": {
    "iso:country":"PA",
    "name:spa_x_preferred":[
        "Santa Ana"
    ],
    "qs:gn_country":"PA",
    "qs:gn_fcode":"PPL",
    "qs:gn_pop":0,
    "qs:name":"Santa Ana",
    "qs:name_adm0":"Panam\u00e1",
    "qs:name_adm1":"Panam\u00e1",
    "qs:photos":165,
    "qs:photos_1k":33,
    "qs:photos_9k":1,
    "qs:photos_9r":4,
    "qs:photos_all":165,
    "qs:photos_sr":4,
    "qs:placetype":"Town",
    "qs:pop_sr":"0",
    "qs:woe_adm0":23424924,
    "wof:name":"Santa Ana",
    "wof:placetype":"locality"
},
  "geometry": {"coordinates":[-80.43333,8.56667],"type":"Point"}
}