{
  "type": "Feature",
  "properties": {
    "gn:admin1_code":"08",
    "gn:asciiname":"Quebrada Barro",
    "gn:country_code":"PA",
    "gn:dem":42,
    "gn:feature_class":"P",
    "gn:feature_code":"PPL",
    "gn:name":"Quebrada Barro",
    "gn:population":0,
    "gn:timezone":"America/Panama",
    "iso:country":"PA",
    "wof:name":"Quebrada Barro",
    "wof:placetype":"locality"
},
  "geometry": {"coordinates":[-78.93333,8.35],"type":"Point"}
}