{
  "type": "Feature",
  "properties": {
    "gn:admin1_code":"01",
    "gn:asciiname":"Sieyic",
    "gn:country_code":"PA",
    "gn:dem":108,
    "gn:feature_class":"P",
    "gn:feature_code":"PPLA3",
    "gn:name":"Sieyic",
    "gn:population":0,
    "gn:timezone":"America/Panama",
    "iso:country":"PA",
    "name:spa_x_preferred":[
        "Sieyic"
    ],
    "wof:name":"Sieyic",
    "wof:placetype":"locality"
},
  "geometry": {"coordinates":[-82.65205999999998,9.38323],"type":"Point"}
}