{
  "type": "Feature",
  "properties": {
    "gn:admin1_code":"06",
    "gn:asciiname":"El Pedrito",
    "gn:country_code":"PA",
    "gn:dem":228,
    "gn:feature_class":"P",
    "gn:feature_code":"PPL",
    "gn:name":"El Pedrito",
    "gn:population":6,
    "gn:timezone":"America/Panama",
    "iso:country":"PA",
    "wof:name":"El Pedrito",
    "wof:placetype":"locality",
    "wof:population":6
},
  "geometry": {"coordinates":[-80.63963000000003,7.63311],"type":"Point"}
}