{
  "type": "Feature",
  "properties": {
    "gn:admin1_code":"06",
    "gn:asciiname":"Las Niguas",
    "gn:country_code":"PA",
    "gn:dem":387,
    "gn:feature_class":"P",
    "gn:feature_code":"PPL",
    "gn:name":"Las Niguas",
    "gn:population":0,
    "gn:timezone":"America/Panama",
    "iso:country":"PA",
    "wof:name":"Las Niguas",
    "wof:placetype":"locality"
},
  "geometry": {"coordinates":[-80.66667,7.63333],"type":"Point"}
}