{
  "type": "Feature",
  "properties": {
    "iso:country":"PA",
    "name:ceb_x_preferred":[
        "Sabanitas"
    ],
    "name:eng_x_preferred":[
        "Sabanitas"
    ],
    "name:ita_x_preferred":[
        "Sabanitas"
    ],
    "name:nld_x_preferred":[
        "Sabanitas"
    ],
    "name:pol_x_preferred":[
        "Sabanitas"
    ],
    "name:spa_x_preferred":[
        "Sabanitas"
    ],
    "name:urd_x_preferred":[
        "\u0633\u0628\u0646\u0679\u0627\u0633"
    ],
    "name:zho_x_preferred":[
        "\u85a9\u5df4\u5c3c\u5854\u65af"
    ],
    "qs:gn_country":"PA",
    "qs:gn_fcode":"PPL",
    "qs:gn_pop":12871,
    "qs:name":"Sabanita",
    "qs:name_adm0":"Panam\u00e1",
    "qs:name_adm1":"Col\u00f3n",
    "qs:photos":9,
    "qs:photos_1k":2,
    "qs:photos_9k":1,
    "qs:photos_9r":1,
    "qs:photos_all":9,
    "qs:photos_sr":1,
    "qs:placetype":"Town",
    "qs:pop_sr":"6",
    "qs:woe_adm0":23424924,
    "wd:wordcount":75,
    "wof:name":"Sabanita",
    "wof:placetype":"locality",
    "wof:population":12871
},
  "geometry": {"coordinates":[-79.80110999999999,9.34222],"type":"Point"}
}