{
  "type": "Feature",
  "properties": {
    "gn:admin1_code":"07",
    "gn:asciiname":"El Hato",
    "gn:country_code":"PA",
    "gn:dem":77,
    "gn:feature_class":"P",
    "gn:feature_code":"PPL",
    "gn:name":"El Hato",
    "gn:population":23,
    "gn:timezone":"America/Panama",
    "iso:country":"PA",
    "name:ita_x_preferred":[
        "El Hato"
    ],
    "name:spa_x_preferred":[
        "El Hato"
    ],
    "name:zho_x_preferred":[
        "\u57c3\u723e\u963f\u6258"
    ],
    "wof:name":"El Hato",
    "wof:placetype":"locality",
    "wof:population":23
},
  "geometry": {"coordinates":[-80.55,7.78333],"type":"Point"}
}