{
  "type": "Feature",
  "properties": {
    "gn:admin1_code":"12",
    "gn:asciiname":"Odoarigote",
    "gn:country_code":"PA",
    "gn:dem":15,
    "gn:feature_class":"P",
    "gn:feature_code":"PPL",
    "gn:name":"Odoarigote",
    "gn:population":0,
    "gn:timezone":"America/Panama",
    "iso:country":"PA",
    "wof:name":"Odoarigote",
    "wof:placetype":"locality"
},
  "geometry": {"coordinates":[-81.93333,8.86667],"type":"Point"}
}