{
  "type": "Feature",
  "properties": {
    "iso:country":"PA",
    "name:ceb_x_preferred":[
        "Nuevo Arraij\u00e1n"
    ],
    "name:eng_x_preferred":[
        "Nuevo Arraij\u00e1n"
    ],
    "name:fra_x_preferred":[
        "Nuevo Arraij\u00e1n"
    ],
    "name:kat_x_preferred":[
        "\u10dc\u10e3\u10d4\u10d5\u10dd-\u10d0\u10e0\u10d0\u10d8\u10ee\u10d0\u10dc\u10d8"
    ],
    "name:nld_x_preferred":[
        "Nuevo Arraij\u00e1n"
    ],
    "name:pol_x_preferred":[
        "Nuevo Arraij\u00e1n"
    ],
    "name:spa_x_preferred":[
        "Nuevo Arraij\u00e1n"
    ],
    "qs:gn_country":"PA",
    "qs:gn_fcode":"PPL",
    "qs:gn_pop":23594,
    "qs:name":"Nuevo Arraij\u00e1n",
    "qs:name_adm0":"Panam\u00e1",
    "qs:name_adm1":"Panam\u00e1",
    "qs:photos":0,
    "qs:photos_1k":0,
    "qs:photos_9k":1,
    "qs:photos_9r":1,
    "qs:photos_all":1,
    "qs:photos_sr":0,
    "qs:placetype":"Town",
    "qs:pop_sr":"7",
    "qs:woe_adm0":23424924,
    "wd:wordcount":21,
    "wof:name":"Nuevo Arraij\u00e1n",
    "wof:placetype":"locality",
    "wof:population":23594
},
  "geometry": {"coordinates":[-79.71666999999999,8.91667],"type":"Point"}
}