{
  "type": "Feature",
  "properties": {
    "gn:admin1_code":"10",
    "gn:asciiname":"San Pedro de La Horqueta",
    "gn:country_code":"PA",
    "gn:dem":44,
    "gn:feature_class":"P",
    "gn:feature_code":"PPL",
    "gn:name":"San Pedro de La Horqueta",
    "gn:population":296,
    "gn:timezone":"America/Panama",
    "iso:country":"PA",
    "name:spa_x_preferred":[
        "San Pedro de La Horqueta"
    ],
    "wof:name":"San Pedro de La Horqueta",
    "wof:placetype":"locality",
    "wof:population":296
},
  "geometry": {"coordinates":[-81.09634,8.12289],"type":"Point"}
}