{
  "type": "Feature",
  "properties": {
    "gn:admin1_code":"02",
    "gn:asciiname":"Porton",
    "gn:country_code":"PA",
    "gn:dem":252,
    "gn:feature_class":"P",
    "gn:feature_code":"PPL",
    "gn:name":"Port\u00f3n",
    "gn:population":689,
    "gn:timezone":"America/Panama",
    "iso:country":"PA",
    "name:fas_x_preferred":[
        "\u067e\u0648\u0631\u062a\u0648\u0646"
    ],
    "name:pol_x_preferred":[
        "Porton"
    ],
    "name:rus_x_preferred":[
        "\u041f\u043e\u0440\u0442\u043e\u043d"
    ],
    "name:spa_x_preferred":[
        "Port\u00f3n"
    ],
    "name:spa_x_variant":[
        "Porton"
    ],
    "wof:name":"Porton",
    "wof:placetype":"locality",
    "wof:population":689
},
  "geometry": {"coordinates":[-82.78503000000001,8.56125],"type":"Point"}
}