{
  "type": "Feature",
  "properties": {
    "gn:gn_country":"PA",
    "gn:gn_fcode":"PPLX",
    "gn:gn_pop":0,
    "iso:country":"PA",
    "name:spa_x_preferred":[
        "Paitilla"
    ],
    "name:unk_x_variant":[
        "Paitilla"
    ],
    "qs_pg:aaroncc":"PA",
    "qs_pg:gn_country":"PA",
    "qs_pg:gn_fcode":"PPLX",
    "qs_pg:gn_pop":0,
    "qs_pg:name":"Paitilla",
    "qs_pg:name_adm0":"Panam\u00e1",
    "qs_pg:name_adm1":"Panam\u00e1",
    "qs_pg:photos":654,
    "qs_pg:photos_1k":133,
    "qs_pg:photos_9k":3,
    "qs_pg:photos_9r":5,
    "qs_pg:photos_all":654,
    "qs_pg:photos_sr":8,
    "qs_pg:pop_sr":0,
    "qs_pg:qs_pg_placetype":"neighbourhood",
    "qs_pg:qs_pg_placetype_gp":"Suburb",
    "qs_pg:woe_adm0":23424924,
    "woe:adm0_id":23424924,
    "woe:name_adm0":"Panam\u00e1",
    "woe:name_adm1":"Panam\u00e1",
    "woe:placetype":"Suburb",
    "wof:name":"Paitilla",
    "wof:placetype":"neighbourhood"
},
  "geometry": {"coordinates":[-79.51667,8.98333],"type":"Point"}
}