{
  "type": "Feature",
  "properties": {
    "gn:admin1_code":"06",
    "gn:asciiname":"Puerto Chitre",
    "gn:cc2":"PA",
    "gn:country_code":"PA",
    "gn:dem":8,
    "gn:feature_class":"P",
    "gn:feature_code":"PPL",
    "gn:name":"Puerto Chitr\u00e9",
    "gn:population":0,
    "gn:timezone":"America/Panama",
    "iso:country":"PA",
    "name:und_x_variant":[
        "Puerta Chitr\u00e9",
        "Puerto Chitr\u00e9"
    ],
    "wof:name":"Puerto Chitre",
    "wof:placetype":"locality"
},
  "geometry": {"coordinates":[-80.40000000000001,7.98333],"type":"Point"}
}