{
  "type": "Feature",
  "properties": {
    "gn:admin1_code":"09",
    "gn:asciiname":"Canigal",
    "gn:country_code":"PA",
    "gn:dem":13,
    "gn:feature_class":"P",
    "gn:feature_code":"PPL",
    "gn:name":"Canigal",
    "gn:population":0,
    "gn:timezone":"America/Panama",
    "iso:country":"PA",
    "wof:name":"Canigal",
    "wof:placetype":"locality"
},
  "geometry": {"coordinates":[-79.11667,9.46667],"type":"Point"}
}