{
  "type": "Feature",
  "properties": {
    "gn:admin1_code":"08",
    "gn:asciiname":"Wuacuco",
    "gn:country_code":"PA",
    "gn:dem":103,
    "gn:feature_class":"P",
    "gn:feature_code":"PPL",
    "gn:name":"Wuacuco",
    "gn:population":0,
    "gn:timezone":"America/Panama",
    "iso:country":"PA",
    "name:spa_x_preferred":[
        "Wuacuco"
    ],
    "wof:name":"Wuacuco",
    "wof:placetype":"locality"
},
  "geometry": {"coordinates":[-78.45035,8.95449],"type":"Point"}
}