{
  "type": "Feature",
  "properties": {
    "gn:admin1_code":"02",
    "gn:asciiname":"Alto Jaramillo",
    "gn:country_code":"PA",
    "gn:dem":1302,
    "gn:feature_class":"P",
    "gn:feature_code":"PPL",
    "gn:name":"Alto Jaramillo",
    "gn:population":342,
    "gn:timezone":"America/Panama",
    "iso:country":"PA",
    "name:spa_x_preferred":[
        "Alto Jaramillo"
    ],
    "wof:name":"Alto Jaramillo",
    "wof:placetype":"locality",
    "wof:population":342
},
  "geometry": {"coordinates":[-82.40143,8.75405],"type":"Point"}
}