{
  "type": "Feature",
  "properties": {
    "gn:admin1_code":"06",
    "gn:asciiname":"Borrola",
    "gn:country_code":"PA",
    "gn:dem":115,
    "gn:feature_class":"P",
    "gn:feature_code":"PPL",
    "gn:name":"Borrola",
    "gn:population":0,
    "gn:timezone":"America/Panama",
    "iso:country":"PA",
    "name:und_x_variant":[
        "Barrola",
        "Borrola"
    ],
    "wof:name":"Borrola",
    "wof:placetype":"locality"
},
  "geometry": {"coordinates":[-80.6362,7.82251],"type":"Point"}
}