{
  "type": "Feature",
  "properties": {
    "gn:admin1_code":"02",
    "gn:asciiname":"Bambito",
    "gn:country_code":"PA",
    "gn:dem":1719,
    "gn:feature_class":"P",
    "gn:feature_code":"PPL",
    "gn:name":"Bambito",
    "gn:population":431,
    "gn:timezone":"America/Panama",
    "iso:country":"PA",
    "name:spa_x_preferred":[
        "Bambito"
    ],
    "wof:name":"Bambito",
    "wof:placetype":"locality",
    "wof:population":431
},
  "geometry": {"coordinates":[-82.60909000000002,8.83362],"type":"Point"}
}