{
  "type": "Feature",
  "properties": {
    "gn:admin1_code":"13",
    "gn:asciiname":"Pena Blanca",
    "gn:country_code":"PA",
    "gn:dem":28,
    "gn:feature_class":"P",
    "gn:feature_code":"PPL",
    "gn:name":"Pe\u00f1a Blanca",
    "gn:population":0,
    "gn:timezone":"America/Panama",
    "iso:country":"PA",
    "wof:name":"Pena Blanca",
    "wof:placetype":"locality"
},
  "geometry": {"coordinates":[-79.90000000000001,9.15],"type":"Point"}
}