{
  "type": "Feature",
  "properties": {
    "gn:admin1_code":"04",
    "gn:asciiname":"Quebrada la Ullama",
    "gn:country_code":"PA",
    "gn:dem":32,
    "gn:feature_class":"P",
    "gn:feature_code":"PPL",
    "gn:name":"Quebrada la Ullama",
    "gn:population":0,
    "gn:timezone":"America/Panama",
    "iso:country":"PA",
    "wof:name":"Quebrada la Ullama",
    "wof:placetype":"locality"
},
  "geometry": {"coordinates":[-79.96666999999999,9.15],"type":"Point"}
}