{
  "type": "Feature",
  "properties": {
    "iso:country":"PA",
    "name:ceb_x_preferred":[
        "Yaviza"
    ],
    "name:deu_x_preferred":[
        "Yaviza"
    ],
    "name:eng_x_preferred":[
        "Yaviza"
    ],
    "name:fra_x_preferred":[
        "Yaviza"
    ],
    "name:hun_x_preferred":[
        "Yaviza"
    ],
    "name:ita_x_preferred":[
        "Yaviza"
    ],
    "name:jpn_x_preferred":[
        "\u30e4\u30f4\u30a3\u30b5"
    ],
    "name:lit_x_preferred":[
        "Javisa"
    ],
    "name:nld_x_preferred":[
        "Yaviza"
    ],
    "name:pol_x_preferred":[
        "Yaviza"
    ],
    "name:por_x_preferred":[
        "Yaviza"
    ],
    "name:ron_x_preferred":[
        "Yaviza"
    ],
    "name:spa_x_preferred":[
        "Yaviza"
    ],
    "name:und_x_variant":[
        "Yavisa"
    ],
    "name:urd_x_preferred":[
        "\u06cc\u0648\u06cc\u0632\u0627"
    ],
    "name:zho_x_preferred":[
        "\u4e9e\u7dad\u85a9"
    ],
    "qs:gn_country":"PA",
    "qs:gn_fcode":"PPL",
    "qs:gn_pop":1611,
    "qs:name":"Yaviza",
    "qs:name_adm0":"Panam\u00e1",
    "qs:name_adm1":"Dari\u00e9n",
    "qs:photos":0,
    "qs:photos_1k":0,
    "qs:photos_9k":1,
    "qs:photos_9r":1,
    "qs:photos_all":1,
    "qs:photos_sr":0,
    "qs:placetype":"Town",
    "qs:pop_sr":"3",
    "qs:woe_adm0":23424924,
    "wd:wordcount":100,
    "wof:name":"Yaviza",
    "wof:placetype":"locality",
    "wof:population":1611
},
  "geometry": {"coordinates":[-77.69307999999999,8.1537],"type":"Point"}
}