{
  "type": "Feature",
  "properties": {
    "gn:admin1_code":"03",
    "gn:asciiname":"Pajonal Arriba",
    "gn:country_code":"PA",
    "gn:dem":270,
    "gn:feature_class":"P",
    "gn:feature_code":"PPL",
    "gn:name":"Pajonal Arriba",
    "gn:population":205,
    "gn:timezone":"America/Panama",
    "iso:country":"PA",
    "name:und_x_variant":[
        "Pajonal",
        "Pajonal Arriba"
    ],
    "wof:name":"Pajonal Arriba",
    "wof:placetype":"locality",
    "wof:population":205
},
  "geometry": {"coordinates":[-80.23241999999998,8.60515],"type":"Point"}
}