{
  "type": "Feature",
  "properties": {
    "gn:admin1_code":"08",
    "gn:asciiname":"Chepillo",
    "gn:country_code":"PA",
    "gn:dem":8,
    "gn:feature_class":"P",
    "gn:feature_code":"PPLA3",
    "gn:name":"Chepillo",
    "gn:population":255,
    "gn:timezone":"America/Panama",
    "iso:country":"PA",
    "name:ita_x_preferred":[
        "Chepillo"
    ],
    "name:spa_x_preferred":[
        "Chepillo"
    ],
    "name:zho_x_preferred":[
        "\u5207\u76ae\u7565"
    ],
    "wof:name":"Chepillo",
    "wof:placetype":"locality",
    "wof:population":255
},
  "geometry": {"coordinates":[-79.12855999999999,8.95396],"type":"Point"}
}