{
  "type": "Feature",
  "properties": {
    "gn:admin1_code":"10",
    "gn:asciiname":"Los Lucas",
    "gn:country_code":"PA",
    "gn:dem":128,
    "gn:feature_class":"P",
    "gn:feature_code":"PPL",
    "gn:name":"Los Lucas",
    "gn:population":0,
    "gn:timezone":"America/Panama",
    "iso:country":"PA",
    "wof:name":"Los Lucas",
    "wof:placetype":"locality"
},
  "geometry": {"coordinates":[-81.41667,8.13333],"type":"Point"}
}