{
  "type": "Feature",
  "properties": {
    "gn:admin1_code":"05",
    "gn:asciiname":"Seteganti",
    "gn:country_code":"PA",
    "gn:dem":74,
    "gn:feature_class":"P",
    "gn:feature_code":"PPL",
    "gn:name":"Setegant\u00ed",
    "gn:population":0,
    "gn:timezone":"America/Panama",
    "iso:country":"PA",
    "name:ita_x_preferred":[
        "Setegant\u00ed"
    ],
    "name:spa_x_preferred":[
        "Setegant\u00ed"
    ],
    "name:und_x_variant":[
        "Setegant\u00ed"
    ],
    "name:zho_x_preferred":[
        "\u585e\u7279\u7518\u8482"
    ],
    "wof:name":"Seteganti",
    "wof:placetype":"locality"
},
  "geometry": {"coordinates":[-78.0775,8.23167],"type":"Point"}
}