{
  "type": "Feature",
  "properties": {
    "gn:admin1_code":"12",
    "gn:asciiname":"Cabuya",
    "gn:country_code":"PA",
    "gn:dem":348,
    "gn:feature_class":"P",
    "gn:feature_code":"PPL",
    "gn:name":"Cabuya",
    "gn:population":265,
    "gn:timezone":"America/Panama",
    "iso:country":"PA",
    "name:fra_x_preferred":[
        "Cabuya"
    ],
    "name:ita_x_preferred":[
        "Cabuya"
    ],
    "name:spa_x_preferred":[
        "Cabuya"
    ],
    "wof:name":"Cabuya",
    "wof:placetype":"locality",
    "wof:population":265
},
  "geometry": {"coordinates":[-81.90049999999999,8.43029],"type":"Point"}
}