{
  "type": "Feature",
  "properties": {
    "gn:admin1_code":"02",
    "gn:asciiname":"Las Lajas",
    "gn:country_code":"PA",
    "gn:dem":69,
    "gn:feature_class":"P",
    "gn:feature_code":"PPLA2",
    "gn:name":"Las Lajas",
    "gn:population":1012,
    "gn:timezone":"America/Panama",
    "iso:country":"PA",
    "name:ita_x_preferred":[
        "Las Lajas"
    ],
    "name:spa_x_preferred":[
        "Las Lajas"
    ],
    "name:und_x_variant":[
        "Lajas",
        "Las Lajas"
    ],
    "name:zho_x_preferred":[
        "\u62c9\u65af\u62c9\u54c8\u65af"
    ],
    "wof:name":"Las Lajas",
    "wof:placetype":"locality",
    "wof:population":1012
},
  "geometry": {"coordinates":[-81.86931,8.24184],"type":"Point"}
}