{
  "type": "Feature",
  "properties": {
    "gn:admin1_code":"02",
    "gn:asciiname":"Las Lajas",
    "gn:country_code":"PA",
    "gn:dem":69,
    "gn:feature_class":"P",
    "gn:feature_code":"PPLA2",
    "gn:name":"Las Lajas",
    "gn:population":1012,
    "gn:timezone":"America/Panama",
    "iso:country":"PA",
    "name:ara_x_preferred":[
        "\u0644\u0627\u0633 \u0644\u0627\u062c\u0627\u0633"
    ],
    "name:ben_x_preferred":[
        "\u09b2\u09be\u09b8 \u09b2\u09be\u099c\u09be\u09b8"
    ],
    "name:ell_x_preferred":[
        "\u039b\u03b1\u03c2 \u039b\u03ac\u03c7\u03b1\u03c2"
    ],
    "name:heb_x_preferred":[
        "\u05dc\u05d0\u05e1 \u05dc\u05d0\u05d7\u05d0\u05e1"
    ],
    "name:hin_x_preferred":[
        "\u0932\u093e \u0932\u091c\u093e\u0938"
    ],
    "name:hun_x_preferred":[
        "Las Lajas"
    ],
    "name:ind_x_preferred":[
        "Las Lajas"
    ],
    "name:ita_x_preferred":[
        "Las Lajas"
    ],
    "name:jpn_x_preferred":[
        "\u30e9\u30b9\u30e9\u30cf\u30b9"
    ],
    "name:kor_x_preferred":[
        "\ub77c\uc2a4 \ub77c\ud558\uc2a4"
    ],
    "name:spa_x_preferred":[
        "Las Lajas"
    ],
    "name:swe_x_preferred":[
        "Las Lajas"
    ],
    "name:und_x_variant":[
        "Lajas"
    ],
    "name:urd_x_preferred":[
        "\u0644\u0627\u0633 \u0644\u0627\u062c\u0627\u0633"
    ],
    "name:vie_x_preferred":[
        "Las Lajas"
    ],
    "name:zho_x_preferred":[
        "\u62c9\u65af\u62c9\u54c8\u65af"
    ],
    "wof:name":"Las Lajas",
    "wof:placetype":"locality",
    "wof:population":1012
},
  "geometry": {"coordinates":[-81.86931,8.24184],"type":"Point"}
}