{
  "type": "Feature",
  "properties": {
    "gn:admin1_code":"06",
    "gn:asciiname":"Limon de Tijeras",
    "gn:country_code":"PA",
    "gn:dem":275,
    "gn:feature_class":"P",
    "gn:feature_code":"PPLA3",
    "gn:name":"Lim\u00f3n de Tijeras",
    "gn:population":56,
    "gn:timezone":"America/Panama",
    "iso:country":"PA",
    "name:spa_x_preferred":[
        "Lim\u00f3n de Tijeras"
    ],
    "wof:name":"Limon de Tijeras",
    "wof:placetype":"locality",
    "wof:population":56
},
  "geometry": {"coordinates":[-80.91334999999999,7.81756],"type":"Point"}
}