{
  "type": "Feature",
  "properties": {
    "gn:admin1_code":"05",
    "gn:asciiname":"El Mamey",
    "gn:country_code":"PA",
    "gn:dem":25,
    "gn:feature_class":"P",
    "gn:feature_code":"PPL",
    "gn:name":"El Mamey",
    "gn:population":24,
    "gn:timezone":"America/Panama",
    "iso:country":"PA",
    "name:spa_x_preferred":[
        "El Mamey"
    ],
    "wof:name":"El Mamey",
    "wof:placetype":"locality",
    "wof:population":24
},
  "geometry": {"coordinates":[-78.00861,7.47528],"type":"Point"}
}