{
  "type": "Feature",
  "properties": {
    "gn:admin1_code":"03",
    "gn:asciiname":"Los Ruices",
    "gn:country_code":"PA",
    "gn:dem":556,
    "gn:feature_class":"P",
    "gn:feature_code":"PPL",
    "gn:name":"Los Ruices",
    "gn:population":0,
    "gn:timezone":"America/Panama",
    "iso:country":"PA",
    "name:spa_x_preferred":[
        "Los Ruices"
    ],
    "wof:name":"Los Ruices",
    "wof:placetype":"locality"
},
  "geometry": {"coordinates":[-80.15000000000001,8.56667],"type":"Point"}
}