{
  "type": "Feature",
  "properties": {
    "gn:admin1_code":"09",
    "gn:asciiname":"Tupak",
    "gn:cc2":"PA",
    "gn:country_code":"PA",
    "gn:dem":10,
    "gn:feature_class":"P",
    "gn:feature_code":"PPL",
    "gn:name":"Tupak",
    "gn:population":0,
    "gn:timezone":"America/Panama",
    "iso:country":"PA",
    "name:und_x_variant":[
        "Isla Pino",
        "Pinos",
        "Isla de Pino",
        "Tupak"
    ],
    "wof:name":"Tupak",
    "wof:placetype":"locality"
},
  "geometry": {"coordinates":[-77.76269000000001,9.00776],"type":"Point"}
}