{
  "type": "Feature",
  "properties": {
    "gn:country":"PA",
    "gn:fcode":"PPL",
    "gn:pop":1105,
    "iso:country":"PA",
    "name:eng_x_preferred":[
        "Llano de Piedra"
    ],
    "name:ita_x_preferred":[
        "Llano de Piedra"
    ],
    "name:kat_x_preferred":[
        "\u10da\u10d8\u10d0\u10dc\u10dd-\u10d3\u10d4-\u10de\u10d8\u10d4\u10d3\u10e0\u10d0"
    ],
    "name:spa_x_preferred":[
        "Llano de Piedras"
    ],
    "name:zho_x_preferred":[
        "\u5229\u4e9e\u8afe\u5fb7\u5f7c\u5fb7\u62c9\u65af"
    ],
    "qs:name":"Llano de Piedra",
    "qs:photos_9r":0,
    "qs:photos_sr":0,
    "qs:pop_sr":"3",
    "wd:wordcount":80,
    "wof:name":"Llano de Piedra",
    "wof:placetype":"locality",
    "wof:population":1105
},
  "geometry": {"coordinates":[-80.56667,7.66667],"type":"Point"}
}