{
  "type": "Feature",
  "properties": {
    "gn:admin1_code":"10",
    "gn:asciiname":"Leones Arriba",
    "gn:country_code":"PA",
    "gn:dem":15,
    "gn:feature_class":"P",
    "gn:feature_code":"PPLA3",
    "gn:name":"Leones Arriba",
    "gn:population":69,
    "gn:timezone":"America/Panama",
    "iso:country":"PA",
    "name:spa_x_preferred":[
        "Leones Arriba"
    ],
    "wof:name":"Leones Arriba",
    "wof:placetype":"locality",
    "wof:population":69
},
  "geometry": {"coordinates":[-81.11556,7.75415],"type":"Point"}
}