{
  "type": "Feature",
  "properties": {
    "gn:admin1_code":"02",
    "gn:asciiname":"Finca La Contesa",
    "gn:country_code":"PA",
    "gn:dem":8,
    "gn:feature_class":"P",
    "gn:feature_code":"PPL",
    "gn:name":"Finca La Contesa",
    "gn:population":0,
    "gn:timezone":"America/Panama",
    "iso:country":"PA",
    "wof:name":"Finca La Contesa",
    "wof:placetype":"locality"
},
  "geometry": {"coordinates":[-82.75,8.35],"type":"Point"}
}