{
  "type": "Feature",
  "properties": {
    "iso:country":"PA",
    "name:ceb_x_preferred":[
        "Mata del Nance"
    ],
    "name:eng_x_preferred":[
        "Mata del Nance"
    ],
    "name:kat_x_preferred":[
        "\u10db\u10d0\u10e2\u10d0-\u10d3\u10d4\u10da-\u10dc\u10d0\u10dc\u10e1\u10d4"
    ],
    "name:nld_x_preferred":[
        "Mata del Nance"
    ],
    "qs:gn_country":"PA",
    "qs:gn_fcode":"PPL",
    "qs:gn_pop":1051,
    "qs:name":"Mata del Nance",
    "qs:name_adm0":"Panam\u00e1",
    "qs:name_adm1":"Chiriqu\u00ed",
    "qs:photos":0,
    "qs:photos_1k":0,
    "qs:photos_9k":1,
    "qs:photos_9r":1,
    "qs:photos_all":6,
    "qs:photos_sr":0,
    "qs:placetype":"Town",
    "qs:pop_sr":"3",
    "qs:woe_adm0":23424924,
    "wd:wordcount":18,
    "wof:name":"Mata del Nance",
    "wof:placetype":"locality",
    "wof:population":1051
},
  "geometry": {"coordinates":[-82.40000000000001,8.45],"type":"Point"}
}