{
  "type": "Feature",
  "properties": {
    "gn:admin1_code":"10",
    "gn:asciiname":"Bajo de San Juan",
    "gn:country_code":"PA",
    "gn:dem":393,
    "gn:feature_class":"P",
    "gn:feature_code":"PPL",
    "gn:name":"Bajo de San Juan",
    "gn:population":0,
    "gn:timezone":"America/Panama",
    "iso:country":"PA",
    "wof:name":"Bajo de San Juan",
    "wof:placetype":"locality"
},
  "geometry": {"coordinates":[-81.06667,8.48333],"type":"Point"}
}