{
  "type": "Feature",
  "properties": {
    "gn:admin1_code":"07",
    "gn:asciiname":"La Palma",
    "gn:country_code":"PA",
    "gn:dem":193,
    "gn:feature_class":"P",
    "gn:feature_code":"PPL",
    "gn:name":"La Palma",
    "gn:population":1283,
    "gn:timezone":"America/Panama",
    "iso:country":"PA",
    "wof:name":"La Palma",
    "wof:placetype":"locality",
    "wof:population":1283
},
  "geometry": {"coordinates":[-80.38333,7.71667],"type":"Point"}
}