{
  "type": "Feature",
  "properties": {
    "gn:admin1_code":"10",
    "gn:asciiname":"La Redonda",
    "gn:country_code":"PA",
    "gn:dem":40,
    "gn:feature_class":"P",
    "gn:feature_code":"PPL",
    "gn:name":"La Redonda",
    "gn:population":118,
    "gn:timezone":"America/Panama",
    "iso:country":"PA",
    "wof:name":"La Redonda",
    "wof:placetype":"locality",
    "wof:population":118
},
  "geometry": {"coordinates":[-81.03721999999998,7.97583],"type":"Point"}
}