{
  "type": "Feature",
  "properties": {
    "gn:admin1_code":"10",
    "gn:asciiname":"La Vaca",
    "gn:country_code":"PA",
    "gn:dem":80,
    "gn:feature_class":"P",
    "gn:feature_code":"PPL",
    "gn:name":"La Vaca",
    "gn:population":0,
    "gn:timezone":"America/Panama",
    "iso:country":"PA",
    "wof:name":"La Vaca",
    "wof:placetype":"locality"
},
  "geometry": {"coordinates":[-81.56944,7.92472],"type":"Point"}
}