{
  "type": "Feature",
  "properties": {
    "gn:admin1_code":"12",
    "gn:asciiname":"Pumuna",
    "gn:country_code":"PA",
    "gn:dem":3,
    "gn:feature_class":"P",
    "gn:feature_code":"PPL",
    "gn:name":"Pumuna",
    "gn:population":0,
    "gn:timezone":"America/Panama",
    "iso:country":"PA",
    "name:spa_x_preferred":[
        "Pumuna"
    ],
    "wof:name":"Pumuna",
    "wof:placetype":"locality"
},
  "geometry": {"coordinates":[-82.0574,8.89916],"type":"Point"}
}