{
  "type": "Feature",
  "properties": {
    "gn:admin1_code":"02",
    "gn:asciiname":"Boca Toro",
    "gn:country_code":"PA",
    "gn:dem":6,
    "gn:feature_class":"P",
    "gn:feature_code":"PPL",
    "gn:name":"Boca Toro",
    "gn:population":0,
    "gn:timezone":"America/Panama",
    "iso:country":"PA",
    "wof:name":"Boca Toro",
    "wof:placetype":"locality"
},
  "geometry": {"coordinates":[-81.78333000000001,8.13333],"type":"Point"}
}