{
  "type": "Feature",
  "properties": {
    "iso:country":"PA",
    "name:eng_x_preferred":[
        "Puerto Pil\u00f3n"
    ],
    "name:ita_x_preferred":[
        "Puerto Pil\u00f3n"
    ],
    "name:nld_x_preferred":[
        "Puerto Pil\u00f3n"
    ],
    "name:spa_x_preferred":[
        "Puerto Pil\u00f3n"
    ],
    "name:zho_x_preferred":[
        "\u6ce2\u591a\u76ae\u9686"
    ],
    "qs:gn_country":"PA",
    "qs:gn_fcode":"PPL",
    "qs:gn_pop":5688,
    "qs:name":"Puerto Pil\u00f3n",
    "qs:name_adm0":"Panam\u00e1",
    "qs:name_adm1":"Col\u00f3n",
    "qs:photos":0,
    "qs:photos_1k":0,
    "qs:photos_9k":1,
    "qs:photos_9r":1,
    "qs:photos_all":1,
    "qs:photos_sr":0,
    "qs:placetype":"Town",
    "qs:pop_sr":"5",
    "qs:woe_adm0":23424924,
    "wd:wordcount":76,
    "wof:name":"Puerto Pil\u00f3n",
    "wof:placetype":"locality",
    "wof:population":5688
},
  "geometry": {"coordinates":[-79.79333,9.36444],"type":"Point"}
}