{
  "type": "Feature",
  "properties": {
    "gn:admin1_code":"13",
    "gn:asciiname":"La Divisa",
    "gn:country_code":"PA",
    "gn:dem":229,
    "gn:feature_class":"P",
    "gn:feature_code":"PPL",
    "gn:name":"La Divisa",
    "gn:population":2,
    "gn:timezone":"America/Panama",
    "iso:country":"PA",
    "wof:name":"La Divisa",
    "wof:placetype":"locality",
    "wof:population":2
},
  "geometry": {"coordinates":[-79.96666999999999,8.58333],"type":"Point"}
}