{
  "type": "Feature",
  "properties": {
    "gn:admin1_code":"10",
    "gn:asciiname":"Pasacarnal",
    "gn:country_code":"PA",
    "gn:dem":138,
    "gn:feature_class":"P",
    "gn:feature_code":"PPL",
    "gn:name":"Pasacarnal",
    "gn:population":0,
    "gn:timezone":"America/Panama",
    "iso:country":"PA",
    "wof:name":"Pasacarnal",
    "wof:placetype":"locality"
},
  "geometry": {"coordinates":[-80.90000000000001,8.33333],"type":"Point"}
}