{
  "type": "Feature",
  "properties": {
    "gn:admin1_code":"10",
    "gn:asciiname":"La Mona",
    "gn:country_code":"PA",
    "gn:dem":35,
    "gn:feature_class":"P",
    "gn:feature_code":"PPL",
    "gn:name":"La Mona",
    "gn:population":0,
    "gn:timezone":"America/Panama",
    "iso:country":"PA",
    "wof:name":"La Mona",
    "wof:placetype":"locality"
},
  "geometry": {"coordinates":[-81.57139000000002,7.78889],"type":"Point"}
}