{
  "type": "Feature",
  "properties": {
    "gn:admin1_code":"07",
    "gn:asciiname":"El Pilon",
    "gn:country_code":"PA",
    "gn:dem":446,
    "gn:feature_class":"P",
    "gn:feature_code":"PPL",
    "gn:name":"El Pil\u00f3n",
    "gn:population":0,
    "gn:timezone":"America/Panama",
    "iso:country":"PA",
    "wof:name":"El Pilon",
    "wof:placetype":"locality"
},
  "geometry": {"coordinates":[-80.66667,7.41667],"type":"Point"}
}