{
  "type": "Feature",
  "properties": {
    "gn:admin1_code":"03",
    "gn:asciiname":"Machuca",
    "gn:country_code":"PA",
    "gn:dem":260,
    "gn:feature_class":"P",
    "gn:feature_code":"PPL",
    "gn:name":"Machuca",
    "gn:population":702,
    "gn:timezone":"America/Panama",
    "iso:country":"PA",
    "name:deu_x_preferred":[
        "Machuca"
    ],
    "name:glg_x_preferred":[
        "Machuca"
    ],
    "name:ita_x_preferred":[
        "Machuca"
    ],
    "name:nld_x_preferred":[
        "Machuca"
    ],
    "name:por_x_preferred":[
        "Machuca"
    ],
    "name:spa_x_preferred":[
        "Machuca"
    ],
    "name:swe_x_preferred":[
        "Machuca"
    ],
    "wof:name":"Machuca",
    "wof:placetype":"locality",
    "wof:population":702
},
  "geometry": {"coordinates":[-80.54819000000001,8.62182],"type":"Point"}
}