{
  "type": "Feature",
  "properties": {
    "gn:admin1_code":"12",
    "gn:asciiname":"Cerro Santo",
    "gn:country_code":"PA",
    "gn:dem":556,
    "gn:feature_class":"P",
    "gn:feature_code":"PPL",
    "gn:name":"Cerro Santo",
    "gn:population":67,
    "gn:timezone":"America/Panama",
    "iso:country":"PA",
    "name:und_x_variant":[
        "Cerro Santos"
    ],
    "wof:name":"Cerro Santo",
    "wof:placetype":"locality",
    "wof:population":67
},
  "geometry": {"coordinates":[-81.72976,8.41849],"type":"Point"}
}