{
  "type": "Feature",
  "properties": {
    "gn:admin1_code":"01",
    "gn:asciiname":"Valle Junquito",
    "gn:country_code":"PA",
    "gn:dem":140,
    "gn:feature_class":"P",
    "gn:feature_code":"PPL",
    "gn:name":"Valle Junquito",
    "gn:population":358,
    "gn:timezone":"America/Panama",
    "iso:country":"PA",
    "name:spa_x_preferred":[
        "Valle Junquito"
    ],
    "wof:name":"Valle Junquito",
    "wof:placetype":"locality",
    "wof:population":358
},
  "geometry": {"coordinates":[-82.48371,9.36359],"type":"Point"}
}