{
  "type": "Feature",
  "properties": {
    "gn:admin1_code":"02",
    "gn:asciiname":"Buena Vista",
    "gn:country_code":"PA",
    "gn:dem":204,
    "gn:feature_class":"P",
    "gn:feature_code":"PPL",
    "gn:name":"Buena Vista",
    "gn:population":311,
    "gn:timezone":"America/Panama",
    "iso:country":"PA",
    "name:spa_x_preferred":[
        "Buena Vista"
    ],
    "wof:name":"Buena Vista",
    "wof:placetype":"locality",
    "wof:population":311
},
  "geometry": {"coordinates":[-82.49327,8.50947],"type":"Point"}
}