{
  "type": "Feature",
  "properties": {
    "gn:admin1_code":"10",
    "gn:asciiname":"Guias Arriba",
    "gn:country_code":"PA",
    "gn:dem":52,
    "gn:feature_class":"P",
    "gn:feature_code":"PPL",
    "gn:name":"Gu\u00edas Arriba",
    "gn:population":0,
    "gn:timezone":"America/Panama",
    "iso:country":"PA",
    "name:spa_x_preferred":[
        "Gu\u00edas Arriba"
    ],
    "wof:name":"Guias Arriba",
    "wof:placetype":"locality"
},
  "geometry": {"coordinates":[-80.77124000000001,8.24433],"type":"Point"}
}