{
  "type": "Feature",
  "properties": {
    "gn:admin1_code":"03",
    "gn:asciiname":"Chumical",
    "gn:country_code":"PA",
    "gn:dem":122,
    "gn:feature_class":"P",
    "gn:feature_code":"PPL",
    "gn:name":"Chumical",
    "gn:population":0,
    "gn:timezone":"America/Panama",
    "iso:country":"PA",
    "name:ita_x_preferred":[
        "Chumical"
    ],
    "name:spa_x_preferred":[
        "Chumical"
    ],
    "name:zho_x_preferred":[
        "\u4e18\u7c73\u5361\u723e"
    ],
    "wof:name":"Chumical",
    "wof:placetype":"locality"
},
  "geometry": {"coordinates":[-80.43333,8.63333],"type":"Point"}
}