{
  "type": "Feature",
  "properties": {
    "gn:admin1_code":"06",
    "gn:asciiname":"Los Higos",
    "gn:country_code":"PA",
    "gn:dem":191,
    "gn:feature_class":"P",
    "gn:feature_code":"PPL",
    "gn:name":"Los Higos",
    "gn:population":25,
    "gn:timezone":"America/Panama",
    "iso:country":"PA",
    "wof:name":"Los Higos",
    "wof:placetype":"locality",
    "wof:population":25
},
  "geometry": {"coordinates":[-80.86667,7.88333],"type":"Point"}
}