{
  "type": "Feature",
  "properties": {
    "gn:admin1_code":"10",
    "gn:asciiname":"Nuestro Amo",
    "gn:country_code":"PA",
    "gn:dem":131,
    "gn:feature_class":"P",
    "gn:feature_code":"PPL",
    "gn:name":"Nuestro Amo",
    "gn:population":0,
    "gn:timezone":"America/Panama",
    "iso:country":"PA",
    "name:spa_x_preferred":[
        "Nuestro Amo"
    ],
    "wof:name":"Nuestro Amo",
    "wof:placetype":"locality"
},
  "geometry": {"coordinates":[-80.91667,8.00201],"type":"Point"}
}