{
  "type": "Feature",
  "properties": {
    "gn:admin1_code":"12",
    "gn:asciiname":"Guibale",
    "gn:country_code":"PA",
    "gn:dem":772,
    "gn:feature_class":"P",
    "gn:feature_code":"PPLA3",
    "gn:name":"G\u00fcibale",
    "gn:population":0,
    "gn:timezone":"America/Panama",
    "iso:country":"PA",
    "name:spa_x_preferred":[
        "G\u00fcibale"
    ],
    "wof:name":"Guibale",
    "wof:placetype":"locality"
},
  "geometry": {"coordinates":[-81.36256999999998,8.51225],"type":"Point"}
}