{
  "type": "Feature",
  "properties": {
    "gn:admin1_code":"12",
    "gn:asciiname":"Mananti Abajo",
    "gn:country_code":"PA",
    "gn:dem":7,
    "gn:feature_class":"P",
    "gn:feature_code":"PPL",
    "gn:name":"Manant\u00ed Abajo",
    "gn:population":0,
    "gn:timezone":"America/Panama",
    "iso:country":"PA",
    "name:und_x_variant":[
        "Manat\u00ed Creek",
        "Mananti",
        "Manat\u00ed",
        "Quebrada Manat\u00ed",
        "Manant\u00ed Abajo"
    ],
    "wof:name":"Mananti Abajo",
    "wof:placetype":"locality"
},
  "geometry": {"coordinates":[-81.96666999999999,8.93333],"type":"Point"}
}