{
  "type": "Feature",
  "properties": {
    "gn:admin1_code":"02",
    "gn:asciiname":"Los Angeles",
    "gn:country_code":"PA",
    "gn:dem":349,
    "gn:feature_class":"P",
    "gn:feature_code":"PPLA3",
    "gn:name":"Los \u00c1ngeles",
    "gn:population":250,
    "gn:timezone":"America/Panama",
    "iso:country":"PA",
    "name:spa_x_preferred":[
        "Los \u00c1ngeles"
    ],
    "name:zho_x_preferred":[
        "\u6d1b\u6749\u77f6"
    ],
    "wof:name":"Los Angeles",
    "wof:placetype":"locality",
    "wof:population":250
},
  "geometry": {"coordinates":[-82.19996999999999,8.52271],"type":"Point"}
}