{
  "type": "Feature",
  "properties": {
    "gn:admin1_code":"13",
    "gn:asciiname":"Dos Aguas",
    "gn:country_code":"PA",
    "gn:dem":123,
    "gn:feature_class":"P",
    "gn:feature_code":"PPL",
    "gn:name":"Dos Aguas",
    "gn:population":136,
    "gn:timezone":"America/Panama",
    "iso:country":"PA",
    "name:arg_x_preferred":[
        "Dos Aguas"
    ],
    "name:ast_x_preferred":[
        "Dos Enag\u00fces"
    ],
    "name:cat_x_preferred":[
        "Dosaig\u00fces"
    ],
    "name:ceb_x_preferred":[
        "Dos Aguas"
    ],
    "name:epo_x_preferred":[
        "Dos Aguas"
    ],
    "name:eus_x_preferred":[
        "Dos Aguas"
    ],
    "name:fra_x_preferred":[
        "Dos Aguas"
    ],
    "name:hun_x_preferred":[
        "Dos Aguas"
    ],
    "name:ita_x_preferred":[
        "Dos Aguas"
    ],
    "name:msa_x_preferred":[
        "Dosaig\u00fces"
    ],
    "name:oci_x_preferred":[
        "Dos Aguas"
    ],
    "name:pol_x_preferred":[
        "Dos Aguas"
    ],
    "name:por_x_preferred":[
        "Dos Aguas"
    ],
    "name:rus_x_preferred":[
        "\u0414\u043e\u0441-\u0410\u0433\u0443\u0430\u0441"
    ],
    "name:spa_x_preferred":[
        "Dos Aguas"
    ],
    "name:sqi_x_preferred":[
        "Dos Aguas"
    ],
    "name:swe_x_preferred":[
        "Dos Aguas"
    ],
    "name:ukr_x_preferred":[
        "\u0414\u043e\u0441-\u0410\u0433\u0443\u0430\u0441"
    ],
    "name:war_x_preferred":[
        "Dos Aguas"
    ],
    "name:zho_x_preferred":[
        "\u591a\u8428\u74dc\u65af"
    ],
    "wof:name":"Dos Aguas",
    "wof:placetype":"locality",
    "wof:population":136
},
  "geometry": {"coordinates":[-80.10110999999998,8.94879],"type":"Point"}
}