{
  "type": "Feature",
  "properties": {
    "gn:admin1_code":"02",
    "gn:asciiname":"Chatal",
    "gn:country_code":"PA",
    "gn:dem":607,
    "gn:feature_class":"P",
    "gn:feature_code":"PPL",
    "gn:name":"Chatal",
    "gn:population":0,
    "gn:timezone":"America/Panama",
    "iso:country":"PA",
    "wof:name":"Chatal",
    "wof:placetype":"locality"
},
  "geometry": {"coordinates":[-82.63333,8.61667],"type":"Point"}
}