{
  "type": "Feature",
  "properties": {
    "gn:admin1_code":"03",
    "gn:asciiname":"Cabecera de Limon",
    "gn:country_code":"PA",
    "gn:dem":169,
    "gn:feature_class":"P",
    "gn:feature_code":"PPL",
    "gn:name":"Cabecera de Lim\u00f3n",
    "gn:population":0,
    "gn:timezone":"America/Panama",
    "iso:country":"PA",
    "wof:name":"Cabecera de Limon",
    "wof:placetype":"locality"
},
  "geometry": {"coordinates":[-80.28333000000001,8.86667],"type":"Point"}
}