{
  "type": "Feature",
  "properties": {
    "gn:admin1_code":"03",
    "gn:asciiname":"Llano Santo",
    "gn:country_code":"PA",
    "gn:dem":39,
    "gn:feature_class":"P",
    "gn:feature_code":"PPL",
    "gn:name":"Llano Santo",
    "gn:population":350,
    "gn:timezone":"America/Panama",
    "iso:country":"PA",
    "name:spa_x_preferred":[
        "Llano Santo"
    ],
    "wof:name":"Llano Santo",
    "wof:placetype":"locality",
    "wof:population":350
},
  "geometry": {"coordinates":[-80.7304,8.19065],"type":"Point"}
}