{
  "type": "Feature",
  "properties": {
    "gn:admin1_code":"01",
    "gn:asciiname":"San San Tigra",
    "gn:country_code":"PA",
    "gn:dem":11,
    "gn:feature_class":"P",
    "gn:feature_code":"PPL",
    "gn:name":"San San Tigra",
    "gn:population":217,
    "gn:timezone":"America/Panama",
    "iso:country":"PA",
    "name:spa_x_preferred":[
        "San San Tigra"
    ],
    "wof:name":"San San Tigra",
    "wof:placetype":"locality",
    "wof:population":217
},
  "geometry": {"coordinates":[-82.6559,9.43561],"type":"Point"}
}