{
  "type": "Feature",
  "properties": {
    "gn:admin1_code":"03",
    "gn:asciiname":"Churube Abajo",
    "gn:country_code":"PA",
    "gn:dem":24,
    "gn:feature_class":"P",
    "gn:feature_code":"PPL",
    "gn:name":"Churub\u00e9 Abajo",
    "gn:population":774,
    "gn:timezone":"America/Panama",
    "iso:country":"PA",
    "name:und_x_variant":[
        "Churub\u00e9",
        "Churub\u00e9 Abajo"
    ],
    "wof:name":"Churube Abajo",
    "wof:placetype":"locality",
    "wof:population":774
},
  "geometry": {"coordinates":[-80.54156,8.39889],"type":"Point"}
}