{
  "type": "Feature",
  "properties": {
    "gn:admin1_code":"06",
    "gn:asciiname":"La Concepcion",
    "gn:country_code":"PA",
    "gn:dem":29,
    "gn:feature_class":"P",
    "gn:feature_code":"PPL",
    "gn:name":"La Concepci\u00f3n",
    "gn:population":211,
    "gn:timezone":"America/Panama",
    "iso:country":"PA",
    "name:spa_x_preferred":[
        "La Concepci\u00f3n"
    ],
    "wof:name":"La Concepcion",
    "wof:placetype":"locality",
    "wof:population":211
},
  "geometry": {"coordinates":[-80.69286,8.05953],"type":"Point"}
}