{
  "type": "Feature",
  "properties": {
    "gn:admin1_code":"01",
    "gn:asciiname":"Sibubi",
    "gn:country_code":"PA",
    "gn:dem":46,
    "gn:feature_class":"P",
    "gn:feature_code":"PPL",
    "gn:name":"Sibubi",
    "gn:population":0,
    "gn:timezone":"America/Panama",
    "iso:country":"PA",
    "name:spa_x_preferred":[
        "Sibubi"
    ],
    "name:und_x_variant":[
        "Sibube"
    ],
    "wof:name":"Sibubi",
    "wof:placetype":"locality"
},
  "geometry": {"coordinates":[-82.81983000000002,9.5935],"type":"Point"}
}