{
  "type": "Feature",
  "properties": {
    "gn:admin1_code":"12",
    "gn:asciiname":"Boca de Sagui",
    "gn:country_code":"PA",
    "gn:dem":381,
    "gn:feature_class":"P",
    "gn:feature_code":"PPL",
    "gn:name":"Boca de Sagu\u00ed",
    "gn:population":0,
    "gn:timezone":"America/Panama",
    "iso:country":"PA",
    "name:spa_x_preferred":[
        "Boca de Sagu\u00ed"
    ],
    "wof:name":"Boca de Sagui",
    "wof:placetype":"locality"
},
  "geometry": {"coordinates":[-81.98714,8.55162],"type":"Point"}
}