{
  "type": "Feature",
  "properties": {
    "gn:admin1_code":"03",
    "gn:asciiname":"El Pinzon",
    "gn:country_code":"PA",
    "gn:dem":91,
    "gn:feature_class":"P",
    "gn:feature_code":"PPL",
    "gn:name":"El Pinz\u00f3n",
    "gn:population":131,
    "gn:timezone":"America/Panama",
    "iso:country":"PA",
    "name:und_x_variant":[
        "Pinz\u00f3n",
        "El Pinz\u00f3n"
    ],
    "wof:name":"El Pinzon",
    "wof:placetype":"locality",
    "wof:population":131
},
  "geometry": {"coordinates":[-80.70128000000003,8.27527],"type":"Point"}
}