{
  "type": "Feature",
  "properties": {
    "gn:admin1_code":"07",
    "gn:asciiname":"La Corocita",
    "gn:country_code":"PA",
    "gn:dem":51,
    "gn:feature_class":"P",
    "gn:feature_code":"PPL",
    "gn:name":"La Corocita",
    "gn:population":0,
    "gn:timezone":"America/Panama",
    "iso:country":"PA",
    "name:spa_x_preferred":[
        "La Corocita"
    ],
    "name:und_x_variant":[
        "La Corocito"
    ],
    "wof:name":"La Corocita",
    "wof:placetype":"locality"
},
  "geometry": {"coordinates":[-80.5172,7.44876],"type":"Point"}
}