{
  "type": "Feature",
  "properties": {
    "gn:admin1_code":"13",
    "gn:asciiname":"El Maranon",
    "gn:country_code":"PA",
    "gn:dem":70,
    "gn:feature_class":"P",
    "gn:feature_code":"PPL",
    "gn:name":"El Mara\u00f1\u00f3n",
    "gn:population":0,
    "gn:timezone":"America/Panama",
    "iso:country":"PA",
    "wof:name":"El Maranon",
    "wof:placetype":"locality"
},
  "geometry": {"coordinates":[-79.96666999999999,8.61667],"type":"Point"}
}