{
  "type": "Feature",
  "properties": {
    "gn:admin1_code":"08",
    "gn:asciiname":"San Cristobal",
    "gn:country_code":"PA",
    "gn:dem":343,
    "gn:feature_class":"P",
    "gn:feature_code":"PPL",
    "gn:name":"San Crist\u00f3bal",
    "gn:population":27,
    "gn:timezone":"America/Panama",
    "iso:country":"PA",
    "name:spa_x_preferred":[
        "San Crist\u00f3bal"
    ],
    "wof:name":"San Cristobal",
    "wof:placetype":"locality",
    "wof:population":27
},
  "geometry": {"coordinates":[-79.38475,9.2737],"type":"Point"}
}