{
  "type": "Feature",
  "properties": {
    "gn:admin1_code":"10",
    "gn:asciiname":"La Falua",
    "gn:cc2":"PA",
    "gn:country_code":"PA",
    "gn:dem":108,
    "gn:feature_class":"P",
    "gn:feature_code":"PPL",
    "gn:name":"La Fal\u00faa",
    "gn:population":25,
    "gn:timezone":"America/Panama",
    "iso:country":"PA",
    "name:und_x_variant":[
        "La Faller",
        "La Fal\u00faa"
    ],
    "wof:name":"La Falua",
    "wof:placetype":"locality",
    "wof:population":25
},
  "geometry": {"coordinates":[-81.52611,7.96139],"type":"Point"}
}