{
  "type": "Feature",
  "properties": {
    "gn:admin1_code":"13",
    "gn:asciiname":"La Tuerta",
    "gn:country_code":"PA",
    "gn:dem":192,
    "gn:feature_class":"P",
    "gn:feature_code":"PPL",
    "gn:name":"La Tuerta",
    "gn:population":0,
    "gn:timezone":"America/Panama",
    "iso:country":"PA",
    "wof:name":"La Tuerta",
    "wof:placetype":"locality"
},
  "geometry": {"coordinates":[-79.96666999999999,8.91667],"type":"Point"}
}