{
  "type": "Feature",
  "properties": {
    "iso:country":"PA",
    "name:spa_x_preferred":[
        "Barrio Norte"
    ],
    "qs_pg:aaroncc":"PA",
    "qs_pg:name":"Barrio Norte",
    "qs_pg:name_adm0":"Panam\u00e1",
    "qs_pg:name_adm1":"Col\u00f3n",
    "qs_pg:photos":4,
    "qs_pg:photos_1k":1,
    "qs_pg:photos_9k":1,
    "qs_pg:photos_9r":4,
    "qs_pg:photos_all":276,
    "qs_pg:photos_sr":1,
    "qs_pg:pop_sr":0,
    "qs_pg:qs_pg_placetype":"localadmin",
    "qs_pg:qs_pg_placetype_gp":"LocalAdmin",
    "qs_pg:woe_adm0":23424924,
    "woe:adm0_id":23424924,
    "woe:name_adm0":"Panam\u00e1",
    "woe:name_adm1":"Col\u00f3n",
    "woe:placetype":"LocalAdmin",
    "wof:name":"Barrio Norte",
    "wof:placetype":"localadmin"
},
  "geometry": {"coordinates":[-79.902877,9.363414],"type":"Point"}
}