{
  "type": "Feature",
  "properties": {
    "gn:admin1_code":"06",
    "gn:asciiname":"Cerro Gordo",
    "gn:country_code":"PA",
    "gn:dem":295,
    "gn:feature_class":"P",
    "gn:feature_code":"PPL",
    "gn:name":"Cerro Gordo",
    "gn:population":136,
    "gn:timezone":"America/Panama",
    "iso:country":"PA",
    "wof:name":"Cerro Gordo",
    "wof:placetype":"locality",
    "wof:population":136
},
  "geometry": {"coordinates":[-80.69911,7.79048],"type":"Point"}
}