{
  "type": "Feature",
  "properties": {
    "gn:admin1_code":"06",
    "gn:asciiname":"La Quebrada de la Palma",
    "gn:cc2":"PA",
    "gn:country_code":"PA",
    "gn:dem":238,
    "gn:feature_class":"P",
    "gn:feature_code":"PPL",
    "gn:name":"La Quebrada de la Palma",
    "gn:population":0,
    "gn:timezone":"America/Panama",
    "iso:country":"PA",
    "name:und_x_variant":[
        "Quebrada de la Palma",
        "La Palma",
        "La Quebrada de la Palma"
    ],
    "wof:name":"La Quebrada de la Palma",
    "wof:placetype":"locality"
},
  "geometry": {"coordinates":[-80.63333,7.71667],"type":"Point"}
}