{
  "type": "Feature",
  "properties": {
    "gn:admin1_code":"10",
    "gn:asciiname":"Cerro Banco",
    "gn:country_code":"PA",
    "gn:dem":39,
    "gn:feature_class":"P",
    "gn:feature_code":"PPL",
    "gn:name":"Cerro Banco",
    "gn:population":141,
    "gn:timezone":"America/Panama",
    "iso:country":"PA",
    "name:und_x_variant":[
        "Cerro Blanco",
        "Cerro Banco"
    ],
    "wof:name":"Cerro Banco",
    "wof:placetype":"locality",
    "wof:population":141
},
  "geometry": {"coordinates":[-81.16649,7.92235],"type":"Point"}
}