{
  "type": "Feature",
  "properties": {
    "gn:admin1_code":"13",
    "gn:asciiname":"Los Barbudos",
    "gn:country_code":"PA",
    "gn:dem":405,
    "gn:feature_class":"P",
    "gn:feature_code":"PPL",
    "gn:name":"Los Barbudos",
    "gn:population":0,
    "gn:timezone":"America/Panama",
    "iso:country":"PA",
    "wof:name":"Los Barbudos",
    "wof:placetype":"locality"
},
  "geometry": {"coordinates":[-80.03333000000001,8.58333],"type":"Point"}
}