{
  "type": "Feature",
  "properties": {
    "iso:country":"PA",
    "qs:gn_pop":0,
    "qs:name":"La Pintada",
    "qs:name_adm0":"Panam\u00e1",
    "qs:name_adm1":"Cocl\u00e9",
    "qs:photos":3,
    "qs:photos_1k":1,
    "qs:photos_9k":1,
    "qs:photos_9r":3,
    "qs:photos_all":125,
    "qs:photos_sr":1,
    "qs:placetype":"LocalAdmin",
    "qs:pop_sr":"0",
    "qs:woe_adm0":23424924,
    "wof:name":"La Pintada",
    "wof:placetype":"localadmin"
},
  "geometry": {"coordinates":[-80.44807400000001,8.596127],"type":"Point"}
}