{
  "type": "Feature",
  "properties": {
    "gn:admin1_code":"10",
    "gn:asciiname":"San Pedro del Rincon",
    "gn:country_code":"PA",
    "gn:dem":42,
    "gn:feature_class":"P",
    "gn:feature_code":"PPL",
    "gn:name":"San Pedro del Rinc\u00f3n",
    "gn:population":321,
    "gn:timezone":"America/Panama",
    "iso:country":"PA",
    "name:spa_x_preferred":[
        "San Pedro del Rinc\u00f3n"
    ],
    "name:und_x_variant":[
        "Rinc\u00f3n Sucio"
    ],
    "wof:name":"San Pedro del Rincon",
    "wof:placetype":"locality",
    "wof:population":321
},
  "geometry": {"coordinates":[-81.08584999999999,8.08477],"type":"Point"}
}