{
  "type": "Feature",
  "properties": {
    "gn:admin1_code":"06",
    "gn:asciiname":"Paso Hondo",
    "gn:country_code":"PA",
    "gn:dem":267,
    "gn:feature_class":"P",
    "gn:feature_code":"PPL",
    "gn:name":"Paso Hondo",
    "gn:population":0,
    "gn:timezone":"America/Panama",
    "iso:country":"PA",
    "wof:name":"Paso Hondo",
    "wof:placetype":"locality"
},
  "geometry": {"coordinates":[-80.91667,7.81667],"type":"Point"}
}