{
  "type": "Feature",
  "properties": {
    "gn:admin1_code":"02",
    "gn:asciiname":"Chorcha Abajo",
    "gn:country_code":"PA",
    "gn:dem":35,
    "gn:feature_class":"P",
    "gn:feature_code":"PPL",
    "gn:name":"Chorcha Abajo",
    "gn:population":271,
    "gn:timezone":"America/Panama",
    "iso:country":"PA",
    "name:und_x_variant":[
        "Chorcha",
        "Chorcha Abajo"
    ],
    "wof:name":"Chorcha Abajo",
    "wof:placetype":"locality",
    "wof:population":271
},
  "geometry": {"coordinates":[-82.27893,8.36511],"type":"Point"}
}