{
  "type": "Feature",
  "properties": {
    "gn:admin1_code":"10",
    "gn:asciiname":"La Galera",
    "gn:country_code":"PA",
    "gn:dem":17,
    "gn:feature_class":"P",
    "gn:feature_code":"PPL",
    "gn:name":"La Galera",
    "gn:population":0,
    "gn:timezone":"America/Panama",
    "iso:country":"PA",
    "wof:name":"La Galera",
    "wof:placetype":"locality"
},
  "geometry": {"coordinates":[-81.74389000000002,7.49111],"type":"Point"}
}