{
  "type": "Feature",
  "properties": {
    "gn:admin1_code":"04",
    "gn:asciiname":"Villa Alondra",
    "gn:country_code":"PA",
    "gn:dem":19,
    "gn:feature_class":"P",
    "gn:feature_code":"PPL",
    "gn:name":"Villa Alondra",
    "gn:population":705,
    "gn:timezone":"America/Panama",
    "iso:country":"PA",
    "name:spa_x_preferred":[
        "Villa Alondra"
    ],
    "wof:name":"Villa Alondra",
    "wof:placetype":"locality",
    "wof:population":705
},
  "geometry": {"coordinates":[-79.78159000000002,9.38695],"type":"Point"}
}