{
  "type": "Feature",
  "properties": {
    "gn:admin1_code":"10",
    "gn:asciiname":"El Tigre",
    "gn:cc2":"PA",
    "gn:country_code":"PA",
    "gn:dem":171,
    "gn:feature_class":"P",
    "gn:feature_code":"PPL",
    "gn:name":"El Tigre",
    "gn:population":70,
    "gn:timezone":"America/Panama",
    "iso:country":"PA",
    "name:und_x_variant":[
        "Quebrada El Tigre",
        "El Tigre"
    ],
    "wof:name":"El Tigre",
    "wof:placetype":"locality",
    "wof:population":70
},
  "geometry": {"coordinates":[-81.58738000000002,8.16005],"type":"Point"}
}