{
  "type": "Feature",
  "properties": {
    "gn:admin1_code":"03",
    "gn:asciiname":"La Pita",
    "gn:country_code":"PA",
    "gn:dem":97,
    "gn:feature_class":"P",
    "gn:feature_code":"PPL",
    "gn:name":"La Pita",
    "gn:population":0,
    "gn:timezone":"America/Panama",
    "iso:country":"PA",
    "wof:name":"La Pita",
    "wof:placetype":"locality"
},
  "geometry": {"coordinates":[-80.28333000000001,8.93333],"type":"Point"}
}