{
  "type": "Feature",
  "properties": {
    "gn:admin1_code":"01",
    "gn:asciiname":"El Aji",
    "gn:country_code":"PA",
    "gn:dem":4,
    "gn:feature_class":"P",
    "gn:feature_code":"PPL",
    "gn:name":"El Aj\u00ed",
    "gn:population":0,
    "gn:timezone":"America/Panama",
    "iso:country":"PA",
    "wof:name":"El Aji",
    "wof:placetype":"locality"
},
  "geometry": {"coordinates":[-82.03333000000001,8.91667],"type":"Point"}
}