{
  "type": "Feature",
  "properties": {
    "iso:country":"PA",
    "name:ceb_x_preferred":[
        "Volc\u00e1n"
    ],
    "name:deu_x_preferred":[
        "Volc\u00e1n"
    ],
    "name:eng_x_preferred":[
        "Volc\u00e1n"
    ],
    "name:fra_x_preferred":[
        "Volc\u00e1n"
    ],
    "name:ita_x_preferred":[
        "Volc\u00e1n"
    ],
    "name:kat_x_preferred":[
        "\u10d5\u10dd\u10da\u10d9\u10d0\u10dc\u10d8"
    ],
    "name:pol_x_preferred":[
        "Volc\u00e1n"
    ],
    "name:spa_x_preferred":[
        "Volc\u00e1n"
    ],
    "name:und_x_variant":[
        "El Hato"
    ],
    "name:zho_x_preferred":[
        "\u535a\u723e\u574e"
    ],
    "qs:gn_country":"PA",
    "qs:gn_fcode":"PPL",
    "qs:gn_pop":11245,
    "qs:name":"Volc\u00e1n",
    "qs:name_adm0":"Panam\u00e1",
    "qs:name_adm1":"Chiriqu\u00ed",
    "qs:photos":93,
    "qs:photos_1k":19,
    "qs:photos_9k":1,
    "qs:photos_9r":3,
    "qs:photos_all":93,
    "qs:photos_sr":3,
    "qs:placetype":"Town",
    "qs:pop_sr":"6",
    "qs:woe_adm0":23424924,
    "wd:wordcount":367,
    "wof:name":"Volc\u00e1n",
    "wof:placetype":"locality",
    "wof:population":11245
},
  "geometry": {"coordinates":[-82.63333,8.76667],"type":"Point"}
}