{
  "type": "Feature",
  "properties": {
    "gn:country":"PA",
    "gn:fcode":"PPLX",
    "gn:population":0,
    "iso:country":"PA",
    "name:spa_x_preferred":[
        "Loma Alegre"
    ],
    "qs:gn_adm0_cc":"PA",
    "qs:gn_fcode":"PPLX",
    "qs:gn_local":3703443,
    "qs:gn_namadm1":"08",
    "qs:gn_name":"Loma Alegre",
    "qs:local_max":4729,
    "qs:local_sum":17462,
    "qs:localhoods":20,
    "qs:name":"Loma Alegre",
    "qs:name_adm0":"Panam\u00e1",
    "qs:name_adm1":"Panam\u00e1",
    "qs:name_adm2":"Panam\u00e1",
    "qs:name_lau":"San Francisco",
    "qs:name_local":"Ciudad de Panam\u00e1",
    "qs:photo_max":45,
    "qs:photo_sum":85,
    "qs:placetype":"Suburb",
    "qs:quad_count":6,
    "qs:woe_adm0":23424924,
    "qs:woe_adm1":2346558,
    "qs:woe_adm2":26793125,
    "qs:woe_lau":26793513,
    "qs:woe_local":159386,
    "qs:woe_ver":"7.10.0",
    "qs_pg:aaroncc":"PA",
    "qs_pg:gn_country":"PA",
    "qs_pg:gn_fcode":"PPLX",
    "qs_pg:gn_pop":0,
    "qs_pg:name":"Loma Alegre",
    "qs_pg:name_adm0":"Panam\u00e1",
    "qs_pg:name_adm1":"Panam\u00e1",
    "qs_pg:photos":76,
    "qs_pg:photos_1k":15,
    "qs_pg:photos_9k":1,
    "qs_pg:photos_9r":3,
    "qs_pg:photos_all":76,
    "qs_pg:photos_sr":3,
    "qs_pg:pop_sr":0,
    "qs_pg:qs_pg_placetype":"neighbourhood",
    "qs_pg:qs_pg_placetype_gp":"Suburb",
    "qs_pg:woe_adm0":23424924,
    "wof:lang":[
        "spa"
    ],
    "wof:name":"Loma Alegre",
    "wof:placetype":"neighbourhood"
},
  "geometry": {"coordinates":[-79.50860900000001,8.99546],"type":"Point"}
}