{
  "type": "Feature",
  "properties": {
    "gn:admin1_code":"10",
    "gn:asciiname":"El Rodeo de los Bonilla",
    "gn:cc2":"PA",
    "gn:country_code":"PA",
    "gn:dem":59,
    "gn:feature_class":"P",
    "gn:feature_code":"PPL",
    "gn:name":"El Rodeo de los Bonilla",
    "gn:population":0,
    "gn:timezone":"America/Panama",
    "iso:country":"PA",
    "name:und_x_variant":[
        "El Rodeo de Los Bonillas",
        "El Rodeo de los Bonilla"
    ],
    "wof:name":"El Rodeo de los Bonilla",
    "wof:placetype":"locality"
},
  "geometry": {"coordinates":[-81.09999999999999,8.16667],"type":"Point"}
}