{
  "type": "Feature",
  "properties": {
    "gn:gn_country":"PA",
    "gn:gn_fcode":"PPLX",
    "gn:gn_pop":0,
    "iso:country":"PA",
    "name:spa_x_preferred":[
        "Llano Bonito"
    ],
    "name:unk_x_variant":[
        "Llano Bonito"
    ],
    "qs:gn_adm0_cc":"PA",
    "qs:gn_fcode":"PPLX",
    "qs:gn_local":3712384,
    "qs:gn_namadm1":"06",
    "qs:gn_name":"Llano Bonito",
    "qs:local_max":228,
    "qs:local_sum":228,
    "qs:localhoods":1,
    "qs:name":"Llano Bonito",
    "qs:name_adm0":"Panam\u00e1",
    "qs:name_adm1":"Herrera",
    "qs:name_adm2":"Chitr\u00e9",
    "qs:name_lau":"Chitre",
    "qs:name_local":"Chitr\u00e9",
    "qs:photo_max":50,
    "qs:photo_sum":228,
    "qs:placetype":"Suburb",
    "qs:quad_count":13,
    "qs:woe_adm0":23424924,
    "qs:woe_adm1":2346556,
    "qs:woe_adm2":26793104,
    "qs:woe_lau":26793382,
    "qs:woe_local":155582,
    "qs:woe_ver":"7.10.0",
    "qs_pg:aaroncc":"PA",
    "qs_pg:gn_country":"PA",
    "qs_pg:gn_fcode":"PPLX",
    "qs_pg:gn_pop":0,
    "qs_pg:name":"Llano Bonito",
    "qs_pg:name_adm0":"Panam\u00e1",
    "qs_pg:name_adm1":"Herrera",
    "qs_pg:photos":211,
    "qs_pg:photos_1k":43,
    "qs_pg:photos_9k":1,
    "qs_pg:photos_9r":4,
    "qs_pg:photos_all":211,
    "qs_pg:photos_sr":4,
    "qs_pg:pop_sr":0,
    "qs_pg:qs_pg_placetype":"neighbourhood",
    "qs_pg:qs_pg_placetype_gp":"Suburb",
    "qs_pg:woe_adm0":23424924,
    "wd:wordcount":109,
    "wof:lang":[
        "spa"
    ],
    "wof:name":"Llano Bonito",
    "wof:placetype":"neighbourhood"
},
  "geometry": {"coordinates":[-80.425421,7.971834],"type":"Point"}
}