{
  "type": "Feature",
  "properties": {
    "gn:admin1_code":"10",
    "gn:asciiname":"Bajo de Jeronimo",
    "gn:cc2":"PA",
    "gn:country_code":"PA",
    "gn:dem":378,
    "gn:feature_class":"P",
    "gn:feature_code":"PPL",
    "gn:name":"Bajo de Jer\u00f3nimo",
    "gn:population":17,
    "gn:timezone":"America/Panama",
    "iso:country":"PA",
    "name:und_x_variant":[
        "Bajo de Geronimo",
        "Bajo de Jer\u00f3nimo"
    ],
    "wof:name":"Bajo de Jeronimo",
    "wof:placetype":"locality",
    "wof:population":17
},
  "geometry": {"coordinates":[-81.45194000000002,7.89556],"type":"Point"}
}