{
  "type": "Feature",
  "properties": {
    "iso:country":"PA",
    "name:ara_x_preferred":[
        "\u0648\u0645\u0642\u0627\u0637\u0639\u0629 \u062a\u0634\u064a\u062a\u0631\u064a"
    ],
    "name:deu_x_preferred":[
        "Chitr\u00e9"
    ],
    "name:ell_x_preferred":[
        "\u03a4\u03c3\u03b9\u03c4\u03c1\u03ad"
    ],
    "name:eng_x_preferred":[
        "Chitr\u00e9"
    ],
    "name:fra_x_preferred":[
        "Chitr\u00e9"
    ],
    "name:heb_x_preferred":[
        "\u05e6'\u05d9\u05d8\u05e8\u05d4"
    ],
    "name:hun_x_preferred":[
        "Chitr\u00e9"
    ],
    "name:ita_x_preferred":[
        "Chitr\u00e9"
    ],
    "name:jpn_x_preferred":[
        "\u30c1\u30c8\u30ec"
    ],
    "name:kat_x_preferred":[
        "\u10e9\u10d8\u10e2\u10e0\u10d4"
    ],
    "name:kor_x_preferred":[
        "\uce58\ud2b8\ub808"
    ],
    "name:lad_x_preferred":[
        "Chitr\u00e9"
    ],
    "name:lit_x_preferred":[
        "\u010citr\u0117"
    ],
    "name:nld_x_preferred":[
        "Chitr\u00e9"
    ],
    "name:pol_x_preferred":[
        "Chitr\u00e9"
    ],
    "name:por_x_preferred":[
        "Chitr\u00e9"
    ],
    "name:rus_x_preferred":[
        "\u0427\u0438\u0442\u0440\u0435"
    ],
    "name:spa_x_preferred":[
        "Chitr\u00e9"
    ],
    "name:urd_x_preferred":[
        "\u0686\u06cc\u062a\u0631\u06d2"
    ],
    "name:zho_x_preferred":[
        "\u5947\u7279\u96f7"
    ],
    "qs:gn_pop":0,
    "qs:name":"Chitr\u00e9",
    "qs:name_adm0":"Panam\u00e1",
    "qs:name_adm1":"Herrera",
    "qs:photos":61,
    "qs:photos_1k":12,
    "qs:photos_9k":1,
    "qs:photos_9r":4,
    "qs:photos_all":272,
    "qs:photos_sr":2,
    "qs:placetype":"Town",
    "qs:pop_sr":"0",
    "qs:woe_adm0":23424924,
    "wd:elevation":24.0,
    "wd:wordcount":1305,
    "wof:name":"Chitr\u00e9",
    "wof:placetype":"locality"
},
  "geometry": {"coordinates":[-80.42899300000001,7.961147],"type":"Point"}
}