{
  "type": "Feature",
  "properties": {
    "gn:admin1_code":"10",
    "gn:asciiname":"Bajo del Limon",
    "gn:country_code":"PA",
    "gn:dem":1253,
    "gn:feature_class":"P",
    "gn:feature_code":"PPL",
    "gn:name":"Bajo del Lim\u00f3n",
    "gn:population":0,
    "gn:timezone":"America/Panama",
    "iso:country":"PA",
    "wof:name":"Bajo del Limon",
    "wof:placetype":"locality"
},
  "geometry": {"coordinates":[-80.88333,8.55],"type":"Point"}
}