{
  "type": "Feature",
  "properties": {
    "gn:admin1_code":"07",
    "gn:asciiname":"La Calzada",
    "gn:cc2":"PA",
    "gn:country_code":"PA",
    "gn:dem":28,
    "gn:feature_class":"P",
    "gn:feature_code":"PPL",
    "gn:name":"La Calzada",
    "gn:population":0,
    "gn:timezone":"America/Panama",
    "iso:country":"PA",
    "name:und_x_variant":[
        "Madro\u00f1al",
        "La Calzada"
    ],
    "wof:name":"La Calzada",
    "wof:placetype":"locality"
},
  "geometry": {"coordinates":[-80.31667,7.83333],"type":"Point"}
}