{
  "type": "Feature",
  "properties": {
    "gn:admin1_code":"01",
    "gn:asciiname":"Bocatorito",
    "gn:cc2":"PA",
    "gn:country_code":"PA",
    "gn:dem":0,
    "gn:feature_class":"P",
    "gn:feature_code":"PPL",
    "gn:name":"Bocatorito",
    "gn:population":134,
    "gn:timezone":"America/Panama",
    "iso:country":"PA",
    "name:und_x_variant":[
        "Bacatorito",
        "Bocatorito"
    ],
    "wof:name":"Bocatorito",
    "wof:placetype":"locality",
    "wof:population":134
},
  "geometry": {"coordinates":[-82.26382,9.23732],"type":"Point"}
}