{
  "type": "Feature",
  "properties": {
    "gn:admin1_code":"01",
    "gn:asciiname":"Las Tablas",
    "gn:country_code":"PA",
    "gn:dem":22,
    "gn:feature_class":"P",
    "gn:feature_code":"PPL",
    "gn:name":"Las Tablas",
    "gn:population":0,
    "gn:timezone":"America/Panama",
    "iso:country":"PA",
    "name:spa_x_preferred":[
        "Las Tablas"
    ],
    "wof:name":"Las Tablas",
    "wof:placetype":"locality"
},
  "geometry": {"coordinates":[-82.75033000000001,9.55026],"type":"Point"}
}