{
  "type": "Feature",
  "properties": {
    "gn:admin1_code":"02",
    "gn:asciiname":"La Corocita",
    "gn:country_code":"PA",
    "gn:dem":1,
    "gn:feature_class":"P",
    "gn:feature_code":"PPL",
    "gn:name":"La Corocita",
    "gn:population":0,
    "gn:timezone":"America/Panama",
    "iso:country":"PA",
    "wof:name":"La Corocita",
    "wof:placetype":"locality"
},
  "geometry": {"coordinates":[-81.68333,8.01667],"type":"Point"}
}