{
  "type": "Feature",
  "properties": {
    "iso:country":"PA",
    "name:und_x_variant":[
        "Fort Davis"
    ],
    "qs:gn_country":"PA",
    "qs:gn_fcode":"PPL",
    "qs:gn_pop":0,
    "qs:name":"Fuerte Davis",
    "qs:name_adm0":"Panam\u00e1",
    "qs:name_adm1":"Col\u00f3n",
    "qs:photos":440,
    "qs:photos_1k":89,
    "qs:photos_9k":2,
    "qs:photos_9r":5,
    "qs:photos_all":440,
    "qs:photos_sr":6,
    "qs:placetype":"Town",
    "qs:pop_sr":"0",
    "qs:woe_adm0":23424924,
    "wof:name":"Fuerte Davis",
    "wof:placetype":"locality"
},
  "geometry": {"coordinates":[-79.9075,9.28556],"type":"Point"}
}