{
  "type": "Feature",
  "properties": {
    "gn:admin1_code":"10",
    "gn:asciiname":"Martin Grande",
    "gn:country_code":"PA",
    "gn:dem":48,
    "gn:feature_class":"P",
    "gn:feature_code":"PPL",
    "gn:name":"Mart\u00edn Grande",
    "gn:population":457,
    "gn:timezone":"America/Panama",
    "iso:country":"PA",
    "name:spa_x_preferred":[
        "Mart\u00edn Grande"
    ],
    "wof:name":"Martin Grande",
    "wof:placetype":"locality",
    "wof:population":457
},
  "geometry": {"coordinates":[-81.00676999999997,8.06886],"type":"Point"}
}