{
  "type": "Feature",
  "properties": {
    "gn:admin1_code":"03",
    "gn:asciiname":"El Corozo",
    "gn:cc2":"PA",
    "gn:country_code":"PA",
    "gn:dem":4,
    "gn:feature_class":"P",
    "gn:feature_code":"PPL",
    "gn:name":"El Corozo",
    "gn:population":0,
    "gn:timezone":"America/Panama",
    "iso:country":"PA",
    "name:und_x_variant":[
        "El Coroso",
        "El Corozo"
    ],
    "wof:name":"El Corozo",
    "wof:placetype":"locality"
},
  "geometry": {"coordinates":[-80.46666999999999,8.31667],"type":"Point"}
}