{
  "type": "Feature",
  "properties": {
    "gn:admin1_code":"09",
    "gn:asciiname":"Ustupo Yantupo",
    "gn:cc2":"PA",
    "gn:country_code":"PA",
    "gn:dem":1,
    "gn:feature_class":"P",
    "gn:feature_code":"PPL",
    "gn:name":"Ustupo Yantupo",
    "gn:population":0,
    "gn:timezone":"America/Panama",
    "iso:country":"PA",
    "name:und_x_variant":[
        "Yantupo",
        "Ustupo",
        "Ustupo Yantupo"
    ],
    "wof:name":"Ustupo Yantupo",
    "wof:placetype":"locality"
},
  "geometry": {"coordinates":[-78.56667,9.45],"type":"Point"}
}