{
  "type": "Feature",
  "properties": {
    "gn:admin1_code":"10",
    "gn:asciiname":"El Pajaro",
    "gn:country_code":"PA",
    "gn:dem":57,
    "gn:feature_class":"P",
    "gn:feature_code":"PPLA3",
    "gn:name":"El P\u00e1jaro",
    "gn:population":112,
    "gn:timezone":"America/Panama",
    "iso:country":"PA",
    "name:spa_x_preferred":[
        "El P\u00e1jaro"
    ],
    "wof:name":"El Pajaro",
    "wof:placetype":"locality",
    "wof:population":112
},
  "geometry": {"coordinates":[-81.12154,7.95342],"type":"Point"}
}