{
  "type": "Feature",
  "properties": {
    "gn:admin1_code":"08",
    "gn:asciiname":"Porcada Valdez",
    "gn:cc2":"PA",
    "gn:country_code":"PA",
    "gn:dem":6,
    "gn:feature_class":"P",
    "gn:feature_code":"PPL",
    "gn:name":"Porcada Valdez",
    "gn:population":0,
    "gn:timezone":"America/Panama",
    "iso:country":"PA",
    "name:und_x_variant":[
        "La Porcada",
        "Valdez",
        "Procada Valdez",
        "Porcardo Valdez",
        "Porcada Valdez"
    ],
    "wof:name":"Porcada Valdez",
    "wof:placetype":"locality"
},
  "geometry": {"coordinates":[-79.09999999999999,9.13333],"type":"Point"}
}