{
  "type": "Feature",
  "properties": {
    "gn:admin1_code":"03",
    "gn:asciiname":"El Palmar Abajo",
    "gn:country_code":"PA",
    "gn:dem":195,
    "gn:feature_class":"P",
    "gn:feature_code":"PPL",
    "gn:name":"El Palmar Abajo",
    "gn:population":143,
    "gn:timezone":"America/Panama",
    "iso:country":"PA",
    "name:spa_x_preferred":[
        "El Palmar Abajo"
    ],
    "wof:name":"El Palmar Abajo",
    "wof:placetype":"locality",
    "wof:population":143
},
  "geometry": {"coordinates":[-80.38998000000002,8.66085],"type":"Point"}
}