{
  "type": "Feature",
  "properties": {
    "gn:admin1_code":"07",
    "gn:asciiname":"Los Medios",
    "gn:country_code":"PA",
    "gn:dem":307,
    "gn:feature_class":"P",
    "gn:feature_code":"PPL",
    "gn:name":"Los Medios",
    "gn:population":0,
    "gn:timezone":"America/Panama",
    "iso:country":"PA",
    "wof:name":"Los Medios",
    "wof:placetype":"locality"
},
  "geometry": {"coordinates":[-80.26666999999998,7.51667],"type":"Point"}
}