{
  "type": "Feature",
  "properties": {
    "gn:admin1_code":"07",
    "gn:asciiname":"La Pasera",
    "gn:country_code":"PA",
    "gn:dem":36,
    "gn:feature_class":"P",
    "gn:feature_code":"PPLA3",
    "gn:name":"La Pasera",
    "gn:population":563,
    "gn:timezone":"America/Panama",
    "iso:country":"PA",
    "name:ita_x_preferred":[
        "La Pasera"
    ],
    "name:spa_x_preferred":[
        "La Pasera"
    ],
    "name:und_x_variant":[
        "Llano del Hato",
        "La Pasera"
    ],
    "name:zho_x_preferred":[
        "\u62c9\u5e15\u585e\u62c9"
    ],
    "wof:name":"La Pasera",
    "wof:placetype":"locality",
    "wof:population":563
},
  "geometry": {"coordinates":[-80.30341999999997,7.79757],"type":"Point"}
}