{
  "type": "Feature",
  "properties": {
    "gn:admin1_code":"10",
    "gn:asciiname":"Seria Abajo",
    "gn:country_code":"PA",
    "gn:dem":21,
    "gn:feature_class":"P",
    "gn:feature_code":"PPL",
    "gn:name":"Seria Abajo",
    "gn:population":0,
    "gn:timezone":"America/Panama",
    "iso:country":"PA",
    "wof:name":"Seria Abajo",
    "wof:placetype":"locality"
},
  "geometry": {"coordinates":[-81.27278000000003,7.95889],"type":"Point"}
}