{
  "type": "Feature",
  "properties": {
    "gn:admin1_code":"10",
    "gn:asciiname":"Cerro Bubi",
    "gn:country_code":"PA",
    "gn:dem":527,
    "gn:feature_class":"P",
    "gn:feature_code":"PPL",
    "gn:name":"Cerro Bub\u00ed",
    "gn:population":5,
    "gn:timezone":"America/Panama",
    "iso:country":"PA",
    "wof:name":"Cerro Bubi",
    "wof:placetype":"locality",
    "wof:population":5
},
  "geometry": {"coordinates":[-81.49836999999999,7.92228],"type":"Point"}
}