{
  "type": "Feature",
  "properties": {
    "gn:admin1_code":"08",
    "gn:asciiname":"Rio Chico",
    "gn:cc2":"PA",
    "gn:country_code":"PA",
    "gn:dem":29,
    "gn:feature_class":"P",
    "gn:feature_code":"PPL",
    "gn:name":"R\u00edo Chico",
    "gn:population":0,
    "gn:timezone":"America/Panama",
    "iso:country":"PA",
    "name:und_x_variant":[
        "Chico",
        "R\u00edo Chico"
    ],
    "wof:name":"Rio Chico",
    "wof:placetype":"locality"
},
  "geometry": {"coordinates":[-79.16667,9.03333],"type":"Point"}
}