{
  "type": "Feature",
  "properties": {
    "iso:country":"PA",
    "qs:gn_pop":0,
    "qs:name":"La Laguna",
    "qs:name_adm0":"Panam\u00e1",
    "qs:name_adm1":"Panam\u00e1",
    "qs:photos":187,
    "qs:photos_1k":38,
    "qs:photos_9k":2,
    "qs:photos_9r":5,
    "qs:photos_all":485,
    "qs:photos_sr":4,
    "qs:placetype":"LocalAdmin",
    "qs:pop_sr":"0",
    "qs:woe_adm0":23424924,
    "wof:name":"La Laguna",
    "wof:placetype":"localadmin"
},
  "geometry": {"coordinates":[-80.04924,8.60834],"type":"Point"}
}