{
  "type": "Feature",
  "properties": {
    "gn:admin1_code":"07",
    "gn:asciiname":"Los Macanitos",
    "gn:country_code":"PA",
    "gn:dem":106,
    "gn:feature_class":"P",
    "gn:feature_code":"PPL",
    "gn:name":"Los Macanitos",
    "gn:population":3,
    "gn:timezone":"America/Panama",
    "iso:country":"PA",
    "wof:name":"Los Macanitos",
    "wof:placetype":"locality",
    "wof:population":3
},
  "geometry": {"coordinates":[-80.19904,7.61073],"type":"Point"}
}