{
  "type": "Feature",
  "properties": {
    "gn:admin1_code":"10",
    "gn:asciiname":"Querque Abajo",
    "gn:country_code":"PA",
    "gn:dem":45,
    "gn:feature_class":"P",
    "gn:feature_code":"PPL",
    "gn:name":"Querque Abajo",
    "gn:population":77,
    "gn:timezone":"America/Panama",
    "iso:country":"PA",
    "name:spa_x_preferred":[
        "Querque Abajo"
    ],
    "wof:name":"Querque Abajo",
    "wof:placetype":"locality",
    "wof:population":77
},
  "geometry": {"coordinates":[-81.38457,8.06507],"type":"Point"}
}