{
  "type": "Feature",
  "properties": {
    "gn:admin1_code":"11",
    "gn:asciiname":"Nuevo Santa Rosa",
    "gn:country_code":"PA",
    "gn:dem":36,
    "gn:feature_class":"P",
    "gn:feature_code":"PPL",
    "gn:name":"Nuevo Santa Rosa",
    "gn:population":0,
    "gn:timezone":"America/Panama",
    "iso:country":"PA",
    "name:spa_x_preferred":[
        "Nuevo Santa Rosa"
    ],
    "wof:name":"Nuevo Santa Rosa",
    "wof:placetype":"locality"
},
  "geometry": {"coordinates":[-77.76644,8.56216],"type":"Point"}
}