{
  "type": "Feature",
  "properties": {
    "iso:country":"PA",
    "name:eng_x_preferred":[
        "Puerto Obald\u00eda"
    ],
    "name:ita_x_preferred":[
        "Puerto Obald\u00eda"
    ],
    "name:jpn_x_preferred":[
        "\u30d7\u30a8\u30eb\u30c8\u30fb\u30aa\u30d0\u30eb\u30c7\u30a3\u30a2"
    ],
    "name:nld_x_preferred":[
        "Puerto Obald\u00eda"
    ],
    "name:spa_x_preferred":[
        "Puerto Obald\u00eda"
    ],
    "name:unk_x_variant":[
        "Obaldia"
    ],
    "qs:gn_country":"PA",
    "qs:gn_fcode":"PPL",
    "qs:gn_pop":0,
    "qs:name":"Puerto Obald\u00eda",
    "qs:name_adm0":"Panam\u00e1",
    "qs:name_adm1":"Kuna Yala",
    "qs:photos":9,
    "qs:photos_1k":2,
    "qs:photos_9k":1,
    "qs:photos_9r":1,
    "qs:photos_all":9,
    "qs:photos_sr":1,
    "qs:placetype":"Town",
    "qs:pop_sr":"0",
    "qs:woe_adm0":23424924,
    "wd:wordcount":93,
    "wof:name":"Puerto Obald\u00eda",
    "wof:placetype":"locality"
},
  "geometry": {"coordinates":[-77.41887,8.66435],"type":"Point"}
}