{
  "type": "Feature",
  "properties": {
    "gn:admin1_code":"06",
    "gn:asciiname":"Travesia",
    "gn:country_code":"PA",
    "gn:dem":58,
    "gn:feature_class":"P",
    "gn:feature_code":"PPL",
    "gn:name":"Traves\u00eda",
    "gn:population":0,
    "gn:timezone":"America/Panama",
    "iso:country":"PA",
    "wof:name":"Travesia",
    "wof:placetype":"locality"
},
  "geometry": {"coordinates":[-80.61667,7.85],"type":"Point"}
}