{
  "type": "Feature",
  "properties": {
    "gn:admin1_code":"10",
    "gn:asciiname":"El Cortezo",
    "gn:country_code":"PA",
    "gn:dem":329,
    "gn:feature_class":"P",
    "gn:feature_code":"PPL",
    "gn:name":"El Cortezo",
    "gn:population":0,
    "gn:timezone":"America/Panama",
    "iso:country":"PA",
    "name:ita_x_preferred":[
        "El Cortezo"
    ],
    "name:spa_x_preferred":[
        "El Cortezo"
    ],
    "wof:name":"El Cortezo",
    "wof:placetype":"locality"
},
  "geometry": {"coordinates":[-81.32925999999998,8.37554],"type":"Point"}
}