{
  "type": "Feature",
  "properties": {
    "gn:admin1_code":"07",
    "gn:asciiname":"Quebrada Grande",
    "gn:country_code":"PA",
    "gn:dem":347,
    "gn:feature_class":"P",
    "gn:feature_code":"PPL",
    "gn:name":"Quebrada Grande",
    "gn:population":41,
    "gn:timezone":"America/Panama",
    "iso:country":"PA",
    "wof:name":"Quebrada Grande",
    "wof:placetype":"locality",
    "wof:population":41
},
  "geometry": {"coordinates":[-80.41667,7.61667],"type":"Point"}
}