{
  "type": "Feature",
  "properties": {
    "gn:admin1_code":"02",
    "gn:asciiname":"Chalapa",
    "gn:cc2":"PA",
    "gn:country_code":"PA",
    "gn:dem":-9999,
    "gn:feature_class":"P",
    "gn:feature_code":"PPL",
    "gn:name":"Chalapa",
    "gn:population":0,
    "gn:timezone":"America/Panama",
    "iso:country":"PA",
    "name:und_x_variant":[
        "Las Chalapas",
        "Chalapa"
    ],
    "wof:name":"Chalapa",
    "wof:placetype":"locality"
},
  "geometry": {"coordinates":[-82.31667,8.25],"type":"Point"}
}