{
  "type": "Feature",
  "properties": {
    "gn:admin1_code":"07",
    "gn:asciiname":"Los Toretos",
    "gn:country_code":"PA",
    "gn:dem":365,
    "gn:feature_class":"P",
    "gn:feature_code":"PPL",
    "gn:name":"Los Toretos",
    "gn:population":22,
    "gn:timezone":"America/Panama",
    "iso:country":"PA",
    "wof:name":"Los Toretos",
    "wof:placetype":"locality",
    "wof:population":22
},
  "geometry": {"coordinates":[-80.42744999999999,7.66786],"type":"Point"}
}