{
  "type": "Feature",
  "properties": {
    "gn:admin1_code":"03",
    "gn:asciiname":"Lubre",
    "gn:country_code":"PA",
    "gn:dem":165,
    "gn:feature_class":"P",
    "gn:feature_code":"PPL",
    "gn:name":"Lubr\u00e9",
    "gn:population":0,
    "gn:timezone":"America/Panama",
    "iso:country":"PA",
    "wof:name":"Lubre",
    "wof:placetype":"locality"
},
  "geometry": {"coordinates":[-80.40000000000001,8.78333],"type":"Point"}
}