{
  "type": "Feature",
  "properties": {
    "gn:admin1_code":"06",
    "gn:asciiname":"Correa",
    "gn:country_code":"PA",
    "gn:dem":8,
    "gn:feature_class":"P",
    "gn:feature_code":"PPL",
    "gn:name":"Correa",
    "gn:population":0,
    "gn:timezone":"America/Panama",
    "iso:country":"PA",
    "wof:name":"Correa",
    "wof:placetype":"locality"
},
  "geometry": {"coordinates":[-80.58333,8.08333],"type":"Point"}
}