{
  "type": "Feature",
  "properties": {
    "gn:admin1_code":"06",
    "gn:asciiname":"Correa",
    "gn:country_code":"PA",
    "gn:dem":8,
    "gn:feature_class":"P",
    "gn:feature_code":"PPL",
    "gn:name":"Correa",
    "gn:population":0,
    "gn:timezone":"America/Panama",
    "iso:country":"PA",
    "name:ceb_x_preferred":[
        "Correa"
    ],
    "name:deu_x_preferred":[
        "Correa"
    ],
    "name:fra_x_preferred":[
        "Correa"
    ],
    "name:heb_x_preferred":[
        "\u05e7\u05d5\u05e8\u05d0\u05d4"
    ],
    "name:ita_x_preferred":[
        "Correa"
    ],
    "name:jpn_x_preferred":[
        "\u30b3\u30ec\u30a2"
    ],
    "name:nld_x_preferred":[
        "Correa"
    ],
    "name:por_x_preferred":[
        "Correa"
    ],
    "name:rus_x_preferred":[
        "\u041a\u043e\u0440\u0440\u0435\u0430"
    ],
    "name:spa_x_preferred":[
        "Correa"
    ],
    "name:swe_x_preferred":[
        "Correa"
    ],
    "name:ukr_x_preferred":[
        "\u041a\u043e\u0440\u0440\u0435\u044f"
    ],
    "wof:name":"Correa",
    "wof:placetype":"locality"
},
  "geometry": {"coordinates":[-80.58333,8.08333],"type":"Point"}
}