{
  "type": "Feature",
  "properties": {
    "gn:admin1_code":"08",
    "gn:asciiname":"Nueva Esperanza",
    "gn:country_code":"PA",
    "gn:dem":24,
    "gn:feature_class":"P",
    "gn:feature_code":"PPL",
    "gn:name":"Nueva Esperanza",
    "gn:population":9342,
    "gn:timezone":"America/Panama",
    "iso:country":"PA",
    "name:spa_x_preferred":[
        "Nueva Esperanza"
    ],
    "wof:name":"Nueva Esperanza",
    "wof:placetype":"locality",
    "wof:population":9342
},
  "geometry": {"coordinates":[-79.33414,9.1021],"type":"Point"}
}