{
  "type": "Feature",
  "properties": {
    "gn:admin1_code":"06",
    "gn:asciiname":"Las Cabras",
    "gn:country_code":"PA",
    "gn:dem":53,
    "gn:feature_class":"P",
    "gn:feature_code":"PPLA3",
    "gn:name":"Las Cabras",
    "gn:population":0,
    "gn:timezone":"America/Panama",
    "iso:country":"PA",
    "name:spa_x_preferred":[
        "Las Cabras"
    ],
    "wof:name":"Las Cabras",
    "wof:placetype":"locality"
},
  "geometry": {"coordinates":[-80.54912,7.87561],"type":"Point"}
}