{
  "type": "Feature",
  "properties": {
    "gn:admin1_code":"07",
    "gn:asciiname":"La Mesa",
    "gn:country_code":"PA",
    "gn:dem":171,
    "gn:feature_class":"P",
    "gn:feature_code":"PPLA3",
    "gn:name":"La Mesa",
    "gn:population":392,
    "gn:timezone":"America/Panama",
    "iso:country":"PA",
    "name:spa_x_preferred":[
        "La Mesa"
    ],
    "wof:name":"La Mesa",
    "wof:placetype":"locality",
    "wof:population":392
},
  "geometry": {"coordinates":[-80.61794,7.6567],"type":"Point"}
}