{
  "type": "Feature",
  "properties": {
    "gn:admin1_code":"06",
    "gn:asciiname":"Canazosa",
    "gn:country_code":"PA",
    "gn:dem":48,
    "gn:feature_class":"P",
    "gn:feature_code":"PPL",
    "gn:name":"Ca\u00f1azosa",
    "gn:population":0,
    "gn:timezone":"America/Panama",
    "iso:country":"PA",
    "wof:name":"Canazosa",
    "wof:placetype":"locality"
},
  "geometry": {"coordinates":[-80.93333,7.88333],"type":"Point"}
}