{
  "type": "Feature",
  "properties": {
    "gn:admin1_code":"03",
    "gn:asciiname":"La Chorrerita Numero Dos",
    "gn:cc2":"PA",
    "gn:country_code":"PA",
    "gn:dem":298,
    "gn:feature_class":"P",
    "gn:feature_code":"PPL",
    "gn:name":"La Chorrerita N\u00famero Dos",
    "gn:population":0,
    "gn:timezone":"America/Panama",
    "iso:country":"PA",
    "name:und_x_variant":[
        "Chorrerita N\u00famero Dos",
        "La Chorrerita N\u00famero Dos"
    ],
    "wof:name":"La Chorrerita Numero Dos",
    "wof:placetype":"locality"
},
  "geometry": {"coordinates":[-80.21666999999999,8.56667],"type":"Point"}
}