{
  "type": "Feature",
  "properties": {
    "gn:admin1_code":"07",
    "gn:asciiname":"El Tabano",
    "gn:country_code":"PA",
    "gn:dem":244,
    "gn:feature_class":"P",
    "gn:feature_code":"PPL",
    "gn:name":"El T\u00e1bano",
    "gn:population":24,
    "gn:timezone":"America/Panama",
    "iso:country":"PA",
    "wof:name":"El Tabano",
    "wof:placetype":"locality",
    "wof:population":24
},
  "geometry": {"coordinates":[-80.18333,7.56667],"type":"Point"}
}