{
  "type": "Feature",
  "properties": {
    "gn:admin1_code":"10",
    "gn:asciiname":"Ojo de Agua",
    "gn:country_code":"PA",
    "gn:dem":310,
    "gn:feature_class":"P",
    "gn:feature_code":"PPL",
    "gn:name":"Ojo de Agua",
    "gn:population":0,
    "gn:timezone":"America/Panama",
    "iso:country":"PA",
    "name:spa_x_preferred":[
        "Ojo de Agua"
    ],
    "wof:name":"Ojo de Agua",
    "wof:placetype":"locality"
},
  "geometry": {"coordinates":[-81.51817,8.19568],"type":"Point"}
}