{
  "type": "Feature",
  "properties": {
    "gn:admin1_code":"10",
    "gn:asciiname":"Potrerillos",
    "gn:cc2":"PA",
    "gn:country_code":"PA",
    "gn:dem":303,
    "gn:feature_class":"P",
    "gn:feature_code":"PPL",
    "gn:name":"Potrerillos",
    "gn:population":0,
    "gn:timezone":"America/Panama",
    "iso:country":"PA",
    "name:ceb_x_preferred":[
        "Potrerillos"
    ],
    "name:deu_x_preferred":[
        "Potrerillos"
    ],
    "name:fra_x_preferred":[
        "Potrerillos"
    ],
    "name:ita_x_preferred":[
        "Potrerillos"
    ],
    "name:nld_x_preferred":[
        "Potrerillos"
    ],
    "name:pol_x_preferred":[
        "Potrerillos"
    ],
    "name:por_x_preferred":[
        "Potrerillos"
    ],
    "name:spa_x_preferred":[
        "Potrerillos"
    ],
    "name:swe_x_preferred":[
        "Potrerillos"
    ],
    "name:und_x_variant":[
        "El Potrerillo",
        "Potrerillos"
    ],
    "wof:name":"Potrerillos",
    "wof:placetype":"locality"
},
  "geometry": {"coordinates":[-80.93333,8.33333],"type":"Point"}
}