{
  "type": "Feature",
  "properties": {
    "gn:admin1_code":"12",
    "gn:asciiname":"Playa Raya",
    "gn:country_code":"PA",
    "gn:dem":33,
    "gn:feature_class":"P",
    "gn:feature_code":"PPL",
    "gn:name":"Playa Raya",
    "gn:population":0,
    "gn:timezone":"America/Panama",
    "iso:country":"PA",
    "wof:name":"Playa Raya",
    "wof:placetype":"locality"
},
  "geometry": {"coordinates":[-81.93333,9.13333],"type":"Point"}
}