{
  "type": "Feature",
  "properties": {
    "gn:admin1_code":"08",
    "gn:asciiname":"Bonete",
    "gn:country_code":"PA",
    "gn:dem":32,
    "gn:feature_class":"P",
    "gn:feature_code":"PPL",
    "gn:name":"Bonete",
    "gn:population":0,
    "gn:timezone":"America/Panama",
    "iso:country":"PA",
    "name:ara_x_preferred":[
        "\u0628\u0648\u0646\u064a\u062a\u064a"
    ],
    "name:arg_x_preferred":[
        "Bonet"
    ],
    "name:cat_x_preferred":[
        "Bonete"
    ],
    "name:ceb_x_preferred":[
        "Bonete"
    ],
    "name:eus_x_preferred":[
        "Bonete"
    ],
    "name:fas_x_preferred":[
        "\u0628\u0646\u062a\u0647"
    ],
    "name:fra_x_preferred":[
        "Bonete"
    ],
    "name:hun_x_preferred":[
        "Bonete"
    ],
    "name:ina_x_preferred":[
        "Bonete"
    ],
    "name:ita_x_preferred":[
        "Bonete"
    ],
    "name:msa_x_preferred":[
        "Bonete"
    ],
    "name:nld_x_preferred":[
        "Bonete"
    ],
    "name:oci_x_preferred":[
        "Bonete"
    ],
    "name:pam_x_preferred":[
        "Bonete"
    ],
    "name:pol_x_preferred":[
        "Bonete"
    ],
    "name:por_x_preferred":[
        "Bonete"
    ],
    "name:ron_x_preferred":[
        "Bonete"
    ],
    "name:rus_x_preferred":[
        "\u0411\u043e\u043d\u0435\u0442\u0435"
    ],
    "name:scn_x_preferred":[
        "Scazzetta"
    ],
    "name:spa_x_preferred":[
        "Bonete"
    ],
    "name:swe_x_preferred":[
        "Bonete"
    ],
    "name:ukr_x_preferred":[
        "\u0411\u043e\u043d\u0435\u0442\u0435"
    ],
    "name:vie_x_preferred":[
        "Bonete"
    ],
    "name:war_x_preferred":[
        "Bonete"
    ],
    "name:zho_x_preferred":[
        "\u535a\u5185\u7279"
    ],
    "wof:name":"Bonete",
    "wof:placetype":"locality"
},
  "geometry": {"coordinates":[-79.08766,9.19463],"type":"Point"}
}