{
  "type": "Feature",
  "properties": {
    "gn:admin1_code":"08",
    "gn:asciiname":"Bonete",
    "gn:country_code":"PA",
    "gn:dem":32,
    "gn:feature_class":"P",
    "gn:feature_code":"PPL",
    "gn:name":"Bonete",
    "gn:population":0,
    "gn:timezone":"America/Panama",
    "iso:country":"PA",
    "wof:name":"Bonete",
    "wof:placetype":"locality"
},
  "geometry": {"coordinates":[-79.08766,9.19463],"type":"Point"}
}