{
  "type": "Feature",
  "properties": {
    "gn:admin1_code":"03",
    "gn:asciiname":"Las Quebradas",
    "gn:cc2":"PA",
    "gn:country_code":"PA",
    "gn:dem":120,
    "gn:feature_class":"P",
    "gn:feature_code":"PPL",
    "gn:name":"Las Quebradas",
    "gn:population":0,
    "gn:timezone":"America/Panama",
    "iso:country":"PA",
    "name:und_x_variant":[
        "Las Quebradas de Uracillo",
        "Las Quebradas"
    ],
    "wof:name":"Las Quebradas",
    "wof:placetype":"locality"
},
  "geometry": {"coordinates":[-80.20555999999998,8.94889],"type":"Point"}
}