{
  "type": "Feature",
  "properties": {
    "gn:admin1_code":"03",
    "gn:asciiname":"Buena Vista",
    "gn:country_code":"PA",
    "gn:dem":213,
    "gn:feature_class":"P",
    "gn:feature_code":"PPL",
    "gn:name":"Buena Vista",
    "gn:population":0,
    "gn:timezone":"America/Panama",
    "iso:country":"PA",
    "wof:name":"Buena Vista",
    "wof:placetype":"locality"
},
  "geometry": {"coordinates":[-80.66667,8.41667],"type":"Point"}
}