{
  "type": "Feature",
  "properties": {
    "gn:admin1_code":"05",
    "gn:asciiname":"Aguadilla",
    "gn:country_code":"PA",
    "gn:dem":27,
    "gn:feature_class":"P",
    "gn:feature_code":"PPL",
    "gn:name":"Aguadilla",
    "gn:population":0,
    "gn:timezone":"America/Panama",
    "iso:country":"PA",
    "wof:name":"Aguadilla",
    "wof:placetype":"locality"
},
  "geometry": {"coordinates":[-78.11100999999999,8.45117],"type":"Point"}
}