{
  "type": "Feature",
  "properties": {
    "gn:admin1_code":"04",
    "gn:asciiname":"Quebrada Grande",
    "gn:country_code":"PA",
    "gn:dem":132,
    "gn:feature_class":"P",
    "gn:feature_code":"PPL",
    "gn:name":"Quebrada Grande",
    "gn:population":282,
    "gn:timezone":"America/Panama",
    "iso:country":"PA",
    "name:spa_x_preferred":[
        "Quebrada Grande"
    ],
    "wof:name":"Quebrada Grande",
    "wof:placetype":"locality",
    "wof:population":282
},
  "geometry": {"coordinates":[-79.73226,9.28219],"type":"Point"}
}