{
  "type": "Feature",
  "properties": {
    "gn:admin1_code":"02",
    "gn:asciiname":"El Comun",
    "gn:country_code":"PA",
    "gn:dem":397,
    "gn:feature_class":"P",
    "gn:feature_code":"PPL",
    "gn:name":"El Com\u00fan",
    "gn:population":215,
    "gn:timezone":"America/Panama",
    "iso:country":"PA",
    "name:und_x_variant":[
        "Com\u00fan",
        "El Com\u00fan"
    ],
    "wof:name":"El Comun",
    "wof:placetype":"locality",
    "wof:population":215
},
  "geometry": {"coordinates":[-81.68259,8.20474],"type":"Point"}
}