{
  "type": "Feature",
  "properties": {
    "gn:admin1_code":"02",
    "gn:asciiname":"El Macano",
    "gn:country_code":"PA",
    "gn:dem":293,
    "gn:feature_class":"P",
    "gn:feature_code":"PPL",
    "gn:name":"El Macano",
    "gn:population":0,
    "gn:timezone":"America/Panama",
    "iso:country":"PA",
    "name:ita_x_preferred":[
        "El Macano"
    ],
    "name:por_x_preferred":[
        "El Macano"
    ],
    "name:spa_x_preferred":[
        "El Macano"
    ],
    "name:und_x_variant":[
        "Macano",
        "Macano Arriba"
    ],
    "name:zho_x_preferred":[
        "\u57c3\u723e\u99ac\u5361\u8afe"
    ],
    "wof:name":"El Macano",
    "wof:placetype":"locality"
},
  "geometry": {"coordinates":[-82.38609,8.60461],"type":"Point"}
}