{
  "type": "Feature",
  "properties": {
    "gn:admin1_code":"05",
    "gn:asciiname":"Bajo Lepe",
    "gn:country_code":"PA",
    "gn:dem":94,
    "gn:feature_class":"P",
    "gn:feature_code":"PPL",
    "gn:name":"Bajo Lepe",
    "gn:population":0,
    "gn:timezone":"America/Panama",
    "iso:country":"PA",
    "name:spa_x_preferred":[
        "Bajo Lepe"
    ],
    "wof:name":"Bajo Lepe",
    "wof:placetype":"locality"
},
  "geometry": {"coordinates":[-77.61509000000002,7.95751],"type":"Point"}
}