{
  "type": "Feature",
  "properties": {
    "gn:admin1_code":"02",
    "gn:asciiname":"Finca Zapote",
    "gn:country_code":"PA",
    "gn:dem":18,
    "gn:feature_class":"P",
    "gn:feature_code":"PPL",
    "gn:name":"Finca Zapote",
    "gn:population":148,
    "gn:timezone":"America/Panama",
    "iso:country":"PA",
    "name:spa_x_preferred":[
        "Finca Zapote"
    ],
    "wof:name":"Finca Zapote",
    "wof:placetype":"locality",
    "wof:population":148
},
  "geometry": {"coordinates":[-82.84818,8.37716],"type":"Point"}
}