{
  "type": "Feature",
  "properties": {
    "gn:admin1_code":"01",
    "gn:asciiname":"Corriente Grande",
    "gn:country_code":"PA",
    "gn:dem":214,
    "gn:feature_class":"P",
    "gn:feature_code":"PPL",
    "gn:name":"Corriente Grande",
    "gn:population":0,
    "gn:timezone":"America/Panama",
    "iso:country":"PA",
    "wof:name":"Corriente Grande",
    "wof:placetype":"locality"
},
  "geometry": {"coordinates":[-82.86667,9.51667],"type":"Point"}
}