{
  "type": "Feature",
  "properties": {
    "gn:admin1_code":"06",
    "gn:asciiname":"El Nuco",
    "gn:country_code":"PA",
    "gn:dem":619,
    "gn:feature_class":"P",
    "gn:feature_code":"PPL",
    "gn:name":"El \u00d1uco",
    "gn:population":18,
    "gn:timezone":"America/Panama",
    "iso:country":"PA",
    "wof:name":"El Nuco",
    "wof:placetype":"locality",
    "wof:population":18
},
  "geometry": {"coordinates":[-80.80589000000001,7.75716],"type":"Point"}
}