{
  "type": "Feature",
  "properties": {
    "gn:admin1_code":"06",
    "gn:asciiname":"El Nuquito",
    "gn:country_code":"PA",
    "gn:dem":480,
    "gn:feature_class":"P",
    "gn:feature_code":"PPL",
    "gn:name":"El \u00d1uquito",
    "gn:population":0,
    "gn:timezone":"America/Panama",
    "iso:country":"PA",
    "wof:name":"El Nuquito",
    "wof:placetype":"locality"
},
  "geometry": {"coordinates":[-80.76666999999998,7.75],"type":"Point"}
}