{
  "type": "Feature",
  "properties": {
    "gn:admin1_code":"07",
    "gn:asciiname":"Sabana Grande Abajo",
    "gn:country_code":"PA",
    "gn:dem":29,
    "gn:feature_class":"P",
    "gn:feature_code":"PPL",
    "gn:name":"Sabana Grande Abajo",
    "gn:population":255,
    "gn:timezone":"America/Panama",
    "iso:country":"PA",
    "name:spa_x_preferred":[
        "Sabana Grande Abajo"
    ],
    "wof:name":"Sabana Grande Abajo",
    "wof:placetype":"locality",
    "wof:population":255
},
  "geometry": {"coordinates":[-80.34999999999999,7.85],"type":"Point"}
}