{
  "type": "Feature",
  "properties": {
    "gn:admin1_code":"01",
    "gn:admin2_code":"102.0",
    "gn:asciiname":"Finca Cuarenta y Uno",
    "gn:cc2":"PA",
    "gn:country_code":"PA",
    "gn:dem":5,
    "gn:feature_class":"P",
    "gn:feature_code":"PPL",
    "gn:name":"Finca Cuarenta y Uno",
    "gn:population":0,
    "gn:timezone":"America/Panama",
    "iso:country":"PA",
    "name:und_x_variant":[
        "Finca 41",
        "Finca Cuarenta y Uno"
    ],
    "wof:name":"Finca Cuarenta y Uno",
    "wof:placetype":"locality"
},
  "geometry": {"coordinates":[-82.51864999999999,9.46375],"type":"Point"}
}