{
  "type": "Feature",
  "properties": {
    "gn:admin1_code":"03",
    "gn:asciiname":"Boca de Chiguiri",
    "gn:country_code":"PA",
    "gn:dem":135,
    "gn:feature_class":"P",
    "gn:feature_code":"PPL",
    "gn:name":"Boca de Chiguir\u00ed",
    "gn:population":113,
    "gn:timezone":"America/Panama",
    "iso:country":"PA",
    "name:spa_x_preferred":[
        "Boca de Chiguir\u00ed"
    ],
    "wof:name":"Boca de Chiguiri",
    "wof:placetype":"locality",
    "wof:population":113
},
  "geometry": {"coordinates":[-80.29079,8.71426],"type":"Point"}
}