{
  "type": "Feature",
  "properties": {
    "gn:admin1_code":"03",
    "gn:asciiname":"Las Trancas",
    "gn:country_code":"PA",
    "gn:dem":126,
    "gn:feature_class":"P",
    "gn:feature_code":"PPL",
    "gn:name":"Las Trancas",
    "gn:population":248,
    "gn:timezone":"America/Panama",
    "iso:country":"PA",
    "name:spa_x_preferred":[
        "Las Trancas"
    ],
    "wof:name":"Las Trancas",
    "wof:placetype":"locality",
    "wof:population":248
},
  "geometry": {"coordinates":[-80.0865,8.4603],"type":"Point"}
}