{
  "type": "Feature",
  "properties": {
    "gn:admin1_code":"03",
    "gn:asciiname":"Orari",
    "gn:country_code":"PA",
    "gn:dem":230,
    "gn:feature_class":"P",
    "gn:feature_code":"PPL",
    "gn:name":"Orari",
    "gn:population":120,
    "gn:timezone":"America/Panama",
    "iso:country":"PA",
    "name:ara_x_preferred":[
        "\u0623\u0648\u0631\u0627\u0631\u064a"
    ],
    "name:ben_x_preferred":[
        "\u0993\u09b0\u09be\u09b0\u09bf"
    ],
    "name:deu_x_preferred":[
        "Orari River"
    ],
    "name:ell_x_preferred":[
        "\u039f\u03c1\u03ac\u03c1\u03b9"
    ],
    "name:fas_x_preferred":[
        "\u0627\u0648\u0631\u0627\u0631\u06cc"
    ],
    "name:heb_x_preferred":[
        "\u05d0\u05d5\u05e8\u05d0\u05e8\u05d9"
    ],
    "name:hin_x_preferred":[
        "\u0913\u0930\u093e\u0930\u0940"
    ],
    "name:hun_x_preferred":[
        "Orari"
    ],
    "name:ind_x_preferred":[
        "Orari"
    ],
    "name:ita_x_preferred":[
        "Orari"
    ],
    "name:jpn_x_preferred":[
        "\u30aa\u30e9\u30ea\u5ddd"
    ],
    "name:kor_x_preferred":[
        "\uc624\ub77c\ub9ac"
    ],
    "name:nld_x_preferred":[
        "Orari"
    ],
    "name:pol_x_preferred":[
        "Orari"
    ],
    "name:por_x_preferred":[
        "Orari"
    ],
    "name:rus_x_preferred":[
        "\u0440\u0435\u043a\u0430 \u041e\u0440\u0430\u0440\u0438"
    ],
    "name:spa_x_preferred":[
        "Orari"
    ],
    "name:swe_x_preferred":[
        "Orari River"
    ],
    "name:tur_x_preferred":[
        "Orari"
    ],
    "name:ukr_x_preferred":[
        "\u041e\u0440\u0430\u0440\u0456"
    ],
    "name:urd_x_preferred":[
        "\u0627\u0648\u0631\u0627\u0631\u06cc"
    ],
    "name:vie_x_preferred":[
        "S\u00f4ng Orari"
    ],
    "name:zho_cn_x_preferred":[
        "\u5965\u62c9\u91cc\u6cb3"
    ],
    "name:zho_tw_x_preferred":[
        "\u5967\u62c9\u91cc\u6cb3"
    ],
    "wof:name":"Orari",
    "wof:placetype":"locality",
    "wof:population":120
},
  "geometry": {"coordinates":[-80.48066,8.61116],"type":"Point"}
}