{
  "type": "Feature",
  "properties": {
    "gn:admin1_code":"03",
    "gn:asciiname":"Orari",
    "gn:country_code":"PA",
    "gn:dem":230,
    "gn:feature_class":"P",
    "gn:feature_code":"PPL",
    "gn:name":"Orari",
    "gn:population":120,
    "gn:timezone":"America/Panama",
    "iso:country":"PA",
    "name:spa_x_preferred":[
        "Orari"
    ],
    "wof:name":"Orari",
    "wof:placetype":"locality",
    "wof:population":120
},
  "geometry": {"coordinates":[-80.48066,8.61116],"type":"Point"}
}