{
  "type": "Feature",
  "properties": {
    "gn:admin1_code":"10",
    "gn:asciiname":"El Restingue",
    "gn:country_code":"PA",
    "gn:dem":36,
    "gn:feature_class":"P",
    "gn:feature_code":"PPL",
    "gn:name":"El Restingue",
    "gn:population":0,
    "gn:timezone":"America/Panama",
    "iso:country":"PA",
    "wof:name":"El Restingue",
    "wof:placetype":"locality"
},
  "geometry": {"coordinates":[-81.14166999999998,7.89694],"type":"Point"}
}