{
  "type": "Feature",
  "properties": {
    "gn:admin1_code":"10",
    "gn:asciiname":"La Meseta",
    "gn:country_code":"PA",
    "gn:dem":451,
    "gn:feature_class":"P",
    "gn:feature_code":"PPL",
    "gn:name":"La Meseta",
    "gn:population":6,
    "gn:timezone":"America/Panama",
    "iso:country":"PA",
    "wof:name":"La Meseta",
    "wof:placetype":"locality",
    "wof:population":6
},
  "geometry": {"coordinates":[-81.51349999999999,8.0794],"type":"Point"}
}