{
  "type": "Feature",
  "properties": {
    "gn:admin1_code":"05",
    "gn:asciiname":"La Moneda",
    "gn:country_code":"PA",
    "gn:dem":69,
    "gn:feature_class":"P",
    "gn:feature_code":"PPL",
    "gn:name":"La Moneda",
    "gn:population":0,
    "gn:timezone":"America/Panama",
    "iso:country":"PA",
    "name:spa_x_preferred":[
        "La Moneda"
    ],
    "wof:name":"La Moneda",
    "wof:placetype":"locality"
},
  "geometry": {"coordinates":[-78.03704,8.57466],"type":"Point"}
}