{
  "type": "Feature",
  "properties": {
    "gn:admin1_code":"07",
    "gn:asciiname":"Quebrada El Cercado",
    "gn:country_code":"PA",
    "gn:dem":66,
    "gn:feature_class":"P",
    "gn:feature_code":"PPL",
    "gn:name":"Quebrada El Cercado",
    "gn:population":0,
    "gn:timezone":"America/Panama",
    "iso:country":"PA",
    "wof:name":"Quebrada El Cercado",
    "wof:placetype":"locality"
},
  "geometry": {"coordinates":[-80.13333,7.63333],"type":"Point"}
}