{
  "type": "Feature",
  "properties": {
    "gn:admin1_code":"12",
    "gn:asciiname":"Cerro Mosquito",
    "gn:country_code":"PA",
    "gn:dem":430,
    "gn:feature_class":"P",
    "gn:feature_code":"PPL",
    "gn:name":"Cerro Mosquito",
    "gn:population":579,
    "gn:timezone":"America/Panama",
    "iso:country":"PA",
    "name:spa_x_preferred":[
        "Cerro Mosquito"
    ],
    "wof:name":"Cerro Mosquito",
    "wof:placetype":"locality",
    "wof:population":579
},
  "geometry": {"coordinates":[-81.68926,8.34777],"type":"Point"}
}