{
  "type": "Feature",
  "properties": {
    "gn:admin1_code":"10",
    "gn:asciiname":"El Guineo",
    "gn:country_code":"PA",
    "gn:dem":24,
    "gn:feature_class":"P",
    "gn:feature_code":"PPL",
    "gn:name":"El Guineo",
    "gn:population":3,
    "gn:timezone":"America/Panama",
    "iso:country":"PA",
    "wof:name":"El Guineo",
    "wof:placetype":"locality",
    "wof:population":3
},
  "geometry": {"coordinates":[-81.30139,7.75583],"type":"Point"}
}