{
  "type": "Feature",
  "properties": {
    "gn:admin1_code":"05",
    "gn:asciiname":"El Real",
    "gn:country_code":"PA",
    "gn:dem":14,
    "gn:feature_class":"P",
    "gn:feature_code":"PPLL",
    "gn:name":"El Real",
    "gn:population":0,
    "gn:timezone":"America/Panama",
    "iso:country":"PA",
    "wof:name":"El Real",
    "wof:placetype":"locality"
},
  "geometry": {"coordinates":[-77.73441,8.1171],"type":"Point"}
}