{
  "type": "Feature",
  "properties": {
    "gn:admin1_code":"13",
    "gn:asciiname":"Nueva Arenosa",
    "gn:country_code":"PA",
    "gn:dem":126,
    "gn:feature_class":"P",
    "gn:feature_code":"PPLA3",
    "gn:name":"Nueva Arenosa",
    "gn:population":283,
    "gn:timezone":"America/Panama",
    "iso:country":"PA",
    "name:spa_x_preferred":[
        "Nueva Arenosa"
    ],
    "wof:name":"Nueva Arenosa",
    "wof:placetype":"locality",
    "wof:population":283
},
  "geometry": {"coordinates":[-79.99472,8.86944],"type":"Point"}
}