{
  "type": "Feature",
  "properties": {
    "gn:admin1_code":"03",
    "gn:asciiname":"Maranon",
    "gn:country_code":"PA",
    "gn:dem":164,
    "gn:feature_class":"P",
    "gn:feature_code":"PPL",
    "gn:name":"Mara\u00f1\u00f3n",
    "gn:population":7,
    "gn:timezone":"America/Panama",
    "iso:country":"PA",
    "wof:name":"Maranon",
    "wof:placetype":"locality",
    "wof:population":7
},
  "geometry": {"coordinates":[-80.64676999999998,8.46356],"type":"Point"}
}