{
  "type": "Feature",
  "properties": {
    "gn:admin1_code":"13",
    "gn:asciiname":"Los Negros",
    "gn:country_code":"PA",
    "gn:dem":255,
    "gn:feature_class":"P",
    "gn:feature_code":"PPL",
    "gn:name":"Los Negros",
    "gn:population":0,
    "gn:timezone":"America/Panama",
    "iso:country":"PA",
    "name:ita_x_preferred":[
        "Los Negros"
    ],
    "name:jpn_x_preferred":[
        "\u30ed\u30b9\u30fb\u30cd\u30b0\u30ed\u30b9"
    ],
    "name:rus_x_preferred":[
        "\u041b\u043e\u0441-\u041d\u0435\u0433\u0440\u043e\u0441"
    ],
    "name:spa_x_preferred":[
        "Los Negros"
    ],
    "wof:name":"Los Negros",
    "wof:placetype":"locality"
},
  "geometry": {"coordinates":[-80.03333000000001,8.83333],"type":"Point"}
}