{
  "type": "Feature",
  "properties": {
    "gn:admin1_code":"13",
    "gn:asciiname":"Los Canones",
    "gn:country_code":"PA",
    "gn:dem":180,
    "gn:feature_class":"P",
    "gn:feature_code":"PPL",
    "gn:name":"Los Ca\u00f1ones",
    "gn:population":263,
    "gn:timezone":"America/Panama",
    "iso:country":"PA",
    "name:spa_x_preferred":[
        "Los Ca\u00f1ones"
    ],
    "wof:name":"Los Canones",
    "wof:placetype":"locality",
    "wof:population":263
},
  "geometry": {"coordinates":[-80.04343,8.93526],"type":"Point"}
}