{
  "type": "Feature",
  "properties": {
    "gn:admin1_code":"07",
    "gn:asciiname":"Pena Blanca",
    "gn:country_code":"PA",
    "gn:dem":87,
    "gn:feature_class":"P",
    "gn:feature_code":"PPLA3",
    "gn:name":"Pe\u00f1a Blanca",
    "gn:population":804,
    "gn:timezone":"America/Panama",
    "iso:country":"PA",
    "name:ita_x_preferred":[
        "Pe\u00f1a Blanca"
    ],
    "name:spa_x_preferred":[
        "Pe\u00f1a Blanca"
    ],
    "name:zho_x_preferred":[
        "\u4f69\u5c3c\u4e9a\u5e03\u5170\u5361"
    ],
    "wof:name":"Pena Blanca",
    "wof:placetype":"locality",
    "wof:population":804
},
  "geometry": {"coordinates":[-80.28366,7.71931],"type":"Point"}
}