{
  "type": "Feature",
  "properties": {
    "gn:admin1_code":"12",
    "gn:asciiname":"Cerro Pifa",
    "gn:country_code":"PA",
    "gn:dem":245,
    "gn:feature_class":"P",
    "gn:feature_code":"PPL",
    "gn:name":"Cerro Pif\u00e1",
    "gn:population":205,
    "gn:timezone":"America/Panama",
    "iso:country":"PA",
    "name:spa_x_preferred":[
        "Cerro Pif\u00e1"
    ],
    "wof:name":"Cerro Pifa",
    "wof:placetype":"locality",
    "wof:population":205
},
  "geometry": {"coordinates":[-81.65222,8.31353],"type":"Point"}
}