{
  "type": "Feature",
  "properties": {
    "iso:country":"PA",
    "qs:gn_pop":0,
    "qs:name":"Alto Pineda",
    "qs:name_adm0":"Panam\u00e1",
    "qs:name_adm1":"Chiriqu\u00ed",
    "qs:photos":337,
    "qs:photos_1k":68,
    "qs:photos_9k":1,
    "qs:photos_9r":5,
    "qs:photos_all":337,
    "qs:photos_sr":5,
    "qs:placetype":"Town",
    "qs:pop_sr":"0",
    "qs:woe_adm0":23424924,
    "wof:name":"Alto Pineda",
    "wof:placetype":"locality"
},
  "geometry": {"coordinates":[-82.54300000000001,8.807385],"type":"Point"}
}