{
  "type": "Feature",
  "properties": {
    "gn:admin1_code":"01",
    "gn:asciiname":"El Tapao",
    "gn:country_code":"PA",
    "gn:dem":35,
    "gn:feature_class":"P",
    "gn:feature_code":"PPL",
    "gn:name":"El Tapao",
    "gn:population":0,
    "gn:timezone":"America/Panama",
    "iso:country":"PA",
    "wof:name":"El Tapao",
    "wof:placetype":"locality"
},
  "geometry": {"coordinates":[-82.27345,9.09881],"type":"Point"}
}