{
  "type": "Feature",
  "properties": {
    "gn:admin1_code":"13",
    "gn:asciiname":"Quebrada Grande",
    "gn:country_code":"PA",
    "gn:dem":42,
    "gn:feature_class":"P",
    "gn:feature_code":"PPL",
    "gn:name":"Quebrada Grande",
    "gn:population":163,
    "gn:timezone":"America/Panama",
    "iso:country":"PA",
    "name:spa_x_preferred":[
        "Quebrada Grande"
    ],
    "wof:name":"Quebrada Grande",
    "wof:placetype":"locality",
    "wof:population":163
},
  "geometry": {"coordinates":[-79.8103,8.7558],"type":"Point"}
}