{
  "type": "Feature",
  "properties": {
    "gn:admin1_code":"02",
    "gn:asciiname":"Cerro Gordo",
    "gn:country_code":"PA",
    "gn:dem":1223,
    "gn:feature_class":"P",
    "gn:feature_code":"PPL",
    "gn:name":"Cerro Gordo",
    "gn:population":0,
    "gn:timezone":"America/Panama",
    "iso:country":"PA",
    "wof:name":"Cerro Gordo",
    "wof:placetype":"locality"
},
  "geometry": {"coordinates":[-82.66667,8.73333],"type":"Point"}
}