{
  "type": "Feature",
  "properties": {
    "gn:admin1_code":"08",
    "gn:asciiname":"Los Algarrobos",
    "gn:country_code":"PA",
    "gn:dem":161,
    "gn:feature_class":"P",
    "gn:feature_code":"PPL",
    "gn:name":"Los Algarrobos",
    "gn:population":0,
    "gn:timezone":"America/Panama",
    "iso:country":"PA",
    "wof:name":"Los Algarrobos",
    "wof:placetype":"locality"
},
  "geometry": {"coordinates":[-79.51666999999998,9.05],"type":"Point"}
}