{
  "type": "Feature",
  "properties": {
    "gn:admin1_code":"07",
    "gn:asciiname":"Quebrada Grande",
    "gn:country_code":"PA",
    "gn:dem":176,
    "gn:feature_class":"P",
    "gn:feature_code":"PPL",
    "gn:name":"Quebrada Grande",
    "gn:population":0,
    "gn:timezone":"America/Panama",
    "iso:country":"PA",
    "wof:name":"Quebrada Grande",
    "wof:placetype":"locality"
},
  "geometry": {"coordinates":[-80.43333,7.71667],"type":"Point"}
}