{
  "type": "Feature",
  "properties": {
    "gn:admin1_code":"13",
    "gn:asciiname":"Vacamonte",
    "gn:country_code":"PA",
    "gn:dem":33,
    "gn:feature_class":"P",
    "gn:feature_code":"PPL",
    "gn:name":"Vacamonte",
    "gn:population":0,
    "gn:timezone":"America/Panama",
    "iso:country":"PA",
    "name:fra_x_preferred":[
        "Vacamonte"
    ],
    "name:nld_x_preferred":[
        "Vacamonte"
    ],
    "wof:name":"Vacamonte",
    "wof:placetype":"locality"
},
  "geometry": {"coordinates":[-79.66667,8.86667],"type":"Point"}
}