{
  "type": "Feature",
  "properties": {
    "gn:admin1_code":"10",
    "gn:asciiname":"La Iguana",
    "gn:country_code":"PA",
    "gn:dem":123,
    "gn:feature_class":"P",
    "gn:feature_code":"PPL",
    "gn:name":"La Iguana",
    "gn:population":171,
    "gn:timezone":"America/Panama",
    "iso:country":"PA",
    "name:spa_x_preferred":[
        "La Iguana"
    ],
    "wof:name":"La Iguana",
    "wof:placetype":"locality",
    "wof:population":171
},
  "geometry": {"coordinates":[-81.03443,8.10916],"type":"Point"}
}