{
  "type": "Feature",
  "properties": {
    "gn:admin1_code":"10",
    "gn:asciiname":"El Limon",
    "gn:country_code":"PA",
    "gn:dem":80,
    "gn:feature_class":"P",
    "gn:feature_code":"PPL",
    "gn:name":"El Lim\u00f3n",
    "gn:population":0,
    "gn:timezone":"America/Panama",
    "iso:country":"PA",
    "wof:name":"El Limon",
    "wof:placetype":"locality"
},
  "geometry": {"coordinates":[-81.26666999999998,8.28333],"type":"Point"}
}