{
  "type": "Feature",
  "properties": {
    "gn:admin1_code":"10",
    "gn:asciiname":"El Peru",
    "gn:country_code":"PA",
    "gn:dem":75,
    "gn:feature_class":"P",
    "gn:feature_code":"PPL",
    "gn:name":"El Per\u00fa",
    "gn:population":103,
    "gn:timezone":"America/Panama",
    "iso:country":"PA",
    "name:spa_x_preferred":[
        "El Per\u00fa"
    ],
    "wof:name":"El Peru",
    "wof:placetype":"locality",
    "wof:population":103
},
  "geometry": {"coordinates":[-81.24078,8.20089],"type":"Point"}
}