{
  "type": "Feature",
  "properties": {
    "gn:admin1_code":"03",
    "gn:asciiname":"La Mula",
    "gn:cc2":"PA",
    "gn:country_code":"PA",
    "gn:dem":284,
    "gn:feature_class":"P",
    "gn:feature_code":"PPL",
    "gn:name":"La Mula",
    "gn:population":0,
    "gn:timezone":"America/Panama",
    "iso:country":"PA",
    "name:und_x_variant":[
        "Mula",
        "Las Mulas",
        "La Mula"
    ],
    "wof:name":"La Mula",
    "wof:placetype":"locality"
},
  "geometry": {"coordinates":[-80.46666999999999,8.66667],"type":"Point"}
}