{
  "type": "Feature",
  "properties": {
    "gn:admin1_code":"10",
    "gn:asciiname":"Barnizal",
    "gn:country_code":"PA",
    "gn:dem":367,
    "gn:feature_class":"P",
    "gn:feature_code":"PPLA3",
    "gn:name":"Barnizal",
    "gn:population":74,
    "gn:timezone":"America/Panama",
    "iso:country":"PA",
    "name:spa_x_preferred":[
        "Barnizal"
    ],
    "wof:name":"Barnizal",
    "wof:placetype":"locality",
    "wof:population":74
},
  "geometry": {"coordinates":[-80.77764999999999,8.4046],"type":"Point"}
}