{
  "type": "Feature",
  "properties": {
    "gn:admin1_code":"10",
    "gn:asciiname":"El Macho",
    "gn:country_code":"PA",
    "gn:dem":199,
    "gn:feature_class":"P",
    "gn:feature_code":"PPL",
    "gn:name":"El Macho",
    "gn:population":0,
    "gn:timezone":"America/Panama",
    "iso:country":"PA",
    "name:deu_x_preferred":[
        "El Macho"
    ],
    "name:ita_x_preferred":[
        "El macho"
    ],
    "wof:name":"El Macho",
    "wof:placetype":"locality"
},
  "geometry": {"coordinates":[-81.47694,7.99833],"type":"Point"}
}