{
  "type": "Feature",
  "properties": {
    "gn:admin1_code":"10",
    "gn:asciiname":"Los Diaz",
    "gn:country_code":"PA",
    "gn:dem":48,
    "gn:feature_class":"P",
    "gn:feature_code":"PPL",
    "gn:name":"Los D\u00edaz",
    "gn:population":210,
    "gn:timezone":"America/Panama",
    "iso:country":"PA",
    "name:und_x_variant":[
        "Los Diaz de R\u00edo de Jes\u00fas",
        "Los D\u00edaz"
    ],
    "wof:name":"Los Diaz",
    "wof:placetype":"locality",
    "wof:population":210
},
  "geometry": {"coordinates":[-81.17008,7.97318],"type":"Point"}
}