{
  "type": "Feature",
  "properties": {
    "gn:admin1_code":"10",
    "gn:asciiname":"El Piro",
    "gn:country_code":"PA",
    "gn:dem":143,
    "gn:feature_class":"P",
    "gn:feature_code":"PPL",
    "gn:name":"El Piro",
    "gn:population":27,
    "gn:timezone":"America/Panama",
    "iso:country":"PA",
    "wof:name":"El Piro",
    "wof:placetype":"locality",
    "wof:population":27
},
  "geometry": {"coordinates":[-81.17064999999999,8.23846],"type":"Point"}
}