{
  "type": "Feature",
  "properties": {
    "gn:admin1_code":"08",
    "gn:asciiname":"La Ocho",
    "gn:country_code":"PA",
    "gn:dem":101,
    "gn:feature_class":"P",
    "gn:feature_code":"PPL",
    "gn:name":"La Ocho",
    "gn:population":84,
    "gn:timezone":"America/Panama",
    "iso:country":"PA",
    "name:spa_x_preferred":[
        "La Ocho"
    ],
    "wof:name":"La Ocho",
    "wof:placetype":"locality",
    "wof:population":84
},
  "geometry": {"coordinates":[-78.20125,8.91711],"type":"Point"}
}