{
  "type": "Feature",
  "properties": {
    "gn:admin1_code":"13",
    "gn:asciiname":"Vargas",
    "gn:country_code":"PA",
    "gn:dem":109,
    "gn:feature_class":"P",
    "gn:feature_code":"PPL",
    "gn:name":"Vargas",
    "gn:population":9,
    "gn:timezone":"America/Panama",
    "iso:country":"PA",
    "wof:name":"Vargas",
    "wof:placetype":"locality",
    "wof:population":9
},
  "geometry": {"coordinates":[-79.94521,8.5696],"type":"Point"}
}