{
  "type": "Feature",
  "properties": {
    "gn:admin1_code":"06",
    "gn:asciiname":"El Banco",
    "gn:country_code":"PA",
    "gn:dem":85,
    "gn:feature_class":"P",
    "gn:feature_code":"PPL",
    "gn:name":"El Banco",
    "gn:population":95,
    "gn:timezone":"America/Panama",
    "iso:country":"PA",
    "name:spa_x_preferred":[
        "El Banco"
    ],
    "wof:name":"El Banco",
    "wof:placetype":"locality",
    "wof:population":95
},
  "geometry": {"coordinates":[-80.61898000000002,7.83234],"type":"Point"}
}