{
  "type": "Feature",
  "properties": {
    "gn:admin1_code":"10",
    "gn:asciiname":"El Gavilan",
    "gn:country_code":"PA",
    "gn:dem":438,
    "gn:feature_class":"P",
    "gn:feature_code":"PPL",
    "gn:name":"El Gavil\u00e1n",
    "gn:population":119,
    "gn:timezone":"America/Panama",
    "iso:country":"PA",
    "name:spa_x_preferred":[
        "El Gavil\u00e1n"
    ],
    "name:und_x_variant":[
        "El Gavill\u00e1n",
        "Gavil\u00e1n"
    ],
    "wof:name":"El Gavilan",
    "wof:placetype":"locality",
    "wof:population":119
},
  "geometry": {"coordinates":[-81.47357,8.36826],"type":"Point"}
}