{
  "type": "Feature",
  "properties": {
    "gn:admin1_code":"10",
    "gn:asciiname":"La Chichicosa",
    "gn:country_code":"PA",
    "gn:dem":23,
    "gn:feature_class":"P",
    "gn:feature_code":"PPL",
    "gn:name":"La Chichicosa",
    "gn:population":0,
    "gn:timezone":"America/Panama",
    "iso:country":"PA",
    "wof:name":"La Chichicosa",
    "wof:placetype":"locality"
},
  "geometry": {"coordinates":[-81.47667,7.77194],"type":"Point"}
}