{
  "type": "Feature",
  "properties": {
    "gn:admin1_code":"12",
    "gn:asciiname":"El Salitre",
    "gn:country_code":"PA",
    "gn:dem":120,
    "gn:feature_class":"P",
    "gn:feature_code":"PPL",
    "gn:name":"El Salitre",
    "gn:population":126,
    "gn:timezone":"America/Panama",
    "iso:country":"PA",
    "name:spa_x_preferred":[
        "El Salitre"
    ],
    "wof:name":"El Salitre",
    "wof:placetype":"locality",
    "wof:population":126
},
  "geometry": {"coordinates":[-81.72126999999998,8.27061],"type":"Point"}
}