{
  "type": "Feature",
  "properties": {
    "gn:admin1_code":"07",
    "gn:asciiname":"La Gallinaza",
    "gn:country_code":"PA",
    "gn:dem":64,
    "gn:feature_class":"P",
    "gn:feature_code":"PPL",
    "gn:name":"La Gallinaza",
    "gn:population":0,
    "gn:timezone":"America/Panama",
    "iso:country":"PA",
    "wof:name":"La Gallinaza",
    "wof:placetype":"locality"
},
  "geometry": {"coordinates":[-80.28333000000001,7.73333],"type":"Point"}
}