{
  "type": "Feature",
  "properties": {
    "gn:admin1_code":"02",
    "gn:asciiname":"Tambor",
    "gn:country_code":"PA",
    "gn:dem":179,
    "gn:feature_class":"P",
    "gn:feature_code":"PPL",
    "gn:name":"Tambor",
    "gn:population":0,
    "gn:timezone":"America/Panama",
    "iso:country":"PA",
    "name:spa_x_preferred":[
        "Tambor"
    ],
    "name:und_x_variant":[
        "Tambo"
    ],
    "wof:name":"Tambor",
    "wof:placetype":"locality"
},
  "geometry": {"coordinates":[-81.59506,8.31758],"type":"Point"}
}