{
  "type": "Feature",
  "properties": {
    "iso:country":"PA",
    "name:ceb_x_preferred":[
        "El Espino"
    ],
    "name:deu_x_preferred":[
        "El Espino"
    ],
    "name:ita_x_preferred":[
        "El Espino"
    ],
    "name:srp_x_preferred":[
        "\u0415\u043b \u0415\u0441\u043f\u0438\u043d\u043e"
    ],
    "name:swe_x_preferred":[
        "El Espino"
    ],
    "qs:gn_pop":0,
    "qs:name":"El Espino",
    "qs:name_adm0":"Panam\u00e1",
    "qs:name_adm1":"Panam\u00e1",
    "qs:photos":42,
    "qs:photos_1k":9,
    "qs:photos_9k":1,
    "qs:photos_9r":2,
    "qs:photos_all":42,
    "qs:photos_sr":2,
    "qs:placetype":"LocalAdmin",
    "qs:pop_sr":"0",
    "qs:woe_adm0":23424924,
    "wof:name":"El Espino",
    "wof:placetype":"localadmin"
},
  "geometry": {"coordinates":[-80.03336,8.515755],"type":"Point"}
}