{
  "type": "Feature",
  "properties": {
    "gn:admin1_code":"10",
    "gn:asciiname":"El Bongo",
    "gn:country_code":"PA",
    "gn:dem":263,
    "gn:feature_class":"P",
    "gn:feature_code":"PPL",
    "gn:name":"El Bongo",
    "gn:population":0,
    "gn:timezone":"America/Panama",
    "iso:country":"PA",
    "name:ita_x_preferred":[
        "El Bongo"
    ],
    "name:spa_x_preferred":[
        "El Bongo"
    ],
    "name:zho_x_preferred":[
        "\u57c3\u5c14\u90a6\u6208"
    ],
    "wof:name":"El Bongo",
    "wof:placetype":"locality"
},
  "geometry": {"coordinates":[-81.38333,8.31667],"type":"Point"}
}