{
  "type": "Feature",
  "properties": {
    "gn:admin1_code":"12",
    "gn:asciiname":"Cerro Dios",
    "gn:country_code":"PA",
    "gn:dem":886,
    "gn:feature_class":"P",
    "gn:feature_code":"PPL",
    "gn:name":"Cerro Dios",
    "gn:population":0,
    "gn:timezone":"America/Panama",
    "iso:country":"PA",
    "name:spa_x_preferred":[
        "Cerro Dios"
    ],
    "wof:name":"Cerro Dios",
    "wof:placetype":"locality"
},
  "geometry": {"coordinates":[-81.76052,8.40131],"type":"Point"}
}