{
  "type": "Feature",
  "properties": {
    "gn:admin1_code":"10",
    "gn:asciiname":"El Cervante",
    "gn:cc2":"PA",
    "gn:country_code":"PA",
    "gn:dem":108,
    "gn:feature_class":"P",
    "gn:feature_code":"PPL",
    "gn:name":"El Cervante",
    "gn:population":0,
    "gn:timezone":"America/Panama",
    "iso:country":"PA",
    "name:und_x_variant":[
        "Cervante",
        "El Quemado",
        "Cervantes",
        "El Cervante"
    ],
    "wof:name":"El Cervante",
    "wof:placetype":"locality"
},
  "geometry": {"coordinates":[-80.76666999999998,8.26667],"type":"Point"}
}