{
  "type": "Feature",
  "properties": {
    "gn:admin1_code":"05",
    "gn:asciiname":"Cocalito",
    "gn:country_code":"PA",
    "gn:dem":279,
    "gn:feature_class":"P",
    "gn:feature_code":"PPL",
    "gn:name":"Cocalito",
    "gn:population":0,
    "gn:timezone":"America/Panama",
    "iso:country":"PA",
    "name:und_x_variant":[
        "Cocalita",
        "Cocalito"
    ],
    "wof:name":"Cocalito",
    "wof:placetype":"locality"
},
  "geometry": {"coordinates":[-77.98430999999999,7.31719],"type":"Point"}
}