{
  "type": "Feature",
  "properties": {
    "gn:admin1_code":"10",
    "gn:asciiname":"Pina",
    "gn:country_code":"PA",
    "gn:dem":84,
    "gn:feature_class":"P",
    "gn:feature_code":"PPL",
    "gn:name":"Pi\u00f1a",
    "gn:population":47,
    "gn:timezone":"America/Panama",
    "iso:country":"PA",
    "name:arg_x_preferred":[
        "Pina"
    ],
    "name:bre_x_preferred":[
        "Pina"
    ],
    "name:cat_x_preferred":[
        "Pina"
    ],
    "name:ceb_x_preferred":[
        "Pina"
    ],
    "name:ces_x_preferred":[
        "Pina"
    ],
    "name:deu_x_preferred":[
        "Pina"
    ],
    "name:fas_x_preferred":[
        "\u067e\u06cc\u0646\u0627"
    ],
    "name:fra_x_preferred":[
        "Pina"
    ],
    "name:hun_x_preferred":[
        "Pina"
    ],
    "name:pol_x_preferred":[
        "Pina"
    ],
    "name:por_x_preferred":[
        "Pina"
    ],
    "name:spa_x_preferred":[
        "Pina"
    ],
    "name:swe_x_preferred":[
        "Pina"
    ],
    "wof:name":"Pina",
    "wof:placetype":"locality",
    "wof:population":47
},
  "geometry": {"coordinates":[-80.71666999999999,8.28333],"type":"Point"}
}