{
  "type": "Feature",
  "properties": {
    "gn:admin1_code":"02",
    "gn:asciiname":"San Isidro",
    "gn:country_code":"PA",
    "gn:dem":126,
    "gn:feature_class":"P",
    "gn:feature_code":"PPL",
    "gn:name":"San Isidro",
    "gn:population":1648,
    "gn:timezone":"America/Panama",
    "iso:country":"PA",
    "name:aze_x_preferred":[
        "San-\u0130sidro"
    ],
    "name:cat_x_preferred":[
        "San Isidro"
    ],
    "name:ceb_x_preferred":[
        "San Isidro"
    ],
    "name:deu_x_preferred":[
        "San Isidro"
    ],
    "name:eus_x_preferred":[
        "San Isidro"
    ],
    "name:fra_x_preferred":[
        "San Isidro"
    ],
    "name:ilo_x_preferred":[
        "San Isidro"
    ],
    "name:ita_x_preferred":[
        "San Isidro"
    ],
    "name:lit_x_preferred":[
        "San Isidras"
    ],
    "name:mlg_x_preferred":[
        "San Isidro"
    ],
    "name:nds_x_preferred":[
        "San Isidro"
    ],
    "name:nld_x_preferred":[
        "San Isidro"
    ],
    "name:pol_x_preferred":[
        "San Isidro"
    ],
    "name:por_x_preferred":[
        "San Isidro"
    ],
    "name:rus_x_preferred":[
        "\u0421\u0430\u043d-\u0418\u0441\u0438\u0434\u0440\u043e"
    ],
    "name:sco_x_preferred":[
        "San Isidro"
    ],
    "name:spa_x_preferred":[
        "San Isidro"
    ],
    "name:srp_x_preferred":[
        "\u0421\u0430\u043d \u0418\u0441\u0438\u0434\u0440\u043e"
    ],
    "name:swe_x_preferred":[
        "San Isidro"
    ],
    "name:und_x_variant":[
        "San Sidro",
        "Capacho"
    ],
    "name:vie_x_preferred":[
        "San Isidro"
    ],
    "name:war_x_preferred":[
        "San Isidro"
    ],
    "wof:name":"San Isidro",
    "wof:placetype":"locality",
    "wof:population":1648
},
  "geometry": {"coordinates":[-82.8272,8.53032],"type":"Point"}
}