{
  "type": "Feature",
  "properties": {
    "gn:admin1_code":"08",
    "gn:asciiname":"Los Guayabitos",
    "gn:cc2":"PA",
    "gn:country_code":"PA",
    "gn:dem":16,
    "gn:feature_class":"P",
    "gn:feature_code":"PPL",
    "gn:name":"Los Guayabitos",
    "gn:population":0,
    "gn:timezone":"America/Panama",
    "iso:country":"PA",
    "name:und_x_variant":[
        "Guayabito",
        "Los Guayabitos"
    ],
    "wof:name":"Los Guayabitos",
    "wof:placetype":"locality"
},
  "geometry": {"coordinates":[-79.43333,9.05],"type":"Point"}
}