{
  "type": "Feature",
  "properties": {
    "gn:admin1_code":"03",
    "gn:asciiname":"Las Marias",
    "gn:country_code":"PA",
    "gn:dem":172,
    "gn:feature_class":"P",
    "gn:feature_code":"PPLA3",
    "gn:name":"Las Marias",
    "gn:population":71,
    "gn:timezone":"America/Panama",
    "iso:country":"PA",
    "name:spa_x_preferred":[
        "Las Marias"
    ],
    "wof:name":"Las Marias",
    "wof:placetype":"locality",
    "wof:population":71
},
  "geometry": {"coordinates":[-80.21893,8.88809],"type":"Point"}
}