{
  "type": "Feature",
  "properties": {
    "gn:admin1_code":"02",
    "gn:asciiname":"Ule",
    "gn:country_code":"PA",
    "gn:dem":307,
    "gn:feature_class":"P",
    "gn:feature_code":"PPL",
    "gn:name":"Ul\u00e9",
    "gn:population":65,
    "gn:timezone":"America/Panama",
    "iso:country":"PA",
    "name:slv_x_preferred":[
        "Ule"
    ],
    "name:spa_x_preferred":[
        "Ul\u00e9"
    ],
    "wof:name":"Ule",
    "wof:placetype":"locality",
    "wof:population":65
},
  "geometry": {"coordinates":[-81.60720000000001,8.19291],"type":"Point"}
}