{
  "type": "Feature",
  "properties": {
    "gn:admin1_code":"10",
    "gn:asciiname":"Rincon Largo",
    "gn:country_code":"PA",
    "gn:dem":105,
    "gn:feature_class":"P",
    "gn:feature_code":"PPL",
    "gn:name":"Rinc\u00f3n Largo",
    "gn:population":4,
    "gn:timezone":"America/Panama",
    "iso:country":"PA",
    "wof:name":"Rincon Largo",
    "wof:placetype":"locality",
    "wof:population":4
},
  "geometry": {"coordinates":[-81.16667,8.13333],"type":"Point"}
}