{
  "type": "Feature",
  "properties": {
    "gn:admin1_code":"13",
    "gn:asciiname":"Maria Vicenta",
    "gn:country_code":"PA",
    "gn:dem":74,
    "gn:feature_class":"P",
    "gn:feature_code":"PPL",
    "gn:name":"Mar\u00eda Vicenta",
    "gn:population":351,
    "gn:timezone":"America/Panama",
    "iso:country":"PA",
    "name:spa_x_preferred":[
        "Mar\u00eda Vicenta"
    ],
    "wof:name":"Maria Vicenta",
    "wof:placetype":"locality",
    "wof:population":351
},
  "geometry": {"coordinates":[-80.05118,8.44764],"type":"Point"}
}