{
  "type": "Feature",
  "properties": {
    "gn:admin1_code":"12",
    "gn:asciiname":"Alto Meregilda",
    "gn:country_code":"PA",
    "gn:dem":390,
    "gn:feature_class":"P",
    "gn:feature_code":"PPL",
    "gn:name":"Alto Meregilda",
    "gn:population":243,
    "gn:timezone":"America/Panama",
    "iso:country":"PA",
    "name:spa_x_preferred":[
        "Alto Meregilda"
    ],
    "wof:name":"Alto Meregilda",
    "wof:placetype":"locality",
    "wof:population":243
},
  "geometry": {"coordinates":[-81.63694,8.29977],"type":"Point"}
}