{
  "type": "Feature",
  "properties": {
    "gn:admin1_code":"03",
    "gn:asciiname":"Bijagual",
    "gn:country_code":"PA",
    "gn:dem":24,
    "gn:feature_class":"P",
    "gn:feature_code":"PPL",
    "gn:name":"Bijagual",
    "gn:population":865,
    "gn:timezone":"America/Panama",
    "iso:country":"PA",
    "name:ita_x_preferred":[
        "Bijagual"
    ],
    "name:spa_x_preferred":[
        "Bijagual"
    ],
    "wof:name":"Bijagual",
    "wof:placetype":"locality",
    "wof:population":865
},
  "geometry": {"coordinates":[-80.25497,8.37057],"type":"Point"}
}