{
  "type": "Feature",
  "properties": {
    "gn:admin1_code":"02",
    "gn:asciiname":"Cerro Guabal",
    "gn:country_code":"PA",
    "gn:dem":891,
    "gn:feature_class":"P",
    "gn:feature_code":"PPL",
    "gn:name":"Cerro Guabal",
    "gn:population":0,
    "gn:timezone":"America/Panama",
    "iso:country":"PA",
    "wof:name":"Cerro Guabal",
    "wof:placetype":"locality"
},
  "geometry": {"coordinates":[-82.26666999999998,8.65],"type":"Point"}
}