{
  "type": "Feature",
  "properties": {
    "gn:admin1_code":"03",
    "gn:asciiname":"Perecabecito",
    "gn:country_code":"PA",
    "gn:dem":316,
    "gn:feature_class":"P",
    "gn:feature_code":"PPL",
    "gn:name":"Perecabecito",
    "gn:population":0,
    "gn:timezone":"America/Panama",
    "iso:country":"PA",
    "name:spa_x_preferred":[
        "Perecabecito"
    ],
    "wof:name":"Perecabecito",
    "wof:placetype":"locality"
},
  "geometry": {"coordinates":[-80.36814,8.64969],"type":"Point"}
}