{
  "type": "Feature",
  "properties": {
    "gn:admin1_code":"10",
    "gn:asciiname":"El Peru",
    "gn:country_code":"PA",
    "gn:dem":222,
    "gn:feature_class":"P",
    "gn:feature_code":"PPL",
    "gn:name":"El Per\u00fa",
    "gn:population":227,
    "gn:timezone":"America/Panama",
    "iso:country":"PA",
    "name:und_x_variant":[
        "Per\u00fa",
        "El Per\u00fa"
    ],
    "wof:name":"El Peru",
    "wof:placetype":"locality",
    "wof:population":227
},
  "geometry": {"coordinates":[-81.4278,8.32302],"type":"Point"}
}