{
  "type": "Feature",
  "properties": {
    "iso:country":"PA",
    "name:ceb_x_preferred":[
        "Monte Lirio"
    ],
    "name:ita_x_preferred":[
        "Monte Lirio"
    ],
    "name:kat_x_preferred":[
        "\u10db\u10dd\u10dc\u10e2\u10d4-\u10da\u10d8\u10e0\u10d8\u10dd"
    ],
    "name:spa_x_preferred":[
        "Monte Lirio"
    ],
    "name:zho_x_preferred":[
        "\u8499\u7279\u5229\u91cc\u5965"
    ],
    "qs:gn_pop":0,
    "qs:name":"Monte Lirio",
    "qs:name_adm0":"Panam\u00e1",
    "qs:name_adm1":"Chiriqu\u00ed",
    "qs:photos":187,
    "qs:photos_1k":38,
    "qs:photos_9k":1,
    "qs:photos_9r":4,
    "qs:photos_all":202,
    "qs:photos_sr":4,
    "qs:placetype":"LocalAdmin",
    "qs:pop_sr":"0",
    "qs:woe_adm0":23424924,
    "wof:name":"Monte Lirio",
    "wof:placetype":"localadmin"
},
  "geometry": {"coordinates":[-82.74353000000001,8.845508],"type":"Point"}
}