{
  "type": "Feature",
  "properties": {
    "gn:admin1_code":"10",
    "gn:asciiname":"Las Balillas",
    "gn:country_code":"PA",
    "gn:dem":68,
    "gn:feature_class":"P",
    "gn:feature_code":"PPL",
    "gn:name":"Las Balillas",
    "gn:population":18,
    "gn:timezone":"America/Panama",
    "iso:country":"PA",
    "wof:name":"Las Balillas",
    "wof:placetype":"locality",
    "wof:population":18
},
  "geometry": {"coordinates":[-80.84999999999999,8.23333],"type":"Point"}
}