{
  "type": "Feature",
  "properties": {
    "gn:admin1_code":"01",
    "gn:asciiname":"Quebrada Garay",
    "gn:country_code":"PA",
    "gn:dem":18,
    "gn:feature_class":"P",
    "gn:feature_code":"PPL",
    "gn:name":"Quebrada Garay",
    "gn:population":12,
    "gn:timezone":"America/Panama",
    "iso:country":"PA",
    "wof:name":"Quebrada Garay",
    "wof:placetype":"locality",
    "wof:population":12
},
  "geometry": {"coordinates":[-82.34466999999999,9.19874],"type":"Point"}
}