{
  "type": "Feature",
  "properties": {
    "gn:admin1_code":"10",
    "gn:asciiname":"El Quirri",
    "gn:cc2":"PA",
    "gn:country_code":"PA",
    "gn:dem":160,
    "gn:feature_class":"P",
    "gn:feature_code":"PPL",
    "gn:name":"El Quirr\u00ed",
    "gn:population":0,
    "gn:timezone":"America/Panama",
    "iso:country":"PA",
    "name:und_x_variant":[
        "El Quirre",
        "El Quirr\u00ed"
    ],
    "wof:name":"El Quirri",
    "wof:placetype":"locality"
},
  "geometry": {"coordinates":[-80.95,7.95],"type":"Point"}
}