{
  "type": "Feature",
  "properties": {
    "gn:admin1_code":"12",
    "gn:asciiname":"Oriente",
    "gn:country_code":"PA",
    "gn:dem":119,
    "gn:feature_class":"P",
    "gn:feature_code":"PPL",
    "gn:name":"Oriente",
    "gn:population":0,
    "gn:timezone":"America/Panama",
    "iso:country":"PA",
    "name:spa_x_preferred":[
        "Oriente"
    ],
    "wof:name":"Oriente",
    "wof:placetype":"locality"
},
  "geometry": {"coordinates":[-82.22033,8.88609],"type":"Point"}
}