{
  "type": "Feature",
  "properties": {
    "gn:admin1_code":"13",
    "gn:asciiname":"Filipina",
    "gn:country_code":"PA",
    "gn:dem":649,
    "gn:feature_class":"P",
    "gn:feature_code":"PPL",
    "gn:name":"Filipina",
    "gn:population":0,
    "gn:timezone":"America/Panama",
    "iso:country":"PA",
    "wof:name":"Filipina",
    "wof:placetype":"locality"
},
  "geometry": {"coordinates":[-80.03333000000001,8.65],"type":"Point"}
}