{
  "type": "Feature",
  "properties": {
    "gn:admin1_code":"10",
    "gn:asciiname":"La Macha",
    "gn:country_code":"PA",
    "gn:dem":20,
    "gn:feature_class":"P",
    "gn:feature_code":"PPL",
    "gn:name":"La Macha",
    "gn:population":0,
    "gn:timezone":"America/Panama",
    "iso:country":"PA",
    "wof:name":"La Macha",
    "wof:placetype":"locality"
},
  "geometry": {"coordinates":[-81.59999999999999,7.98333],"type":"Point"}
}