{
  "type": "Feature",
  "properties": {
    "gn:admin1_code":"08",
    "gn:asciiname":"Nuevo Guarumal",
    "gn:country_code":"PA",
    "gn:dem":150,
    "gn:feature_class":"P",
    "gn:feature_code":"PPL",
    "gn:name":"Nuevo Guarumal",
    "gn:population":0,
    "gn:timezone":"America/Panama",
    "iso:country":"PA",
    "name:spa_x_preferred":[
        "Nuevo Guarumal"
    ],
    "wof:name":"Nuevo Guarumal",
    "wof:placetype":"locality"
},
  "geometry": {"coordinates":[-79.53191,9.16725],"type":"Point"}
}