{
  "type": "Feature",
  "properties": {
    "gn:admin1_code":"04",
    "gn:asciiname":"Calle Larga",
    "gn:country_code":"PA",
    "gn:dem":102,
    "gn:feature_class":"P",
    "gn:feature_code":"PPL",
    "gn:name":"Calle Larga",
    "gn:population":140,
    "gn:timezone":"America/Panama",
    "iso:country":"PA",
    "name:spa_x_preferred":[
        "Calle Larga"
    ],
    "wof:name":"Calle Larga",
    "wof:placetype":"locality",
    "wof:population":140
},
  "geometry": {"coordinates":[-80.7328,8.7484],"type":"Point"}
}