{
  "type": "Feature",
  "properties": {
    "gn:admin1_code":"02",
    "gn:asciiname":"Santa Clara",
    "gn:country_code":"PA",
    "gn:dem":209,
    "gn:feature_class":"P",
    "gn:feature_code":"PPL",
    "gn:name":"Santa Clara",
    "gn:population":0,
    "gn:timezone":"America/Panama",
    "iso:country":"PA",
    "wof:name":"Santa Clara",
    "wof:placetype":"locality"
},
  "geometry": {"coordinates":[-82.65000000000001,8.51667],"type":"Point"}
}