{
  "type": "Feature",
  "properties": {
    "gn:admin1_code":"10",
    "gn:asciiname":"Talanquera",
    "gn:country_code":"PA",
    "gn:dem":188,
    "gn:feature_class":"P",
    "gn:feature_code":"PPL",
    "gn:name":"Talanquera",
    "gn:population":0,
    "gn:timezone":"America/Panama",
    "iso:country":"PA",
    "wof:name":"Talanquera",
    "wof:placetype":"locality"
},
  "geometry": {"coordinates":[-81.48333000000002,7.88333],"type":"Point"}
}