{
  "type": "Feature",
  "properties": {
    "gn:admin1_code":"10",
    "gn:asciiname":"El Juan",
    "gn:country_code":"PA",
    "gn:dem":220,
    "gn:feature_class":"P",
    "gn:feature_code":"PPL",
    "gn:name":"El Juan",
    "gn:population":94,
    "gn:timezone":"America/Panama",
    "iso:country":"PA",
    "name:spa_x_preferred":[
        "El Juan"
    ],
    "wof:name":"El Juan",
    "wof:placetype":"locality",
    "wof:population":94
},
  "geometry": {"coordinates":[-81.35868000000001,8.1899],"type":"Point"}
}