{
  "type": "Feature",
  "properties": {
    "gn:admin1_code":"10",
    "gn:asciiname":"Guabal Poniente",
    "gn:country_code":"PA",
    "gn:dem":120,
    "gn:feature_class":"P",
    "gn:feature_code":"PPL",
    "gn:name":"Guabal Poniente",
    "gn:population":149,
    "gn:timezone":"America/Panama",
    "iso:country":"PA",
    "name:und_x_variant":[
        "Guabal",
        "Guabal Poniente"
    ],
    "wof:name":"Guabal Poniente",
    "wof:placetype":"locality",
    "wof:population":149
},
  "geometry": {"coordinates":[-81.30672,8.31418],"type":"Point"}
}