{
  "type": "Feature",
  "properties": {
    "gn:admin1_code":"03",
    "gn:asciiname":"Los Callejones",
    "gn:cc2":"PA",
    "gn:country_code":"PA",
    "gn:dem":111,
    "gn:feature_class":"P",
    "gn:feature_code":"PPL",
    "gn:name":"Los Callejones",
    "gn:population":45,
    "gn:timezone":"America/Panama",
    "iso:country":"PA",
    "name:und_x_variant":[
        "Boca de Puerco",
        "Callejones",
        "Los Callejones"
    ],
    "wof:name":"Los Callejones",
    "wof:placetype":"locality",
    "wof:population":45
},
  "geometry": {"coordinates":[-80.68901,8.27935],"type":"Point"}
}