{
  "type": "Feature",
  "properties": {
    "iso:country":"PA",
    "name:fas_x_preferred":[
        "\u0641\u0627\u0631\u0641\u0627\u0646"
    ],
    "name:und_x_variant":[
        "Farfan Housing"
    ],
    "qs:gn_country":"PA",
    "qs:gn_fcode":"PPL",
    "qs:gn_pop":0,
    "qs:name":"Farfan",
    "qs:name_adm0":"Panam\u00e1",
    "qs:name_adm1":"Panam\u00e1",
    "qs:photos":194,
    "qs:photos_1k":39,
    "qs:photos_9k":1,
    "qs:photos_9r":4,
    "qs:photos_all":194,
    "qs:photos_sr":4,
    "qs:placetype":"Town",
    "qs:pop_sr":"0",
    "qs:woe_adm0":23424924,
    "wd:wordcount":100,
    "wof:name":"Farfan",
    "wof:placetype":"locality"
},
  "geometry": {"coordinates":[-79.58333,8.93333],"type":"Point"}
}