{
  "type": "Feature",
  "properties": {
    "gn:admin1_code":"10",
    "gn:asciiname":"Zancudo",
    "gn:country_code":"PA",
    "gn:dem":30,
    "gn:feature_class":"P",
    "gn:feature_code":"PPL",
    "gn:name":"Zancudo",
    "gn:population":163,
    "gn:timezone":"America/Panama",
    "iso:country":"PA",
    "name:spa_x_preferred":[
        "Zancudo"
    ],
    "name:und_x_variant":[
        "El Zancudo"
    ],
    "wof:name":"Zancudo",
    "wof:placetype":"locality",
    "wof:population":163
},
  "geometry": {"coordinates":[-81.30875999999998,7.76734],"type":"Point"}
}