{
  "type": "Feature",
  "properties": {
    "gn:admin1_code":"04",
    "gn:asciiname":"Nueva America",
    "gn:country_code":"PA",
    "gn:dem":31,
    "gn:feature_class":"P",
    "gn:feature_code":"PPL",
    "gn:name":"Nueva Am\u00e9rica",
    "gn:population":0,
    "gn:timezone":"America/Panama",
    "iso:country":"PA",
    "wof:name":"Nueva America",
    "wof:placetype":"locality"
},
  "geometry": {"coordinates":[-80.05,9.06667],"type":"Point"}
}