{
  "type": "Feature",
  "properties": {
    "gn:admin1_code":"10",
    "gn:asciiname":"Tranquillas",
    "gn:country_code":"PA",
    "gn:dem":100,
    "gn:feature_class":"P",
    "gn:feature_code":"PPL",
    "gn:name":"Tranquillas",
    "gn:population":124,
    "gn:timezone":"America/Panama",
    "iso:country":"PA",
    "name:und_x_variant":[
        "Las Tranquillas"
    ],
    "wof:name":"Tranquillas",
    "wof:placetype":"locality",
    "wof:population":124
},
  "geometry": {"coordinates":[-80.91238,7.94315],"type":"Point"}
}