{
  "type": "Feature",
  "properties": {
    "gn:admin1_code":"03",
    "gn:asciiname":"La Estancia Numero Uno",
    "gn:cc2":"PA",
    "gn:country_code":"PA",
    "gn:dem":270,
    "gn:feature_class":"P",
    "gn:feature_code":"PPL",
    "gn:name":"La Estancia N\u00famero Uno",
    "gn:population":0,
    "gn:timezone":"America/Panama",
    "iso:country":"PA",
    "name:und_x_variant":[
        "La Estancia",
        "La Estancia N\u00famero Uno"
    ],
    "wof:name":"La Estancia Numero Uno",
    "wof:placetype":"locality"
},
  "geometry": {"coordinates":[-80.21666999999999,8.55],"type":"Point"}
}