{
  "type": "Feature",
  "properties": {
    "gn:admin1_code":"10",
    "gn:asciiname":"El Nance",
    "gn:country_code":"PA",
    "gn:dem":85,
    "gn:feature_class":"P",
    "gn:feature_code":"PPL",
    "gn:name":"El Nance",
    "gn:population":193,
    "gn:timezone":"America/Panama",
    "iso:country":"PA",
    "name:spa_x_preferred":[
        "El Nance"
    ],
    "wof:name":"El Nance",
    "wof:placetype":"locality",
    "wof:population":193
},
  "geometry": {"coordinates":[-81.08381,8.15253],"type":"Point"}
}