{
  "type": "Feature",
  "properties": {
    "gn:admin1_code":"13",
    "gn:asciiname":"Cuchirvo",
    "gn:country_code":"PA",
    "gn:dem":66,
    "gn:feature_class":"P",
    "gn:feature_code":"PPL",
    "gn:name":"Cuchirvo",
    "gn:population":16,
    "gn:timezone":"America/Panama",
    "iso:country":"PA",
    "name:und_x_variant":[
        "Cuchiro",
        "Cuchirvo"
    ],
    "wof:name":"Cuchirvo",
    "wof:placetype":"locality",
    "wof:population":16
},
  "geometry": {"coordinates":[-79.95,9.06667],"type":"Point"}
}