{
  "type": "Feature",
  "properties": {
    "gn:admin1_code":"13",
    "gn:asciiname":"Ciri Numero Dos",
    "gn:country_code":"PA",
    "gn:dem":228,
    "gn:feature_class":"P",
    "gn:feature_code":"PPL",
    "gn:name":"Cir\u00ed N\u00famero Dos",
    "gn:population":0,
    "gn:timezone":"America/Panama",
    "iso:country":"PA",
    "wof:name":"Ciri Numero Dos",
    "wof:placetype":"locality"
},
  "geometry": {"coordinates":[-80.06667,8.85],"type":"Point"}
}