{
  "type": "Feature",
  "properties": {
    "gn:admin1_code":"10",
    "gn:asciiname":"Charco Negro",
    "gn:country_code":"PA",
    "gn:dem":65,
    "gn:feature_class":"P",
    "gn:feature_code":"PPL",
    "gn:name":"Charco Negro",
    "gn:population":122,
    "gn:timezone":"America/Panama",
    "iso:country":"PA",
    "wof:name":"Charco Negro",
    "wof:placetype":"locality",
    "wof:population":122
},
  "geometry": {"coordinates":[-81.17941999999999,8.07214],"type":"Point"}
}