{
  "type": "Feature",
  "properties": {
    "gn:admin1_code":"07",
    "gn:asciiname":"La Bonita",
    "gn:country_code":"PA",
    "gn:dem":36,
    "gn:feature_class":"P",
    "gn:feature_code":"PPL",
    "gn:name":"La Bonita",
    "gn:population":127,
    "gn:timezone":"America/Panama",
    "iso:country":"PA",
    "wof:name":"La Bonita",
    "wof:placetype":"locality",
    "wof:population":127
},
  "geometry": {"coordinates":[-80.46135,7.3871],"type":"Point"}
}