{
  "type": "Feature",
  "properties": {
    "gn:admin1_code":"12",
    "gn:asciiname":"Rio Hacha",
    "gn:country_code":"PA",
    "gn:dem":1213,
    "gn:feature_class":"P",
    "gn:feature_code":"PPL",
    "gn:name":"R\u00edo Hacha",
    "gn:population":0,
    "gn:timezone":"America/Panama",
    "iso:country":"PA",
    "name:spa_x_preferred":[
        "R\u00edo Hacha"
    ],
    "wof:name":"Rio Hacha",
    "wof:placetype":"locality"
},
  "geometry": {"coordinates":[-81.77856,8.52512],"type":"Point"}
}