{
  "type": "Feature",
  "properties": {
    "gn:admin1_code":"10",
    "gn:asciiname":"Corotu",
    "gn:country_code":"PA",
    "gn:dem":17,
    "gn:feature_class":"P",
    "gn:feature_code":"PPL",
    "gn:name":"Corot\u00fa",
    "gn:population":20,
    "gn:timezone":"America/Panama",
    "iso:country":"PA",
    "wof:name":"Corotu",
    "wof:placetype":"locality",
    "wof:population":20
},
  "geometry": {"coordinates":[-81.49028,7.77],"type":"Point"}
}