{
  "type": "Feature",
  "properties": {
    "gn:admin1_code":"04",
    "gn:asciiname":"Piloncito",
    "gn:country_code":"PA",
    "gn:dem":5,
    "gn:feature_class":"P",
    "gn:feature_code":"PPL",
    "gn:name":"Piloncito",
    "gn:population":16,
    "gn:timezone":"America/Panama",
    "iso:country":"PA",
    "wof:name":"Piloncito",
    "wof:placetype":"locality",
    "wof:population":16
},
  "geometry": {"coordinates":[-80.22417,9.18639],"type":"Point"}
}