{
  "type": "Feature",
  "properties": {
    "gn:admin1_code":"10",
    "gn:asciiname":"El Espejo",
    "gn:country_code":"PA",
    "gn:dem":112,
    "gn:feature_class":"P",
    "gn:feature_code":"PPL",
    "gn:name":"El Espejo",
    "gn:population":0,
    "gn:timezone":"America/Panama",
    "iso:country":"PA",
    "wof:name":"El Espejo",
    "wof:placetype":"locality"
},
  "geometry": {"coordinates":[-81.34555999999998,7.75306],"type":"Point"}
}