{
  "type": "Feature",
  "properties": {
    "gn:admin1_code":"03",
    "gn:asciiname":"Las Minas",
    "gn:country_code":"PA",
    "gn:dem":209,
    "gn:feature_class":"P",
    "gn:feature_code":"PPLA3",
    "gn:name":"Las Minas",
    "gn:population":548,
    "gn:timezone":"America/Panama",
    "iso:country":"PA",
    "name:spa_x_preferred":[
        "Las Minas"
    ],
    "wof:name":"Las Minas",
    "wof:placetype":"locality",
    "wof:population":548
},
  "geometry": {"coordinates":[-80.39431999999999,8.64118],"type":"Point"}
}