{
  "type": "Feature",
  "properties": {
    "gn:admin1_code":"03",
    "gn:asciiname":"La Pinuela",
    "gn:country_code":"PA",
    "gn:dem":319,
    "gn:feature_class":"P",
    "gn:feature_code":"PPL",
    "gn:name":"La Pi\u00f1uela",
    "gn:population":0,
    "gn:timezone":"America/Panama",
    "iso:country":"PA",
    "wof:name":"La Pinuela",
    "wof:placetype":"locality"
},
  "geometry": {"coordinates":[-80.13333,8.51667],"type":"Point"}
}