{
  "type": "Feature",
  "properties": {
    "gn:admin1_code":"07",
    "gn:asciiname":"Quebrada La Yeguada",
    "gn:country_code":"PA",
    "gn:dem":9,
    "gn:feature_class":"P",
    "gn:feature_code":"PPL",
    "gn:name":"Quebrada La Yeguada",
    "gn:population":0,
    "gn:timezone":"America/Panama",
    "iso:country":"PA",
    "wof:name":"Quebrada La Yeguada",
    "wof:placetype":"locality"
},
  "geometry": {"coordinates":[-80.11667,7.68333],"type":"Point"}
}