{
  "type": "Feature",
  "properties": {
    "gn:admin1_code":"10",
    "gn:asciiname":"Llano Largo",
    "gn:country_code":"PA",
    "gn:dem":30,
    "gn:feature_class":"P",
    "gn:feature_code":"PPL",
    "gn:name":"Llano Largo",
    "gn:population":0,
    "gn:timezone":"America/Panama",
    "iso:country":"PA",
    "name:und_x_variant":[
        "Llano Grande Largo",
        "Llano Largo",
        "Llano Grande"
    ],
    "wof:name":"Llano Largo",
    "wof:placetype":"locality"
},
  "geometry": {"coordinates":[-81.08729,8.03397],"type":"Point"}
}