{
  "type": "Feature",
  "properties": {
    "gn:admin1_code":"10",
    "gn:asciiname":"Llano Largo",
    "gn:country_code":"PA",
    "gn:dem":30,
    "gn:feature_class":"P",
    "gn:feature_code":"PPL",
    "gn:name":"Llano Largo",
    "gn:population":0,
    "gn:timezone":"America/Panama",
    "iso:country":"PA",
    "name:ceb_x_preferred":[
        "Llano Largo"
    ],
    "name:ita_x_preferred":[
        "Llano Largo"
    ],
    "name:kat_x_preferred":[
        "\u10da\u10d8\u10d0\u10dc\u10dd-\u10da\u10d0\u10e0\u10d2\u10dd"
    ],
    "name:spa_x_preferred":[
        "Llano Largo"
    ],
    "name:und_x_variant":[
        "Llano Grande Largo",
        "Llano Grande"
    ],
    "name:zho_x_preferred":[
        "\u5229\u4e9e\u8afe\u62c9\u723e\u6208"
    ],
    "wof:name":"Llano Largo",
    "wof:placetype":"locality"
},
  "geometry": {"coordinates":[-81.08729,8.03397],"type":"Point"}
}