{
  "type": "Feature",
  "properties": {
    "gn:admin1_code":"10",
    "gn:asciiname":"El Bajo",
    "gn:country_code":"PA",
    "gn:dem":225,
    "gn:feature_class":"P",
    "gn:feature_code":"PPL",
    "gn:name":"El Bajo",
    "gn:population":0,
    "gn:timezone":"America/Panama",
    "iso:country":"PA",
    "wof:name":"El Bajo",
    "wof:placetype":"locality"
},
  "geometry": {"coordinates":[-81.4225,7.95806],"type":"Point"}
}