{
  "type": "Feature",
  "properties": {
    "gn:admin1_code":"06",
    "gn:asciiname":"La Iguana",
    "gn:country_code":"PA",
    "gn:dem":137,
    "gn:feature_class":"P",
    "gn:feature_code":"PPL",
    "gn:name":"La Iguana",
    "gn:population":42,
    "gn:timezone":"America/Panama",
    "iso:country":"PA",
    "wof:name":"La Iguana",
    "wof:placetype":"locality",
    "wof:population":42
},
  "geometry": {"coordinates":[-80.88333,7.88333],"type":"Point"}
}