{
  "type": "Feature",
  "properties": {
    "gn:admin1_code":"12",
    "gn:asciiname":"Alto Cana",
    "gn:country_code":"PA",
    "gn:dem":669,
    "gn:feature_class":"P",
    "gn:feature_code":"PPL",
    "gn:name":"Alto Ca\u00f1a",
    "gn:population":0,
    "gn:timezone":"America/Panama",
    "iso:country":"PA",
    "wof:name":"Alto Cana",
    "wof:placetype":"locality"
},
  "geometry": {"coordinates":[-81.78333000000001,8.43333],"type":"Point"}
}