{
  "type": "Feature",
  "properties": {
    "iso:country":"PA",
    "name:ceb_x_preferred":[
        "El Roble"
    ],
    "name:eng_x_preferred":[
        "El Roble"
    ],
    "name:ita_x_preferred":[
        "El Roble"
    ],
    "name:nld_x_preferred":[
        "El Roble"
    ],
    "name:spa_x_preferred":[
        "El Roble"
    ],
    "name:zho_x_preferred":[
        "\u57c3\u5c14\u7f57\u592b\u83b1"
    ],
    "qs:gn_country":"PA",
    "qs:gn_fcode":"PPL",
    "qs:gn_pop":1610,
    "qs:name":"El Roble",
    "qs:name_adm0":"Panam\u00e1",
    "qs:name_adm1":"Cocl\u00e9",
    "qs:photos":0,
    "qs:photos_1k":0,
    "qs:photos_9k":0,
    "qs:photos_9r":0,
    "qs:photos_all":0,
    "qs:photos_sr":0,
    "qs:placetype":"Town",
    "qs:pop_sr":"3",
    "qs:woe_adm0":23424924,
    "wd:wordcount":106,
    "wof:name":"El Roble",
    "wof:placetype":"locality",
    "wof:population":1610
},
  "geometry": {"coordinates":[-80.65000000000001,8.16667],"type":"Point"}
}