{
  "type": "Feature",
  "properties": {
    "gn:admin1_code":"07",
    "gn:asciiname":"Los Rastrojos",
    "gn:country_code":"PA",
    "gn:dem":135,
    "gn:feature_class":"P",
    "gn:feature_code":"PPL",
    "gn:name":"Los Rastrojos",
    "gn:population":65,
    "gn:timezone":"America/Panama",
    "iso:country":"PA",
    "wof:name":"Los Rastrojos",
    "wof:placetype":"locality",
    "wof:population":65
},
  "geometry": {"coordinates":[-80.50591,7.70075],"type":"Point"}
}