{
  "type": "Feature",
  "properties": {
    "gn:admin1_code":"02",
    "gn:asciiname":"Alto de Divala",
    "gn:country_code":"PA",
    "gn:dem":91,
    "gn:feature_class":"P",
    "gn:feature_code":"PPL",
    "gn:name":"Alto de Dival\u00e1",
    "gn:population":0,
    "gn:timezone":"America/Panama",
    "iso:country":"PA",
    "name:und_x_variant":[
        "Alto de Dival\u00e1",
        "Alto Dival\u00e1"
    ],
    "wof:name":"Alto de Divala",
    "wof:placetype":"locality"
},
  "geometry": {"coordinates":[-82.70116999999998,8.45246],"type":"Point"}
}