{
  "type": "Feature",
  "properties": {
    "gn:admin1_code":"01",
    "gn:asciiname":"Aguadulce",
    "gn:country_code":"PA",
    "gn:dem":386,
    "gn:feature_class":"P",
    "gn:feature_code":"PPL",
    "gn:name":"Aguadulce",
    "gn:population":0,
    "gn:timezone":"America/Panama",
    "iso:country":"PA",
    "wof:name":"Aguadulce",
    "wof:placetype":"locality"
},
  "geometry": {"coordinates":[-82.46666999999999,9.28333],"type":"Point"}
}