{
  "type": "Feature",
  "properties": {
    "gn:admin1_code":"10",
    "gn:asciiname":"El Rompio",
    "gn:country_code":"PA",
    "gn:dem":19,
    "gn:feature_class":"P",
    "gn:feature_code":"PPL",
    "gn:name":"El Romp\u00edo",
    "gn:population":0,
    "gn:timezone":"America/Panama",
    "iso:country":"PA",
    "wof:name":"El Rompio",
    "wof:placetype":"locality"
},
  "geometry": {"coordinates":[-80.84999999999999,7.43333],"type":"Point"}
}