{
  "type": "Feature",
  "properties": {
    "gn:admin1_code":"10",
    "gn:asciiname":"Los Corralillos",
    "gn:cc2":"PA",
    "gn:country_code":"PA",
    "gn:dem":44,
    "gn:feature_class":"P",
    "gn:feature_code":"PPL",
    "gn:name":"Los Corralillos",
    "gn:population":111,
    "gn:timezone":"America/Panama",
    "iso:country":"PA",
    "name:und_x_variant":[
        "Los Carralillos",
        "Los Corralillos"
    ],
    "wof:name":"Los Corralillos",
    "wof:placetype":"locality",
    "wof:population":111
},
  "geometry": {"coordinates":[-80.94247,7.98107],"type":"Point"}
}