{
  "type": "Feature",
  "properties": {
    "gn:admin1_code":"03",
    "gn:asciiname":"Palma Seca",
    "gn:country_code":"PA",
    "gn:dem":102,
    "gn:feature_class":"P",
    "gn:feature_code":"PPL",
    "gn:name":"Palma Seca",
    "gn:population":0,
    "gn:timezone":"America/Panama",
    "iso:country":"PA",
    "wof:name":"Palma Seca",
    "wof:placetype":"locality"
},
  "geometry": {"coordinates":[-80.18333,8.45],"type":"Point"}
}