{
  "type": "Feature",
  "properties": {
    "gn:admin1_code":"08",
    "gn:asciiname":"Mocambito",
    "gn:country_code":"PA",
    "gn:dem":216,
    "gn:feature_class":"P",
    "gn:feature_code":"PPL",
    "gn:name":"Mocambito",
    "gn:population":0,
    "gn:timezone":"America/Panama",
    "iso:country":"PA",
    "wof:name":"Mocambito",
    "wof:placetype":"locality"
},
  "geometry": {"coordinates":[-79.45,9.12],"type":"Point"}
}