{
  "type": "Feature",
  "properties": {
    "gn:admin1_code":"06",
    "gn:asciiname":"El Hatillo",
    "gn:country_code":"PA",
    "gn:dem":49,
    "gn:feature_class":"P",
    "gn:feature_code":"PPL",
    "gn:name":"El Hatillo",
    "gn:population":0,
    "gn:timezone":"America/Panama",
    "iso:country":"PA",
    "wof:name":"El Hatillo",
    "wof:placetype":"locality"
},
  "geometry": {"coordinates":[-80.52868000000002,7.96657],"type":"Point"}
}