{
  "type": "Feature",
  "properties": {
    "gn:admin1_code":"01",
    "gn:asciiname":"Isla Grande",
    "gn:country_code":"PA",
    "gn:dem":10,
    "gn:feature_class":"P",
    "gn:feature_code":"PPL",
    "gn:name":"Isla Grande",
    "gn:population":0,
    "gn:timezone":"America/Panama",
    "iso:country":"PA",
    "name:ceb_x_preferred":[
        "Isla Grande"
    ],
    "name:fra_x_preferred":[
        "Isla Grande"
    ],
    "name:ita_x_preferred":[
        "Isla Grande"
    ],
    "name:nor_x_preferred":[
        "Isla Grande"
    ],
    "name:pol_x_preferred":[
        "Isla Grande"
    ],
    "name:por_x_preferred":[
        "Ilha Grande"
    ],
    "name:spa_x_preferred":[
        "Isla Grande"
    ],
    "wof:name":"Isla Grande",
    "wof:placetype":"locality"
},
  "geometry": {"coordinates":[-82.66667,9.48333],"type":"Point"}
}