{
  "type": "Feature",
  "properties": {
    "gn:admin1_code":"13",
    "gn:asciiname":"La Monita",
    "gn:country_code":"PA",
    "gn:dem":121,
    "gn:feature_class":"P",
    "gn:feature_code":"PPL",
    "gn:name":"La Monita",
    "gn:population":0,
    "gn:timezone":"America/Panama",
    "iso:country":"PA",
    "wof:name":"La Monita",
    "wof:placetype":"locality"
},
  "geometry": {"coordinates":[-79.88333,8.78333],"type":"Point"}
}