{
  "type": "Feature",
  "properties": {
    "gn:admin1_code":"12",
    "gn:asciiname":"Shark Hole Point",
    "gn:country_code":"PA",
    "gn:dem":-9999,
    "gn:feature_class":"P",
    "gn:feature_code":"PPL",
    "gn:name":"Shark Hole Point",
    "gn:population":0,
    "gn:timezone":"America/Panama",
    "iso:country":"PA",
    "name:und_x_variant":[
        "Chacol",
        "Shark Hole",
        "Shark Hole Point"
    ],
    "wof:name":"Shark Hole Point",
    "wof:placetype":"locality"
},
  "geometry": {"coordinates":[-81.78333000000001,9.06667],"type":"Point"}
}