{
  "type": "Feature",
  "properties": {
    "gn:admin1_code":"04",
    "gn:asciiname":"La Jicotea",
    "gn:cc2":"PA",
    "gn:country_code":"PA",
    "gn:dem":53,
    "gn:feature_class":"P",
    "gn:feature_code":"PPL",
    "gn:name":"La Jicotea",
    "gn:population":0,
    "gn:timezone":"America/Panama",
    "iso:country":"PA",
    "name:und_x_variant":[
        "La Hicotea",
        "La Jicotea"
    ],
    "wof:name":"La Jicotea",
    "wof:placetype":"locality"
},
  "geometry": {"coordinates":[-80.13333,9.11667],"type":"Point"}
}