{
  "type": "Feature",
  "properties": {
    "gn:admin1_code":"07",
    "gn:asciiname":"El Limon",
    "gn:country_code":"PA",
    "gn:dem":10,
    "gn:feature_class":"P",
    "gn:feature_code":"PPL",
    "gn:name":"El Lim\u00f3n",
    "gn:population":0,
    "gn:timezone":"America/Panama",
    "iso:country":"PA",
    "wof:name":"El Limon",
    "wof:placetype":"locality"
},
  "geometry": {"coordinates":[-80.38333,7.43333],"type":"Point"}
}