{
  "type": "Feature",
  "properties": {
    "gn:admin1_code":"10",
    "gn:asciiname":"Piedra de Agua",
    "gn:country_code":"PA",
    "gn:dem":857,
    "gn:feature_class":"P",
    "gn:feature_code":"PPL",
    "gn:name":"Piedra de Agua",
    "gn:population":0,
    "gn:timezone":"America/Panama",
    "iso:country":"PA",
    "name:spa_x_preferred":[
        "Piedra de Agua"
    ],
    "wof:name":"Piedra de Agua",
    "wof:placetype":"locality"
},
  "geometry": {"coordinates":[-81.29236999999998,8.48688],"type":"Point"}
}