{
  "type": "Feature",
  "properties": {
    "gn:admin1_code":"12",
    "gn:asciiname":"Quebrada Frijoles",
    "gn:country_code":"PA",
    "gn:dem":272,
    "gn:feature_class":"P",
    "gn:feature_code":"PPL",
    "gn:name":"Quebrada Frijoles",
    "gn:population":0,
    "gn:timezone":"America/Panama",
    "iso:country":"PA",
    "wof:name":"Quebrada Frijoles",
    "wof:placetype":"locality"
},
  "geometry": {"coordinates":[-81.83333,8.36667],"type":"Point"}
}