{
  "type": "Feature",
  "properties": {
    "gn:admin1_code":"10",
    "gn:asciiname":"Llano de Los Muertos",
    "gn:country_code":"PA",
    "gn:dem":208,
    "gn:feature_class":"P",
    "gn:feature_code":"PPL",
    "gn:name":"Llano de Los Muertos",
    "gn:population":174,
    "gn:timezone":"America/Panama",
    "iso:country":"PA",
    "name:spa_x_preferred":[
        "Llano de Los Muertos"
    ],
    "wof:name":"Llano de Los Muertos",
    "wof:placetype":"locality",
    "wof:population":174
},
  "geometry": {"coordinates":[-81.43875,8.08405],"type":"Point"}
}