{
  "type": "Feature",
  "properties": {
    "gn:admin1_code":"06",
    "gn:asciiname":"El Guayabito",
    "gn:country_code":"PA",
    "gn:dem":151,
    "gn:feature_class":"P",
    "gn:feature_code":"PPL",
    "gn:name":"El Guayabito",
    "gn:population":124,
    "gn:timezone":"America/Panama",
    "iso:country":"PA",
    "name:spa_x_preferred":[
        "El Guayabito"
    ],
    "wof:name":"El Guayabito",
    "wof:placetype":"locality",
    "wof:population":124
},
  "geometry": {"coordinates":[-80.8254,7.91435],"type":"Point"}
}