{
  "type": "Feature",
  "properties": {
    "gn:admin1_code":"07",
    "gn:asciiname":"Las Huertas",
    "gn:country_code":"PA",
    "gn:dem":174,
    "gn:feature_class":"P",
    "gn:feature_code":"PPL",
    "gn:name":"Las Huertas",
    "gn:population":0,
    "gn:timezone":"America/Panama",
    "iso:country":"PA",
    "wof:name":"Las Huertas",
    "wof:placetype":"locality"
},
  "geometry": {"coordinates":[-80.61667,7.61667],"type":"Point"}
}