{
  "type": "Feature",
  "properties": {
    "gn:admin1_code":"10",
    "gn:asciiname":"La Hilaria",
    "gn:cc2":"PA",
    "gn:country_code":"PA",
    "gn:dem":67,
    "gn:feature_class":"P",
    "gn:feature_code":"PPL",
    "gn:name":"La Hilaria",
    "gn:population":0,
    "gn:timezone":"America/Panama",
    "iso:country":"PA",
    "name:und_x_variant":[
        "Sardina",
        "La Hilaria"
    ],
    "wof:name":"La Hilaria",
    "wof:placetype":"locality"
},
  "geometry": {"coordinates":[-80.98333000000002,8.23333],"type":"Point"}
}