{
  "type": "Feature",
  "properties": {
    "gn:admin1_code":"10",
    "gn:asciiname":"Sabaneta del Alto de la Montana",
    "gn:cc2":"PA",
    "gn:country_code":"PA",
    "gn:dem":184,
    "gn:feature_class":"P",
    "gn:feature_code":"PPL",
    "gn:name":"Sabaneta del Alto de la Monta\u00f1a",
    "gn:population":0,
    "gn:timezone":"America/Panama",
    "iso:country":"PA",
    "name:und_x_variant":[
        "Sabaneta",
        "Sabaneta del Alto de la Monta\u00f1a"
    ],
    "wof:name":"Sabaneta del Alto de la Montana",
    "wof:placetype":"locality"
},
  "geometry": {"coordinates":[-81.23333000000002,8.15],"type":"Point"}
}