{
  "type": "Feature",
  "properties": {
    "gn:admin1_code":"02",
    "gn:asciiname":"Morita",
    "gn:country_code":"PA",
    "gn:dem":126,
    "gn:feature_class":"P",
    "gn:feature_code":"PPL",
    "gn:name":"Morita",
    "gn:population":0,
    "gn:timezone":"America/Panama",
    "iso:country":"PA",
    "name:deu_x_preferred":[
        "Morita"
    ],
    "name:fin_x_preferred":[
        "Morita"
    ],
    "name:fra_x_preferred":[
        "Morita"
    ],
    "name:ita_x_preferred":[
        "Morita"
    ],
    "name:kor_x_preferred":[
        "\ubaa8\ub9ac\ud0c0"
    ],
    "name:nld_x_preferred":[
        "Morita"
    ],
    "name:por_x_preferred":[
        "Morita"
    ],
    "name:spa_x_preferred":[
        "Morita"
    ],
    "wof:name":"Morita",
    "wof:placetype":"locality"
},
  "geometry": {"coordinates":[-82.51666999999998,8.48333],"type":"Point"}
}