{
  "type": "Feature",
  "properties": {
    "gn:admin1_code":"13",
    "gn:asciiname":"Barriada Panama",
    "gn:country_code":"PA",
    "gn:dem":21,
    "gn:feature_class":"P",
    "gn:feature_code":"PPL",
    "gn:name":"Barriada Panam\u00e1",
    "gn:population":0,
    "gn:timezone":"America/Panama",
    "iso:country":"PA",
    "name:spa_x_preferred":[
        "Barriada Panam\u00e1"
    ],
    "wof:name":"Barriada Panama",
    "wof:placetype":"locality"
},
  "geometry": {"coordinates":[-79.61724,8.89682],"type":"Point"}
}