{
  "type": "Feature",
  "properties": {
    "gn:admin1_code":"10",
    "gn:asciiname":"La Seca",
    "gn:country_code":"PA",
    "gn:dem":13,
    "gn:feature_class":"P",
    "gn:feature_code":"PPL",
    "gn:name":"La Seca",
    "gn:population":0,
    "gn:timezone":"America/Panama",
    "iso:country":"PA",
    "name:arg_x_preferred":[
        "La Seca"
    ],
    "name:azb_x_preferred":[
        "\u0644\u0627 \u0633\u06a9\u0627"
    ],
    "name:cat_x_preferred":[
        "La Seca"
    ],
    "name:ceb_x_preferred":[
        "La Seca"
    ],
    "name:eus_x_preferred":[
        "La Seca"
    ],
    "name:fas_x_preferred":[
        "\u0644\u0627 \u0633\u06a9\u0627"
    ],
    "name:fra_x_preferred":[
        "La Seca"
    ],
    "name:glg_x_preferred":[
        "La Seca"
    ],
    "name:hun_x_preferred":[
        "La Seca"
    ],
    "name:hye_x_preferred":[
        "\u053c\u0561 \u054d\u0565\u056f\u0561"
    ],
    "name:ina_x_preferred":[
        "La Seca"
    ],
    "name:ita_x_preferred":[
        "La Seca"
    ],
    "name:msa_x_preferred":[
        "La Seca"
    ],
    "name:nld_x_preferred":[
        "La Seca"
    ],
    "name:oci_x_preferred":[
        "La Seca"
    ],
    "name:pol_x_preferred":[
        "La Seca"
    ],
    "name:por_x_preferred":[
        "La Seca"
    ],
    "name:rus_x_preferred":[
        "\u041b\u0430-\u0421\u0435\u043a\u0430"
    ],
    "name:spa_x_preferred":[
        "La Seca"
    ],
    "name:ukr_x_preferred":[
        "\u041b\u0430-\u0421\u0435\u043a\u0430"
    ],
    "name:uzb_x_preferred":[
        "La Seca"
    ],
    "name:vie_x_preferred":[
        "La Seca"
    ],
    "name:war_x_preferred":[
        "La Seca"
    ],
    "name:zho_x_preferred":[
        "\u62c9\u585e\u5361"
    ],
    "wof:name":"La Seca",
    "wof:placetype":"locality"
},
  "geometry": {"coordinates":[-80.88333,7.33333],"type":"Point"}
}