{
  "type": "Feature",
  "properties": {
    "gn:admin1_code":"10",
    "gn:asciiname":"Piedras Negras",
    "gn:country_code":"PA",
    "gn:dem":73,
    "gn:feature_class":"P",
    "gn:feature_code":"PPL",
    "gn:name":"Piedras Negras",
    "gn:population":110,
    "gn:timezone":"America/Panama",
    "iso:country":"PA",
    "name:spa_x_preferred":[
        "Piedras Negras"
    ],
    "wof:name":"Piedras Negras",
    "wof:placetype":"locality",
    "wof:population":110
},
  "geometry": {"coordinates":[-81.22075,8.03227],"type":"Point"}
}