{
  "type": "Feature",
  "properties": {
    "gn:admin1_code":"03",
    "gn:asciiname":"Los Alveos",
    "gn:country_code":"PA",
    "gn:dem":337,
    "gn:feature_class":"P",
    "gn:feature_code":"PPL",
    "gn:name":"Los Alveos",
    "gn:population":177,
    "gn:timezone":"America/Panama",
    "iso:country":"PA",
    "wof:name":"Los Alveos",
    "wof:placetype":"locality",
    "wof:population":177
},
  "geometry": {"coordinates":[-80.1709,8.53484],"type":"Point"}
}