{
  "type": "Feature",
  "properties": {
    "gn:admin1_code":"04",
    "gn:asciiname":"Rio Alejandro Arriba",
    "gn:country_code":"PA",
    "gn:dem":132,
    "gn:feature_class":"P",
    "gn:feature_code":"PPL",
    "gn:name":"R\u00edo Alejandro Arriba",
    "gn:population":0,
    "gn:timezone":"America/Panama",
    "iso:country":"PA",
    "wof:name":"Rio Alejandro Arriba",
    "wof:placetype":"locality"
},
  "geometry": {"coordinates":[-79.76666999999998,9.36667],"type":"Point"}
}