{
  "type": "Feature",
  "properties": {
    "gn:admin1_code":"02",
    "gn:asciiname":"Los Planes",
    "gn:country_code":"PA",
    "gn:dem":972,
    "gn:feature_class":"P",
    "gn:feature_code":"PPL",
    "gn:name":"Los Planes",
    "gn:population":179,
    "gn:timezone":"America/Panama",
    "iso:country":"PA",
    "name:spa_x_preferred":[
        "Los Planes"
    ],
    "wof:name":"Los Planes",
    "wof:placetype":"locality",
    "wof:population":179
},
  "geometry": {"coordinates":[-82.21247,8.6244],"type":"Point"}
}