{
  "type": "Feature",
  "properties": {
    "gn:admin1_code":"03",
    "gn:asciiname":"Zumbador",
    "gn:country_code":"PA",
    "gn:dem":259,
    "gn:feature_class":"P",
    "gn:feature_code":"PPL",
    "gn:name":"Zumbador",
    "gn:population":116,
    "gn:timezone":"America/Panama",
    "iso:country":"PA",
    "name:spa_x_preferred":[
        "Zumbador"
    ],
    "wof:name":"Zumbador",
    "wof:placetype":"locality",
    "wof:population":116
},
  "geometry": {"coordinates":[-80.39234999999999,8.61032],"type":"Point"}
}