{
  "type": "Feature",
  "properties": {
    "iso:country":"PA",
    "name:ita_x_preferred":[
        "Pajonal"
    ],
    "name:spa_x_preferred":[
        "Pajonal"
    ],
    "name:zho_x_preferred":[
        "\u5e15\u970d\u7eb3\u5c14"
    ],
    "qs:gn_pop":0,
    "qs:name":"Pajonal",
    "qs:name_adm0":"Panam\u00e1",
    "qs:name_adm1":"Cocl\u00e9",
    "qs:photos":27,
    "qs:photos_1k":5,
    "qs:photos_9k":1,
    "qs:photos_9r":4,
    "qs:photos_all":179,
    "qs:photos_sr":2,
    "qs:placetype":"LocalAdmin",
    "qs:pop_sr":"0",
    "qs:woe_adm0":23424924,
    "wof:name":"Pajonal",
    "wof:placetype":"localadmin"
},
  "geometry": {"coordinates":[-80.120716,8.630751],"type":"Point"}
}