{
  "type": "Feature",
  "properties": {
    "gn:admin1_code":"02",
    "gn:asciiname":"Balsa Numero Dos",
    "gn:country_code":"PA",
    "gn:dem":51,
    "gn:feature_class":"P",
    "gn:feature_code":"PPL",
    "gn:name":"Balsa N\u00famero Dos",
    "gn:population":0,
    "gn:timezone":"America/Panama",
    "iso:country":"PA",
    "wof:name":"Balsa Numero Dos",
    "wof:placetype":"locality"
},
  "geometry": {"coordinates":[-82.86667,8.08333],"type":"Point"}
}