{
  "type": "Feature",
  "properties": {
    "gn:admin1_code":"08",
    "gn:asciiname":"Playa Colorada",
    "gn:country_code":"PA",
    "gn:dem":-9999,
    "gn:feature_class":"P",
    "gn:feature_code":"PPL",
    "gn:name":"Playa Colorada",
    "gn:population":0,
    "gn:timezone":"America/Panama",
    "iso:country":"PA",
    "wof:name":"Playa Colorada",
    "wof:placetype":"locality"
},
  "geometry": {"coordinates":[-78.61667,8.66667],"type":"Point"}
}