{
  "type": "Feature",
  "properties": {
    "gn:admin1_code":"13",
    "gn:asciiname":"Huile",
    "gn:country_code":"PA",
    "gn:dem":147,
    "gn:feature_class":"P",
    "gn:feature_code":"PPL",
    "gn:name":"Huile",
    "gn:population":486,
    "gn:timezone":"America/Panama",
    "iso:country":"PA",
    "name:spa_x_preferred":[
        "Huile"
    ],
    "wof:name":"Huile",
    "wof:placetype":"locality",
    "wof:population":486
},
  "geometry": {"coordinates":[-79.73810999999998,9.03112],"type":"Point"}
}