{
  "type": "Feature",
  "properties": {
    "gn:admin1_code":"03",
    "gn:asciiname":"Las Saldanas",
    "gn:cc2":"PA",
    "gn:country_code":"PA",
    "gn:dem":84,
    "gn:feature_class":"P",
    "gn:feature_code":"PPL",
    "gn:name":"Las Salda\u00f1as",
    "gn:population":0,
    "gn:timezone":"America/Panama",
    "iso:country":"PA",
    "name:und_x_variant":[
        "Las Salda\u00f1a",
        "Los Salda\u00f1os",
        "Las Salda\u00f1as"
    ],
    "wof:name":"Las Saldanas",
    "wof:placetype":"locality"
},
  "geometry": {"coordinates":[-80.51666999999998,8.48333],"type":"Point"}
}