{
  "type": "Feature",
  "properties": {
    "gn:admin1_code":"10",
    "gn:asciiname":"Managua",
    "gn:country_code":"PA",
    "gn:dem":22,
    "gn:feature_class":"P",
    "gn:feature_code":"PPL",
    "gn:name":"Managua",
    "gn:population":16,
    "gn:timezone":"America/Panama",
    "iso:country":"PA",
    "wof:name":"Managua",
    "wof:placetype":"locality",
    "wof:population":16
},
  "geometry": {"coordinates":[-81.47583,7.735],"type":"Point"}
}