{
  "type": "Feature",
  "properties": {
    "gn:admin1_code":"02",
    "gn:asciiname":"La Esperanza",
    "gn:country_code":"PA",
    "gn:dem":188,
    "gn:feature_class":"P",
    "gn:feature_code":"PPL",
    "gn:name":"La Esperanza",
    "gn:population":81,
    "gn:timezone":"America/Panama",
    "iso:country":"PA",
    "wof:name":"La Esperanza",
    "wof:placetype":"locality",
    "wof:population":81
},
  "geometry": {"coordinates":[-82.33188,8.58999],"type":"Point"}
}