{
  "type": "Feature",
  "properties": {
    "gn:admin1_code":"03",
    "gn:asciiname":"Las Delicias",
    "gn:country_code":"PA",
    "gn:dem":257,
    "gn:feature_class":"P",
    "gn:feature_code":"PPL",
    "gn:name":"Las Delicias",
    "gn:population":180,
    "gn:timezone":"America/Panama",
    "iso:country":"PA",
    "name:spa_x_preferred":[
        "Las Delicias"
    ],
    "wof:name":"Las Delicias",
    "wof:placetype":"locality",
    "wof:population":180
},
  "geometry": {"coordinates":[-80.49325,8.64183],"type":"Point"}
}