{
  "type": "Feature",
  "properties": {
    "gn:admin1_code":"13",
    "gn:asciiname":"Monte Claro",
    "gn:country_code":"PA",
    "gn:dem":46,
    "gn:feature_class":"P",
    "gn:feature_code":"PPL",
    "gn:name":"Monte Claro",
    "gn:population":618,
    "gn:timezone":"America/Panama",
    "iso:country":"PA",
    "name:spa_x_preferred":[
        "Monte Claro"
    ],
    "wof:name":"Monte Claro",
    "wof:placetype":"locality",
    "wof:population":618
},
  "geometry": {"coordinates":[-79.66830999999998,8.92874],"type":"Point"}
}