{
  "type": "Feature",
  "properties": {
    "gn:admin1_code":"10",
    "gn:asciiname":"Las Eajitas",
    "gn:country_code":"PA",
    "gn:dem":138,
    "gn:feature_class":"P",
    "gn:feature_code":"PPL",
    "gn:name":"Las Eajitas",
    "gn:population":0,
    "gn:timezone":"America/Panama",
    "iso:country":"PA",
    "wof:name":"Las Eajitas",
    "wof:placetype":"locality"
},
  "geometry": {"coordinates":[-81.25,8.26667],"type":"Point"}
}