{
  "type": "Feature",
  "properties": {
    "gn:admin1_code":"13",
    "gn:asciiname":"El Congal",
    "gn:country_code":"PA",
    "gn:dem":145,
    "gn:feature_class":"P",
    "gn:feature_code":"PPL",
    "gn:name":"El Congal",
    "gn:population":0,
    "gn:timezone":"America/Panama",
    "iso:country":"PA",
    "wof:name":"El Congal",
    "wof:placetype":"locality"
},
  "geometry": {"coordinates":[-79.73333000000002,9.01667],"type":"Point"}
}