{
  "type": "Feature",
  "properties": {
    "gn:admin1_code":"09",
    "gn:asciiname":"Ustupo Yantupo",
    "gn:country_code":"PA",
    "gn:dem":1,
    "gn:feature_class":"P",
    "gn:feature_code":"PPL",
    "gn:name":"Ustupo Yantupo",
    "gn:population":0,
    "gn:timezone":"America/Panama",
    "iso:country":"PA",
    "wof:name":"Ustupo Yantupo",
    "wof:placetype":"locality"
},
  "geometry": {"coordinates":[-77.93333,9.13333],"type":"Point"}
}