{
  "type": "Feature",
  "properties": {
    "gn:admin1_code":"13",
    "gn:asciiname":"El Arenal",
    "gn:country_code":"PA",
    "gn:dem":39,
    "gn:feature_class":"P",
    "gn:feature_code":"PPL",
    "gn:name":"El Arenal",
    "gn:population":178,
    "gn:timezone":"America/Panama",
    "iso:country":"PA",
    "name:ceb_x_preferred":[
        "El Arenal"
    ],
    "name:deu_x_preferred":[
        "El Arenal"
    ],
    "name:epo_x_preferred":[
        "El Arenal"
    ],
    "name:eus_x_preferred":[
        "El Arenal"
    ],
    "name:hun_x_preferred":[
        "El Arenal"
    ],
    "name:nld_x_preferred":[
        "El Arenal"
    ],
    "name:rus_x_preferred":[
        "\u042d\u043b\u044c-\u0410\u0440\u0435\u043d\u0430\u043b\u044c"
    ],
    "name:spa_x_preferred":[
        "El Arenal"
    ],
    "name:srp_x_preferred":[
        "\u0415\u043b \u0410\u0440\u0435\u043d\u0430\u043b"
    ],
    "name:swe_x_preferred":[
        "El Arenal"
    ],
    "name:vie_x_preferred":[
        "El Arenal"
    ],
    "wof:name":"El Arenal",
    "wof:placetype":"locality",
    "wof:population":178
},
  "geometry": {"coordinates":[-79.96666999999999,8.48333],"type":"Point"}
}