{
  "type": "Feature",
  "properties": {
    "gn:admin1_code":"06",
    "gn:asciiname":"La Cal",
    "gn:country_code":"PA",
    "gn:dem":120,
    "gn:feature_class":"P",
    "gn:feature_code":"PPL",
    "gn:name":"La Cal",
    "gn:population":0,
    "gn:timezone":"America/Panama",
    "iso:country":"PA",
    "wof:name":"La Cal",
    "wof:placetype":"locality"
},
  "geometry": {"coordinates":[-80.78333000000001,7.91667],"type":"Point"}
}