{
  "type": "Feature",
  "properties": {
    "gn:admin1_code":"06",
    "gn:asciiname":"Quebro",
    "gn:country_code":"PA",
    "gn:dem":345,
    "gn:feature_class":"P",
    "gn:feature_code":"PPL",
    "gn:name":"Quebro",
    "gn:population":0,
    "gn:timezone":"America/Panama",
    "iso:country":"PA",
    "wof:name":"Quebro",
    "wof:placetype":"locality"
},
  "geometry": {"coordinates":[-80.68333,7.71667],"type":"Point"}
}