{
  "type": "Feature",
  "properties": {
    "gn:admin1_code":"06",
    "gn:asciiname":"Boqueron",
    "gn:country_code":"PA",
    "gn:dem":108,
    "gn:feature_class":"P",
    "gn:feature_code":"PPL",
    "gn:name":"Boquer\u00f3n",
    "gn:population":140,
    "gn:timezone":"America/Panama",
    "iso:country":"PA",
    "name:spa_x_preferred":[
        "Boquer\u00f3n"
    ],
    "wof:name":"Boqueron",
    "wof:placetype":"locality",
    "wof:population":140
},
  "geometry": {"coordinates":[-80.92261999999999,7.87164],"type":"Point"}
}