{
  "type": "Feature",
  "properties": {
    "gn:admin1_code":"09",
    "gn:asciiname":"Masargantupo",
    "gn:cc2":"PA",
    "gn:country_code":"PA",
    "gn:dem":-9999,
    "gn:feature_class":"P",
    "gn:feature_code":"PPL",
    "gn:name":"Masargantupo",
    "gn:population":0,
    "gn:timezone":"America/Panama",
    "iso:country":"PA",
    "name:und_x_variant":[
        "Icaco",
        "Masargantupo"
    ],
    "wof:name":"Masargantupo",
    "wof:placetype":"locality"
},
  "geometry": {"coordinates":[-78.83333,9.56667],"type":"Point"}
}