{
  "type": "Feature",
  "properties": {
    "gn:admin1_code":"02",
    "gn:asciiname":"Barriada Nuevo Amanecer",
    "gn:country_code":"PA",
    "gn:dem":10,
    "gn:feature_class":"P",
    "gn:feature_code":"PPL",
    "gn:name":"Barriada Nuevo Amanecer",
    "gn:population":0,
    "gn:timezone":"America/Panama",
    "iso:country":"PA",
    "name:spa_x_preferred":[
        "Barriada Nuevo Amanecer"
    ],
    "wof:name":"Barriada Nuevo Amanecer",
    "wof:placetype":"locality"
},
  "geometry": {"coordinates":[-82.85514000000001,8.28363],"type":"Point"}
}