{
  "type": "Feature",
  "properties": {
    "gn:admin1_code":"10",
    "gn:asciiname":"Morron",
    "gn:country_code":"PA",
    "gn:dem":14,
    "gn:feature_class":"P",
    "gn:feature_code":"PPL",
    "gn:name":"Morr\u00f3n",
    "gn:population":1,
    "gn:timezone":"America/Panama",
    "iso:country":"PA",
    "wof:name":"Morron",
    "wof:placetype":"locality",
    "wof:population":1
},
  "geometry": {"coordinates":[-81.08166999999997,7.87],"type":"Point"}
}