{
  "type": "Feature",
  "properties": {
    "gn:admin1_code":"03",
    "gn:asciiname":"El Cocal",
    "gn:country_code":"PA",
    "gn:dem":171,
    "gn:feature_class":"P",
    "gn:feature_code":"PPL",
    "gn:name":"El Cocal",
    "gn:population":226,
    "gn:timezone":"America/Panama",
    "iso:country":"PA",
    "name:ita_x_preferred":[
        "El Cocal"
    ],
    "name:spa_x_preferred":[
        "El Cocal"
    ],
    "name:und_x_variant":[
        "Cocal",
        "El Cocal"
    ],
    "name:zho_x_preferred":[
        "\u57c3\u5c14\u79d1\u5361\u5c14"
    ],
    "wof:name":"El Cocal",
    "wof:placetype":"locality",
    "wof:population":226
},
  "geometry": {"coordinates":[-80.28737,8.58973],"type":"Point"}
}