{
  "type": "Feature",
  "properties": {
    "gn:admin1_code":"07",
    "gn:asciiname":"Rodeito",
    "gn:country_code":"PA",
    "gn:dem":65,
    "gn:feature_class":"P",
    "gn:feature_code":"PPL",
    "gn:name":"Rodeito",
    "gn:population":145,
    "gn:timezone":"America/Panama",
    "iso:country":"PA",
    "name:und_x_variant":[
        "Rode\u00edto N\u00famero Uno"
    ],
    "wof:name":"Rodeito",
    "wof:placetype":"locality",
    "wof:population":145
},
  "geometry": {"coordinates":[-80.55634000000001,7.83548],"type":"Point"}
}