{
  "type": "Feature",
  "properties": {
    "gn:admin1_code":"06",
    "gn:asciiname":"El Toro",
    "gn:country_code":"PA",
    "gn:dem":399,
    "gn:feature_class":"P",
    "gn:feature_code":"PPLA3",
    "gn:name":"El Toro",
    "gn:population":176,
    "gn:timezone":"America/Panama",
    "iso:country":"PA",
    "name:spa_x_preferred":[
        "El Toro"
    ],
    "wof:name":"El Toro",
    "wof:placetype":"locality",
    "wof:population":176
},
  "geometry": {"coordinates":[-80.86943000000002,7.7511],"type":"Point"}
}