{
  "type": "Feature",
  "properties": {
    "gn:admin1_code":"13",
    "gn:asciiname":"El Guayabo",
    "gn:country_code":"PA",
    "gn:dem":76,
    "gn:feature_class":"P",
    "gn:feature_code":"PPL",
    "gn:name":"El Guayabo",
    "gn:population":33,
    "gn:timezone":"America/Panama",
    "iso:country":"PA",
    "wof:name":"El Guayabo",
    "wof:placetype":"locality",
    "wof:population":33
},
  "geometry": {"coordinates":[-80.03333000000001,8.46667],"type":"Point"}
}