{
  "type": "Feature",
  "properties": {
    "gn:admin1_code":"06",
    "gn:asciiname":"Rio Senales",
    "gn:country_code":"PA",
    "gn:dem":215,
    "gn:feature_class":"P",
    "gn:feature_code":"PPL",
    "gn:name":"R\u00edo Se\u00f1ales",
    "gn:population":0,
    "gn:timezone":"America/Panama",
    "iso:country":"PA",
    "wof:name":"Rio Senales",
    "wof:placetype":"locality"
},
  "geometry": {"coordinates":[-80.81667,7.88333],"type":"Point"}
}