{
  "type": "Feature",
  "properties": {
    "gn:admin1_code":"08",
    "gn:asciiname":"San Diego",
    "gn:country_code":"PA",
    "gn:dem":25,
    "gn:feature_class":"P",
    "gn:feature_code":"PPL",
    "gn:name":"San Diego",
    "gn:population":323,
    "gn:timezone":"America/Panama",
    "iso:country":"PA",
    "name:spa_x_preferred":[
        "San Diego"
    ],
    "wof:name":"San Diego",
    "wof:placetype":"locality",
    "wof:population":323
},
  "geometry": {"coordinates":[-79.25139,9.10347],"type":"Point"}
}