{
  "type": "Feature",
  "properties": {
    "gn:admin1_code":"01",
    "gn:asciiname":"Junco",
    "gn:country_code":"PA",
    "gn:dem":29,
    "gn:feature_class":"P",
    "gn:feature_code":"PPL",
    "gn:name":"Junco",
    "gn:population":0,
    "gn:timezone":"America/Panama",
    "iso:country":"PA",
    "name:spa_x_preferred":[
        "Junco"
    ],
    "wof:name":"Junco",
    "wof:placetype":"locality"
},
  "geometry": {"coordinates":[-82.51385000000001,9.37312],"type":"Point"}
}