{
  "type": "Feature",
  "properties": {
    "gn:country":"PA",
    "gn:fcode":"PPL",
    "gn:pop":3347,
    "iso:country":"PA",
    "name:spa_x_preferred":[
        "La Herradura"
    ],
    "qs:name":"La Herradura",
    "qs:photos_9r":0,
    "qs:photos_sr":0,
    "qs:pop_sr":"4",
    "wof:name":"La Herradura",
    "wof:placetype":"locality",
    "wof:population":3347
},
  "geometry": {"coordinates":[-79.80722,8.85222],"type":"Point"}
}