{
  "type": "Feature",
  "properties": {
    "gn:admin1_code":"10",
    "gn:asciiname":"Los Manguitos",
    "gn:country_code":"PA",
    "gn:dem":124,
    "gn:feature_class":"P",
    "gn:feature_code":"PPL",
    "gn:name":"Los Manguitos",
    "gn:population":0,
    "gn:timezone":"America/Panama",
    "iso:country":"PA",
    "wof:name":"Los Manguitos",
    "wof:placetype":"locality"
},
  "geometry": {"coordinates":[-81.16667,7.91667],"type":"Point"}
}