{
  "type": "Feature",
  "properties": {
    "gn:admin1_code":"10",
    "gn:asciiname":"Charco Negro",
    "gn:country_code":"PA",
    "gn:dem":69,
    "gn:feature_class":"P",
    "gn:feature_code":"PPL",
    "gn:name":"Charco Negro",
    "gn:population":0,
    "gn:timezone":"America/Panama",
    "iso:country":"PA",
    "wof:name":"Charco Negro",
    "wof:placetype":"locality"
},
  "geometry": {"coordinates":[-81.39667,7.79944],"type":"Point"}
}