{
  "type": "Feature",
  "properties": {
    "gn:admin1_code":"13",
    "gn:asciiname":"Cerro Agudo",
    "gn:country_code":"PA",
    "gn:dem":557,
    "gn:feature_class":"P",
    "gn:feature_code":"PPL",
    "gn:name":"Cerro Agudo",
    "gn:population":16,
    "gn:timezone":"America/Panama",
    "iso:country":"PA",
    "wof:name":"Cerro Agudo",
    "wof:placetype":"locality",
    "wof:population":16
},
  "geometry": {"coordinates":[-80.06483,8.57754],"type":"Point"}
}