{
  "type": "Feature",
  "properties": {
    "gn:admin1_code":"05",
    "gn:asciiname":"Puerto Lara",
    "gn:country_code":"PA",
    "gn:dem":17,
    "gn:feature_class":"P",
    "gn:feature_code":"PPL",
    "gn:name":"Puerto Lara",
    "gn:population":353,
    "gn:timezone":"America/Panama",
    "iso:country":"PA",
    "name:spa_x_preferred":[
        "Puerto Lara"
    ],
    "wof:name":"Puerto Lara",
    "wof:placetype":"locality",
    "wof:population":353
},
  "geometry": {"coordinates":[-78.1467,8.61359],"type":"Point"}
}