{
  "type": "Feature",
  "properties": {
    "gn:admin1_code":"13",
    "gn:asciiname":"Los Mortales",
    "gn:country_code":"PA",
    "gn:dem":167,
    "gn:feature_class":"P",
    "gn:feature_code":"PPL",
    "gn:name":"Los Mortales",
    "gn:population":351,
    "gn:timezone":"America/Panama",
    "iso:country":"PA",
    "name:und_x_variant":[
        "Los Mortales Abajo",
        "Los Mortales"
    ],
    "wof:name":"Los Mortales",
    "wof:placetype":"locality",
    "wof:population":351
},
  "geometry": {"coordinates":[-79.94540000000001,8.84944],"type":"Point"}
}