{
  "type": "Feature",
  "properties": {
    "gn:admin1_code":"04",
    "gn:asciiname":"Valle Escobal",
    "gn:country_code":"PA",
    "gn:dem":131,
    "gn:feature_class":"P",
    "gn:feature_code":"PPL",
    "gn:name":"Valle Escobal",
    "gn:population":77,
    "gn:timezone":"America/Panama",
    "iso:country":"PA",
    "wof:name":"Valle Escobal",
    "wof:placetype":"locality",
    "wof:population":77
},
  "geometry": {"coordinates":[-80.33787,8.94236],"type":"Point"}
}