{
  "type": "Feature",
  "properties": {
    "gn:admin1_code":"10",
    "gn:asciiname":"Canazas",
    "gn:country_code":"PA",
    "gn:dem":68,
    "gn:feature_class":"P",
    "gn:feature_code":"PPL",
    "gn:name":"Ca\u00f1azas",
    "gn:population":0,
    "gn:timezone":"America/Panama",
    "iso:country":"PA",
    "name:und_x_variant":[
        "Ca\u00f1azas",
        "Ca\u00f1azas Arriba"
    ],
    "wof:name":"Canazas",
    "wof:placetype":"locality"
},
  "geometry": {"coordinates":[-80.89784,8.11667],"type":"Point"}
}