{
  "type": "Feature",
  "properties": {
    "gn:admin1_code":"05",
    "gn:asciiname":"El Salto",
    "gn:country_code":"PA",
    "gn:dem":25,
    "gn:feature_class":"P",
    "gn:feature_code":"PPL",
    "gn:name":"El Salto",
    "gn:population":0,
    "gn:timezone":"America/Panama",
    "iso:country":"PA",
    "name:und_x_variant":[
        "El Salto N\u00famero Dos",
        "El Salto"
    ],
    "wof:name":"El Salto",
    "wof:placetype":"locality"
},
  "geometry": {"coordinates":[-78.15788000000001,8.68027],"type":"Point"}
}