{
  "type": "Feature",
  "properties": {
    "gn:admin1_code":"10",
    "gn:asciiname":"La Gallinaza",
    "gn:country_code":"PA",
    "gn:dem":56,
    "gn:feature_class":"P",
    "gn:feature_code":"PPL",
    "gn:name":"La Gallinaza",
    "gn:population":166,
    "gn:timezone":"America/Panama",
    "iso:country":"PA",
    "name:spa_x_preferred":[
        "La Gallinaza"
    ],
    "wof:name":"La Gallinaza",
    "wof:placetype":"locality",
    "wof:population":166
},
  "geometry": {"coordinates":[-80.78735999999998,8.24908],"type":"Point"}
}