{
  "type": "Feature",
  "properties": {
    "gn:admin1_code":"10",
    "gn:asciiname":"Alto de San Juanito",
    "gn:country_code":"PA",
    "gn:dem":400,
    "gn:feature_class":"P",
    "gn:feature_code":"PPL",
    "gn:name":"Alto de San Juanito",
    "gn:population":0,
    "gn:timezone":"America/Panama",
    "iso:country":"PA",
    "wof:name":"Alto de San Juanito",
    "wof:placetype":"locality"
},
  "geometry": {"coordinates":[-81.34639,7.84722],"type":"Point"}
}