{
  "type": "Feature",
  "properties": {
    "gn:admin1_code":"04",
    "gn:asciiname":"El Astillero",
    "gn:country_code":"PA",
    "gn:dem":28,
    "gn:feature_class":"P",
    "gn:feature_code":"PPL",
    "gn:name":"El Astillero",
    "gn:population":0,
    "gn:timezone":"America/Panama",
    "iso:country":"PA",
    "wof:name":"El Astillero",
    "wof:placetype":"locality"
},
  "geometry": {"coordinates":[-79.96666999999999,9.01667],"type":"Point"}
}