{
  "type": "Feature",
  "properties": {
    "gn:admin1_code":"01",
    "gn:asciiname":"Catalina",
    "gn:country_code":"PA",
    "gn:dem":73,
    "gn:feature_class":"P",
    "gn:feature_code":"PPL",
    "gn:name":"Catalina",
    "gn:population":0,
    "gn:timezone":"America/Panama",
    "iso:country":"PA",
    "wof:name":"Catalina",
    "wof:placetype":"locality"
},
  "geometry": {"coordinates":[-82.18333,8.86667],"type":"Point"}
}