{
  "type": "Feature",
  "properties": {
    "gn:admin1_code":"01",
    "gn:asciiname":"Catalina",
    "gn:country_code":"PA",
    "gn:dem":73,
    "gn:feature_class":"P",
    "gn:feature_code":"PPL",
    "gn:name":"Catalina",
    "gn:population":0,
    "gn:timezone":"America/Panama",
    "iso:country":"PA",
    "name:bre_x_preferred":[
        "Catalina"
    ],
    "name:cat_x_preferred":[
        "Catalina"
    ],
    "name:ceb_x_preferred":[
        "Catalina"
    ],
    "name:ces_x_preferred":[
        "Catalina"
    ],
    "name:deu_x_preferred":[
        "Catalina"
    ],
    "name:epo_x_preferred":[
        "Catalina"
    ],
    "name:fin_x_preferred":[
        "Catalina"
    ],
    "name:fra_x_preferred":[
        "Catalina"
    ],
    "name:heb_x_preferred":[
        "\u05e7\u05d8\u05dc\u05d9\u05e0\u05d4"
    ],
    "name:ita_x_preferred":[
        "Catalina"
    ],
    "name:kor_x_preferred":[
        "\uce74\ud0c8\ub9ac\ub098"
    ],
    "name:nld_x_preferred":[
        "Catalina"
    ],
    "name:pol_x_preferred":[
        "Catalina"
    ],
    "name:por_x_preferred":[
        "Catalina"
    ],
    "name:rus_x_preferred":[
        "\u041a\u0430\u0442\u0430\u043b\u0438\u043d\u0430"
    ],
    "name:spa_x_preferred":[
        "Catalina"
    ],
    "name:swe_x_preferred":[
        "Catalina"
    ],
    "name:ukr_x_preferred":[
        "\u041a\u0430\u0442\u0430\u043b\u0456\u043d\u0430"
    ],
    "wof:name":"Catalina",
    "wof:placetype":"locality"
},
  "geometry": {"coordinates":[-82.18333,8.86667],"type":"Point"}
}