{
  "type": "Feature",
  "properties": {
    "gn:admin1_code":"02",
    "gn:asciiname":"La Meseta",
    "gn:country_code":"PA",
    "gn:dem":336,
    "gn:feature_class":"P",
    "gn:feature_code":"PPL",
    "gn:name":"La Meseta",
    "gn:population":691,
    "gn:timezone":"America/Panama",
    "iso:country":"PA",
    "name:spa_x_preferred":[
        "La Meseta"
    ],
    "wof:name":"La Meseta",
    "wof:placetype":"locality",
    "wof:population":691
},
  "geometry": {"coordinates":[-82.59489000000001,8.5532],"type":"Point"}
}