{
  "type": "Feature",
  "properties": {
    "gn:admin1_code":"07",
    "gn:asciiname":"Los Gomez",
    "gn:country_code":"PA",
    "gn:dem":152,
    "gn:feature_class":"P",
    "gn:feature_code":"PPL",
    "gn:name":"Los G\u00f3mez",
    "gn:population":0,
    "gn:timezone":"America/Panama",
    "iso:country":"PA",
    "wof:name":"Los Gomez",
    "wof:placetype":"locality"
},
  "geometry": {"coordinates":[-80.16667,7.56667],"type":"Point"}
}