{
  "type": "Feature",
  "properties": {
    "gn:admin1_code":"05",
    "gn:asciiname":"Coiba",
    "gn:country_code":"PA",
    "gn:dem":13,
    "gn:feature_class":"P",
    "gn:feature_code":"PPL",
    "gn:name":"Coiba",
    "gn:population":0,
    "gn:timezone":"America/Panama",
    "iso:country":"PA",
    "name:ces_x_preferred":[
        "Coiba"
    ],
    "name:deu_x_preferred":[
        "Nationalpark Coiba"
    ],
    "name:fra_x_preferred":[
        "\u00cele Coiba"
    ],
    "name:glg_x_preferred":[
        "Coiba"
    ],
    "name:heb_x_preferred":[
        "\u05e7\u05d5\u05d9\u05d1\u05d4"
    ],
    "name:hrv_x_preferred":[
        "Coiba"
    ],
    "name:jpn_x_preferred":[
        "\u30b3\u30a4\u30d0\u5cf6"
    ],
    "name:lit_x_preferred":[
        "Koiba"
    ],
    "name:mal_x_preferred":[
        "\u0d15\u0d4a\u0d2f\u0d3f\u0d2c"
    ],
    "name:por_x_preferred":[
        "Coiba"
    ],
    "name:rus_x_preferred":[
        "\u041a\u043e\u0439\u0431\u0430"
    ],
    "name:slk_x_preferred":[
        "Coiba"
    ],
    "name:swe_x_preferred":[
        "Coiba"
    ],
    "name:tur_x_preferred":[
        "Coiba"
    ],
    "name:vie_x_preferred":[
        "Coiba"
    ],
    "name:zho_x_preferred":[
        "\u79d1\u4f0a\u74e6\u5cf6"
    ],
    "wof:name":"Coiba",
    "wof:placetype":"locality"
},
  "geometry": {"coordinates":[-78.13374,8.58002],"type":"Point"}
}