{
  "type": "Feature",
  "properties": {
    "gn:admin1_code":"08",
    "gn:asciiname":"Las Huacas",
    "gn:cc2":"PA",
    "gn:country_code":"PA",
    "gn:dem":33,
    "gn:feature_class":"P",
    "gn:feature_code":"PPL",
    "gn:name":"Las Huacas",
    "gn:population":0,
    "gn:timezone":"America/Panama",
    "iso:country":"PA",
    "name:ceb_x_preferred":[
        "Las Huacas"
    ],
    "name:spa_x_preferred":[
        "Las Huacas"
    ],
    "name:swe_x_preferred":[
        "Las Huacas"
    ],
    "name:und_x_variant":[
        "La Huaca",
        "Las Guacas"
    ],
    "wof:name":"Las Huacas",
    "wof:placetype":"locality"
},
  "geometry": {"coordinates":[-79.65000000000001,9.18333],"type":"Point"}
}