{
  "type": "Feature",
  "properties": {
    "gn:admin1_code":"02",
    "gn:asciiname":"Brazos de Gariche",
    "gn:country_code":"PA",
    "gn:dem":1016,
    "gn:feature_class":"P",
    "gn:feature_code":"PPL",
    "gn:name":"Brazos de Garich\u00e9",
    "gn:population":149,
    "gn:timezone":"America/Panama",
    "iso:country":"PA",
    "name:und_x_variant":[
        "Brazo de Garich\u00e9",
        "Brazos de Garich\u00e9"
    ],
    "wof:name":"Brazos de Gariche",
    "wof:placetype":"locality",
    "wof:population":149
},
  "geometry": {"coordinates":[-82.66904,8.7062],"type":"Point"}
}