{
  "type": "Feature",
  "properties": {
    "gn:admin1_code":"06",
    "gn:asciiname":"El Espinito",
    "gn:country_code":"PA",
    "gn:dem":74,
    "gn:feature_class":"P",
    "gn:feature_code":"PPL",
    "gn:name":"El Espin\u00edto",
    "gn:population":109,
    "gn:timezone":"America/Panama",
    "iso:country":"PA",
    "name:spa_x_preferred":[
        "El Espin\u00edto"
    ],
    "wof:name":"El Espinito",
    "wof:placetype":"locality",
    "wof:population":109
},
  "geometry": {"coordinates":[-80.78992,8.05476],"type":"Point"}
}