{
  "type": "Feature",
  "properties": {
    "gn:admin1_code":"10",
    "gn:asciiname":"El Cacao",
    "gn:country_code":"PA",
    "gn:dem":21,
    "gn:feature_class":"P",
    "gn:feature_code":"PPL",
    "gn:name":"El Cacao",
    "gn:population":141,
    "gn:timezone":"America/Panama",
    "iso:country":"PA",
    "name:ita_x_preferred":[
        "El Cacao"
    ],
    "name:spa_x_preferred":[
        "El Cacao"
    ],
    "name:und_x_variant":[
        "Cacao"
    ],
    "name:zho_x_preferred":[
        "\u57c3\u5c14\u53ef\u53ef"
    ],
    "wof:name":"El Cacao",
    "wof:placetype":"locality",
    "wof:population":141
},
  "geometry": {"coordinates":[-80.87130000000001,7.34138],"type":"Point"}
}