{
  "type": "Feature",
  "properties": {
    "gn:admin1_code":"13",
    "gn:asciiname":"El Celaje",
    "gn:country_code":"PA",
    "gn:dem":27,
    "gn:feature_class":"P",
    "gn:feature_code":"PPL",
    "gn:name":"El Celaje",
    "gn:population":0,
    "gn:timezone":"America/Panama",
    "iso:country":"PA",
    "name:und_x_variant":[
        "Celaje",
        "El Celaje"
    ],
    "wof:name":"El Celaje",
    "wof:placetype":"locality"
},
  "geometry": {"coordinates":[-79.90000000000001,8.58333],"type":"Point"}
}