{
  "type": "Feature",
  "properties": {
    "gn:admin1_code":"02",
    "gn:asciiname":"Brazo de Cochea",
    "gn:country_code":"PA",
    "gn:dem":849,
    "gn:feature_class":"P",
    "gn:feature_code":"PPL",
    "gn:name":"Brazo de Cochea",
    "gn:population":77,
    "gn:timezone":"America/Panama",
    "iso:country":"PA",
    "name:spa_x_preferred":[
        "Brazo de Cochea"
    ],
    "wof:name":"Brazo de Cochea",
    "wof:placetype":"locality",
    "wof:population":77
},
  "geometry": {"coordinates":[-82.47136,8.70165],"type":"Point"}
}