{
  "type": "Feature",
  "properties": {
    "gn:admin1_code":"07",
    "gn:asciiname":"Planes del Canaveral",
    "gn:country_code":"PA",
    "gn:dem":127,
    "gn:feature_class":"P",
    "gn:feature_code":"PPL",
    "gn:name":"Planes del Ca\u00f1averal",
    "gn:population":0,
    "gn:timezone":"America/Panama",
    "iso:country":"PA",
    "wof:name":"Planes del Canaveral",
    "wof:placetype":"locality"
},
  "geometry": {"coordinates":[-80.16667,7.45],"type":"Point"}
}