{
  "type": "Feature",
  "properties": {
    "gn:admin1_code":"06",
    "gn:asciiname":"Las Planetas",
    "gn:cc2":"PA",
    "gn:country_code":"PA",
    "gn:dem":509,
    "gn:feature_class":"P",
    "gn:feature_code":"PPL",
    "gn:name":"Las Planetas",
    "gn:population":0,
    "gn:timezone":"America/Panama",
    "iso:country":"PA",
    "name:und_x_variant":[
        "Rio Mariato",
        "Los Planetas",
        "Las Planetas"
    ],
    "wof:name":"Las Planetas",
    "wof:placetype":"locality"
},
  "geometry": {"coordinates":[-80.83333,7.66667],"type":"Point"}
}