{
  "type": "Feature",
  "properties": {
    "gn:admin1_code":"10",
    "gn:asciiname":"Las Animas",
    "gn:country_code":"PA",
    "gn:dem":155,
    "gn:feature_class":"P",
    "gn:feature_code":"PPL",
    "gn:name":"Las \u00c1nimas",
    "gn:population":0,
    "gn:timezone":"America/Panama",
    "iso:country":"PA",
    "wof:name":"Las Animas",
    "wof:placetype":"locality"
},
  "geometry": {"coordinates":[-81.16667,8.15],"type":"Point"}
}