{
  "type": "Feature",
  "properties": {
    "gn:admin1_code":"11",
    "gn:asciiname":"Boca de Pavarando",
    "gn:country_code":"PA",
    "gn:dem":54,
    "gn:feature_class":"P",
    "gn:feature_code":"PPL",
    "gn:name":"Boca de Pavarand\u00f3",
    "gn:population":0,
    "gn:timezone":"America/Panama",
    "iso:country":"PA",
    "wof:name":"Boca de Pavarando",
    "wof:placetype":"locality"
},
  "geometry": {"coordinates":[-78.04472,7.825],"type":"Point"}
}