{
  "type": "Feature",
  "properties": {
    "gn:admin1_code":"10",
    "gn:asciiname":"La Estancia",
    "gn:country_code":"PA",
    "gn:dem":26,
    "gn:feature_class":"P",
    "gn:feature_code":"PPL",
    "gn:name":"La Estancia",
    "gn:population":0,
    "gn:timezone":"America/Panama",
    "iso:country":"PA",
    "name:ceb_x_preferred":[
        "La Estancia"
    ],
    "name:deu_x_preferred":[
        "La Estancia"
    ],
    "name:spa_x_preferred":[
        "La Estancia"
    ],
    "name:swe_x_preferred":[
        "La Estancia"
    ],
    "wof:name":"La Estancia",
    "wof:placetype":"locality"
},
  "geometry": {"coordinates":[-81.58166999999997,7.94639],"type":"Point"}
}