{
  "type": "Feature",
  "properties": {
    "gn:admin1_code":"13",
    "gn:asciiname":"El Penon",
    "gn:country_code":"PA",
    "gn:dem":87,
    "gn:feature_class":"P",
    "gn:feature_code":"PPL",
    "gn:name":"El Pe\u00f1\u00f3n",
    "gn:population":1,
    "gn:timezone":"America/Panama",
    "iso:country":"PA",
    "wof:name":"El Penon",
    "wof:placetype":"locality",
    "wof:population":1
},
  "geometry": {"coordinates":[-79.88333,8.68333],"type":"Point"}
}