{
  "type": "Feature",
  "properties": {
    "gn:admin1_code":"10",
    "gn:asciiname":"Los Mangos",
    "gn:country_code":"PA",
    "gn:dem":190,
    "gn:feature_class":"P",
    "gn:feature_code":"PPL",
    "gn:name":"Los Mangos",
    "gn:population":34,
    "gn:timezone":"America/Panama",
    "iso:country":"PA",
    "wof:name":"Los Mangos",
    "wof:placetype":"locality",
    "wof:population":34
},
  "geometry": {"coordinates":[-81.28399999999998,8.311],"type":"Point"}
}