{
  "type": "Feature",
  "properties": {
    "gn:admin1_code":"03",
    "gn:asciiname":"Pajonal Abajo",
    "gn:country_code":"PA",
    "gn:dem":212,
    "gn:feature_class":"P",
    "gn:feature_code":"PPL",
    "gn:name":"Pajonal Abajo",
    "gn:population":676,
    "gn:timezone":"America/Panama",
    "iso:country":"PA",
    "name:spa_x_preferred":[
        "Pajonal Abajo"
    ],
    "wof:name":"Pajonal Abajo",
    "wof:placetype":"locality",
    "wof:population":676
},
  "geometry": {"coordinates":[-80.25832,8.58529],"type":"Point"}
}