{
  "type": "Feature",
  "properties": {
    "gn:admin1_code":"03",
    "gn:asciiname":"Aguacate",
    "gn:country_code":"PA",
    "gn:dem":372,
    "gn:feature_class":"P",
    "gn:feature_code":"PPL",
    "gn:name":"Aguacate",
    "gn:population":0,
    "gn:timezone":"America/Panama",
    "iso:country":"PA",
    "wof:name":"Aguacate",
    "wof:placetype":"locality"
},
  "geometry": {"coordinates":[-80.09999999999999,8.53333],"type":"Point"}
}