{
  "type": "Feature",
  "properties": {
    "gn:admin1_code":"07",
    "gn:asciiname":"Las Vergaras",
    "gn:cc2":"PA",
    "gn:country_code":"PA",
    "gn:dem":38,
    "gn:feature_class":"P",
    "gn:feature_code":"PPL",
    "gn:name":"Las Vergaras",
    "gn:population":0,
    "gn:timezone":"America/Panama",
    "iso:country":"PA",
    "name:und_x_variant":[
        "Las Veragaras",
        "Las Vergaras"
    ],
    "wof:name":"Las Vergaras",
    "wof:placetype":"locality"
},
  "geometry": {"coordinates":[-80.11343000000002,7.65318],"type":"Point"}
}