{
  "type": "Feature",
  "properties": {
    "gn:admin1_code":"03",
    "gn:asciiname":"La Cotava Abajo",
    "gn:cc2":"PA",
    "gn:country_code":"PA",
    "gn:dem":50,
    "gn:feature_class":"P",
    "gn:feature_code":"PPL",
    "gn:name":"La Cotava Abajo",
    "gn:population":0,
    "gn:timezone":"America/Panama",
    "iso:country":"PA",
    "name:und_x_variant":[
        "Cotava Abajo",
        "La Cotava Abajo"
    ],
    "wof:name":"La Cotava Abajo",
    "wof:placetype":"locality"
},
  "geometry": {"coordinates":[-80.71666999999999,8.21667],"type":"Point"}
}