{
  "type": "Feature",
  "properties": {
    "gn:admin1_code":"10",
    "gn:asciiname":"Los Barriales",
    "gn:country_code":"PA",
    "gn:dem":109,
    "gn:feature_class":"P",
    "gn:feature_code":"PPL",
    "gn:name":"Los Barriales",
    "gn:population":0,
    "gn:timezone":"America/Panama",
    "iso:country":"PA",
    "name:und_x_variant":[
        "Cerro In\u00e9s",
        "Los Barriales"
    ],
    "wof:name":"Los Barriales",
    "wof:placetype":"locality"
},
  "geometry": {"coordinates":[-81.01209,8.10146],"type":"Point"}
}