{
  "type": "Feature",
  "properties": {
    "gn:admin1_code":"05",
    "gn:asciiname":"Boca de Sabalo",
    "gn:cc2":"PA",
    "gn:country_code":"PA",
    "gn:dem":10,
    "gn:feature_class":"P",
    "gn:feature_code":"PPL",
    "gn:name":"Boca de S\u00e1balo",
    "gn:population":0,
    "gn:timezone":"America/Panama",
    "iso:country":"PA",
    "name:und_x_variant":[
        "Sabolo",
        "S\u00e1boli",
        "S\u00e1balo",
        "Boca de S\u00e1balo"
    ],
    "wof:name":"Boca de Sabalo",
    "wof:placetype":"locality"
},
  "geometry": {"coordinates":[-78.21772,8.0339],"type":"Point"}
}