{
  "type": "Feature",
  "properties": {
    "gn:admin1_code":"10",
    "gn:asciiname":"Los Zahinos",
    "gn:country_code":"PA",
    "gn:dem":73,
    "gn:feature_class":"P",
    "gn:feature_code":"PPL",
    "gn:name":"Los Zahinos",
    "gn:population":0,
    "gn:timezone":"America/Panama",
    "iso:country":"PA",
    "wof:name":"Los Zahinos",
    "wof:placetype":"locality"
},
  "geometry": {"coordinates":[-81.42083000000002,7.81278],"type":"Point"}
}