{
  "type": "Feature",
  "properties": {
    "gn:admin1_code":"12",
    "gn:asciiname":"Guayabo",
    "gn:country_code":"PA",
    "gn:dem":1237,
    "gn:feature_class":"P",
    "gn:feature_code":"PPL",
    "gn:name":"Guayabo",
    "gn:population":0,
    "gn:timezone":"America/Panama",
    "iso:country":"PA",
    "name:spa_x_preferred":[
        "Guayabo"
    ],
    "wof:name":"Guayabo",
    "wof:placetype":"locality"
},
  "geometry": {"coordinates":[-81.65550999999998,8.52507],"type":"Point"}
}