{
  "type": "Feature",
  "properties": {
    "gn:admin1_code":"03",
    "gn:asciiname":"Larguillo Arriba",
    "gn:country_code":"PA",
    "gn:dem":299,
    "gn:feature_class":"P",
    "gn:feature_code":"PPL",
    "gn:name":"Larguillo Arriba",
    "gn:population":0,
    "gn:timezone":"America/Panama",
    "iso:country":"PA",
    "wof:name":"Larguillo Arriba",
    "wof:placetype":"locality"
},
  "geometry": {"coordinates":[-80.21666999999999,8.66667],"type":"Point"}
}