{
  "type": "Feature",
  "properties": {
    "gn:admin1_code":"10",
    "gn:asciiname":"Puerto Orlas",
    "gn:cc2":"PA",
    "gn:country_code":"PA",
    "gn:dem":9,
    "gn:feature_class":"P",
    "gn:feature_code":"PPL",
    "gn:name":"Puerto Orlas",
    "gn:population":0,
    "gn:timezone":"America/Panama",
    "iso:country":"PA",
    "name:und_x_variant":[
        "Puerto Orla",
        "Puerto Orlas"
    ],
    "wof:name":"Puerto Orlas",
    "wof:placetype":"locality"
},
  "geometry": {"coordinates":[-81.19639000000002,7.94667],"type":"Point"}
}