{
  "type": "Feature",
  "properties": {
    "gn:admin1_code":"12",
    "gn:asciiname":"Cerro Iglesias",
    "gn:country_code":"PA",
    "gn:dem":369,
    "gn:feature_class":"P",
    "gn:feature_code":"PPLA2",
    "gn:name":"Cerro Iglesias",
    "gn:population":0,
    "gn:timezone":"America/Panama",
    "iso:country":"PA",
    "name:spa_x_preferred":[
        "Cerro Iglesias"
    ],
    "name:und_x_variant":[
        "Cerro Iglesia"
    ],
    "wof:name":"Cerro Iglesias",
    "wof:placetype":"locality"
},
  "geometry": {"coordinates":[-81.79804,8.28523],"type":"Point"}
}