{
  "type": "Feature",
  "properties": {
    "gn:admin1_code":"02",
    "gn:asciiname":"Bajo Negro",
    "gn:country_code":"PA",
    "gn:dem":182,
    "gn:feature_class":"P",
    "gn:feature_code":"PPL",
    "gn:name":"Bajo Negro",
    "gn:population":0,
    "gn:timezone":"America/Panama",
    "iso:country":"PA",
    "wof:name":"Bajo Negro",
    "wof:placetype":"locality"
},
  "geometry": {"coordinates":[-82.28333000000001,8.55],"type":"Point"}
}