{
  "type": "Feature",
  "properties": {
    "gn:admin1_code":"07",
    "gn:asciiname":"Chara",
    "gn:country_code":"PA",
    "gn:dem":13,
    "gn:feature_class":"P",
    "gn:feature_code":"PPL",
    "gn:name":"Chara",
    "gn:population":0,
    "gn:timezone":"America/Panama",
    "iso:country":"PA",
    "wof:name":"Chara",
    "wof:placetype":"locality"
},
  "geometry": {"coordinates":[-80.40000000000001,7.41667],"type":"Point"}
}