{
  "type": "Feature",
  "properties": {
    "iso:country":"PA",
    "name:ceb_x_preferred":[
        "Escobal"
    ],
    "name:eng_x_preferred":[
        "Escobal"
    ],
    "name:ita_x_preferred":[
        "Escobal"
    ],
    "name:nld_x_preferred":[
        "Escobal"
    ],
    "name:spa_x_preferred":[
        "Escobal"
    ],
    "name:zho_x_preferred":[
        "\u57c3\u65af\u79d1\u74e6\u5c14"
    ],
    "qs:gn_country":"PA",
    "qs:gn_fcode":"PPL",
    "qs:gn_pop":1790,
    "qs:name":"Escobal",
    "qs:name_adm0":"Panam\u00e1",
    "qs:name_adm1":"Col\u00f3n",
    "qs:photos":0,
    "qs:photos_1k":0,
    "qs:photos_9k":1,
    "qs:photos_9r":4,
    "qs:photos_all":185,
    "qs:photos_sr":0,
    "qs:placetype":"LocalAdmin",
    "qs:pop_sr":"3",
    "qs:woe_adm0":23424924,
    "wd:wordcount":84,
    "wof:name":"Escobal",
    "wof:placetype":"localadmin",
    "wof:population":1790
},
  "geometry": {"coordinates":[-79.96194,9.14722],"type":"Point"}
}