{
  "type": "Feature",
  "properties": {
    "gn:admin1_code":"09",
    "gn:asciiname":"Arritupo",
    "gn:country_code":"PA",
    "gn:dem":-9999,
    "gn:feature_class":"P",
    "gn:feature_code":"PPL",
    "gn:name":"Arritupo",
    "gn:population":0,
    "gn:timezone":"America/Panama",
    "iso:country":"PA",
    "name:und_x_variant":[
        "Arritupo N\u00famero Uno",
        "Arritupo"
    ],
    "wof:name":"Arritupo",
    "wof:placetype":"locality"
},
  "geometry": {"coordinates":[-79.02459,9.4979],"type":"Point"}
}