{
  "type": "Feature",
  "properties": {
    "gn:admin1_code":"10",
    "gn:asciiname":"Quebrada Conga",
    "gn:country_code":"PA",
    "gn:dem":367,
    "gn:feature_class":"P",
    "gn:feature_code":"PPL",
    "gn:name":"Quebrada Conga",
    "gn:population":0,
    "gn:timezone":"America/Panama",
    "iso:country":"PA",
    "wof:name":"Quebrada Conga",
    "wof:placetype":"locality"
},
  "geometry": {"coordinates":[-81.56667,8.11667],"type":"Point"}
}