{
  "type": "Feature",
  "properties": {
    "gn:admin1_code":"03",
    "gn:asciiname":"Boca de Toabre",
    "gn:country_code":"PA",
    "gn:dem":14,
    "gn:feature_class":"P",
    "gn:feature_code":"PPL",
    "gn:name":"Boca de Toabr\u00e9",
    "gn:population":0,
    "gn:timezone":"America/Panama",
    "iso:country":"PA",
    "name:spa_x_preferred":[
        "Boca de Toabr\u00e9"
    ],
    "wof:name":"Boca de Toabre",
    "wof:placetype":"locality"
},
  "geometry": {"coordinates":[-80.53264,8.94061],"type":"Point"}
}