{
  "type": "Feature",
  "properties": {
    "gn:admin1_code":"10",
    "gn:admin2_code":"966.0",
    "gn:asciiname":"Pueblo Nuevo de Sona",
    "gn:country_code":"PA",
    "gn:dem":14,
    "gn:feature_class":"P",
    "gn:feature_code":"PPL",
    "gn:name":"Pueblo Nuevo de Sona",
    "gn:population":0,
    "gn:timezone":"America/Panama",
    "iso:country":"PA",
    "name:und_x_variant":[
        "Pueblo Nuevo de Son\u00e1",
        "Pueblo Nuevo"
    ],
    "wof:name":"Pueblo Nuevo de Sona",
    "wof:placetype":"locality"
},
  "geometry": {"coordinates":[-81.31278,7.99934],"type":"Point"}
}