{
  "type": "Feature",
  "properties": {
    "gn:admin1_code":"10",
    "gn:asciiname":"Cerro Gato",
    "gn:country_code":"PA",
    "gn:dem":352,
    "gn:feature_class":"P",
    "gn:feature_code":"PPL",
    "gn:name":"Cerro Gato",
    "gn:population":18,
    "gn:timezone":"America/Panama",
    "iso:country":"PA",
    "wof:name":"Cerro Gato",
    "wof:placetype":"locality",
    "wof:population":18
},
  "geometry": {"coordinates":[-81.53333000000001,8.11667],"type":"Point"}
}