{
  "type": "Feature",
  "properties": {
    "gn:admin1_code":"04",
    "gn:asciiname":"Boca de Mosquera",
    "gn:country_code":"PA",
    "gn:dem":10,
    "gn:feature_class":"P",
    "gn:feature_code":"PPL",
    "gn:name":"Boca de Mosquera",
    "gn:population":0,
    "gn:timezone":"America/Panama",
    "iso:country":"PA",
    "wof:name":"Boca de Mosquera",
    "wof:placetype":"locality"
},
  "geometry": {"coordinates":[-80.08333,9.18333],"type":"Point"}
}