{
  "type": "Feature",
  "properties": {
    "gn:admin1_code":"10",
    "gn:asciiname":"El Horcon",
    "gn:country_code":"PA",
    "gn:dem":100,
    "gn:feature_class":"P",
    "gn:feature_code":"PPL",
    "gn:name":"El Horc\u00f3n",
    "gn:population":0,
    "gn:timezone":"America/Panama",
    "iso:country":"PA",
    "wof:name":"El Horcon",
    "wof:placetype":"locality"
},
  "geometry": {"coordinates":[-81.25,8.28333],"type":"Point"}
}