{
  "type": "Feature",
  "properties": {
    "gn:admin1_code":"01",
    "gn:asciiname":"Barranquilla Numero Dos",
    "gn:country_code":"PA",
    "gn:dem":91,
    "gn:feature_class":"P",
    "gn:feature_code":"PPL",
    "gn:name":"Barranquilla N\u00famero Dos",
    "gn:population":0,
    "gn:timezone":"America/Panama",
    "iso:country":"PA",
    "name:spa_x_preferred":[
        "Barranquilla N\u00famero Dos"
    ],
    "name:und_x_variant":[
        "Barranquila",
        "Barranquilla"
    ],
    "wof:name":"Barranquilla Numero Dos",
    "wof:placetype":"locality"
},
  "geometry": {"coordinates":[-82.2033,8.91835],"type":"Point"}
}