{
  "type": "Feature",
  "properties": {
    "gn:admin1_code":"08",
    "gn:asciiname":"Alcatriz",
    "gn:country_code":"PA",
    "gn:dem":172,
    "gn:feature_class":"P",
    "gn:feature_code":"PPL",
    "gn:name":"Alcatriz",
    "gn:population":65,
    "gn:timezone":"America/Panama",
    "iso:country":"PA",
    "name:spa_x_preferred":[
        "Alcatriz"
    ],
    "wof:name":"Alcatriz",
    "wof:placetype":"locality",
    "wof:population":65
},
  "geometry": {"coordinates":[-78.57355,9.00186],"type":"Point"}
}