{
  "type": "Feature",
  "properties": {
    "gn:admin1_code":"05",
    "gn:asciiname":"Lagarto",
    "gn:country_code":"PA",
    "gn:dem":20,
    "gn:feature_class":"P",
    "gn:feature_code":"PPL",
    "gn:name":"Lagarto",
    "gn:population":0,
    "gn:timezone":"America/Panama",
    "iso:country":"PA",
    "wof:name":"Lagarto",
    "wof:placetype":"locality"
},
  "geometry": {"coordinates":[-78.15128,8.47626],"type":"Point"}
}