{
  "type": "Feature",
  "properties": {
    "gn:admin1_code":"05",
    "gn:asciiname":"Lagarto",
    "gn:country_code":"PA",
    "gn:dem":20,
    "gn:feature_class":"P",
    "gn:feature_code":"PPL",
    "gn:name":"Lagarto",
    "gn:population":0,
    "gn:timezone":"America/Panama",
    "iso:country":"PA",
    "name:bpy_x_preferred":[
        "\u09b2\u09be\u0997\u09be\u09b0\u09cd\u099f\u09cb"
    ],
    "name:ceb_x_preferred":[
        "Lagarto"
    ],
    "name:deu_x_preferred":[
        "Lagarto"
    ],
    "name:glg_x_preferred":[
        "Lagarto"
    ],
    "name:ita_x_preferred":[
        "Lagarto"
    ],
    "name:mlg_x_preferred":[
        "Lagarto"
    ],
    "name:por_x_preferred":[
        "Lagarto"
    ],
    "name:sco_x_preferred":[
        "Lagarto"
    ],
    "name:spa_x_preferred":[
        "Lagarto"
    ],
    "name:swe_x_preferred":[
        "Lagarto"
    ],
    "name:vie_x_preferred":[
        "Lagarto"
    ],
    "wof:name":"Lagarto",
    "wof:placetype":"locality"
},
  "geometry": {"coordinates":[-78.15128,8.47626],"type":"Point"}
}