{
  "type": "Feature",
  "properties": {
    "gn:admin1_code":"12",
    "gn:asciiname":"El Cedro Abajo",
    "gn:country_code":"PA",
    "gn:dem":213,
    "gn:feature_class":"P",
    "gn:feature_code":"PPL",
    "gn:name":"El Cedro Abajo",
    "gn:population":0,
    "gn:timezone":"America/Panama",
    "iso:country":"PA",
    "name:spa_x_preferred":[
        "El Cedro Abajo"
    ],
    "wof:name":"El Cedro Abajo",
    "wof:placetype":"locality"
},
  "geometry": {"coordinates":[-82.30762,9.09323],"type":"Point"}
}