{
  "type": "Feature",
  "properties": {
    "gn:admin1_code":"02",
    "gn:asciiname":"Gomez Abajo",
    "gn:country_code":"PA",
    "gn:dem":320,
    "gn:feature_class":"P",
    "gn:feature_code":"PPL",
    "gn:name":"G\u00f3mez Abajo",
    "gn:population":480,
    "gn:timezone":"America/Panama",
    "iso:country":"PA",
    "name:spa_x_preferred":[
        "G\u00f3mez Abajo"
    ],
    "wof:name":"Gomez Abajo",
    "wof:placetype":"locality",
    "wof:population":480
},
  "geometry": {"coordinates":[-82.72417,8.54756],"type":"Point"}
}