{
  "type": "Feature",
  "properties": {
    "gn:admin1_code":"10",
    "gn:asciiname":"Espino del Cobre",
    "gn:cc2":"PA",
    "gn:country_code":"PA",
    "gn:dem":49,
    "gn:feature_class":"P",
    "gn:feature_code":"PPL",
    "gn:name":"Espino del Cobre",
    "gn:population":0,
    "gn:timezone":"America/Panama",
    "iso:country":"PA",
    "name:und_x_variant":[
        "El Espino",
        "Espino del Cobre"
    ],
    "wof:name":"Espino del Cobre",
    "wof:placetype":"locality"
},
  "geometry": {"coordinates":[-81.36667,8.05],"type":"Point"}
}