{
  "type": "Feature",
  "properties": {
    "gn:admin1_code":"02",
    "gn:asciiname":"Potrero de Cana",
    "gn:country_code":"PA",
    "gn:dem":456,
    "gn:feature_class":"P",
    "gn:feature_code":"PPLA3",
    "gn:name":"Potrero de Ca\u00f1a",
    "gn:population":0,
    "gn:timezone":"America/Panama",
    "iso:country":"PA",
    "name:spa_x_preferred":[
        "Potrero de Ca\u00f1a"
    ],
    "wof:name":"Potrero de Cana",
    "wof:placetype":"locality"
},
  "geometry": {"coordinates":[-81.69903000000002,8.29345],"type":"Point"}
}