{
  "type": "Feature",
  "properties": {
    "gn:admin1_code":"10",
    "gn:asciiname":"El Guabo",
    "gn:country_code":"PA",
    "gn:dem":38,
    "gn:feature_class":"P",
    "gn:feature_code":"PPL",
    "gn:name":"El Guabo",
    "gn:population":0,
    "gn:timezone":"America/Panama",
    "iso:country":"PA",
    "name:ceb_x_preferred":[
        "El Guabo"
    ],
    "name:ita_x_preferred":[
        "El Guabo"
    ],
    "name:spa_x_preferred":[
        "El Guabo"
    ],
    "name:swe_x_preferred":[
        "El Guabo"
    ],
    "wof:name":"El Guabo",
    "wof:placetype":"locality"
},
  "geometry": {"coordinates":[-81.20194000000002,7.78083],"type":"Point"}
}