{
  "type": "Feature",
  "properties": {
    "gn:admin1_code":"07",
    "gn:asciiname":"Ave Maria",
    "gn:country_code":"PA",
    "gn:dem":41,
    "gn:feature_class":"P",
    "gn:feature_code":"PPLA3",
    "gn:name":"Ave Mar\u00eda",
    "gn:population":120,
    "gn:timezone":"America/Panama",
    "iso:country":"PA",
    "name:spa_x_preferred":[
        "Ave Mar\u00eda"
    ],
    "wof:name":"Ave Maria",
    "wof:placetype":"locality",
    "wof:population":120
},
  "geometry": {"coordinates":[-80.45361,7.32481],"type":"Point"}
}