{
  "type": "Feature",
  "properties": {
    "iso:country":"PA",
    "name:chi_x_preferred":[
        "\u62c9\u57c3\u65af\u7279\u96f7"
    ],
    "name:eng_x_preferred":[
        "La Estrella"
    ],
    "name:ita_x_preferred":[
        "La Estrella"
    ],
    "name:spa_x_preferred":[
        "La Estrella"
    ],
    "qs:gn_country":"PA",
    "qs:gn_fcode":"PPL",
    "qs:gn_pop":945,
    "qs:name":"La Estrella",
    "qs:name_adm0":"Panam\u00e1",
    "qs:name_adm1":"Chiriqu\u00ed",
    "qs:photos":0,
    "qs:photos_1k":0,
    "qs:photos_9k":0,
    "qs:photos_9r":0,
    "qs:photos_all":0,
    "qs:photos_sr":0,
    "qs:placetype":"Town",
    "qs:pop_sr":"2",
    "qs:woe_adm0":23424924,
    "wd:wordcount":341,
    "wof:name":"La Estrella",
    "wof:placetype":"locality",
    "wof:population":945
},
  "geometry": {"coordinates":[-82.66667,8.51667],"type":"Point"}
}