{
  "type": "Feature",
  "properties": {
    "gn:admin1_code":"10",
    "gn:asciiname":"La Palma",
    "gn:country_code":"PA",
    "gn:dem":67,
    "gn:feature_class":"P",
    "gn:feature_code":"PPL",
    "gn:name":"La Palma",
    "gn:population":8,
    "gn:timezone":"America/Panama",
    "iso:country":"PA",
    "wof:name":"La Palma",
    "wof:placetype":"locality",
    "wof:population":8
},
  "geometry": {"coordinates":[-80.91519,8.22075],"type":"Point"}
}