{
  "type": "Feature",
  "properties": {
    "gn:admin1_code":"13",
    "gn:asciiname":"Nuevo Chorrillo",
    "gn:country_code":"PA",
    "gn:dem":43,
    "gn:feature_class":"P",
    "gn:feature_code":"PPL",
    "gn:name":"Nuevo Chorrillo",
    "gn:population":0,
    "gn:timezone":"America/Panama",
    "iso:country":"PA",
    "name:spa_x_preferred":[
        "Nuevo Chorrillo"
    ],
    "wof:name":"Nuevo Chorrillo",
    "wof:placetype":"locality"
},
  "geometry": {"coordinates":[-79.69269,8.95243],"type":"Point"}
}