{
  "type": "Feature",
  "properties": {
    "iso:country":"PA",
    "qs:gn_country":"PA",
    "qs:gn_fcode":"PPL",
    "qs:gn_pop":0,
    "qs:name":"Playa Coronado",
    "qs:name_adm0":"Panam\u00e1",
    "qs:name_adm1":"Panam\u00e1",
    "qs:photos":48,
    "qs:photos_1k":10,
    "qs:photos_9k":1,
    "qs:photos_9r":2,
    "qs:photos_all":48,
    "qs:photos_sr":2,
    "qs:placetype":"Town",
    "qs:pop_sr":"0",
    "qs:woe_adm0":23424924,
    "wof:name":"Playa Coronado",
    "wof:placetype":"locality"
},
  "geometry": {"coordinates":[-79.89266000000001,8.52585],"type":"Point"}
}