{
  "type": "Feature",
  "properties": {
    "gn:admin1_code":"10",
    "gn:asciiname":"El Jobo",
    "gn:country_code":"PA",
    "gn:dem":31,
    "gn:feature_class":"P",
    "gn:feature_code":"PPL",
    "gn:name":"El Jobo",
    "gn:population":36,
    "gn:timezone":"America/Panama",
    "iso:country":"PA",
    "wof:name":"El Jobo",
    "wof:placetype":"locality",
    "wof:population":36
},
  "geometry": {"coordinates":[-81.19296999999997,7.52998],"type":"Point"}
}