{
  "type": "Feature",
  "properties": {
    "gn:admin1_code":"03",
    "gn:asciiname":"Bermeja",
    "gn:country_code":"PA",
    "gn:dem":238,
    "gn:feature_class":"P",
    "gn:feature_code":"PPL",
    "gn:name":"Bermeja",
    "gn:population":0,
    "gn:timezone":"America/Panama",
    "iso:country":"PA",
    "name:ceb_x_preferred":[
        "Islote Bermeja"
    ],
    "name:deu_x_preferred":[
        "Bermeja"
    ],
    "name:epo_x_preferred":[
        "Berme\u0125o"
    ],
    "name:ind_x_preferred":[
        "Bermeja"
    ],
    "name:ita_x_preferred":[
        "Bermeja"
    ],
    "name:jpn_x_preferred":[
        "\u30d9\u30eb\u30e1\u30cf\u5cf6"
    ],
    "name:pol_x_preferred":[
        "Bermeja"
    ],
    "name:spa_x_preferred":[
        "Isla Bermeja"
    ],
    "name:swe_x_preferred":[
        "Bermeja"
    ],
    "wof:name":"Bermeja",
    "wof:placetype":"locality"
},
  "geometry": {"coordinates":[-80.48333000000002,8.53333],"type":"Point"}
}