{
  "type": "Feature",
  "properties": {
    "gn:admin1_code":"02",
    "gn:asciiname":"Cerro Bubi",
    "gn:country_code":"PA",
    "gn:dem":356,
    "gn:feature_class":"P",
    "gn:feature_code":"PPL",
    "gn:name":"Cerro Bub\u00ed",
    "gn:population":0,
    "gn:timezone":"America/Panama",
    "iso:country":"PA",
    "wof:name":"Cerro Bubi",
    "wof:placetype":"locality"
},
  "geometry": {"coordinates":[-81.56667,8.36667],"type":"Point"}
}