{
  "type": "Feature",
  "properties": {
    "gn:admin1_code":"03",
    "gn:asciiname":"Llano de la Palma",
    "gn:country_code":"PA",
    "gn:dem":285,
    "gn:feature_class":"P",
    "gn:feature_code":"PPL",
    "gn:name":"Llano de la Palma",
    "gn:population":0,
    "gn:timezone":"America/Panama",
    "iso:country":"PA",
    "wof:name":"Llano de la Palma",
    "wof:placetype":"locality"
},
  "geometry": {"coordinates":[-80.71666999999999,8.43333],"type":"Point"}
}