{
  "type": "Feature",
  "properties": {
    "gn:admin1_code":"06",
    "gn:asciiname":"Los Guichiches",
    "gn:country_code":"PA",
    "gn:dem":39,
    "gn:feature_class":"P",
    "gn:feature_code":"PPL",
    "gn:name":"Los G\u00fcichiches",
    "gn:population":0,
    "gn:timezone":"America/Panama",
    "iso:country":"PA",
    "wof:name":"Los Guichiches",
    "wof:placetype":"locality"
},
  "geometry": {"coordinates":[-80.73333000000002,8.11667],"type":"Point"}
}