{
  "type": "Feature",
  "properties": {
    "gn:admin1_code":"12",
    "gn:asciiname":"Paticinky",
    "gn:country_code":"PA",
    "gn:dem":9,
    "gn:feature_class":"P",
    "gn:feature_code":"PPL",
    "gn:name":"Paticinky",
    "gn:population":0,
    "gn:timezone":"America/Panama",
    "iso:country":"PA",
    "name:spa_x_preferred":[
        "Paticinky"
    ],
    "name:und_x_variant":[
        "Paticinqu\u00ed"
    ],
    "wof:name":"Paticinky",
    "wof:placetype":"locality"
},
  "geometry": {"coordinates":[-81.90187,9.09902],"type":"Point"}
}