{
  "type": "Feature",
  "properties": {
    "gn:admin1_code":"03",
    "gn:asciiname":"Los Reyes",
    "gn:country_code":"PA",
    "gn:dem":328,
    "gn:feature_class":"P",
    "gn:feature_code":"PPL",
    "gn:name":"Los Reyes",
    "gn:population":299,
    "gn:timezone":"America/Panama",
    "iso:country":"PA",
    "name:ceb_x_preferred":[
        "Los Reyes"
    ],
    "name:deu_x_preferred":[
        "Los Reyes"
    ],
    "name:epo_x_preferred":[
        "Los Reyes"
    ],
    "name:nds_x_preferred":[
        "Los Reyes"
    ],
    "name:spa_x_preferred":[
        "Los Reyes"
    ],
    "name:swe_x_preferred":[
        "Los Reyes"
    ],
    "wof:name":"Los Reyes",
    "wof:placetype":"locality",
    "wof:population":299
},
  "geometry": {"coordinates":[-80.20444000000001,8.56063],"type":"Point"}
}