{
  "type": "Feature",
  "properties": {
    "gn:admin1_code":"06",
    "gn:asciiname":"Mandinga",
    "gn:country_code":"PA",
    "gn:dem":96,
    "gn:feature_class":"P",
    "gn:feature_code":"PPL",
    "gn:name":"Mandinga",
    "gn:population":0,
    "gn:timezone":"America/Panama",
    "iso:country":"PA",
    "name:spa_x_preferred":[
        "Mandinga"
    ],
    "wof:name":"Mandinga",
    "wof:placetype":"locality"
},
  "geometry": {"coordinates":[-80.66445999999998,7.84934],"type":"Point"}
}