{
  "type": "Feature",
  "properties": {
    "gn:admin1_code":"08",
    "gn:asciiname":"Maje Arriba",
    "gn:country_code":"PA",
    "gn:dem":372,
    "gn:feature_class":"P",
    "gn:feature_code":"PPL",
    "gn:name":"Maj\u00e9 Arriba",
    "gn:population":0,
    "gn:timezone":"America/Panama",
    "iso:country":"PA",
    "wof:name":"Maje Arriba",
    "wof:placetype":"locality"
},
  "geometry": {"coordinates":[-78.51666999999998,8.83333],"type":"Point"}
}