{
  "type": "Feature",
  "properties": {
    "gn:admin1_code":"10",
    "gn:asciiname":"Los Montes",
    "gn:country_code":"PA",
    "gn:dem":94,
    "gn:feature_class":"P",
    "gn:feature_code":"PPL",
    "gn:name":"Los Montes",
    "gn:population":221,
    "gn:timezone":"America/Panama",
    "iso:country":"PA",
    "name:cat_x_preferred":[
        "Los Montes"
    ],
    "name:deu_x_preferred":[
        "Los Montes"
    ],
    "name:eus_x_preferred":[
        "Los Montes"
    ],
    "name:fra_x_preferred":[
        "Los Montes"
    ],
    "name:ita_x_preferred":[
        "Los Montes"
    ],
    "name:kaz_x_preferred":[
        "\u041b\u043e\u0441-\u041c\u043e\u043d\u0442\u0435\u0441"
    ],
    "name:rus_x_preferred":[
        "\u041b\u043e\u0441-\u041c\u043e\u043d\u0442\u0435\u0441"
    ],
    "name:spa_x_preferred":[
        "Los Montes"
    ],
    "wof:name":"Los Montes",
    "wof:placetype":"locality",
    "wof:population":221
},
  "geometry": {"coordinates":[-81.14213000000002,8.0022],"type":"Point"}
}