{
  "type": "Feature",
  "properties": {
    "gn:admin1_code":"08",
    "gn:asciiname":"Rio Ruben",
    "gn:country_code":"PA",
    "gn:dem":152,
    "gn:feature_class":"P",
    "gn:feature_code":"PPL",
    "gn:name":"R\u00edo Rub\u00e9n",
    "gn:population":0,
    "gn:timezone":"America/Panama",
    "iso:country":"PA",
    "name:spa_x_preferred":[
        "R\u00edo Rub\u00e9n"
    ],
    "wof:name":"Rio Ruben",
    "wof:placetype":"locality"
},
  "geometry": {"coordinates":[-78.42574,8.94699],"type":"Point"}
}