{
  "type": "Feature",
  "properties": {
    "gn:admin1_code":"10",
    "gn:asciiname":"El Palmar",
    "gn:country_code":"PA",
    "gn:dem":22,
    "gn:feature_class":"P",
    "gn:feature_code":"PPL",
    "gn:name":"El Palmar",
    "gn:population":25,
    "gn:timezone":"America/Panama",
    "iso:country":"PA",
    "wof:name":"El Palmar",
    "wof:placetype":"locality",
    "wof:population":25
},
  "geometry": {"coordinates":[-81.14485000000001,7.90443],"type":"Point"}
}