{
  "type": "Feature",
  "properties": {
    "iso:country":"PA",
    "name:eng_x_preferred":[
        "Cacique"
    ],
    "name:ita_x_preferred":[
        "Cacique"
    ],
    "name:spa_x_preferred":[
        "Cacique"
    ],
    "qs:gn_country":"PA",
    "qs:gn_fcode":"PPL",
    "qs:gn_pop":0,
    "qs:name":"Cacique",
    "qs:name_adm0":"Panam\u00e1",
    "qs:name_adm1":"Col\u00f3n",
    "qs:photos":16,
    "qs:photos_1k":3,
    "qs:photos_9k":1,
    "qs:photos_9r":1,
    "qs:photos_all":16,
    "qs:photos_sr":1,
    "qs:placetype":"Town",
    "qs:pop_sr":"3",
    "qs:woe_adm0":23424924,
    "wd:wordcount":1084,
    "wof:name":"Cacique",
    "wof:placetype":"locality"
},
  "geometry": {"coordinates":[-79.61667,9.61667],"type":"Point"}
}