{
  "type": "Feature",
  "properties": {
    "iso:country":"PA",
    "qs:gn_pop":0,
    "qs:name":"Soledad",
    "qs:name_adm0":"Panam\u00e1",
    "qs:name_adm1":"Chiriqu\u00ed",
    "qs:photos":84,
    "qs:photos_1k":17,
    "qs:photos_9k":1,
    "qs:photos_9r":3,
    "qs:photos_all":84,
    "qs:photos_sr":3,
    "qs:placetype":"Town",
    "qs:pop_sr":"0",
    "qs:woe_adm0":23424924,
    "wd:wordcount":313,
    "wof:name":"Soledad",
    "wof:placetype":"locality"
},
  "geometry": {"coordinates":[-82.282651,8.737483],"type":"Point"}
}