{
  "type": "Feature",
  "properties": {
    "iso:country":"PA",
    "name:ara_x_preferred":[
        "\u0633\u0648\u0644\u064a\u062f\u0627\u062f"
    ],
    "name:ben_x_preferred":[
        "\u09b8\u09cb\u09b2\u09c7\u09a6\u09be\u09a6"
    ],
    "name:bre_x_preferred":[
        "Soledad"
    ],
    "name:cat_x_preferred":[
        "Soledad"
    ],
    "name:ceb_x_preferred":[
        "Soledad"
    ],
    "name:deu_x_preferred":[
        "Soledad"
    ],
    "name:fra_x_preferred":[
        "Soledad"
    ],
    "name:heb_x_preferred":[
        "\u05e1\u05d5\u05dc\u05d3\u05d0\u05d3"
    ],
    "name:hin_x_preferred":[
        "\u0938\u094b\u0932\u0921\u0948\u0921"
    ],
    "name:hun_x_preferred":[
        "Soledad"
    ],
    "name:ind_x_preferred":[
        "Soledad"
    ],
    "name:ita_x_preferred":[
        "Soledad"
    ],
    "name:kor_x_preferred":[
        "\uc194\ub808\ub2e4\ub4dc"
    ],
    "name:lit_x_preferred":[
        "Soledad"
    ],
    "name:nld_x_preferred":[
        "Soledad"
    ],
    "name:pol_x_preferred":[
        "Soledad"
    ],
    "name:por_x_preferred":[
        "Soledad"
    ],
    "name:spa_x_preferred":[
        "Soledad"
    ],
    "name:srp_x_preferred":[
        "\u0421\u043e\u043b\u0435\u0434\u0430\u0434"
    ],
    "name:swe_x_preferred":[
        "Soledad"
    ],
    "name:vie_x_preferred":[
        "Soledad"
    ],
    "name:vol_x_preferred":[
        "Soledad"
    ],
    "name:war_x_preferred":[
        "Soledad"
    ],
    "qs:gn_pop":0,
    "qs:name":"Soledad",
    "qs:name_adm0":"Panam\u00e1",
    "qs:name_adm1":"Chiriqu\u00ed",
    "qs:photos":84,
    "qs:photos_1k":17,
    "qs:photos_9k":1,
    "qs:photos_9r":3,
    "qs:photos_all":84,
    "qs:photos_sr":3,
    "qs:placetype":"Town",
    "qs:pop_sr":"0",
    "qs:woe_adm0":23424924,
    "wd:wordcount":313,
    "wof:name":"Soledad",
    "wof:placetype":"locality"
},
  "geometry": {"coordinates":[-82.282651,8.737483],"type":"Point"}
}