{
  "type": "Feature",
  "properties": {
    "iso:country":"PA",
    "name:bre_x_preferred":[
        "Soledad"
    ],
    "name:cat_x_preferred":[
        "Soledad"
    ],
    "name:ceb_x_preferred":[
        "Soledad"
    ],
    "name:deu_x_preferred":[
        "Soledad"
    ],
    "name:fra_x_preferred":[
        "Soledad"
    ],
    "name:ita_x_preferred":[
        "Soledad"
    ],
    "name:lit_x_preferred":[
        "Soledad"
    ],
    "name:nld_x_preferred":[
        "Soledad"
    ],
    "name:pol_x_preferred":[
        "Soledad"
    ],
    "name:por_x_preferred":[
        "Soledad"
    ],
    "name:spa_x_preferred":[
        "Soledad"
    ],
    "name:srp_x_preferred":[
        "\u0421\u043e\u043b\u0435\u0434\u0430\u0434"
    ],
    "name:swe_x_preferred":[
        "Soledad"
    ],
    "name:vol_x_preferred":[
        "Soledad"
    ],
    "name:war_x_preferred":[
        "Soledad"
    ],
    "qs:gn_pop":0,
    "qs:name":"Soledad",
    "qs:name_adm0":"Panam\u00e1",
    "qs:name_adm1":"Chiriqu\u00ed",
    "qs:photos":84,
    "qs:photos_1k":17,
    "qs:photos_9k":1,
    "qs:photos_9r":3,
    "qs:photos_all":84,
    "qs:photos_sr":3,
    "qs:placetype":"Town",
    "qs:pop_sr":"0",
    "qs:woe_adm0":23424924,
    "wd:wordcount":313,
    "wof:name":"Soledad",
    "wof:placetype":"locality"
},
  "geometry": {"coordinates":[-82.282651,8.737483],"type":"Point"}
}