{
  "type": "Feature",
  "properties": {
    "gn:admin1_code":"02",
    "gn:asciiname":"Llano Grande",
    "gn:country_code":"PA",
    "gn:dem":29,
    "gn:feature_class":"P",
    "gn:feature_code":"PPL",
    "gn:name":"Llano Grande",
    "gn:population":0,
    "gn:timezone":"America/Panama",
    "iso:country":"PA",
    "wof:name":"Llano Grande",
    "wof:placetype":"locality"
},
  "geometry": {"coordinates":[-82.58333,8.38333],"type":"Point"}
}