{
  "type": "Feature",
  "properties": {
    "gn:admin1_code":"03",
    "gn:asciiname":"Oliver Estate",
    "gn:cc2":"PA",
    "gn:country_code":"PA",
    "gn:dem":13,
    "gn:feature_class":"P",
    "gn:feature_code":"PPL",
    "gn:name":"Oliver Estate",
    "gn:population":0,
    "gn:timezone":"America/Panama",
    "iso:country":"PA",
    "name:und_x_variant":[
        "Olive Estates",
        "Oliver",
        "Oliver Estate"
    ],
    "wof:name":"Oliver Estate",
    "wof:placetype":"locality"
},
  "geometry": {"coordinates":[-80.09999999999999,8.38333],"type":"Point"}
}