{
  "type": "Feature",
  "properties": {
    "gn:admin1_code":"09",
    "gn:admin2_code":"3700392.0",
    "gn:asciiname":"Pito",
    "gn:country_code":"PA",
    "gn:dem":105,
    "gn:feature_class":"P",
    "gn:feature_code":"PPL",
    "gn:name":"Pito",
    "gn:population":0,
    "gn:timezone":"America/Panama",
    "iso:country":"PA",
    "name:cat_x_preferred":[
        "Pit\u00f3"
    ],
    "name:por_x_preferred":[
        "Pito"
    ],
    "name:spa_x_preferred":[
        "Pito"
    ],
    "name:tgl_x_preferred":[
        "Pito"
    ],
    "wof:name":"Pito",
    "wof:placetype":"locality"
},
  "geometry": {"coordinates":[-77.53395,8.68374],"type":"Point"}
}