{
  "type": "Feature",
  "properties": {
    "gn:admin1_code":"04",
    "gn:asciiname":"Demostenes Arosemena",
    "gn:country_code":"PA",
    "gn:dem":68,
    "gn:feature_class":"P",
    "gn:feature_code":"PPL",
    "gn:name":"Dem\u00f3stenes Arosemena",
    "gn:population":0,
    "gn:timezone":"America/Panama",
    "iso:country":"PA",
    "wof:name":"Demostenes Arosemena",
    "wof:placetype":"locality"
},
  "geometry": {"coordinates":[-79.63333,9.23333],"type":"Point"}
}