{
  "type": "Feature",
  "properties": {
    "gn:admin1_code":"08",
    "gn:asciiname":"Pedro de Cocal",
    "gn:country_code":"PA",
    "gn:dem":36,
    "gn:feature_class":"P",
    "gn:feature_code":"PPL",
    "gn:name":"Pedro de Cocal",
    "gn:population":0,
    "gn:timezone":"America/Panama",
    "iso:country":"PA",
    "name:und_x_variant":[
        "Pedro Gonz\u00e1lez",
        "Pedro de Cocal",
        "El Cocal"
    ],
    "wof:name":"Pedro de Cocal",
    "wof:placetype":"locality"
},
  "geometry": {"coordinates":[-79.10465000000001,8.41426],"type":"Point"}
}