{
  "type": "Feature",
  "properties": {
    "gn:admin1_code":"08",
    "gn:asciiname":"Pedro de Cocal",
    "gn:country_code":"PA",
    "gn:dem":36,
    "gn:feature_class":"P",
    "gn:feature_code":"PPL",
    "gn:name":"Pedro de Cocal",
    "gn:population":0,
    "gn:timezone":"America/Panama",
    "iso:country":"PA",
    "name:ita_x_preferred":[
        "Pedro Gonz\u00e1lez"
    ],
    "name:spa_x_preferred":[
        "Pedro Gonz\u00e1lez"
    ],
    "name:und_x_variant":[
        "Pedro de Cocal",
        "El Cocal"
    ],
    "name:zho_x_preferred":[
        "\u4f69\u5fb7\u7f85\u8ca2\u85a9\u840a\u65af"
    ],
    "wof:name":"Pedro de Cocal",
    "wof:placetype":"locality"
},
  "geometry": {"coordinates":[-79.10465000000001,8.41426],"type":"Point"}
}