{
  "type": "Feature",
  "properties": {
    "gn:admin1_code":"04",
    "gn:asciiname":"Gatuncillo",
    "gn:country_code":"PA",
    "gn:dem":50,
    "gn:feature_class":"P",
    "gn:feature_code":"PPL",
    "gn:name":"Gatuncillo",
    "gn:population":4605,
    "gn:timezone":"America/Panama",
    "iso:country":"PA",
    "name:spa_x_preferred":[
        "Gatuncillo"
    ],
    "wof:name":"Gatuncillo",
    "wof:placetype":"locality",
    "wof:population":4605
},
  "geometry": {"coordinates":[-79.64856,9.24346],"type":"Point"}
}