{
  "type": "Feature",
  "properties": {
    "gn:admin1_code":"02",
    "gn:asciiname":"Calabacito",
    "gn:country_code":"PA",
    "gn:dem":188,
    "gn:feature_class":"P",
    "gn:feature_code":"PPL",
    "gn:name":"Calabacito",
    "gn:population":0,
    "gn:timezone":"America/Panama",
    "iso:country":"PA",
    "name:spa_x_preferred":[
        "Calabacito"
    ],
    "wof:name":"Calabacito",
    "wof:placetype":"locality"
},
  "geometry": {"coordinates":[-81.60715999999999,8.27931],"type":"Point"}
}