{
  "type": "Feature",
  "properties": {
    "gn:admin1_code":"07",
    "gn:asciiname":"Bombacho",
    "gn:country_code":"PA",
    "gn:dem":180,
    "gn:feature_class":"P",
    "gn:feature_code":"PPL",
    "gn:name":"Bombacho",
    "gn:population":78,
    "gn:timezone":"America/Panama",
    "iso:country":"PA",
    "name:und_x_variant":[
        "Juanbatcha",
        "Juanbacho",
        "Bombacho"
    ],
    "wof:name":"Bombacho",
    "wof:placetype":"locality",
    "wof:population":78
},
  "geometry": {"coordinates":[-80.5947,7.61656],"type":"Point"}
}