{
  "type": "Feature",
  "properties": {
    "iso:country":"PA",
    "qs:gn_pop":0,
    "qs:name":"Paja de Sombrero",
    "qs:name_adm0":"Panam\u00e1",
    "qs:name_adm1":"Chiriqu\u00ed",
    "qs:photos":1,
    "qs:photos_1k":1,
    "qs:photos_9k":1,
    "qs:photos_9r":1,
    "qs:photos_all":1,
    "qs:photos_sr":1,
    "qs:placetype":"LocalAdmin",
    "qs:pop_sr":"0",
    "qs:woe_adm0":23424924,
    "wof:name":"Paja de Sombrero",
    "wof:placetype":"localadmin"
},
  "geometry": {"coordinates":[-82.2072285,8.712037],"type":"Point"}
}