{
  "type": "Feature",
  "properties": {
    "gn:admin1_code":"10",
    "gn:asciiname":"Arrimadero",
    "gn:country_code":"PA",
    "gn:dem":11,
    "gn:feature_class":"P",
    "gn:feature_code":"PPL",
    "gn:name":"Arrimadero",
    "gn:population":44,
    "gn:timezone":"America/Panama",
    "iso:country":"PA",
    "wof:name":"Arrimadero",
    "wof:placetype":"locality",
    "wof:population":44
},
  "geometry": {"coordinates":[-81.31111,7.66111],"type":"Point"}
}