{
  "type": "Feature",
  "properties": {
    "gn:admin1_code":"13",
    "gn:asciiname":"Bajo Bonito",
    "gn:country_code":"PA",
    "gn:dem":449,
    "gn:feature_class":"P",
    "gn:feature_code":"PPL",
    "gn:name":"Bajo Bonito",
    "gn:population":373,
    "gn:timezone":"America/Panama",
    "iso:country":"PA",
    "name:spa_x_preferred":[
        "Bajo Bonito"
    ],
    "wof:name":"Bajo Bonito",
    "wof:placetype":"locality",
    "wof:population":373
},
  "geometry": {"coordinates":[-80.05672,8.71758],"type":"Point"}
}