{
  "type": "Feature",
  "properties": {
    "gn:admin1_code":"06",
    "gn:asciiname":"Quebrada del Cantaro",
    "gn:country_code":"PA",
    "gn:dem":476,
    "gn:feature_class":"P",
    "gn:feature_code":"PPL",
    "gn:name":"Quebrada del C\u00e1ntaro",
    "gn:population":0,
    "gn:timezone":"America/Panama",
    "iso:country":"PA",
    "name:spa_x_preferred":[
        "Quebrada del C\u00e1ntaro"
    ],
    "wof:name":"Quebrada del Cantaro",
    "wof:placetype":"locality"
},
  "geometry": {"coordinates":[-80.78171,7.68545],"type":"Point"}
}