{
  "type": "Feature",
  "properties": {
    "gn:admin1_code":"02",
    "gn:asciiname":"Jazmin",
    "gn:country_code":"PA",
    "gn:dem":120,
    "gn:feature_class":"P",
    "gn:feature_code":"PPL",
    "gn:name":"Jazm\u00edn",
    "gn:population":87,
    "gn:timezone":"America/Panama",
    "iso:country":"PA",
    "wof:name":"Jazmin",
    "wof:placetype":"locality",
    "wof:population":87
},
  "geometry": {"coordinates":[-82.09999999999999,8.45],"type":"Point"}
}