{
  "type": "Feature",
  "properties": {
    "gn:admin1_code":"10",
    "gn:asciiname":"San Jose",
    "gn:country_code":"PA",
    "gn:dem":359,
    "gn:feature_class":"P",
    "gn:feature_code":"PPL",
    "gn:name":"San Jos\u00e9",
    "gn:population":0,
    "gn:timezone":"America/Panama",
    "iso:country":"PA",
    "name:spa_x_preferred":[
        "San Jos\u00e9"
    ],
    "wof:name":"San Jose",
    "wof:placetype":"locality"
},
  "geometry": {"coordinates":[-81.04307,8.34983],"type":"Point"}
}