{
  "type": "Feature",
  "properties": {
    "gn:admin1_code":"07",
    "gn:asciiname":"Boca de Quema",
    "gn:country_code":"PA",
    "gn:dem":87,
    "gn:feature_class":"P",
    "gn:feature_code":"PPL",
    "gn:name":"Boca de Quema",
    "gn:population":169,
    "gn:timezone":"America/Panama",
    "iso:country":"PA",
    "name:spa_x_preferred":[
        "Boca de Quema"
    ],
    "wof:name":"Boca de Quema",
    "wof:placetype":"locality",
    "wof:population":169
},
  "geometry": {"coordinates":[-80.57903,7.52339],"type":"Point"}
}