{
  "type": "Feature",
  "properties": {
    "gn:admin1_code":"10",
    "gn:asciiname":"Picacho",
    "gn:country_code":"PA",
    "gn:dem":407,
    "gn:feature_class":"P",
    "gn:feature_code":"PPL",
    "gn:name":"Picacho",
    "gn:population":8,
    "gn:timezone":"America/Panama",
    "iso:country":"PA",
    "name:ceb_x_preferred":[
        "Picacho"
    ],
    "name:deu_x_preferred":[
        "Picacho"
    ],
    "name:swe_x_preferred":[
        "Picacho"
    ],
    "wof:name":"Picacho",
    "wof:placetype":"locality",
    "wof:population":8
},
  "geometry": {"coordinates":[-81.32975,8.33441],"type":"Point"}
}