{
  "type": "Feature",
  "properties": {
    "gn:admin1_code":"03",
    "gn:asciiname":"La Negrita",
    "gn:country_code":"PA",
    "gn:dem":160,
    "gn:feature_class":"P",
    "gn:feature_code":"PPL",
    "gn:name":"La Negrita",
    "gn:population":2,
    "gn:timezone":"America/Panama",
    "iso:country":"PA",
    "wof:name":"La Negrita",
    "wof:placetype":"locality",
    "wof:population":2
},
  "geometry": {"coordinates":[-80.65015,8.39612],"type":"Point"}
}