{
  "type": "Feature",
  "properties": {
    "iso:country":"PA",
    "name:spa_x_preferred":[
        "Palmira Centro"
    ],
    "qs:gn_country":"PA",
    "qs:gn_fcode":"PPL",
    "qs:gn_pop":0,
    "qs:name":"Palmiras Centro",
    "qs:name_adm0":"Panam\u00e1",
    "qs:name_adm1":"Chiriqu\u00ed",
    "qs:photos":37,
    "qs:photos_1k":7,
    "qs:photos_9k":1,
    "qs:photos_9r":2,
    "qs:photos_all":37,
    "qs:photos_sr":2,
    "qs:placetype":"Town",
    "qs:pop_sr":"0",
    "qs:woe_adm0":23424924,
    "wof:name":"Palmiras Centro",
    "wof:placetype":"locality"
},
  "geometry": {"coordinates":[-82.45,8.73333],"type":"Point"}
}