{
  "type": "Feature",
  "properties": {
    "gn:admin1_code":"08",
    "gn:asciiname":"Torti Medio",
    "gn:country_code":"PA",
    "gn:dem":102,
    "gn:feature_class":"P",
    "gn:feature_code":"PPL",
    "gn:name":"Tort\u00ed Medio",
    "gn:population":0,
    "gn:timezone":"America/Panama",
    "iso:country":"PA",
    "name:spa_x_preferred":[
        "Tort\u00ed Medio"
    ],
    "wof:name":"Torti Medio",
    "wof:placetype":"locality"
},
  "geometry": {"coordinates":[-78.39806,8.9285],"type":"Point"}
}