{
  "type": "Feature",
  "properties": {
    "gn:admin1_code":"12",
    "gn:asciiname":"Jugli",
    "gn:country_code":"PA",
    "gn:dem":43,
    "gn:feature_class":"P",
    "gn:feature_code":"PPL",
    "gn:name":"Jugli",
    "gn:population":0,
    "gn:timezone":"America/Panama",
    "iso:country":"PA",
    "wof:name":"Jugli",
    "wof:placetype":"locality"
},
  "geometry": {"coordinates":[-81.75,8.91667],"type":"Point"}
}