{
  "type": "Feature",
  "properties": {
    "gn:admin1_code":"07",
    "gn:asciiname":"Colan",
    "gn:country_code":"PA",
    "gn:dem":206,
    "gn:feature_class":"P",
    "gn:feature_code":"PPL",
    "gn:name":"Col\u00e1n",
    "gn:population":84,
    "gn:timezone":"America/Panama",
    "iso:country":"PA",
    "name:ceb_x_preferred":[
        "Colan"
    ],
    "name:deu_x_preferred":[
        "Colan"
    ],
    "name:por_x_preferred":[
        "Colan"
    ],
    "name:swe_x_preferred":[
        "Colan"
    ],
    "wof:name":"Colan",
    "wof:placetype":"locality",
    "wof:population":84
},
  "geometry": {"coordinates":[-80.23333000000002,7.58333],"type":"Point"}
}