{
  "type": "Feature",
  "properties": {
    "gn:admin1_code":"03",
    "gn:asciiname":"Sonadora",
    "gn:country_code":"PA",
    "gn:dem":136,
    "gn:feature_class":"P",
    "gn:feature_code":"PPL",
    "gn:name":"Sonadora",
    "gn:population":515,
    "gn:timezone":"America/Panama",
    "iso:country":"PA",
    "name:spa_x_preferred":[
        "Sonadora"
    ],
    "name:und_x_variant":[
        "La Sonadora"
    ],
    "wof:name":"Sonadora",
    "wof:placetype":"locality",
    "wof:population":515
},
  "geometry": {"coordinates":[-80.32749,8.55167],"type":"Point"}
}