{
  "type": "Feature",
  "properties": {
    "gn:admin1_code":"03",
    "gn:asciiname":"Mosquitero",
    "gn:country_code":"PA",
    "gn:dem":139,
    "gn:feature_class":"P",
    "gn:feature_code":"PPL",
    "gn:name":"Mosquitero",
    "gn:population":190,
    "gn:timezone":"America/Panama",
    "iso:country":"PA",
    "name:spa_x_preferred":[
        "Mosquitero"
    ],
    "wof:name":"Mosquitero",
    "wof:placetype":"locality",
    "wof:population":190
},
  "geometry": {"coordinates":[-80.30748,8.57368],"type":"Point"}
}