{
  "type": "Feature",
  "properties": {
    "gn:admin1_code":"10",
    "gn:asciiname":"Zapiringo",
    "gn:country_code":"PA",
    "gn:dem":92,
    "gn:feature_class":"P",
    "gn:feature_code":"PPL",
    "gn:name":"Zapiringo",
    "gn:population":77,
    "gn:timezone":"America/Panama",
    "iso:country":"PA",
    "name:spa_x_preferred":[
        "Zapiringo"
    ],
    "wof:name":"Zapiringo",
    "wof:placetype":"locality",
    "wof:population":77
},
  "geometry": {"coordinates":[-81.60704,8.1156],"type":"Point"}
}