{
  "type": "Feature",
  "properties": {
    "iso:country":"PA",
    "name:ceb_x_preferred":[
        "Villa Rosario"
    ],
    "name:eng_x_preferred":[
        "Villa Rosario"
    ],
    "name:ita_x_preferred":[
        "Villa Rosario"
    ],
    "name:nld_x_preferred":[
        "Villa Rosario"
    ],
    "name:spa_x_preferred":[
        "Villa Rosario"
    ],
    "name:zho_x_preferred":[
        "\u7f85\u85a9\u91cc\u5967\u93ae"
    ],
    "qs:gn_country":"PA",
    "qs:gn_fcode":"PPL",
    "qs:gn_pop":2947,
    "qs:name":"Villa Rosario",
    "qs:name_adm0":"Panam\u00e1",
    "qs:name_adm1":"Panam\u00e1",
    "qs:photos":0,
    "qs:photos_1k":0,
    "qs:photos_9k":1,
    "qs:photos_9r":1,
    "qs:photos_all":1,
    "qs:photos_sr":0,
    "qs:placetype":"Town",
    "qs:pop_sr":"4",
    "qs:woe_adm0":23424924,
    "wof:name":"Villa Rosario",
    "wof:placetype":"locality",
    "wof:population":2947
},
  "geometry": {"coordinates":[-79.86667,8.78333],"type":"Point"}
}