{
  "type": "Feature",
  "properties": {
    "gn:admin1_code":"03",
    "gn:asciiname":"Los Alonsos",
    "gn:cc2":"PA",
    "gn:country_code":"PA",
    "gn:dem":453,
    "gn:feature_class":"P",
    "gn:feature_code":"PPL",
    "gn:name":"Los Alonsos",
    "gn:population":0,
    "gn:timezone":"America/Panama",
    "iso:country":"PA",
    "name:und_x_variant":[
        "Los Alonzo",
        "Los Alonsos"
    ],
    "wof:name":"Los Alonsos",
    "wof:placetype":"locality"
},
  "geometry": {"coordinates":[-80.15000000000001,8.55],"type":"Point"}
}