{
  "type": "Feature",
  "properties": {
    "gn:admin1_code":"02",
    "gn:asciiname":"Calabazal",
    "gn:country_code":"PA",
    "gn:dem":699,
    "gn:feature_class":"P",
    "gn:feature_code":"PPL",
    "gn:name":"Calabazal",
    "gn:population":125,
    "gn:timezone":"America/Panama",
    "iso:country":"PA",
    "name:spa_x_preferred":[
        "Calabazal"
    ],
    "wof:name":"Calabazal",
    "wof:placetype":"locality",
    "wof:population":125
},
  "geometry": {"coordinates":[-82.26980999999998,8.65818],"type":"Point"}
}