{
  "type": "Feature",
  "properties": {
    "gn:admin1_code":"03",
    "gn:asciiname":"Lura Abajo",
    "gn:country_code":"PA",
    "gn:dem":146,
    "gn:feature_class":"P",
    "gn:feature_code":"PPL",
    "gn:name":"Lur\u00e1 Abajo",
    "gn:population":0,
    "gn:timezone":"America/Panama",
    "iso:country":"PA",
    "wof:name":"Lura Abajo",
    "wof:placetype":"locality"
},
  "geometry": {"coordinates":[-80.34999999999999,8.76667],"type":"Point"}
}