{
  "type": "Feature",
  "properties": {
    "gn:admin1_code":"10",
    "gn:asciiname":"Pandura",
    "gn:country_code":"PA",
    "gn:dem":594,
    "gn:feature_class":"P",
    "gn:feature_code":"PPL",
    "gn:name":"Pandura",
    "gn:population":81,
    "gn:timezone":"America/Panama",
    "iso:country":"PA",
    "name:als_x_preferred":[
        "Pandura"
    ],
    "name:ell_x_preferred":[
        "\u03a0\u03b1\u03bd\u03b4\u03bf\u03cd\u03c1\u03b1"
    ],
    "name:hun_x_preferred":[
        "Pandura"
    ],
    "name:lat_x_preferred":[
        "Pandura"
    ],
    "name:por_x_preferred":[
        "Pandura"
    ],
    "name:spa_x_preferred":[
        "Pandura"
    ],
    "wof:name":"Pandura",
    "wof:placetype":"locality",
    "wof:population":81
},
  "geometry": {"coordinates":[-80.93021,8.50697],"type":"Point"}
}