{
  "type": "Feature",
  "properties": {
    "iso:country":"PA",
    "name:kat_x_preferred":[
        "\u10de\u10dd\u10d9\u10e0\u10d8"
    ],
    "name:nld_x_preferred":[
        "Pocr\u00ed"
    ],
    "name:spa_x_preferred":[
        "Pocr\u00ed"
    ],
    "qs:gn_country":"PA",
    "qs:gn_fcode":"PPL",
    "qs:gn_pop":11447,
    "qs:name":"Pocr\u00ed",
    "qs:name_adm0":"Panam\u00e1",
    "qs:name_adm1":"Cocl\u00e9",
    "qs:photos":0,
    "qs:photos_1k":0,
    "qs:photos_9k":1,
    "qs:photos_9r":1,
    "qs:photos_all":1,
    "qs:photos_sr":0,
    "qs:placetype":"Town",
    "qs:pop_sr":"6",
    "qs:woe_adm0":23424924,
    "wd:wordcount":105,
    "wof:name":"Pocr\u00ed",
    "wof:placetype":"locality",
    "wof:population":11447
},
  "geometry": {"coordinates":[-80.55,8.26667],"type":"Point"}
}