{
  "type": "Feature",
  "properties": {
    "gn:admin1_code":"04",
    "gn:asciiname":"Icacal",
    "gn:country_code":"PA",
    "gn:dem":14,
    "gn:feature_class":"P",
    "gn:feature_code":"PPL",
    "gn:name":"Icacal",
    "gn:population":486,
    "gn:timezone":"America/Panama",
    "iso:country":"PA",
    "name:und_x_variant":[
        "El Hicacal",
        "Icacal"
    ],
    "wof:name":"Icacal",
    "wof:placetype":"locality",
    "wof:population":486
},
  "geometry": {"coordinates":[-80.15131,9.18563],"type":"Point"}
}