{
  "type": "Feature",
  "properties": {
    "iso:country":"PA",
    "name:cat_x_preferred":[
        "Anc\u00f3n"
    ],
    "name:ceb_x_preferred":[
        "Anc\u00f3n"
    ],
    "name:eng_x_preferred":[
        "Anc\u00f3n"
    ],
    "name:fas_x_preferred":[
        "\u0627\u0646\u06a9\u0648\u0646\u060c \u067e\u0627\u0646\u0627\u0645\u0627"
    ],
    "name:fas_x_variant":[
        "\u0627\u0646\u06a9\u0648\u0646"
    ],
    "name:fra_x_preferred":[
        "Anc\u00f3n"
    ],
    "name:heb_x_preferred":[
        "\u05d0\u05e0\u05e7\u05d5\u05df"
    ],
    "name:ita_x_preferred":[
        "Anc\u00f3n"
    ],
    "name:jpn_x_preferred":[
        "\u30a2\u30f3\u30b3\u30f3"
    ],
    "name:nld_x_preferred":[
        "Anc\u00f3n"
    ],
    "name:nob_x_preferred":[
        "Anc\u00f3n"
    ],
    "name:por_x_preferred":[
        "Anc\u00f3n"
    ],
    "name:spa_x_preferred":[
        "Anc\u00f3n"
    ],
    "name:zho_x_preferred":[
        "\u5b89\u8d21"
    ],
    "qs:gn_country":"PA",
    "qs:gn_fcode":"PPL",
    "qs:gn_pop":9169,
    "qs:name":"Anc\u00f3n",
    "qs:name_adm0":"Panam\u00e1",
    "qs:name_adm1":"Panam\u00e1",
    "qs:photos":562,
    "qs:photos_1k":114,
    "qs:photos_9k":2,
    "qs:photos_9r":5,
    "qs:photos_all":562,
    "qs:photos_sr":8,
    "qs:placetype":"Town",
    "qs:pop_sr":"5",
    "qs:woe_adm0":23424924,
    "wd:wordcount":812,
    "wof:name":"Anc\u00f3n",
    "wof:placetype":"locality",
    "wof:population":9169
},
  "geometry": {"coordinates":[-79.55,8.96667],"type":"Point"}
}