{
  "type": "Feature",
  "properties": {
    "gn:admin1_code":"13",
    "gn:asciiname":"El Lucio",
    "gn:country_code":"PA",
    "gn:dem":176,
    "gn:feature_class":"P",
    "gn:feature_code":"PPL",
    "gn:name":"El Luc\u00edo",
    "gn:population":0,
    "gn:timezone":"America/Panama",
    "iso:country":"PA",
    "wof:name":"El Lucio",
    "wof:placetype":"locality"
},
  "geometry": {"coordinates":[-80.03305999999998,8.87],"type":"Point"}
}