{
  "type": "Feature",
  "properties": {
    "iso:country":"PA",
    "name:hbs_x_preferred":[
        "Rejnbou Siti"
    ],
    "name:pol_x_preferred":[
        "Rainbow City"
    ],
    "name:spa_x_preferred":[
        "Arco Iris"
    ],
    "name:srp_x_preferred":[
        "\u0420\u0435\u0458\u043d\u0431\u043e\u0443 \u0421\u0438\u0442\u0438"
    ],
    "name:ukr_x_preferred":[
        "\u0420\u0435\u0439\u043d\u0431\u043e\u0443-\u0421\u0456\u0442\u0456"
    ],
    "name:unk_x_variant":[
        "Rambow City"
    ],
    "qs:gn_country":"PA",
    "qs:gn_fcode":"PPL",
    "qs:gn_pop":0,
    "qs:name":"Rainbow City",
    "qs:name_adm0":"Panam\u00e1",
    "qs:name_adm1":"Col\u00f3n",
    "qs:photos":38,
    "qs:photos_1k":8,
    "qs:photos_9k":1,
    "qs:photos_9r":2,
    "qs:photos_all":38,
    "qs:photos_sr":2,
    "qs:placetype":"Town",
    "qs:pop_sr":"0",
    "qs:woe_adm0":23424924,
    "wd:wordcount":47,
    "wof:name":"Rainbow City",
    "wof:placetype":"locality"
},
  "geometry": {"coordinates":[-79.88333,9.35],"type":"Point"}
}