{
  "type": "Feature",
  "properties": {
    "gn:admin1_code":"09",
    "gn:asciiname":"Wagsalatupo Chico",
    "gn:country_code":"PA",
    "gn:dem":-9999,
    "gn:feature_class":"P",
    "gn:feature_code":"PPL",
    "gn:name":"Wagsalatupo Chico",
    "gn:population":0,
    "gn:timezone":"America/Panama",
    "iso:country":"PA",
    "wof:name":"Wagsalatupo Chico",
    "wof:placetype":"locality"
},
  "geometry": {"coordinates":[-78.90000000000001,9.55],"type":"Point"}
}