{
  "type": "Feature",
  "properties": {
    "gn:country":"PA",
    "gn:fcode":"PPLX",
    "gn:population":0,
    "iso:country":"PA",
    "name:spa_x_preferred":[
        "Plaza la Ceda"
    ],
    "qs_pg:aaroncc":"PA",
    "qs_pg:gn_country":"PA",
    "qs_pg:gn_fcode":"PPLX",
    "qs_pg:gn_pop":0,
    "qs_pg:name":"Plaza la Ceda",
    "qs_pg:name_adm0":"Panam\u00e1",
    "qs_pg:name_adm1":"Panam\u00e1",
    "qs_pg:photos":397,
    "qs_pg:photos_1k":80,
    "qs_pg:photos_9k":2,
    "qs_pg:photos_9r":5,
    "qs_pg:photos_all":397,
    "qs_pg:photos_sr":6,
    "qs_pg:pop_sr":0,
    "qs_pg:qs_pg_placetype":"neighbourhood",
    "qs_pg:qs_pg_placetype_gp":"Suburb",
    "qs_pg:woe_adm0":23424924,
    "woe:adm0_id":23424924,
    "woe:name_adm0":"Panam\u00e1",
    "woe:name_adm1":"Panam\u00e1",
    "woe:placetype":"Suburb",
    "wof:name":"Plaza la Ceda",
    "wof:placetype":"neighbourhood"
},
  "geometry": {"coordinates":[-79.78333000000001,8.88333],"type":"Point"}
}