{
  "type": "Feature",
  "properties": {
    "gn:admin1_code":"04",
    "gn:asciiname":"Boqueron Abajo",
    "gn:country_code":"PA",
    "gn:dem":88,
    "gn:feature_class":"P",
    "gn:feature_code":"PPL",
    "gn:name":"Boquer\u00f3n Abajo",
    "gn:population":0,
    "gn:timezone":"America/Panama",
    "iso:country":"PA",
    "name:und_x_variant":[
        "Boquer\u00f3n",
        "Boquer\u00f3n Abajo"
    ],
    "wof:name":"Boqueron Abajo",
    "wof:placetype":"locality"
},
  "geometry": {"coordinates":[-79.56862,9.35921],"type":"Point"}
}