{
  "type": "Feature",
  "properties": {
    "gn:admin1_code":"10",
    "gn:asciiname":"Rio Canazas",
    "gn:country_code":"PA",
    "gn:dem":194,
    "gn:feature_class":"P",
    "gn:feature_code":"PPL",
    "gn:name":"R\u00edo Ca\u00f1azas",
    "gn:population":0,
    "gn:timezone":"America/Panama",
    "iso:country":"PA",
    "name:spa_x_preferred":[
        "R\u00edo Ca\u00f1azas"
    ],
    "wof:name":"Rio Canazas",
    "wof:placetype":"locality"
},
  "geometry": {"coordinates":[-81.24106,8.34723],"type":"Point"}
}