{
  "type": "Feature",
  "properties": {
    "gn:admin1_code":"02",
    "gn:asciiname":"Soberania",
    "gn:country_code":"PA",
    "gn:dem":19,
    "gn:feature_class":"P",
    "gn:feature_code":"PPL",
    "gn:name":"Soberan\u00eda",
    "gn:population":0,
    "gn:timezone":"America/Panama",
    "iso:country":"PA",
    "name:spa_x_preferred":[
        "Soberan\u00eda"
    ],
    "wof:name":"Soberania",
    "wof:placetype":"locality"
},
  "geometry": {"coordinates":[-82.82656999999998,8.43013],"type":"Point"}
}