{
  "type": "Feature",
  "properties": {
    "gn:admin1_code":"06",
    "gn:asciiname":"Llano de La Cruz",
    "gn:country_code":"PA",
    "gn:dem":36,
    "gn:feature_class":"P",
    "gn:feature_code":"PPLA3",
    "gn:name":"Llano de La Cruz",
    "gn:population":188,
    "gn:timezone":"America/Panama",
    "iso:country":"PA",
    "name:spa_x_preferred":[
        "Llano de La Cruz"
    ],
    "name:und_x_variant":[
        "Juan de la Cruz",
        "Juan La Cruz"
    ],
    "wof:name":"Llano de La Cruz",
    "wof:placetype":"locality",
    "wof:population":188
},
  "geometry": {"coordinates":[-80.64239000000001,7.95178],"type":"Point"}
}