{
  "type": "Feature",
  "properties": {
    "gn:admin1_code":"10",
    "gn:asciiname":"Cerro Gordo",
    "gn:country_code":"PA",
    "gn:dem":67,
    "gn:feature_class":"P",
    "gn:feature_code":"PPL",
    "gn:name":"Cerro Gordo",
    "gn:population":0,
    "gn:timezone":"America/Panama",
    "iso:country":"PA",
    "name:spa_x_preferred":[
        "Cerro Gordo"
    ],
    "wof:name":"Cerro Gordo",
    "wof:placetype":"locality"
},
  "geometry": {"coordinates":[-81.18571,8.02967],"type":"Point"}
}