{
  "type": "Feature",
  "properties": {
    "gn:admin1_code":"10",
    "gn:asciiname":"La Elvira",
    "gn:country_code":"PA",
    "gn:dem":8,
    "gn:feature_class":"P",
    "gn:feature_code":"PPL",
    "gn:name":"La Elvira",
    "gn:population":0,
    "gn:timezone":"America/Panama",
    "iso:country":"PA",
    "wof:name":"La Elvira",
    "wof:placetype":"locality"
},
  "geometry": {"coordinates":[-81.28333000000001,7.93333],"type":"Point"}
}