{
  "type": "Feature",
  "properties": {
    "iso:country":"PA",
    "name:spa_x_preferred":[
        "California"
    ],
    "qs:gn_country":"PA",
    "qs:gn_fcode":"PPL",
    "qs:gn_pop":0,
    "qs:name":"California",
    "qs:name_adm0":"Panam\u00e1",
    "qs:name_adm1":"Bocas del Toro",
    "qs:photos":6,
    "qs:photos_1k":1,
    "qs:photos_9k":1,
    "qs:photos_9r":1,
    "qs:photos_all":6,
    "qs:photos_sr":1,
    "qs:placetype":"Town",
    "qs:pop_sr":"0",
    "qs:woe_adm0":23424924,
    "wof:name":"California",
    "wof:placetype":"locality"
},
  "geometry": {"coordinates":[-82.59999999999999,9.53333],"type":"Point"}
}