{
  "type": "Feature",
  "properties": {
    "gn:admin1_code":"10",
    "gn:asciiname":"Las Huacas",
    "gn:country_code":"PA",
    "gn:dem":67,
    "gn:feature_class":"P",
    "gn:feature_code":"PPL",
    "gn:name":"Las Huacas",
    "gn:population":36,
    "gn:timezone":"America/Panama",
    "iso:country":"PA",
    "name:ceb_x_preferred":[
        "Las Huacas"
    ],
    "name:spa_x_preferred":[
        "Las Huacas"
    ],
    "name:swe_x_preferred":[
        "Las Huacas"
    ],
    "wof:name":"Las Huacas",
    "wof:placetype":"locality",
    "wof:population":36
},
  "geometry": {"coordinates":[-81.21666999999999,8.05],"type":"Point"}
}