{
  "type": "Feature",
  "properties": {
    "gn:admin1_code":"10",
    "gn:asciiname":"El Balillo",
    "gn:country_code":"PA",
    "gn:dem":43,
    "gn:feature_class":"P",
    "gn:feature_code":"PPL",
    "gn:name":"El Balillo",
    "gn:population":0,
    "gn:timezone":"America/Panama",
    "iso:country":"PA",
    "wof:name":"El Balillo",
    "wof:placetype":"locality"
},
  "geometry": {"coordinates":[-81.08389,7.99639],"type":"Point"}
}