{
  "type": "Feature",
  "properties": {
    "gn:admin1_code":"07",
    "gn:asciiname":"Lagartillo",
    "gn:country_code":"PA",
    "gn:dem":18,
    "gn:feature_class":"P",
    "gn:feature_code":"PPL",
    "gn:name":"Lagartillo",
    "gn:population":203,
    "gn:timezone":"America/Panama",
    "iso:country":"PA",
    "name:und_x_variant":[
        "El Lagartillo",
        "Lagartillo"
    ],
    "wof:name":"Lagartillo",
    "wof:placetype":"locality",
    "wof:population":203
},
  "geometry": {"coordinates":[-80.31931,7.88025],"type":"Point"}
}