{
  "type": "Feature",
  "properties": {
    "iso:country":"PA",
    "qs_pg:aaroncc":"PA",
    "qs_pg:name":"Boca Chica",
    "qs_pg:name_adm0":"Panam\u00e1",
    "qs_pg:name_adm1":"Chiriqu\u00ed",
    "qs_pg:photos":1,
    "qs_pg:photos_1k":1,
    "qs_pg:photos_9k":1,
    "qs_pg:photos_9r":3,
    "qs_pg:photos_all":80,
    "qs_pg:photos_sr":1,
    "qs_pg:pop_sr":0,
    "qs_pg:qs_pg_placetype":"localadmin",
    "qs_pg:qs_pg_placetype_gp":"LocalAdmin",
    "qs_pg:woe_adm0":23424924,
    "woe:adm0_id":23424924,
    "woe:name_adm0":"Panam\u00e1",
    "woe:name_adm1":"Chiriqu\u00ed",
    "woe:placetype":"LocalAdmin",
    "wof:name":"Boca Chica",
    "wof:placetype":"localadmin"
},
  "geometry": {"coordinates":[-82.21755899999999,8.213359],"type":"Point"}
}