{
  "type": "Feature",
  "properties": {
    "gn:admin1_code":"06",
    "gn:asciiname":"Rincon Hondo",
    "gn:country_code":"PA",
    "gn:dem":58,
    "gn:feature_class":"P",
    "gn:feature_code":"PPLA3",
    "gn:name":"Rinc\u00f3n Hondo",
    "gn:population":359,
    "gn:timezone":"America/Panama",
    "iso:country":"PA",
    "name:ita_x_preferred":[
        "Rinc\u00f3n Hondo"
    ],
    "name:spa_x_preferred":[
        "Rinc\u00f3n Hondo"
    ],
    "name:zho_x_preferred":[
        "\u6797\u5b54\u7fc1\u591a"
    ],
    "wof:name":"Rincon Hondo",
    "wof:placetype":"locality",
    "wof:population":359
},
  "geometry": {"coordinates":[-80.60396999999998,7.84436],"type":"Point"}
}