{
  "type": "Feature",
  "properties": {
    "gn:admin1_code":"10",
    "gn:asciiname":"El Pavon",
    "gn:cc2":"PA",
    "gn:country_code":"PA",
    "gn:dem":330,
    "gn:feature_class":"P",
    "gn:feature_code":"PPL",
    "gn:name":"El Pav\u00f3n",
    "gn:population":0,
    "gn:timezone":"America/Panama",
    "iso:country":"PA",
    "name:und_x_variant":[
        "Pavon",
        "El Pav\u00f3n"
    ],
    "wof:name":"El Pavon",
    "wof:placetype":"locality"
},
  "geometry": {"coordinates":[-81.48333000000002,8.18333],"type":"Point"}
}