{
  "type": "Feature",
  "properties": {
    "gn:admin1_code":"10",
    "gn:asciiname":"Platanal",
    "gn:country_code":"PA",
    "gn:dem":26,
    "gn:feature_class":"P",
    "gn:feature_code":"PPL",
    "gn:name":"Platanal",
    "gn:population":0,
    "gn:timezone":"America/Panama",
    "iso:country":"PA",
    "wof:name":"Platanal",
    "wof:placetype":"locality"
},
  "geometry": {"coordinates":[-81.0675,7.57667],"type":"Point"}
}