{
  "type": "Feature",
  "properties": {
    "gn:admin1_code":"04",
    "gn:asciiname":"La Cauchera",
    "gn:country_code":"PA",
    "gn:dem":36,
    "gn:feature_class":"P",
    "gn:feature_code":"PPL",
    "gn:name":"La Cauchera",
    "gn:population":0,
    "gn:timezone":"America/Panama",
    "iso:country":"PA",
    "name:spa_x_preferred":[
        "La Cauchera"
    ],
    "wof:name":"La Cauchera",
    "wof:placetype":"locality"
},
  "geometry": {"coordinates":[-80.07701999999998,9.02579],"type":"Point"}
}