{
  "type": "Feature",
  "properties": {
    "gn:admin1_code":"10",
    "gn:asciiname":"El Cuaco",
    "gn:country_code":"PA",
    "gn:dem":142,
    "gn:feature_class":"P",
    "gn:feature_code":"PPL",
    "gn:name":"El Cuaco",
    "gn:population":0,
    "gn:timezone":"America/Panama",
    "iso:country":"PA",
    "wof:name":"El Cuaco",
    "wof:placetype":"locality"
},
  "geometry": {"coordinates":[-81.41528000000002,7.81694],"type":"Point"}
}