{
  "type": "Feature",
  "properties": {
    "gn:admin1_code":"06",
    "gn:asciiname":"La Arena",
    "gn:cc2":"PA",
    "gn:country_code":"PA",
    "gn:dem":139,
    "gn:feature_class":"P",
    "gn:feature_code":"PPL",
    "gn:name":"La Arena",
    "gn:population":0,
    "gn:timezone":"America/Panama",
    "iso:country":"PA",
    "name:ceb_x_preferred":[
        "La Arena"
    ],
    "name:ita_x_preferred":[
        "La Arena"
    ],
    "name:srp_x_preferred":[
        "\u041b\u0430 \u0410\u0440\u0435\u043d\u0430"
    ],
    "name:swe_x_preferred":[
        "La Arena"
    ],
    "name:und_x_variant":[
        "La Arenas"
    ],
    "wof:name":"La Arena",
    "wof:placetype":"locality"
},
  "geometry": {"coordinates":[-80.90000000000001,7.91667],"type":"Point"}
}