{
  "type": "Feature",
  "properties": {
    "gn:admin1_code":"12",
    "gn:asciiname":"Los Bajos",
    "gn:country_code":"PA",
    "gn:dem":349,
    "gn:feature_class":"P",
    "gn:feature_code":"PPL",
    "gn:name":"Los Bajos",
    "gn:population":0,
    "gn:timezone":"America/Panama",
    "iso:country":"PA",
    "wof:name":"Los Bajos",
    "wof:placetype":"locality"
},
  "geometry": {"coordinates":[-81.63333,8.33333],"type":"Point"}
}