{
  "type": "Feature",
  "properties": {
    "gn:admin1_code":"03",
    "gn:asciiname":"Ojo de Agua",
    "gn:country_code":"PA",
    "gn:dem":250,
    "gn:feature_class":"P",
    "gn:feature_code":"PPL",
    "gn:name":"Ojo de Agua",
    "gn:population":3,
    "gn:timezone":"America/Panama",
    "iso:country":"PA",
    "wof:name":"Ojo de Agua",
    "wof:placetype":"locality",
    "wof:population":3
},
  "geometry": {"coordinates":[-80.49744,8.59774],"type":"Point"}
}