{
  "type": "Feature",
  "properties": {
    "gn:admin1_code":"13",
    "gn:asciiname":"Mata Palo Numero Dos",
    "gn:country_code":"PA",
    "gn:dem":363,
    "gn:feature_class":"P",
    "gn:feature_code":"PPL",
    "gn:name":"Mata Palo N\u00famero Dos",
    "gn:population":0,
    "gn:timezone":"America/Panama",
    "iso:country":"PA",
    "wof:name":"Mata Palo Numero Dos",
    "wof:placetype":"locality"
},
  "geometry": {"coordinates":[-80.08333,8.55],"type":"Point"}
}