{
  "type": "Feature",
  "properties": {
    "gn:admin1_code":"13",
    "gn:asciiname":"Alto del Jobo",
    "gn:country_code":"PA",
    "gn:dem":117,
    "gn:feature_class":"P",
    "gn:feature_code":"PPL",
    "gn:name":"Alto del Jobo",
    "gn:population":0,
    "gn:timezone":"America/Panama",
    "iso:country":"PA",
    "name:spa_x_preferred":[
        "Alto del Jobo"
    ],
    "wof:name":"Alto del Jobo",
    "wof:placetype":"locality"
},
  "geometry": {"coordinates":[-79.81269,8.98544],"type":"Point"}
}