{
  "type": "Feature",
  "properties": {
    "gn:admin1_code":"02",
    "gn:asciiname":"Dos Rios Abajo",
    "gn:country_code":"PA",
    "gn:dem":155,
    "gn:feature_class":"P",
    "gn:feature_code":"PPLA3",
    "gn:name":"Dos R\u00edos Abajo",
    "gn:population":0,
    "gn:timezone":"America/Panama",
    "iso:country":"PA",
    "name:spa_x_preferred":[
        "Dos R\u00edos Abajo"
    ],
    "wof:name":"Dos Rios Abajo",
    "wof:placetype":"locality"
},
  "geometry": {"coordinates":[-82.38677,8.52834],"type":"Point"}
}