{
  "type": "Feature",
  "properties": {
    "gn:admin1_code":"02",
    "gn:asciiname":"Las Moras",
    "gn:country_code":"PA",
    "gn:dem":22,
    "gn:feature_class":"P",
    "gn:feature_code":"PPL",
    "gn:name":"Las Moras",
    "gn:population":134,
    "gn:timezone":"America/Panama",
    "iso:country":"PA",
    "name:und_x_variant":[
        "Los Moras",
        "Las Moras"
    ],
    "wof:name":"Las Moras",
    "wof:placetype":"locality",
    "wof:population":134
},
  "geometry": {"coordinates":[-82.58849000000002,8.36798],"type":"Point"}
}