{
  "type": "Feature",
  "properties": {
    "gn:admin1_code":"10",
    "gn:asciiname":"El Ciruelito",
    "gn:country_code":"PA",
    "gn:dem":116,
    "gn:feature_class":"P",
    "gn:feature_code":"PPL",
    "gn:name":"El Ciruelito",
    "gn:population":222,
    "gn:timezone":"America/Panama",
    "iso:country":"PA",
    "name:und_x_variant":[
        "Ciruelito",
        "El Ciruelito"
    ],
    "wof:name":"El Ciruelito",
    "wof:placetype":"locality",
    "wof:population":222
},
  "geometry": {"coordinates":[-80.93352,8.02638],"type":"Point"}
}