{
  "type": "Feature",
  "properties": {
    "gn:admin1_code":"10",
    "gn:asciiname":"El Zapote",
    "gn:country_code":"PA",
    "gn:dem":-9999,
    "gn:feature_class":"P",
    "gn:feature_code":"PPL",
    "gn:name":"El Zapote",
    "gn:population":0,
    "gn:timezone":"America/Panama",
    "iso:country":"PA",
    "name:spa_x_preferred":[
        "El Zapote"
    ],
    "wof:name":"El Zapote",
    "wof:placetype":"locality"
},
  "geometry": {"coordinates":[-81.50843,7.74932],"type":"Point"}
}