{
  "type": "Feature",
  "properties": {
    "gn:admin1_code":"05",
    "gn:asciiname":"Boca de Punusa",
    "gn:country_code":"PA",
    "gn:dem":104,
    "gn:feature_class":"P",
    "gn:feature_code":"PPL",
    "gn:name":"Boca de Punusa",
    "gn:population":0,
    "gn:timezone":"America/Panama",
    "iso:country":"PA",
    "name:spa_x_preferred":[
        "Boca de Punusa"
    ],
    "wof:name":"Boca de Punusa",
    "wof:placetype":"locality"
},
  "geometry": {"coordinates":[-77.52616,7.77228],"type":"Point"}
}