{
  "type": "Feature",
  "properties": {
    "gn:admin1_code":"07",
    "gn:asciiname":"Rio Viejo Arriba",
    "gn:cc2":"PA",
    "gn:country_code":"PA",
    "gn:dem":20,
    "gn:feature_class":"P",
    "gn:feature_code":"PPL",
    "gn:name":"R\u00edo Viejo Arriba",
    "gn:population":0,
    "gn:timezone":"America/Panama",
    "iso:country":"PA",
    "name:und_x_variant":[
        "R\u00edo Viejo Perina",
        "R\u00edo Viejo Arriba"
    ],
    "wof:name":"Rio Viejo Arriba",
    "wof:placetype":"locality"
},
  "geometry": {"coordinates":[-80.48333000000002,7.41667],"type":"Point"}
}