{
  "type": "Feature",
  "properties": {
    "gn:admin1_code":"02",
    "gn:asciiname":"Pedregalito",
    "gn:country_code":"PA",
    "gn:dem":118,
    "gn:feature_class":"P",
    "gn:feature_code":"PPL",
    "gn:name":"Pedregalito",
    "gn:population":303,
    "gn:timezone":"America/Panama",
    "iso:country":"PA",
    "name:spa_x_preferred":[
        "Pedregalito"
    ],
    "wof:name":"Pedregalito",
    "wof:placetype":"locality",
    "wof:population":303
},
  "geometry": {"coordinates":[-82.59373000000002,8.46796],"type":"Point"}
}