{
  "type": "Feature",
  "properties": {
    "gn:admin1_code":"12",
    "gn:asciiname":"Cerro Yuco",
    "gn:country_code":"PA",
    "gn:dem":293,
    "gn:feature_class":"P",
    "gn:feature_code":"PPL",
    "gn:name":"Cerro Yuco",
    "gn:population":0,
    "gn:timezone":"America/Panama",
    "iso:country":"PA",
    "name:und_x_variant":[
        "Cerro Yuca",
        "Cerro Yuco"
    ],
    "wof:name":"Cerro Yuco",
    "wof:placetype":"locality"
},
  "geometry": {"coordinates":[-81.68333,8.36667],"type":"Point"}
}