{
  "type": "Feature",
  "properties": {
    "gn:admin1_code":"02",
    "gn:asciiname":"Portugal",
    "gn:country_code":"PA",
    "gn:dem":277,
    "gn:feature_class":"P",
    "gn:feature_code":"PPL",
    "gn:name":"Portugal",
    "gn:population":0,
    "gn:timezone":"America/Panama",
    "iso:country":"PA",
    "name:spa_x_preferred":[
        "Portugal"
    ],
    "wof:name":"Portugal",
    "wof:placetype":"locality"
},
  "geometry": {"coordinates":[-81.67375,8.22885],"type":"Point"}
}