{
  "type": "Feature",
  "properties": {
    "gn:admin1_code":"12",
    "gn:asciiname":"Diuma",
    "gn:country_code":"PA",
    "gn:dem":452,
    "gn:feature_class":"P",
    "gn:feature_code":"PPL",
    "gn:name":"Diuma",
    "gn:population":0,
    "gn:timezone":"America/Panama",
    "iso:country":"PA",
    "name:deu_x_preferred":[
        "Diuma"
    ],
    "name:nld_x_preferred":[
        "Diuma"
    ],
    "name:rus_x_preferred":[
        "\u0414\u0438\u0443\u043c\u0430 \u041c\u0435\u0440\u0441\u0438\u0439\u0441\u043a\u0438\u0439"
    ],
    "name:spa_x_preferred":[
        "Diuma"
    ],
    "wof:name":"Diuma",
    "wof:placetype":"locality"
},
  "geometry": {"coordinates":[-81.79326999999998,8.31751],"type":"Point"}
}