{
  "type": "Feature",
  "properties": {
    "gn:admin1_code":"04",
    "gn:asciiname":"Rio Mosquera",
    "gn:cc2":"PA",
    "gn:country_code":"PA",
    "gn:dem":16,
    "gn:feature_class":"P",
    "gn:feature_code":"PPL",
    "gn:name":"R\u00edo Mosquera",
    "gn:population":0,
    "gn:timezone":"America/Panama",
    "iso:country":"PA",
    "name:und_x_variant":[
        "Mosquera",
        "R\u00edo Mosquera"
    ],
    "wof:name":"Rio Mosquera",
    "wof:placetype":"locality"
},
  "geometry": {"coordinates":[-80.08750000000001,9.18472],"type":"Point"}
}