{
  "type": "Feature",
  "properties": {
    "gn:admin1_code":"02",
    "gn:asciiname":"San Bartolo",
    "gn:cc2":"PA",
    "gn:country_code":"PA",
    "gn:dem":35,
    "gn:feature_class":"P",
    "gn:feature_code":"PPL",
    "gn:name":"San Bartolo",
    "gn:population":0,
    "gn:timezone":"America/Panama",
    "iso:country":"PA",
    "name:ceb_x_preferred":[
        "San Bartolo"
    ],
    "name:deu_x_preferred":[
        "San Bartolo"
    ],
    "name:epo_x_preferred":[
        "San Bartolo"
    ],
    "name:fra_x_preferred":[
        "San Bartolo"
    ],
    "name:por_x_preferred":[
        "San Bartolo"
    ],
    "name:sco_x_preferred":[
        "San Bartolo"
    ],
    "name:spa_x_preferred":[
        "San Bartolo"
    ],
    "name:srp_x_preferred":[
        "San Bartolo"
    ],
    "name:swe_x_preferred":[
        "San Bartolo"
    ],
    "name:und_x_variant":[
        "San Bartolom\u00e9",
        "San Bartolo Abajo",
        "San Bartolo"
    ],
    "wof:name":"San Bartolo",
    "wof:placetype":"locality"
},
  "geometry": {"coordinates":[-82.88333,8.33333],"type":"Point"}
}