{
  "type": "Feature",
  "properties": {
    "gn:admin1_code":"07",
    "gn:asciiname":"La Totumita",
    "gn:country_code":"PA",
    "gn:dem":531,
    "gn:feature_class":"P",
    "gn:feature_code":"PPL",
    "gn:name":"La Totumita",
    "gn:population":0,
    "gn:timezone":"America/Panama",
    "iso:country":"PA",
    "wof:name":"La Totumita",
    "wof:placetype":"locality"
},
  "geometry": {"coordinates":[-80.45,7.55],"type":"Point"}
}