{
  "type": "Feature",
  "properties": {
    "gn:admin1_code":"02",
    "gn:asciiname":"Los Limones",
    "gn:country_code":"PA",
    "gn:dem":46,
    "gn:feature_class":"P",
    "gn:feature_code":"PPL",
    "gn:name":"Los Limones",
    "gn:population":275,
    "gn:timezone":"America/Panama",
    "iso:country":"PA",
    "name:spa_x_preferred":[
        "Los Limones"
    ],
    "wof:name":"Los Limones",
    "wof:placetype":"locality",
    "wof:population":275
},
  "geometry": {"coordinates":[-82.66934999999999,8.41383],"type":"Point"}
}