{
  "type": "Feature",
  "properties": {
    "gn:admin1_code":"07",
    "gn:asciiname":"Quebrada Seca",
    "gn:cc2":"PA",
    "gn:country_code":"PA",
    "gn:dem":179,
    "gn:feature_class":"P",
    "gn:feature_code":"PPL",
    "gn:name":"Quebrada Seca",
    "gn:population":0,
    "gn:timezone":"America/Panama",
    "iso:country":"PA",
    "name:und_x_variant":[
        "Quebrada de Quema",
        "Quebrada Seca"
    ],
    "wof:name":"Quebrada Seca",
    "wof:placetype":"locality"
},
  "geometry": {"coordinates":[-80.55,7.53333],"type":"Point"}
}