{
  "type": "Feature",
  "properties": {
    "gn:admin1_code":"02",
    "gn:asciiname":"San Pablo Viejo Arriba",
    "gn:country_code":"PA",
    "gn:dem":113,
    "gn:feature_class":"P",
    "gn:feature_code":"PPL",
    "gn:name":"San Pablo Viejo Arriba",
    "gn:population":666,
    "gn:timezone":"America/Panama",
    "iso:country":"PA",
    "name:spa_x_preferred":[
        "San Pablo Viejo Arriba"
    ],
    "wof:name":"San Pablo Viejo Arriba",
    "wof:placetype":"locality",
    "wof:population":666
},
  "geometry": {"coordinates":[-82.50471999999998,8.48011],"type":"Point"}
}