{
  "type": "Feature",
  "properties": {
    "gn:admin1_code":"10",
    "gn:asciiname":"Los Mendozas",
    "gn:country_code":"PA",
    "gn:dem":184,
    "gn:feature_class":"P",
    "gn:feature_code":"PPL",
    "gn:name":"Los Mendozas",
    "gn:population":216,
    "gn:timezone":"America/Panama",
    "iso:country":"PA",
    "name:spa_x_preferred":[
        "Los Mendozas"
    ],
    "wof:name":"Los Mendozas",
    "wof:placetype":"locality",
    "wof:population":216
},
  "geometry": {"coordinates":[-81.06939,8.37748],"type":"Point"}
}