{
  "type": "Feature",
  "properties": {
    "gn:admin1_code":"12",
    "gn:asciiname":"Sapo",
    "gn:country_code":"PA",
    "gn:dem":1541,
    "gn:feature_class":"P",
    "gn:feature_code":"PPL",
    "gn:name":"Sapo",
    "gn:population":0,
    "gn:timezone":"America/Panama",
    "iso:country":"PA",
    "wof:name":"Sapo",
    "wof:placetype":"locality"
},
  "geometry": {"coordinates":[-81.56667,8.48333],"type":"Point"}
}