{
  "type": "Feature",
  "properties": {
    "gn:admin1_code":"10",
    "gn:asciiname":"Bisvalles",
    "gn:country_code":"PA",
    "gn:dem":76,
    "gn:feature_class":"P",
    "gn:feature_code":"PPLA3",
    "gn:name":"Bisvalles",
    "gn:population":141,
    "gn:timezone":"America/Panama",
    "iso:country":"PA",
    "name:und_x_variant":[
        "Bisvaya",
        "Bisvalles"
    ],
    "wof:name":"Bisvalles",
    "wof:placetype":"locality",
    "wof:population":141
},
  "geometry": {"coordinates":[-81.22091999999998,8.18298],"type":"Point"}
}