{
  "type": "Feature",
  "properties": {
    "gn:admin1_code":"10",
    "gn:asciiname":"El Chumico",
    "gn:country_code":"PA",
    "gn:dem":99,
    "gn:feature_class":"P",
    "gn:feature_code":"PPL",
    "gn:name":"El Chumico",
    "gn:population":94,
    "gn:timezone":"America/Panama",
    "iso:country":"PA",
    "wof:name":"El Chumico",
    "wof:placetype":"locality",
    "wof:population":94
},
  "geometry": {"coordinates":[-80.83801,8.26882],"type":"Point"}
}